Workbook
Name test1: #REF!
Name test2: #REF!

Sheet Werte
A1: Referenz | B1: Kategorie | C1: Beschreibung | D1: Abkürzung | E1: Info | F1: Parent | G1: Art | H1: Formel | I1: Pool | J1: Flag | K1: Grad | L1: Kosten | M1: Verfuegbarkeit | O1: Mindest-TaW | P1: Eig-Bonus | Q1: Wirkung
A2: #spruchmagie_erdbeschwoerung_1_splitterwand | B2: Spruchmagie | C2: Splitterwand | F2: Erdbeschwörung | G2: Wert | J2: ACHTUNG: In der Quelle (NN_Spruchmagie_0.57) gibt es mehrere Zeilen mit gleichem Schule+Grad+Name aber abweichendem Wirkungstext (vermutlich alte+neue Version nebeneinander stehen geblieben) - hier wurde die letzte Version uebernommen, bitte pruefen. | K2: 1 | L2: WENN(wert=0;0;10+(wert-1)*grad) | P2: eig_bonus_k_staerke | Q2: Der Magier erschafft eine Wand aus Erde. Die Wahrnehmung durch diese Wand ist stark erschwert bis unmöglich: Alle FK-Attacken sind um {Aura}*2 erschwert. Wer versucht, die Wand zu durchdringen, erleidet Elementarschaden auf jeder TZ. Während der Effektdauer entfaltet die Wand nur die halbe Wirkung. Schaden: W4+{Magie}, RB 6 auf jede TZ.
A3: #spruchmagie_erdbeschwoerung_2_splitterstrahl | B3: Spruchmagie | C3: Splitterstrahl | F3: Erdbeschwörung | G3: Wert | J3: ACHTUNG: In der Quelle (NN_Spruchmagie_0.57) gibt es mehrere Zeilen mit gleichem Schule+Grad+Name aber abweichendem Wirkungstext (vermutlich alte+neue Version nebeneinander stehen geblieben) - hier wurde die letzte Version uebernommen, bitte pruefen. | K3: 2 | L3: WENN(wert=0;0;10+(wert-1)*grad) | P3: eig_bonus_k_staerke | Q3: Aus der Handfläche des Magiers schießt ein {M} cm dicker Strahl aus Erde. Schaden: W10+{Magie}, RB 3, pro sec, Treffer auf eine FK-TZ mit 1 zusätzlichen TZ-Reroll.
A4: #spruchmagie_erdbeschwoerung_3_steinschlag | B4: Spruchmagie | C4: Steinschlag | F4: Erdbeschwörung | G4: Wert | J4: ACHTUNG: In der Quelle (NN_Spruchmagie_0.57) gibt es mehrere Zeilen mit gleichem Schule+Grad+Name aber abweichendem Wirkungstext (vermutlich alte+neue Version nebeneinander stehen geblieben) - hier wurde die letzte Version uebernommen, bitte pruefen. | K4: 3 | L4: WENN(wert=0;0;10+(wert-1)*grad) | P4: eig_bonus_k_staerke | Q4: Der Magus erschafft um das Opfer eine Kugel aus Erde. Treffer auf FK-TZ mit 2 TZ-Rerolls auf die gewünschte Trefferzone. Schaden: 2W6 + {Magie}, RB 6.
A5: #spruchmagie_erdbeschwoerung_4_grosse_splitterwand | B5: Spruchmagie | C5: Große Splitterwand | F5: Erdbeschwörung | G5: Wert | J5: ACHTUNG: In der Quelle (NN_Spruchmagie_0.57) gibt es mehrere Zeilen mit gleichem Schule+Grad+Name aber abweichendem Wirkungstext (vermutlich alte+neue Version nebeneinander stehen geblieben) - hier wurde die letzte Version uebernommen, bitte pruefen. | K5: 4 | L5: WENN(wert=0;0;10+(wert-1)*grad) | P5: eig_bonus_k_staerke | Q5: Der Magier erschafft eine Wand aus Erde. Die Wahrnehmung durch diese Wand ist stark erschwert bis unmöglich: Alle FK-Attacken sind um {Aura}*2 erschwert. Wer versucht, die Wand zu durchdringen, erleidet Elementarschaden auf jeder TZ. Während der Effektdauer entfaltet die Wand nur die halbe Wirkung. Schaden: 2W6 + {Magie}, RB 6. Länge max. {M} m, Breite max. {M}*5cm
A6: #spruchmagie_erdbeschwoerung_5_grosse_splitteraura | B6: Spruchmagie | C6: Große Splitteraura | F6: Erdbeschwörung | G6: Wert | J6: ACHTUNG: In der Quelle (NN_Spruchmagie_0.57) gibt es mehrere Zeilen mit gleichem Schule+Grad+Name aber abweichendem Wirkungstext (vermutlich alte+neue Version nebeneinander stehen geblieben) - hier wurde die letzte Version uebernommen, bitte pruefen. | K6: 5 | L6: WENN(wert=0;0;10+(wert-1)*grad) | P6: eig_bonus_k_staerke | Q6: Der Magus hüllt sich in eine kugelförmige Aura aus Erde. Wer sich in die Aura begibt, erleidet auf jeder TZ innerhalb dieses Gebietes Elementarschaden. Der Magier kann aus der Aura heraus normal zielen, FK-Angriffe sind um {Aura}*2 erschwert. Feindliche Magie ist mit Ziel Aura hiervon nicht betroffen. Schaden: 2W6+{Magie}, RB 6, auf jede TZ.
A7: #spruchmagie_erdbeschwoerung_5_grosser_steinschuss | B7: Spruchmagie | C7: Großer Steinschuss | F7: Erdbeschwörung | G7: Wert | J7: ACHTUNG: In der Quelle (NN_Spruchmagie_0.57) gibt es mehrere Zeilen mit gleichem Schule+Grad+Name aber abweichendem Wirkungstext (vermutlich alte+neue Version nebeneinander stehen geblieben) - hier wurde die letzte Version uebernommen, bitte pruefen. | K7: 5 | L7: WENN(wert=0;0;10+(wert-1)*grad) | P7: eig_bonus_k_staerke | Q7: Der Magus erschafft einen Bolzen aus Erde. Treffer auf FK-TZ. Schaden: 2W10 + {Magie}; RB: 6 + {M}:2
A8: #spruchmagie_erdbeschwoerung_5_splittersturm | B8: Spruchmagie | C8: Splittersturm | F8: Erdbeschwörung | G8: Wert | J8: ACHTUNG: In der Quelle (NN_Spruchmagie_0.57) gibt es mehrere Zeilen mit gleichem Schule+Grad+Name aber abweichendem Wirkungstext (vermutlich alte+neue Version nebeneinander stehen geblieben) - hier wurde die letzte Version uebernommen, bitte pruefen. | K8: 5 | L8: WENN(wert=0;0;10+(wert-1)*grad) | P8: eig_bonus_k_staerke | Q8: Eine vom Magus ausgehende kugelförmige Explosion verursacht Elementarschaden. Es ist unmöglich, dem Schaden zu entgehen. Jede TZ wird getroffen. Schaden: W8 + {Magie}, RB 3.
A9: #spruchmagie_erdbeschwoerung_6_grosser_splitterstrahl | B9: Spruchmagie | C9: Großer Splitterstrahl | F9: Erdbeschwörung | G9: Wert | J9: ACHTUNG: In der Quelle (NN_Spruchmagie_0.57) gibt es mehrere Zeilen mit gleichem Schule+Grad+Name aber abweichendem Wirkungstext (vermutlich alte+neue Version nebeneinander stehen geblieben) - hier wurde die letzte Version uebernommen, bitte pruefen. | K9: 6 | L9: WENN(wert=0;0;10+(wert-1)*grad) | P9: eig_bonus_k_staerke | Q9: Aus der Handfläche des Magiers schießt ein {M} cm dicker Strahl aus Erde. Schaden: 2W10 + {Magie}, RB 6, pro sec, Treffer auf eine FK-TZ mit 1 zusätzlichen TZ-Reroll.
A10: #spruchmagie_erdbeschwoerung_6_grosser_steinschlag | B10: Spruchmagie | C10: Großer Steinschlag | F10: Erdbeschwörung | G10: Wert | J10: ACHTUNG: In der Quelle (NN_Spruchmagie_0.57) gibt es mehrere Zeilen mit gleichem Schule+Grad+Name aber abweichendem Wirkungstext (vermutlich alte+neue Version nebeneinander stehen geblieben) - hier wurde die letzte Version uebernommen, bitte pruefen. | K10: 6 | L10: WENN(wert=0;0;10+(wert-1)*grad) | P10: eig_bonus_k_staerke | Q10: Der Magus erschafft um das Opfer eine Kugel aus Erde. Treffer auf FK-TZ mit 2 TZ-Rerolls auf die gewünschte Trefferzone. Schaden: 2W12 + {Magie}, RB 9.
A11: #spruchmagie_erdbeschwoerung_7_grosser_splittersturm | B11: Spruchmagie | C11: Großer Splittersturm | F11: Erdbeschwörung | G11: Wert | J11: ACHTUNG: In der Quelle (NN_Spruchmagie_0.57) gibt es mehrere Zeilen mit gleichem Schule+Grad+Name aber abweichendem Wirkungstext (vermutlich alte+neue Version nebeneinander stehen geblieben) - hier wurde die letzte Version uebernommen, bitte pruefen. | K11: 7 | L11: WENN(wert=0;0;10+(wert-1)*grad) | P11: eig_bonus_k_staerke | Q11: Eine vom Magus ausgehende kugelförmige Explosion verursacht Elementarschaden. Es ist unmöglich, dem Schaden zu entgehen. Jede TZ wird getroffen. Schaden: 2W15 + {Magie}, RB 15.
A12: #spruchmagie_feuerbeschwoerung_1_flammenwand | B12: Spruchmagie | C12: Flammenwand | F12: Feuerbeschwörung | G12: Wert | J12: ACHTUNG: In der Quelle (NN_Spruchmagie_0.57) gibt es mehrere Zeilen mit gleichem Schule+Grad+Name aber abweichendem Wirkungstext (vermutlich alte+neue Version nebeneinander stehen geblieben) - hier wurde die letzte Version uebernommen, bitte pruefen. | K12: 1 | L12: WENN(wert=0;0;10+(wert-1)*grad) | P12: eig_bonus_g_mut | Q12: Der Magier erschafft eine Wand aus Feuer. Die Wahrnehmung durch diese Wand ist stark erschwert bis unmöglich: Alle FK-Attacken sind um {Aura}*2 erschwert. Wer versucht, die Wand zu durchdringen, erleidet Elementarschaden auf jeder TZ. Während der Effektdauer entfaltet die Wand nur die halbe Wirkung. Schaden: W6+{Magie} auf jede TZ.
A13: #spruchmagie_feuerbeschwoerung_2_flammenaura | B13: Spruchmagie | C13: Flammenaura | F13: Feuerbeschwörung | G13: Wert | J13: ACHTUNG: In der Quelle (NN_Spruchmagie_0.57) gibt es mehrere Zeilen mit gleichem Schule+Grad+Name aber abweichendem Wirkungstext (vermutlich alte+neue Version nebeneinander stehen geblieben) - hier wurde die letzte Version uebernommen, bitte pruefen. | K13: 2 | L13: WENN(wert=0;0;10+(wert-1)*grad) | P13: eig_bonus_g_mut | Q13: Der Magus hüllt sich in eine kugelförmige Aura aus Feuer. Wer sich in die Aura begibt, erleidet auf jeder TZ innerhalb dieses Gebietes Elementarschaden. Der Magier kann aus der Aura heraus normal zielen, FK-Angriffe sind um {Aura}*2 erschwert. Feindliche Magie ist mit Ziel Aura hiervon nicht betroffen. Schaden: W6+{Magie} auf jede TZ.
... A71: #spruchmagie_wasserbeschwoerung_7_grosse_frostbolzen_salve | B71: Spruchmagie | C71: Große Frostbolzen-Salve | F71: Wasserbeschwörung | G71: Wert | J71: ACHTUNG: In der Quelle (NN_Spruchmagie_0.57) gibt es mehrere Zeilen mit gleichem Schule+Grad+Name aber abweichendem Wirkungstext (vermutlich alte+neue Version nebeneinander stehen geblieben) - hier wurde die letzte Version uebernommen, bitte pruefen. | Referenz enthielt Bindestrich (mehrdeutig mit Subtraktion) - zu Unterstrich normalisiert. | K71: 7 | L71: WENN(wert=0;0;10+(wert-1)*grad) | P71: eig_bonus_k_athletik | Q71: Der Magus erschafft {Magie} : 2 Bolzen aus Wasser. Jeweils Treffer auf FK-TZ. Schaden: 2W10 + {Magie}; RB: {M}:2. Pro 5 TP erleidet das Opfer zusätzliche BE 1, nur die höchste so erzielte BE zählt.
A72: ep_abenteuer | B72: Charakterwerte | C72: EP zum Abenteuerende | E72: S.1 | G72: Formel | H72: ep_gesamt-ep_start
A73: le_leberschutz | B73: Kampf | C73: Leberschutz | E73: S.3 | G73: Pool
A74: ep_gesamt | B74: Charakterwerte | C74: Gesamte Erfahrungspunke | E74: S.1 | G74: Wert
A75: ep_start | B75: Charakterwerte | C75: EP bei Abenteuerbeginn | E75: S.1 | G75: Wert
A76: bewegung_f_schnell_schwimmen | B76: Bewegung | C76: Schnell Schwimmen | E76: Meisterscreen S.3 | G76: Formel | H76: (eig_k_konstitution+eig_k_athletik+gr_schwimmen)/30
A77: bewegung_f_sprinten | B77: Bewegung | C77: Sprinten | E77: Meisterscreen S.3 | G77: Formel | H77: (eig_k_athletik+eig_k_schnelligkeit+gr_laufen)/7+4
A78: #spruchmagie_beherrschung_4_einschlaefern | B78: Spruchmagie | C78: Einschläfern | F78: Beherrschung | G78: Wert | K78: 4 | L78: WENN(wert=0;0;10+(wert-1)*grad) | P78: eig_bonus_g_ausstrahlung | Q78: Das Opfer schläft ein. Der Schlaf ist, wenn auch unnatürlich tief, wie normaler schlaf zu Behandeln. Sollte das Opfer also gerade stehen, so fällt es um und wacht durch den Sturz natürlich wieder auf. Auch das abfeuern einer Feuerwaffe in seiner nähe wird wohl, ohne Probe, zum Aufwachen führen. Gewohnte Geräusche gehören natürlich nicht dazu. Ein Heizer einer Dampfmaschine wird durch eben jene nicht Aufwachen.
A79: #spruchmagie_beherrschung_7_maechtige_f_daemonen_herrschaft | B79: Spruchmagie | C79: Mächtige f.Dämonen Herrschaft | F79: Beherrschung | G79: Wert | K79: 7 | L79: WENN(wert=0;0;10+(wert-1)*grad) | P79: eig_bonus_g_ausstrahlung | Q79: Ein freier (nicht von einem anderen Magus beherrschter) Dämon hat eine Willenskraft-Probe erschwert um die Differenz von der {M} des Margus (Macht x2) und des Opfers (Macht x1). Und alle 24 Stunden eine weitere. Wenn sie gelingt fällt der Zauber.1 und 29 sind immer ein Erfolg. Ansonsten wird der Dämon zu einem Willenskraftenlosen Sklaven des Magus. Es wird aufs Wort hören, ganz so als währe es ein Absolut untertäniger Diner. Der Dämon weis zwar immer genau was der Magus von ihm Willenskraft ist aber nicht Intelligenzelligenter als vorher oder verfügt nicht über neue Fertigkeiten. Eine Stroh dummer Dämon wird es wohl nicht schaffen den Banksafe ohne Gewalt zu öffnen.
A80: #spruchmagie_beherrschung_5_massen_besaenftigung | B80: Spruchmagie | C80: Massen Besänftigung | F80: Beherrschung | G80: Wert | K80: 5 | L80: WENN(wert=0;0;10+(wert-1)*grad) | P80: eig_bonus_g_ausstrahlung | Q80: Die Opfer werden ruhig und gelassen, sie verlieren jeglichen drang zu Töten (außer Einer ist ein Sadist und macht es aus Spaß). Sie wissen zwar noch alles, es ist aber nicht mehr so Dramatisch für Sie. Nach dem der Zauber vorbei ist, sind die Opfer immer noch ruhig, es hält Sie aber nichts davon ab wieder Wütend zu werden. Was natürlich auch sofort geschehen kann aber nicht muss, wenn sie sich daran erinnern dass man gerade ihr Dorf nieder gebrannt hat.
A81: #spruchmagie_beherrschung_3_schmerzt_unterdruecken | B81: Spruchmagie | C81: Schmerzt unterdrücken | F81: Beherrschung | G81: Wert | K81: 3 | L81: WENN(wert=0;0;10+(wert-1)*grad) | P81: eig_bonus_g_willenskraft | Q81: Die Gefühle und Schmerzen des Opfers werden unterdrückt. Das Opfer fühlt sich so als würde es unter dem Einfluss eines Betäubungsmittels stehen. Es bekommt eine Generelle Behinderung von 1. Seine TS steigt um das 4 fache an und alle Behinderungen die das Opfer durch Kampfschäden bekommt oder bekommen hat sind gleich null.
A82: #spruchmagie_beherrschung_2_zoegern | B82: Spruchmagie | C82: Zögern | F82: Beherrschung | G82: Wert | K82: 2 | L82: WENN(wert=0;0;10+(wert-1)*grad) | P82: eig_bonus_g_intelligenz | Q82: Das Opfer zögert, das zu tun, was es gerade wollte. Es greift nicht mehr an, sondern verteidigt sich nur noch. Sollte gerade keine Kampf Situation sein so bleibt es sehn und hält inne um seinen nächsten schritt noch mal zu überdenken. Das Opfer zögert maximal 1W4+{Magie} Sekunden lang.
A83: vn_angst_magie_10 | B83: Vor- und Nachteile | C83: Nervosität: Magie | E83: Auswahlgruppe angst_magie; maximal 1 Stufe; Angstwert 10; direkte Konfrontation: bei jeder erneuten direkten Konfrontation; bloße Gegenwart: BE -1. | F83: Angst: Magie | G83: Auswahl | J83: EP-Rate für 'magie' aus NN NPC-Rechner 0.75, Sheet 'NPC-Rechner' Formel '=AOxx*-10' (Zeile 52ff). Kosten = Stufenwert(10) * Rate(-10). | EXKLUSIV_ANGST=angst_magie | ANGST_INTERVALL=NEUE_KONFRONTATION | ANGST_DIREKTE_KONFRONTATION=1 | ANGST_BE=-1 | K83: 10 | L83: -100 | M83: S | Q83: Der Charakter reagiert auf alle Magie mit Nervosität und ist nicht in der Lage, irgendeine Form von Magie außer KI zu wirken. Bei direkter Konfrontation mit Magie, insbesondere wenn er gegen einen Magiewirker vorgeht, muss er bei jeder erneuten direkten Konfrontation eine um 10 erschwerte Mut-Probe bestehen, um handlungsfähig zu bleiben. Um Verzauberungen oder magische Heilung zuzulassen, ein Artefakt zu benutzen oder bewusst mit Magie zu interagieren, muss er einmalig eine um 10 erschwerte Willenskraft-Probe bestehen. Ist Magie zwar gegenwärtig, aber weder direkter Gegner noch Gegenstand, Wesen oder sonstiges Ziel, mit dem sich der Charakter aktuell befasst, sind keine Angst-Proben erforderlich; der Charakter erhält BE -1.
A84: vn_angst_magie_15 | B84: Vor- und Nachteile | C84: Furcht: Magie | E84: Auswahlgruppe angst_magie; maximal 1 Stufe; Angstwert 15; direkte Konfrontation: sofort, danach alle 10 KR; bloße Gegenwart: BE -2. | F84: Angst: Magie | G84: Auswahl | J84: EP-Rate für 'magie' aus NN NPC-Rechner 0.75, Sheet 'NPC-Rechner' Formel '=AOxx*-10' (Zeile 52ff). Kosten = Stufenwert(15) * Rate(-10). | EXKLUSIV_ANGST=angst_magie | ANGST_INTERVALL=10_KR | ANGST_DIREKTE_KONFRONTATION=1 | ANGST_BE=-2 | K84: 15 | L84: -150 | M84: S | Q84: Der Charakter reagiert auf alle Magie mit Furcht und ist nicht in der Lage, irgendeine Form von Magie außer KI zu wirken. Bei direkter Konfrontation mit Magie, insbesondere wenn er gegen einen Magiewirker vorgeht, muss er sofort, danach alle 10 KR eine um 15 erschwerte Mut-Probe bestehen, um handlungsfähig zu bleiben. Um Verzauberungen oder magische Heilung zuzulassen, ein Artefakt zu benutzen oder bewusst mit Magie zu interagieren, muss er einmalig eine um 15 erschwerte Willenskraft-Probe bestehen. Ist Magie zwar gegenwärtig, aber weder direkter Gegner noch Gegenstand, Wesen oder sonstiges Ziel, mit dem sich der Charakter aktuell befasst, sind keine Angst-Proben erforderlich; der Charakter erhält BE -2.
A85: vn_angst_magie_20 | B85: Vor- und Nachteile | C85: Angst: Magie | E85: Auswahlgruppe angst_magie; maximal 1 Stufe; Angstwert 20; direkte Konfrontation: sofort, danach alle 5 KR; bloße Gegenwart: BE -3. | F85: Angst: Magie | G85: Auswahl | J85: EP-Rate für 'magie' aus NN NPC-Rechner 0.75, Sheet 'NPC-Rechner' Formel '=AOxx*-10' (Zeile 52ff). Kosten = Stufenwert(20) * Rate(-10). | EXKLUSIV_ANGST=angst_magie | ANGST_INTERVALL=5_KR | ANGST_DIREKTE_KONFRONTATION=1 | ANGST_BE=-3 | K85: 20 | L85: -200 | M85: S | Q85: Der Charakter reagiert auf alle Magie mit Angst und ist nicht in der Lage, irgendeine Form von Magie außer KI zu wirken. Bei direkter Konfrontation mit Magie, insbesondere wenn er gegen einen Magiewirker vorgeht, muss er sofort, danach alle 5 KR eine um 20 erschwerte Mut-Probe bestehen, um handlungsfähig zu bleiben. Um Verzauberungen oder magische Heilung zuzulassen, ein Artefakt zu benutzen oder bewusst mit Magie zu interagieren, muss er einmalig eine um 20 erschwerte Willenskraft-Probe bestehen. Ist Magie zwar gegenwärtig, aber weder direkter Gegner noch Gegenstand, Wesen oder sonstiges Ziel, mit dem sich der Charakter aktuell befasst, sind keine Angst-Proben erforderlich; der Charakter erhält BE -3.
A86: vn_angst_magie_30 | B86: Vor- und Nachteile | C86: Phobie: Magie | E86: Auswahlgruppe angst_magie; maximal 1 Stufe; Angstwert 30; direkte Konfrontation: sofort, danach jede KR; bloße Gegenwart: BE -5. | F86: Angst: Magie | G86: Auswahl | J86: EP-Rate für 'magie' aus NN NPC-Rechner 0.75, Sheet 'NPC-Rechner' Formel '=AOxx*-10' (Zeile 52ff). Kosten = Stufenwert(30) * Rate(-10). | EXKLUSIV_ANGST=angst_magie | ANGST_INTERVALL=1_KR | ANGST_DIREKTE_KONFRONTATION=1 | ANGST_BE=-5 | K86: 30 | L86: -300 | M86: S | Q86: Der Charakter leidet unter einer Phobie gegenüber aller Magie und ist nicht in der Lage, irgendeine Form von Magie außer KI zu wirken. Bei direkter Konfrontation mit Magie, insbesondere wenn er gegen einen Magiewirker vorgeht, muss er sofort, danach jede KR eine um 30 erschwerte Mut-Probe bestehen, um handlungsfähig zu bleiben. Um Verzauberungen oder magische Heilung zuzulassen, ein Artefakt zu benutzen oder bewusst mit Magie zu interagieren, muss er einmalig eine um 30 erschwerte Willenskraft-Probe bestehen. Ist Magie zwar gegenwärtig, aber weder direkter Gegner noch Gegenstand, Wesen oder sonstiges Ziel, mit dem sich der Charakter aktuell befasst, sind keine Angst-Proben erforderlich; der Charakter erhält BE -5.
A87: vn_angst_magie_5 | B87: Vor- und Nachteile | C87: Unbehagen: Magie | E87: Auswahlgruppe angst_magie; maximal 1 Stufe; Angstwert 5; direkte Konfrontation: einmal pro Situation; bloße Gegenwart: BE 0. | F87: Angst: Magie | G87: Auswahl | J87: EP-Rate für 'magie' aus NN NPC-Rechner 0.75, Sheet 'NPC-Rechner' Formel '=AOxx*-10' (Zeile 52ff). Kosten = Stufenwert(5) * Rate(-10). | EXKLUSIV_ANGST=angst_magie | ANGST_INTERVALL=SITUATION | ANGST_DIREKTE_KONFRONTATION=1 | ANGST_BE=0 | K87: 5 | L87: -50 | M87: S | Q87: Der Charakter empfindet Unbehagen gegenüber aller Magie und ist nicht in der Lage, irgendeine Form von Magie außer KI zu wirken. Bei direkter Konfrontation mit Magie, insbesondere wenn er gegen einen Magiewirker vorgeht, muss er einmal pro Situation eine um 5 erschwerte Mut-Probe bestehen, um handlungsfähig zu bleiben. Um Verzauberungen oder magische Heilung zuzulassen, ein Artefakt zu benutzen oder bewusst mit Magie zu interagieren, muss er einmalig eine um 5 erschwerte Willenskraft-Probe bestehen.
A88: vn_schlechte_eigenschaft_ausstrahlung | B88: Vor- und Nachteile | C88: Schlechte Eigenschaft: Ausstrahlung | E88: Max=9 (ab Kreis 3); Erstellungs-Max=7; nicht uebersteigerbar | G88: Auswahl | J88: Ersetzt die normale Voelker-Maxima-Tabelle fuer diese Eigenschaft komplett (nicht MIN() mit dem Volkswert - die Regel ignoriert explizit die Erstellungs-/Kreis-3-Minima/Maxima und setzt eigene feste Werte). | L88: -200 | M88: E | Q88: Dieser Charakter hat eine unterdurchschnittliche Ausstrahlung. Das absolute Maximum dieser Eigenschaft ist 9 (ab Kreis 3, davor darf die Eigenschaft 7 nicht übersteigen). Dieser Nachteil überschreibt die Spezies-Vorgaben. Die Eigenschaft ist grundsätzlich nicht übersteigerbar.
A89: vn_schlechte_eigenschaft_intelligenz | B89: Vor- und Nachteile | C89: Schlechte Eigenschaft: Intelligenz | E89: Max=9 (ab Kreis 3); Erstellungs-Max=7; nicht uebersteigerbar | G89: Auswahl | J89: Ersetzt die normale Voelker-Maxima-Tabelle fuer diese Eigenschaft komplett (nicht MIN() mit dem Volkswert - die Regel ignoriert explizit die Erstellungs-/Kreis-3-Minima/Maxima und setzt eigene feste Werte). | L89: -200 | M89: E | Q89: Dieser Charakter hat eine unterdurchschnittliche Intelligenz. Das absolute Maximum dieser Eigenschaft ist 9 (ab Kreis 3, davor darf die Eigenschaft 7 nicht übersteigen). Dieser Nachteil überschreibt die Spezies-Vorgaben. Die Eigenschaft ist grundsätzlich nicht übersteigerbar.
A90: vn_schlechte_eigenschaft_mut | B90: Vor- und Nachteile | C90: Schlechte Eigenschaft: Mut | E90: Max=9 (ab Kreis 3); Erstellungs-Max=7; nicht uebersteigerbar | G90: Auswahl | J90: Ersetzt die normale Voelker-Maxima-Tabelle fuer diese Eigenschaft komplett (nicht MIN() mit dem Volkswert - die Regel ignoriert explizit die Erstellungs-/Kreis-3-Minima/Maxima und setzt eigene feste Werte). | L90: -200 | M90: E | Q90: Dieser Charakter hat einen unterdurchschnittlichen Mut. Das absolute Maximum dieser Eigenschaft ist 9 (ab Kreis 3, davor darf die Eigenschaft 7 nicht übersteigen). Dieser Nachteil überschreibt die Spezies-Vorgaben. Die Eigenschaft ist grundsätzlich nicht übersteigerbar.
A91: vn_schlechte_eigenschaft_sinnesschaerfe | B91: Vor- und Nachteile | C91: Schlechte Eigenschaft: Sinnesschaerfe | E91: Max=9 (ab Kreis 3); Erstellungs-Max=7; nicht uebersteigerbar | G91: Auswahl | J91: Ersetzt die normale Voelker-Maxima-Tabelle fuer diese Eigenschaft komplett (nicht MIN() mit dem Volkswert - die Regel ignoriert explizit die Erstellungs-/Kreis-3-Minima/Maxima und setzt eigene feste Werte). | L91: -200 | M91: E | Q91: Dieser Charakter hat eine unterdurchschnittliche Sinnesschärfe. Das absolute Maximum dieser Eigenschaft ist 9 (ab Kreis 3, davor darf die Eigenschaft 7 nicht übersteigen). Dieser Nachteil überschreibt die Spezies-Vorgaben. Die Eigenschaft ist grundsätzlich nicht übersteigerbar.
A92: vn_schlechte_eigenschaft_willenskraft | B92: Vor- und Nachteile | C92: Schlechte Eigenschaft: Willenskraft | E92: Max=9 (ab Kreis 3); Erstellungs-Max=7; nicht uebersteigerbar | G92: Auswahl | J92: Ersetzt die normale Voelker-Maxima-Tabelle fuer diese Eigenschaft komplett (nicht MIN() mit dem Volkswert - die Regel ignoriert explizit die Erstellungs-/Kreis-3-Minima/Maxima und setzt eigene feste Werte). | L92: -200 | M92: E | Q92: Dieser Charakter hat eine unterdurchschnittliche Willenskraft. Das absolute Maximum dieser Eigenschaft ist 9 (ab Kreis 3, davor darf die Eigenschaft 7 nicht übersteigen). Dieser Nachteil überschreibt die Spezies-Vorgaben. Die Eigenschaft ist grundsätzlich nicht übersteigerbar.
A93: vn_schlechte_eigenschaft_athletik | B93: Vor- und Nachteile | C93: Schlechte Eigenschaft: Athletik | E93: Max=9 (ab Kreis 3); Erstellungs-Max=7; nicht uebersteigerbar | G93: Auswahl | J93: Ersetzt die normale Voelker-Maxima-Tabelle fuer diese Eigenschaft komplett (nicht MIN() mit dem Volkswert - die Regel ignoriert explizit die Erstellungs-/Kreis-3-Minima/Maxima und setzt eigene feste Werte). | L93: -200 | M93: E | Q93: Dieser Charakter hat eine unterdurchschnittliche Athletik. Das absolute Maximum dieser Eigenschaft ist 9 (ab Kreis 3, davor darf die Eigenschaft 7 nicht übersteigen). Dieser Nachteil überschreibt die Spezies-Vorgaben. Die Eigenschaft ist grundsätzlich nicht übersteigerbar.
A94: vn_schlechte_eigenschaft_geschicklichkeit | B94: Vor- und Nachteile | C94: Schlechte Eigenschaft: Geschicklichkeit | E94: Max=9 (ab Kreis 3); Erstellungs-Max=7; nicht uebersteigerbar | G94: Auswahl | J94: Ersetzt die normale Voelker-Maxima-Tabelle fuer diese Eigenschaft komplett (nicht MIN() mit dem Volkswert - die Regel ignoriert explizit die Erstellungs-/Kreis-3-Minima/Maxima und setzt eigene feste Werte). | L94: -200 | M94: E | Q94: Dieser Charakter hat eine unterdurchschnittliche Geschicklichkeit. Das absolute Maximum dieser Eigenschaft ist 9 (ab Kreis 3, davor darf die Eigenschaft 7 nicht übersteigen). Dieser Nachteil überschreibt die Spezies-Vorgaben. Die Eigenschaft ist grundsätzlich nicht übersteigerbar.
A95: vn_schlechte_eigenschaft_konstitution | B95: Vor- und Nachteile | C95: Schlechte Eigenschaft: Konstitution | E95: Max=9 (ab Kreis 3); Erstellungs-Max=7; nicht uebersteigerbar | G95: Auswahl | J95: Ersetzt die normale Voelker-Maxima-Tabelle fuer diese Eigenschaft komplett (nicht MIN() mit dem Volkswert - die Regel ignoriert explizit die Erstellungs-/Kreis-3-Minima/Maxima und setzt eigene feste Werte). | L95: -200 | M95: E | Q95: Dieser Charakter hat eine unterdurchschnittliche Konstitution. Das absolute Maximum dieser Eigenschaft ist 9 (ab Kreis 3, davor darf die Eigenschaft 7 nicht übersteigen). Dieser Nachteil überschreibt die Spezies-Vorgaben. Die Eigenschaft ist grundsätzlich nicht übersteigerbar.
A96: vn_schlechte_eigenschaft_schnelligkeit | B96: Vor- und Nachteile | C96: Schlechte Eigenschaft: Schnelligkeit | E96: Max=9 (ab Kreis 3); Erstellungs-Max=7; nicht uebersteigerbar | G96: Auswahl | J96: Ersetzt die normale Voelker-Maxima-Tabelle fuer diese Eigenschaft komplett (nicht MIN() mit dem Volkswert - die Regel ignoriert explizit die Erstellungs-/Kreis-3-Minima/Maxima und setzt eigene feste Werte). | L96: -200 | M96: E | Q96: Dieser Charakter hat eine unterdurchschnittliche Schnelligkeit. Das absolute Maximum dieser Eigenschaft ist 9 (ab Kreis 3, davor darf die Eigenschaft 7 nicht übersteigen). Dieser Nachteil überschreibt die Spezies-Vorgaben. Die Eigenschaft ist grundsätzlich nicht übersteigerbar.
A97: vn_schlechte_eigenschaft_staerke | B97: Vor- und Nachteile | C97: Schlechte Eigenschaft: Staerke | E97: Max=9 (ab Kreis 3); Erstellungs-Max=7; nicht uebersteigerbar | G97: Auswahl | J97: Ersetzt die normale Voelker-Maxima-Tabelle fuer diese Eigenschaft komplett (nicht MIN() mit dem Volkswert - die Regel ignoriert explizit die Erstellungs-/Kreis-3-Minima/Maxima und setzt eigene feste Werte). | L97: -200 | M97: E | Q97: Dieser Charakter hat eine unterdurchschnittliche Stärke. Das absolute Maximum dieser Eigenschaft ist 9 (ab Kreis 3, davor darf die Eigenschaft 7 nicht übersteigen). Dieser Nachteil überschreibt die Spezies-Vorgaben. Die Eigenschaft ist grundsätzlich nicht übersteigerbar.
A98: nk_pool_unbewaffnet | B98: Nahkampf | C98: Pool Unbewaffnet | G98: Pool | I98: MAX(0;(eig_g_mut+eig_k_schnelligkeit+nk_unbewaffnet)/3-20)+MAX(0;(eig_k_athletik+eig_k_schnelligkeit+nk_unbewaffnet)/3-20) | J98: Formel hatte nur den Attacke-seitigen MAX-Term. Alle anderen 'Pool <Gruppe>'-Zeilen (198,203,207,212) kombinieren Attacke- und Parade-seitigen Überschuss - fehlenden Parade-Term ergänzt.
A99: f_ausdauer | B99: Charakterwerte | C99: Ausdauer | D99: Ausd. | E99: S.2 | G99: Formel | H99: eig_k_athletik+2*eig_k_konstitution+(eig_k_staerke/2)+3*att_vitalitaet+stufe | J99: Formel referenzierte 'att_vitalität' (alte Umlautschreibweise) statt der aktuellen Referenz 'att_vitalitaet' - korrigiert.
A100: f_alchemieresistenz | B100: Charakterwerte | C100: Alchemieresistenz | D100: AR | G100: Formel | H100: eig_k_konstitution+3*att_vitalitaet+sf_alchemieresistenz | J100: Formel referenzierte 'att_vitalität' (alte Umlautschreibweise) statt der aktuellen Referenz 'att_vitalitaet' - korrigiert. | Formel referenzierte veraltete Gro�-/Kleinschreibung (sf_Alchemieresistenz) - an aktuelle (kleingeschriebene) Referenz angepasst.
A101: selbstbeherrschung | B101: Charakterwerte | C101: Selbstbeherrschung | D101: SB | E101: S.2 | G101: Formel | H101: (eig_g_mut+eig_g_willenskraft+eig_k_konstitution+eig_k_staerke+sf_selbstbeherrschung)/7+att_vitalitaet+12 | J101: Formel referenzierte 'att_vitalität' (alte Umlautschreibweise) statt der aktuellen Referenz 'att_vitalitaet' - korrigiert. | Formel referenzierte veraltete Gro�-/Kleinschreibung (sf_Selbstbeherrschung) - an aktuelle (kleingeschriebene) Referenz angepasst.
A102: fk_basis_blasrohre | B102: Fernkampf | C102: Fernkampf-Basis-Wert Blasrohre | G102: Formel | H102: (eig_g_sinneschaerfe+eig_k_geschicklichkeit+fk_blasrohre)/4 | J102: Formel referenzierte veraltete Gro�-/Kleinschreibung (fk_blasrohre) - an aktuelle (kleingeschriebene) Referenz angepasst.
A103: fk_basis_spez_blasrohre_blasrohre | B103: Fernkampf | C103: Fernkampf-Spezialisierungs-Wert Blasrohre | G103: Formel | H103: (eig_g_sinneschaerfe+eig_k_geschicklichkeit+fk_blasrohre+fk_spez_blasrohre_blasrohre)/4 | J103: Formel referenzierte veraltete Gro�-/Kleinschreibung (fk_spez_Blasrohre_blasrohre, fk_blasrohre) - an aktuelle (kleingeschriebene) Referenz angepasst.
A104: aw_def_normal | B104: Kampf | C104: Defensives Ausweichen | D104: def. nAW | E104: S.2 | G104: Formel | H104: (eig_k_athletik+eig_k_schnelligkeit+att_glueck+sf_ausweichen)/5+6-gewichtsbelastung | J104: Formel referenzierte veraltete Gro�-/Kleinschreibung (Gewichtsbelastung, sf_Ausweichen) - an aktuelle (kleingeschriebene) Referenz angepasst.
A105: aw_off_normal | B105: Kampf | C105: Offensives Ausweichen | D105: off. nAW | E105: S.2 | G105: Formel | H105: (eig_k_athletik+eig_k_schnelligkeit+att_glueck+sf_ausweichen)/5+2-gewichtsbelastung | J105: Formel referenzierte veraltete Gro�-/Kleinschreibung (Gewichtsbelastung, sf_Ausweichen) - an aktuelle (kleingeschriebene) Referenz angepasst.
A106: aw_gut | B106: Kampf | C106: Gutes Ausweichen | D106: gAW | E106: S.2 | G106: Formel | H106: (eig_bonus_k_athletik+sf_gutes_aw)/5+1 | J106: Formel referenzierte veraltete Gro�-/Kleinschreibung (sf_Gutes_AW) - an aktuelle (kleingeschriebene) Referenz angepasst.
A107: mana | B107: Charakterwerte | C107: Mana | E107: S.1 | G107: Formel | H107: att_aura*7+att_magie*3+3*eig_g_willenskraft-30+eig_bonus_g_intelligenz*att_weisheit+stufe+sf_mana_talent*2 | J107: Formel referenzierte veraltete Gro�-/Kleinschreibung (sf_Mana_Talent) - an aktuelle (kleingeschriebene) Referenz angepasst.
A108: aw_meisterlich | B108: Kampf | C108: Meisterliches Ausweichen | D108: mAW | E108: S.2 | G108: Formel | H108: (eig_bonus_k_schnelligkeit+sf_meisterliches_ausweichen)/5+21 | J108: Formel referenzierte veraltete Gro�-/Kleinschreibung (sf_Meisterliches_ausweichen) - an aktuelle (kleingeschriebene) Referenz angepasst.
A109: gbe_ausgeruestet | B109: Gewichtsbelastung | C109: Ausgerüstet | G109: Formel | H109: eig_k_staerke+sf_tragen*1,5 | J109: Formel referenzierte veraltete Gro�-/Kleinschreibung (sf_Tragen) - an aktuelle (kleingeschriebene) Referenz angepasst.
A110: gbe_leichtes_marschgepaeck | B110: Gewichtsbelastung | C110: Leichtes Marschgepäck | G110: Formel | H110: eig_k_staerke+sf_tragen*3 | J110: Formel referenzierte veraltete Gro�-/Kleinschreibung (sf_Tragen) - an aktuelle (kleingeschriebene) Referenz angepasst.
A111: gbe_max_hebelast | B111: Gewichtsbelastung | C111: max. Hebelast | G111: Formel | H111: eig_k_staerke+sf_tragen*15 | J111: Formel referenzierte veraltete Gro�-/Kleinschreibung (sf_Tragen) - an aktuelle (kleingeschriebene) Referenz angepasst.
A112: gbe_mittel_ueberladen | B112: Gewichtsbelastung | C112: Mittel Überladen | G112: Formel | H112: eig_k_staerke+sf_tragen*7 | J112: Formel referenzierte veraltete Gro�-/Kleinschreibung (sf_Tragen) - an aktuelle (kleingeschriebene) Referenz angepasst.
A113: gbe_schwer_schleppend | B113: Gewichtsbelastung | C113: Schwer schleppend | G113: Formel | H113: eig_k_staerke+sf_tragen*11 | J113: Formel referenzierte veraltete Gro�-/Kleinschreibung (sf_Tragen) - an aktuelle (kleingeschriebene) Referenz angepasst.
A114: gbe_schweres_marschgepaeck | B114: Gewichtsbelastung | C114: Schweres Marschgepäck | G114: Formel | H114: eig_k_staerke+sf_tragen*5 | J114: Formel referenzierte veraltete Gro�-/Kleinschreibung (sf_Tragen) - an aktuelle (kleingeschriebene) Referenz angepasst.
A115: gbe_unbelastet | B115: Gewichtsbelastung | C115: Unbelastet | G115: Formel | H115: eig_k_staerke+sf_tragen*0,5 | J115: Formel referenzierte veraltete Gro�-/Kleinschreibung (sf_Tragen) - an aktuelle (kleingeschriebene) Referenz angepasst.
A116: fk_gute_spez_schusswaffen_armbrueste | B116: Fernkampf | C116: Fernkampf-Spezialisierungs-Gute-Wert Armbrust | E116: Diese Formel geht von der VOLLSTAENDIGEN Probe aus (Basiswert + Waffen-Modifikator + Entfernungs-Modifikator, siehe Waffentabellen z.B. NN_Feuerwaffen_1.1.xlsx). Die Berechnung dieser vollstaendigen Probe sowie die Sonderregel bei Probe<=0 (nur Meisterlich=normaler Treffer bzw. Froehlich=guter Treffer moeglich) gehoeren ins zukuenftige Kampfmodul, nicht in den Charakterbogen - hier steht nur der Basismechanismus. | G116: Formel | H116: WENN(talente_fernkampfgeschick_stufe_2>0;1+AUFRUNDEN(fk_basis_spez_schusswaffen_armbrueste/3;0);WENN(talente_fernkampfgeschick_stufe_1>0;1+AUFRUNDEN(fk_basis_spez_schusswaffen_armbrueste/4;0);1)) | J116: Gleiches Muster wie fk_gute_* (Basiswaffe), nur auf den Spezialisierungs-Basiswert angewandt - Nutzerbestaetigung: 'Spezialisierungen sollten als simples +Spez in der /4 Formel gefuehrt sein'.
A117: fk_gute_spez_blasrohre_blasrohre | B117: Fernkampf | C117: Fernkampf-Spezialisierungs-Gute-Wert Blasrohre | E117: Diese Formel geht von der VOLLSTAENDIGEN Probe aus (Basiswert + Waffen-Modifikator + Entfernungs-Modifikator, siehe Waffentabellen z.B. NN_Feuerwaffen_1.1.xlsx). Die Berechnung dieser vollstaendigen Probe sowie die Sonderregel bei Probe<=0 (nur Meisterlich=normaler Treffer bzw. Froehlich=guter Treffer moeglich) gehoeren ins zukuenftige Kampfmodul, nicht in den Charakterbogen - hier steht nur der Basismechanismus. | G117: Formel | H117: WENN(talente_fernkampfgeschick_stufe_2>0;1+AUFRUNDEN(fk_basis_spez_blasrohre_blasrohre/3;0);WENN(talente_fernkampfgeschick_stufe_1>0;1+AUFRUNDEN(fk_basis_spez_blasrohre_blasrohre/4;0);1)) | J117: Gleiches Muster wie fk_gute_* (Basiswaffe), nur auf den Spezialisierungs-Basiswert angewandt - Nutzerbestaetigung: 'Spezialisierungen sollten als simples +Spez in der /4 Formel gefuehrt sein'.
A118: fk_gute_spez_feuerwaffen_musketen | B118: Fernkampf | C118: Fernkampf-Spezialisierungs-Gute-Wert Musketen | E118: Diese Formel geht von der VOLLSTAENDIGEN Probe aus (Basiswert + Waffen-Modifikator + Entfernungs-Modifikator, siehe Waffentabellen z.B. NN_Feuerwaffen_1.1.xlsx). Die Berechnung dieser vollstaendigen Probe sowie die Sonderregel bei Probe<=0 (nur Meisterlich=normaler Treffer bzw. Froehlich=guter Treffer moeglich) gehoeren ins zukuenftige Kampfmodul, nicht in den Charakterbogen - hier steht nur der Basismechanismus. | G118: Formel | H118: WENN(talente_fernkampfgeschick_stufe_2>0;1+AUFRUNDEN(fk_basis_spez_feuerwaffen_musketen/3;0);WENN(talente_fernkampfgeschick_stufe_1>0;1+AUFRUNDEN(fk_basis_spez_feuerwaffen_musketen/4;0);1)) | J118: Gleiches Muster wie fk_gute_* (Basiswaffe), nur auf den Spezialisierungs-Basiswert angewandt - Nutzerbestaetigung: 'Spezialisierungen sollten als simples +Spez in der /4 Formel gefuehrt sein'.
A119: fk_gute_spez_feuerwaffen_pistolen | B119: Fernkampf | C119: Fernkampf-Spezialisierungs-Gute-Wert Pistolen | E119: Diese Formel geht von der VOLLSTAENDIGEN Probe aus (Basiswert + Waffen-Modifikator + Entfernungs-Modifikator, siehe Waffentabellen z.B. NN_Feuerwaffen_1.1.xlsx). Die Berechnung dieser vollstaendigen Probe sowie die Sonderregel bei Probe<=0 (nur Meisterlich=normaler Treffer bzw. Froehlich=guter Treffer moeglich) gehoeren ins zukuenftige Kampfmodul, nicht in den Charakterbogen - hier steht nur der Basismechanismus. | G119: Formel | H119: WENN(talente_fernkampfgeschick_stufe_2>0;1+AUFRUNDEN(fk_basis_spez_feuerwaffen_pistolen/3;0);WENN(talente_fernkampfgeschick_stufe_1>0;1+AUFRUNDEN(fk_basis_spez_feuerwaffen_pistolen/4;0);1)) | J119: Gleiches Muster wie fk_gute_* (Basiswaffe), nur auf den Spezialisierungs-Basiswert angewandt - Nutzerbestaetigung: 'Spezialisierungen sollten als simples +Spez in der /4 Formel gefuehrt sein'.
A120: fk_gute_spez_boegen_boegen | B120: Fernkampf | C120: Fernkampf-Spezialisierungs-Gute-Wert Bögen | E120: Diese Formel geht von der VOLLSTAENDIGEN Probe aus (Basiswert + Waffen-Modifikator + Entfernungs-Modifikator, siehe Waffentabellen z.B. NN_Feuerwaffen_1.1.xlsx). Die Berechnung dieser vollstaendigen Probe sowie die Sonderregel bei Probe<=0 (nur Meisterlich=normaler Treffer bzw. Froehlich=guter Treffer moeglich) gehoeren ins zukuenftige Kampfmodul, nicht in den Charakterbogen - hier steht nur der Basismechanismus. | G120: Formel | H120: WENN(talente_fernkampfgeschick_stufe_2>0;1+AUFRUNDEN(fk_basis_spez_boegen_boegen/3;0);WENN(talente_fernkampfgeschick_stufe_1>0;1+AUFRUNDEN(fk_basis_spez_boegen_boegen/4;0);1)) | J120: Gleiches Muster wie fk_gute_* (Basiswaffe), nur auf den Spezialisierungs-Basiswert angewandt - Nutzerbestaetigung: 'Spezialisierungen sollten als simples +Spez in der /4 Formel gefuehrt sein'.
A121: fk_meisterlich_spez_schusswaffen_armbrueste | B121: Fernkampf | C121: Fernkampf-Spezialisierungs-Meisterliche-Wert Armbrust | E121: Diese Formel geht von der VOLLSTAENDIGEN Probe aus (Basiswert + Waffen-Modifikator + Entfernungs-Modifikator, siehe Waffentabellen z.B. NN_Feuerwaffen_1.1.xlsx). Die Berechnung dieser vollstaendigen Probe sowie die Sonderregel bei Probe<=0 (nur Meisterlich=normaler Treffer bzw. Froehlich=guter Treffer moeglich) gehoeren ins zukuenftige Kampfmodul, nicht in den Charakterbogen - hier steht nur der Basismechanismus. | G121: Formel | H121: WENN(talente_fernkampfgeschick_stufe_3>0;21+AUFRUNDEN(fk_basis_spez_schusswaffen_armbrueste/20;0);21) | J121: Gleiches Muster wie fk_meisterlich_* (Basiswaffe), nur auf den Spezialisierungs-Basiswert angewandt.
A122: fk_meisterlich_spez_blasrohre_blasrohre | B122: Fernkampf | C122: Fernkampf-Spezialisierungs-Meisterliche-Wert Blasrohre | E122: Diese Formel geht von der VOLLSTAENDIGEN Probe aus (Basiswert + Waffen-Modifikator + Entfernungs-Modifikator, siehe Waffentabellen z.B. NN_Feuerwaffen_1.1.xlsx). Die Berechnung dieser vollstaendigen Probe sowie die Sonderregel bei Probe<=0 (nur Meisterlich=normaler Treffer bzw. Froehlich=guter Treffer moeglich) gehoeren ins zukuenftige Kampfmodul, nicht in den Charakterbogen - hier steht nur der Basismechanismus. | G122: Formel | H122: WENN(talente_fernkampfgeschick_stufe_3>0;21+AUFRUNDEN(fk_basis_spez_blasrohre_blasrohre/20;0);21) | J122: Gleiches Muster wie fk_meisterlich_* (Basiswaffe), nur auf den Spezialisierungs-Basiswert angewandt.
A123: fk_meisterlich_spez_feuerwaffen_musketen | B123: Fernkampf | C123: Fernkampf-Spezialisierungs-Meisterliche-Wert Musketen | E123: Diese Formel geht von der VOLLSTAENDIGEN Probe aus (Basiswert + Waffen-Modifikator + Entfernungs-Modifikator, siehe Waffentabellen z.B. NN_Feuerwaffen_1.1.xlsx). Die Berechnung dieser vollstaendigen Probe sowie die Sonderregel bei Probe<=0 (nur Meisterlich=normaler Treffer bzw. Froehlich=guter Treffer moeglich) gehoeren ins zukuenftige Kampfmodul, nicht in den Charakterbogen - hier steht nur der Basismechanismus. | G123: Formel | H123: WENN(talente_fernkampfgeschick_stufe_3>0;21+AUFRUNDEN(fk_basis_spez_feuerwaffen_musketen/20;0);21) | J123: Gleiches Muster wie fk_meisterlich_* (Basiswaffe), nur auf den Spezialisierungs-Basiswert angewandt.
A124: fk_meisterlich_spez_feuerwaffen_pistolen | B124: Fernkampf | C124: Fernkampf-Spezialisierungs-Meisterliche-Wert Pistolen | E124: Diese Formel geht von der VOLLSTAENDIGEN Probe aus (Basiswert + Waffen-Modifikator + Entfernungs-Modifikator, siehe Waffentabellen z.B. NN_Feuerwaffen_1.1.xlsx). Die Berechnung dieser vollstaendigen Probe sowie die Sonderregel bei Probe<=0 (nur Meisterlich=normaler Treffer bzw. Froehlich=guter Treffer moeglich) gehoeren ins zukuenftige Kampfmodul, nicht in den Charakterbogen - hier steht nur der Basismechanismus. | G124: Formel | H124: WENN(talente_fernkampfgeschick_stufe_3>0;21+AUFRUNDEN(fk_basis_spez_feuerwaffen_pistolen/20;0);21) | J124: Gleiches Muster wie fk_meisterlich_* (Basiswaffe), nur auf den Spezialisierungs-Basiswert angewandt.
A125: fk_meisterlich_spez_boegen_boegen | B125: Fernkampf | C125: Fernkampf-Spezialisierungs-Meisterliche-Wert Bögen | E125: Diese Formel geht von der VOLLSTAENDIGEN Probe aus (Basiswert + Waffen-Modifikator + Entfernungs-Modifikator, siehe Waffentabellen z.B. NN_Feuerwaffen_1.1.xlsx). Die Berechnung dieser vollstaendigen Probe sowie die Sonderregel bei Probe<=0 (nur Meisterlich=normaler Treffer bzw. Froehlich=guter Treffer moeglich) gehoeren ins zukuenftige Kampfmodul, nicht in den Charakterbogen - hier steht nur der Basismechanismus. | G125: Formel | H125: WENN(talente_fernkampfgeschick_stufe_3>0;21+AUFRUNDEN(fk_basis_spez_boegen_boegen/20;0);21) | J125: Gleiches Muster wie fk_meisterlich_* (Basiswaffe), nur auf den Spezialisierungs-Basiswert angewandt.
A126: rs_arme | B126: Kampf | C126: Rüstungsschutz Arme | E126: S.2 | G126: Formel | H126: SUMME(RS der 5 Ruestungslagen in Zone arme) | J126: Jede Koerperzone hat 5 Lagen (Stoff/Leder/Kette/Platte/Addon, siehe Sheets Ruestung-Basis/-Verarbeitung/-Anpassung/-Addons), deren RS sich aufaddieren (Nutzerangabe 2026-07-16, bestaetigt durch das Beispiel-Set in Sheet Ruestungstabelle: Kopf RS = 3+4+6+6+0 = 19). Einzel-Lagen-RS = RS-Basis(Ruestungsteil) + RS-Mod(Verarbeitung) [Anpassung wirkt nie auf RS, siehe Ruestung-Basis-Formel]. Welche Ruestung pro Lage/Zone gewaehlt ist, ist noch keine Referenz in diesem Sheet (keine Auswahl-Mechanik vorhanden) - Aufloesung der SUMME(...) obliegt der App/Charakterbogen-Logik, siehe Entwickeln.
A127: rs_beine | B127: Kampf | C127: Rüstungsschutz Beine | E127: S.2 | G127: Formel | H127: SUMME(RS der 5 Ruestungslagen in Zone beine) | J127: Jede Koerperzone hat 5 Lagen (Stoff/Leder/Kette/Platte/Addon, siehe Sheets Ruestung-Basis/-Verarbeitung/-Anpassung/-Addons), deren RS sich aufaddieren (Nutzerangabe 2026-07-16, bestaetigt durch das Beispiel-Set in Sheet Ruestungstabelle: Kopf RS = 3+4+6+6+0 = 19). Einzel-Lagen-RS = RS-Basis(Ruestungsteil) + RS-Mod(Verarbeitung) [Anpassung wirkt nie auf RS, siehe Ruestung-Basis-Formel]. Welche Ruestung pro Lage/Zone gewaehlt ist, ist noch keine Referenz in diesem Sheet (keine Auswahl-Mechanik vorhanden) - Aufloesung der SUMME(...) obliegt der App/Charakterbogen-Logik, siehe Entwickeln.
... A129: rs_torso | B129: Kampf | C129: Rüstungsschutz Torso | E129: S.2 | G129: Formel | H129: SUMME(RS der 5 Ruestungslagen in Zone torso) | J129: Jede Koerperzone hat 5 Lagen (Stoff/Leder/Kette/Platte/Addon, siehe Sheets Ruestung-Basis/-Verarbeitung/-Anpassung/-Addons), deren RS sich aufaddieren (Nutzerangabe 2026-07-16, bestaetigt durch das Beispiel-Set in Sheet Ruestungstabelle: Kopf RS = 3+4+6+6+0 = 19). Einzel-Lagen-RS = RS-Basis(Ruestungsteil) + RS-Mod(Verarbeitung) [Anpassung wirkt nie auf RS, siehe Ruestung-Basis-Formel]. Welche Ruestung pro Lage/Zone gewaehlt ist, ist noch keine Referenz in diesem Sheet (keine Auswahl-Mechanik vorhanden) - Aufloesung der SUMME(...) obliegt der App/Charakterbogen-Logik, siehe Entwickeln.
A130: talente_gefahrensinn | B130: Talente | C130: Gefahrensinn | F130: Abenteurer | G130: Auswahl | J130: Kein exakter Namenstreffer in NN NPC-Rechner 0.75/Talente - dort heißt das Talent 'Gefahreninstinkt' (Kategorie=Abenteurer). Vermutlich dasselbe Talent unter leicht anderem Namen, Parent trotzdem gesetzt. | L130: 2 | Q130: Erhöht das Maximum der Sonderfertigkeit "Gefahreninstinkt" um 6 Punkte.
A131: bewegung_f_leiter_steigen_schnell | B131: Bewegung | C131: Leiter steigen schnell | E131: Meisterscreen S.3 | G131: Formel | H131: FEHLT | J131: kein Formeltext vorhanden
A132: bewegung_f_seil_hochklettern | B132: Bewegung | C132: Seil hochklettern | E132: Meisterscreen S.3 | G132: Formel | H132: FEHLT | J132: kein Formeltext vorhanden
A133: f_gefahreninstinkt | B133: Charakterwerte | C133: Gefahreninstinkt | D133: GI | E133: S.2 | G133: Formel | H133: eig_g_sinneschaerfe+sf_gefahreninstinkt | J133: kein Formeltext vorhanden | Formel = Sinnesschaerfe + SF Gefahreninstinkt (Nutzerangabe 2026-07-16). Einfache Probe, Probenwert = diese Formel, kann vom Meister situativ erschwert werden. Standard-Offsets fuer evtl. spaetere Gute/Meisterliche-Varianten waeren 1 bzw. 21 (Systemstandard, siehe aw_gut/aw_meisterlich), hier aber keine Sonderwerte noetig.
A134: bewegung_f_lesegeschwindigkeit | B134: Bewegung | C134: Lesegeschwindigkeit (Wörter/min) | E134: Meisterscreen S.3 | G134: Formel | H134: FEHLT | J134: kein Formeltext vorhanden | Referenz (Spalte G) enthält Klammern und Schrägstrich '(.../...)' unverändert aus der Beschreibung übernommen.
A135: ep_verbraucht | B135: Charakterwerte | C135: Verbrauchte EP | E135: S.1 | G135: Formel | H135: SUMME(Kosten aller gewaehlten Werte) | J135: Kein normaler Zeilen-Verweis wie sonst ueblich, sondern eine Summe UEBER DEN GESAMTEN Charakterbogen: alle Kosten-Werte jeder Zeile, die der Spieler tatsaechlich gewaehlt/erhoeht hat (Eigenschaften, Attribute, Grundfertigkeiten, Talente, Vor-/Nachteile, Spruchmagie, ...). Muss von der App als aggregierte Summe berechnet werden, nicht als einzelne Referenz aufloesbar.
A136: startbudget_ausruestung | B136: Charakterwerte | C136: Startbudget Ausruestung | E136: In Dublonen. 1 Dublone = 1000 Fuffzisch. Meister kann Kosten mit % anpassen (App-Verhalten, nicht Formel). | G136: Fixwert | H136: 5000 | J136: KORRIGIERT 2026-07-16 (Nutzerangabe): 5000 Dublonen Startbudget fuer Ausruestung bei Erschaffung (vorher faelschlich 4000 eingetragen).
A137: gr_betoeren | B137: Grundfertigkeit | C137: Betören | E137: Geistige Grundfertigkeiten: Betören steht für die Fähigkeit, jemand anderem zu imponieren, es zu verführen oder sich einzuschmeicheln. Dies kann gegebenenfalls ausgenutzt werden, um eine Person zu beeinflussen. | G137: Wert | J137: Kosten = statisch 9 EP/Punkt (Nutzerangabe). | L137: wert*9
A138: gr_einschuechtern | B138: Grundfertigkeit | C138: Einschüchtern | E138: Geistige Grundfertigkeiten: Einschüchtern ist die Fähigkeit, andere auf subtile Art einzuschüchtern, Angst zu machen, über das Ausmaß an Furcht hinaus, für das es einen objektiven Grund gibt. | G138: Wert | J138: Kosten = statisch 9 EP/Punkt (Nutzerangabe). | L138: wert*9
A139: gr_faehrtensuche | B139: Grundfertigkeit | C139: Fährtensuche | E139: Geistige Grundfertigkeiten: Fährtensuche ist die Fähigkeit, Fährten oder Spuren, die durch Wesen verursacht wurden, aufzufinden. Das Analysieren dieser Spuren geschieht mit der WHK-Fertigkeit Spuren Lesen. | G139: Wert | J139: Kosten = statisch 9 EP/Punkt (Nutzerangabe). | L139: wert*9
A140: gr_fliegen | B140: Grundfertigkeit | C140: Fliegen | E140: Körperliche Grundfertigkeiten: Fliegen beschreibt die Fähigkeit eines Charakters, selbst zu fliegen (sofern er einen Weg dazu beherrscht), oder sich auf einem lebenden Reitflugtier zu halten und es so gut es geht zu steuern, oder sich auf einem fliegenden Magiekorpus zu halten. Große Flugobjekte wie Luftschiffe werden hingegen über die WHK-Fertigkeit Luftschifffahrt gesteuert. | G140: Wert | J140: Kosten = statisch 9 EP/Punkt (Nutzerangabe). | L140: wert*9
A141: gr_klettern | B141: Grundfertigkeit | C141: Klettern | E141: Körperliche Grundfertigkeiten: Klettern kommt zum Tragen, wenn der Charakter in irgendeiner Form klettert und darauf eine Grundfertigkeits-Probe ablegen muss. | G141: Wert | J141: Kosten = statisch 9 EP/Punkt (Nutzerangabe). | L141: wert*9
A142: gr_koerperbeherrschung | B142: Grundfertigkeit | C142: Körperbeherrschung | D142: KB | E142: Körperliche Grundfertigkeiten: Körperbeherrschung ist die Fähigkeit eines Charakters, sich abzurollen, die Balance zu halten, nach einem Sturz aufzustehen und ähnliches. Außerdem zählt Körperbeherrschung zum Probenwert bei einer Ath-Probe wegen eines Sturzes laut Patzer-Tabelle oder SB-Tabelle. | G142: Wert | J142: Kosten = statisch 9 EP/Punkt (Nutzerangabe). | L142: wert*9
A143: gr_laufen | B143: Grundfertigkeit | C143: Laufen | E143: Körperliche Grundfertigkeiten: Laufen ist die Fähigkeit eines Charakters, schneller zu laufen. Dazu wird die Fertigkeit Laufen in die Formeln für Sprinten und Dauerlauf eingerechnet. | G143: Wert | J143: Kosten = statisch 9 EP/Punkt (Nutzerangabe). | L143: wert*9
A144: gr_luft_anhalten | B144: Grundfertigkeit | C144: Luft anhalten | E144: Körperliche Grundfertigkeiten: Luft anhalten beschreibt die Fähigkeit des Helden, über längere Zeit ohne Frischluftzufuhr auszukommen. | G144: Wert | J144: Kosten = statisch 9 EP/Punkt (Nutzerangabe). | L144: wert*9
A145: gr_luegen | B145: Grundfertigkeit | C145: Lügen | E145: Geistige Grundfertigkeiten: Lügen ist die Fähigkeit, glaubwürdig die Unwahrheit zu sagen. | G145: Wert | J145: Kosten = statisch 9 EP/Punkt (Nutzerangabe). | L145: wert*9
A146: gr_menschenkenntnis | B146: Grundfertigkeit | C146: Menschenkenntnis | E146: Geistige Grundfertigkeiten: Menschenkenntnis ist die Fähigkeit, einzelne Personen oder sogar Gruppen zu lesen und kleine Feinheiten in ihrem Verhalten wahrzunehmen, die es erlauben, Beeinflussungsversuche, Lügen und ähnliches zu durchschauen. | G146: Wert | J146: Kosten = statisch 9 EP/Punkt (Nutzerangabe). | L146: wert*9
A147: gr_orientierung | B147: Grundfertigkeit | C147: Orientierung | E147: Geistige Grundfertigkeiten: Orientierung beschreibt die Fähigkeit, sich die Umgebung gut einzuprägen, kleine Details wahrzunehmen, die bei der Navigation helfen, sich intuitiv zu orientieren. | G147: Wert | J147: Kosten = statisch 9 EP/Punkt (Nutzerangabe). | L147: wert*9
A148: gr_reiten | B148: Grundfertigkeit | C148: Reiten | E148: Körperliche Grundfertigkeiten: Reiten erhöht die Sicherheit, mit der der Charakter im Sattel sitzt, und verbessert seine Fähigkeit, das Reittier zu lenken. Besondere andressierte Aktionen wie Springen, Kampfmanöver reiten, kontrolliertes Hochsteigen, still zu sein oder ohne Reiter auf Kommandos zu hören erfordern allerdings die WHK-Fertigkeiten Abrichten. Reiten als Grundfertigkeit ist das rein körperliche Reiten, ohne Dressur, Kunststücke, besondere Kontrolle etc. Die Reiten-Werte der Charaktere sollten dem Meister vor einer längeren Reise mitgeteilt werden, damit er die Erschöpfung und eventuelle Missgeschicke beschreiben kann. | G148: Wert | J148: Kosten = statisch 9 EP/Punkt (Nutzerangabe). | L148: wert*9
A149: gr_rudern | B149: Grundfertigkeit | C149: Rudern | E149: Körperliche Grundfertigkeiten: Rudern zählt zum Probenwert hinzu, wenn eine Probe abgelegt wird, um ein Wasserfahrzeug in irgendeiner Form zu rudern. | G149: Wert | J149: Kosten = statisch 9 EP/Punkt (Nutzerangabe). | L149: wert*9
A150: gr_schaetzen | B150: Grundfertigkeit | C150: Schätzen | E150: Geistige Grundfertigkeiten: Schätzen beschreibt die Fähigkeit, Distanzen, Gewichte, Höhen etc. ohne Hilfsmittel einzuschätzen. Für den Geldwert von Waren benötigt man außerdem die passende WHK. | G150: Wert | J150: Kosten = statisch 9 EP/Punkt (Nutzerangabe). | L150: wert*9
A151: gr_schleichen | B151: Grundfertigkeit | C151: Schleichen | E151: Körperliche Grundfertigkeiten: Schleichen ermöglicht es, bei der Fortbewegung weitestgehend lautlos zu sein. | G151: Wert | J151: Kosten = statisch 9 EP/Punkt (Nutzerangabe). | L151: wert*9
A152: gr_schwimmen | B152: Grundfertigkeit | C152: Schwimmen | E152: Körperliche Grundfertigkeiten: Schwimmen erhöht die Sicherheit und Geschwindigkeit der Bewegung des Charakters in Flüssigkeiten. Ein Charakter mit Schwimmen 0 kann auch Schwimmen, wenn die Eigenchaft+SchwimmenProbe gelingt. | G152: Wert | J152: Kosten = statisch 9 EP/Punkt (Nutzerangabe). | L152: wert*9
A153: gr_springen | B153: Grundfertigkeit | C153: Springen | E153: Körperliche Grundfertigkeiten: Springen: Diese Fertigkeit beschreibt die Fähigkeit, besonders weit oder hoch zu springen. | G153: Wert | J153: Kosten = statisch 9 EP/Punkt (Nutzerangabe). | L153: wert*9
A154: gr_ueberzeugen | B154: Grundfertigkeit | C154: Überzeugen | E154: Geistige Grundfertigkeiten: Überzeugen steht für die Fähigkeit, jemand andere überzeugend klar zu machen, dass die vertretene Position die richtige ist. | G154: Wert | J154: Kosten = statisch 9 EP/Punkt (Nutzerangabe). | L154: wert*9
... A156: gr_werfen | B156: Grundfertigkeit | C156: Werfen | E156: Körperliche Grundfertigkeiten: Werfen beschreibt die Fähigkeit, Dinge nicht nur wegzuschleudern, sondern gezielt durch die Luft an den gewünschten Ort zu befördern. Werfen zählt zusätzlich als Bonus auf Stärke (bzw. Schnelligkeit beim Wurfspeer) in die Wurfweiten-Formeln ein. | G156: Wert | J156: Kosten = statisch 9 EP/Punkt (Nutzerangabe). | L156: wert*9
A157: psi_deformation | B157: PSI | C157: Deformation | E157: Zauberwert (zur Laufzeit, nicht Charaktererstellung) = wert + [Eig-Bonus] + att_aura + att_magie - Erschwerung(gewaehlte Stufe). Erschwerung, MbS und Wirkung je Stufe sowie die übrigen Referenzwerte siehe Sheet 'PSI-Zauberstufen'. Quelle: PSI_Magie_Zaubertabelle_1_421.xlsx. Basis-Maximum=24, durch Talente 'PSI Psinetik Stufe 1/2/3' um +6/+12/+18 erhoehbar (max. 42). | F157: psi_hoehere_telekinese | G157: Wert | J157: Kosten = statisch 9 EP/Punkt (Nutzerangabe). | L157: wert*9 | O157: 10 | P157: eig_bonus_k_staerke
A158: psi_destruktion | B158: PSI | C158: Destruktion | E158: Zauberwert (zur Laufzeit, nicht Charaktererstellung) = wert + [Eig-Bonus] + att_aura + att_magie - Erschwerung(gewaehlte Stufe). Erschwerung, MbS und Wirkung je Stufe sowie die übrigen Referenzwerte siehe Sheet 'PSI-Zauberstufen'. Quelle: PSI_Magie_Zaubertabelle_1_421.xlsx. Basis-Maximum=24, durch Talente 'PSI Psinetik Stufe 1/2/3' um +6/+12/+18 erhoehbar (max. 42). | F158: psi_pyrokinese | G158: Wert | J158: Kosten = statisch 9 EP/Punkt (Nutzerangabe). | L158: wert*9 | O158: 15 | P158: eig_bonus_g_willenskraft
A159: psi_geschosse_ablenken | B159: PSI | C159: Geschosse ablenken | E159: Zauberwert (zur Laufzeit, nicht Charaktererstellung) = wert + [Eig-Bonus] + att_aura + att_magie - Erschwerung(gewaehlte Stufe). Erschwerung, MbS und Wirkung je Stufe sowie die übrigen Referenzwerte siehe Sheet 'PSI-Zauberstufen'. Quelle: PSI_Magie_Zaubertabelle_1_421.xlsx. Basis-Maximum=24, durch Talente 'PSI Psinetik Stufe 1/2/3' um +6/+12/+18 erhoehbar (max. 42). | F159: psi_deformation | G159: Wert | J159: Kosten = statisch 9 EP/Punkt (Nutzerangabe). | L159: wert*9 | O159: 10 | P159: eig_bonus_k_schnelligkeit
...

Sheet EP-Stufe-Kreis
A1: EP ab | B1: Stufe | C1: Kreis
A2: 0 | B2: 0 | C2: 0
A3: 20 | B3: 1 | C3: 1
A4: 60 | B4: 2 | C4: 1
A5: 120 | B5: 3 | C5: 1
A6: 200 | B6: 4 | C6: 2
A7: 300 | B7: 5 | C7: 2
A8: 400 | B8: 6 | C8: 2
A9: 500 | B9: 7 | C9: 2
A10: 600 | B10: 8 | C10: 2
A11: 700 | B11: 9 | C11: 3
A12: 850 | B12: 10 | C12: 3
A13: 1000 | B13: 11 | C13: 3
... A65: 15150 | B65: 63 | C65: 7

Sheet WHK-Spez-Kosten
A1: Wert | B1: EP-Kosten (Schritt) | C1: Gesamt-EP
A2: 0 | B2: 0 | C2: 0
A3: 1 | B3: 4 | C3: 4
A4: 2 | B4: 1 | C4: 5
A5: 3 | B5: 1 | C5: 6
A6: 4 | B6: 1 | C6: 7
A7: 5 | B7: 2 | C7: 9
A8: 6 | B8: 2 | C8: 11
A9: 7 | B9: 2 | C9: 13
A10: 8 | B10: 3 | C10: 16
A11: 9 | B11: 3 | C11: 19
A12: 10 | B12: 3 | C12: 22
A13: 11 | B13: 4 | C13: 26
... A41: 39 | B41: 13 | C41: 264

Sheet Eigenschaften-Kosten
A1: Wert | B1: Gesamt-EP | C1: EP-Kosten (Schritt)
A2: 0 | B2: 0 | C2: 0
A3: 1 | B3: 30 | C3: 30
A4: 2 | B4: 60 | C4: 30
A5: 3 | B5: 90 | C5: 30
A6: 4 | B6: 120 | C6: 30
A7: 5 | B7: 150 | C7: 30
A8: 6 | B8: 180 | C8: 30
A9: 7 | B9: 210 | C9: 30
A10: 8 | B10: 240 | C10: 30
A11: 9 | B11: 270 | C11: 30
A12: 10 | B12: 300 | C12: 30
A13: 11 | B13: 330 | C13: 30
... A66: 64 | B66: 6213 | C66: 189

Sheet Voelker-Maxima
A1: Volk | B1: Eigenschaft | C1: Erstellungs-Min | D1: Erstellungs-Max | E1: Max (ab Kreis 3)
A2: Dalkini | B2: Ausstrahlung | C2: 9 | D2: 21 | E2: 31
A3: Dalkini | B3: Intelligenz | C3: 9 | D3: 21 | E3: 31
A4: Dalkini | B4: Mut | C4: 10 | D4: 22 | E4: 31
A5: Dalkini | B5: Sinnesschaerfe | C5: 9 | D5: 21 | E5: 31
A6: Dalkini | B6: Willenskraft | C6: 15 | D6: 27 | E6: 31
A7: Dalkini | B7: Athletik | C7: 10 | D7: 22 | E7: 31
A8: Dalkini | B8: Geschicklichkeit | C8: 10 | D8: 22 | E8: 31
A9: Dalkini | B9: Konstitution | C9: 11 | D9: 23 | E9: 31
A10: Dalkini | B10: Schnelligkeit | C10: 10 | D10: 22 | E10: 31
A11: Dalkini | B11: Staerke | C11: 11 | D11: 23 | E11: 31
A12: Draw | B12: Ausstrahlung | C12: 11 | D12: 23 | E12: 31
A13: Draw | B13: Intelligenz | C13: 12 | D13: 24 | E13: 31
... A111: Zwerge | B111: Staerke | C111: 12 | D111: 24 | E111: 31

Sheet PSI-Zauberstufen
A1: Referenz | B1: Stufe | C1: Erschwerung | D1: MbS | E1: Wirkung | F1: Name | G1: Regeltext | H1: Aurabann | I1: Ziel | J1: Eig. | K1: RW | L1: VD | M1: ED | N1: W.dauer | O1: Erholungszeit EZ in KR | P1: MpZ | Q1: Quelle
A2: psi_telekinetisches_geschoss | B2: 1 | C2: 3 | D2: 10 | E2: W4 | F2: Telekinetisches Geschoss | G2: SP verteilt auf 3 TZ, Opfer wird um SP/2m zurückgeworfen. Körperbeherrschung+Athletik-Probe, um nicht zu stürzen. Auch Gegenstände werden zurückgeworfen. | H2: Kein Aurabann | I2: Aura | J2: Will | K2: (M)*2m | L2: ST sec | M2: sofort | N2: permanent | O2: 5 | P2: St | Q2: PSI_Magie_Zaubertabelle_1_421.xlsx
A3: psi_telekinetisches_geschoss | B3: 2 | C3: 6 | D3: 20 | E3: W6 | F3: Telekinetisches Geschoss | G3: SP verteilt auf 3 TZ, Opfer wird um SP/2m zurückgeworfen. Körperbeherrschung+Athletik-Probe, um nicht zu stürzen. Auch Gegenstände werden zurückgeworfen. | H3: Kein Aurabann | I3: Aura | J3: Will | K3: (M)*2m | L3: ST sec | M3: sofort | N3: permanent | O3: 5 | P3: St | Q3: PSI_Magie_Zaubertabelle_1_421.xlsx
A4: psi_telekinetisches_geschoss | B4: 3 | C4: 9 | D4: 30 | E4: W8 | F4: Telekinetisches Geschoss | G4: SP verteilt auf 3 TZ, Opfer wird um SP/2m zurückgeworfen. Körperbeherrschung+Athletik-Probe, um nicht zu stürzen. Auch Gegenstände werden zurückgeworfen. | H4: Kein Aurabann | I4: Aura | J4: Will | K4: (M)*2m | L4: ST sec | M4: sofort | N4: permanent | O4: 5 | P4: St | Q4: PSI_Magie_Zaubertabelle_1_421.xlsx
A5: psi_telekinetisches_geschoss | B5: 4 | C5: 12 | D5: 40 | E5: W10 | F5: Telekinetisches Geschoss | G5: SP verteilt auf 3 TZ, Opfer wird um SP/2m zurückgeworfen. Körperbeherrschung+Athletik-Probe, um nicht zu stürzen. Auch Gegenstände werden zurückgeworfen. | H5: Kein Aurabann | I5: Aura | J5: Will | K5: (M)*2m | L5: ST sec | M5: sofort | N5: permanent | O5: 5 | P5: St | Q5: PSI_Magie_Zaubertabelle_1_421.xlsx
A6: psi_telekinetisches_geschoss | B6: 5 | C6: 15 | D6: 55 | E6: W12 | F6: Telekinetisches Geschoss | G6: SP verteilt auf 3 TZ, Opfer wird um SP/2m zurückgeworfen. Körperbeherrschung+Athletik-Probe, um nicht zu stürzen. Auch Gegenstände werden zurückgeworfen. | H6: Kein Aurabann | I6: Aura | J6: Will | K6: (M)*2m | L6: ST sec | M6: sofort | N6: permanent | O6: 5 | P6: St | Q6: PSI_Magie_Zaubertabelle_1_421.xlsx
A7: psi_telekinetisches_geschoss | B7: 6 | C7: 20 | D7: 75 | E7: W20 | F7: Telekinetisches Geschoss | G7: SP verteilt auf 3 TZ, Opfer wird um SP/2m zurückgeworfen. Körperbeherrschung+Athletik-Probe, um nicht zu stürzen. Auch Gegenstände werden zurückgeworfen. | H7: Kein Aurabann | I7: Aura | J7: Will | K7: (M)*2m | L7: ST sec | M7: sofort | N7: permanent | O7: 5 | P7: St | Q7: PSI_Magie_Zaubertabelle_1_421.xlsx
A8: psi_telekinetisches_geschoss | B8: 7 | C8: 30 | D8: 100 | E8: W30 | F8: Telekinetisches Geschoss | G8: SP verteilt auf 3 TZ, Opfer wird um SP/2m zurückgeworfen. Körperbeherrschung+Athletik-Probe, um nicht zu stürzen. Auch Gegenstände werden zurückgeworfen. | H8: Kein Aurabann | I8: Aura | J8: Will | K8: (M)*2m | L8: ST sec | M8: sofort | N8: permanent | O8: 5 | P8: St | Q8: PSI_Magie_Zaubertabelle_1_421.xlsx
A9: psi_pyrokinese | B9: 1 | C9: 4 | D9: 10 | E9: 200° | Watte | +200°/s | F9: Pyrokinese | G9: Der Zauber erhitzt eine Kugel mit Radius (M) x 2 mm³. Gegenstände innerhalb der Kugel brennen nur weiter, wenn sie auch natürlich brennen würden. | H9: Aurabann | I9: Gegenstand | J9: Int | K9: (M) x m | L9: 1 | M9: ST sec | N9: ST sec | O9: 15 | P9: St | Q9: PSI_Magie_Zaubertabelle_1_421.xlsx
A10: psi_pyrokinese | B10: 2 | C10: 7 | D10: 20 | E10: 400° | Stoff | +200°/s | F10: Pyrokinese | G10: Der Zauber erhitzt eine Kugel mit Radius (M) x 2 mm³. Gegenstände innerhalb der Kugel brennen nur weiter, wenn sie auch natürlich brennen würden. | H10: Aurabann | I10: Gegenstand | J10: Int | K10: (M) x m | L10: 1 | M10: ST sec | N10: ST sec | O10: 15 | P10: St | Q10: PSI_Magie_Zaubertabelle_1_421.xlsx
A11: psi_pyrokinese | B11: 3 | C11: 10 | D11: 30 | E11: 800° | Holz | +266°/s | F11: Pyrokinese | G11: Der Zauber erhitzt eine Kugel mit Radius (M) x 2 mm³. Gegenstände innerhalb der Kugel brennen nur weiter, wenn sie auch natürlich brennen würden. | H11: Aurabann | I11: Gegenstand | J11: Int | K11: (M) x m | L11: 1 | M11: ST sec | N11: ST sec | O11: 15 | P11: St | Q11: PSI_Magie_Zaubertabelle_1_421.xlsx
A12: psi_pyrokinese | B12: 4 | C12: 14 | D12: 45 | E12: 1000° | Leder | +250°/s | F12: Pyrokinese | G12: Der Zauber erhitzt eine Kugel mit Radius (M) x 2 mm³. Gegenstände innerhalb der Kugel brennen nur weiter, wenn sie auch natürlich brennen würden. | H12: Aurabann | I12: Gegenstand | J12: Int | K12: (M) x m | L12: 1 | M12: ST sec | N12: ST sec | O12: 15 | P12: St | Q12: PSI_Magie_Zaubertabelle_1_421.xlsx
A13: psi_pyrokinese | B13: 5 | C13: 18 | D13: 60 | E13: 1200° | Guss | +240°/s | F13: Pyrokinese | G13: Der Zauber erhitzt eine Kugel mit Radius (M) x 2 mm³. Gegenstände innerhalb der Kugel brennen nur weiter, wenn sie auch natürlich brennen würden. | H13: Aurabann | I13: Gegenstand | J13: Int | K13: (M) x m | L13: 1 | M13: ST sec | N13: ST sec | O13: 15 | P13: St | Q13: PSI_Magie_Zaubertabelle_1_421.xlsx
A14: psi_pyrokinese | B14: 6 | C14: 22 | D14: 80 | E14: 2200° | Stahl | +366°/s | F14: Pyrokinese | G14: Der Zauber erhitzt eine Kugel mit Radius (M) x 2 mm³. Gegenstände innerhalb der Kugel brennen nur weiter, wenn sie auch natürlich brennen würden. | H14: Aurabann | I14: Gegenstand | J14: Int | K14: (M) x m | L14: 1 | M14: ST sec | N14: ST sec | O14: 15 | P14: St | Q14: PSI_Magie_Zaubertabelle_1_421.xlsx
A15: psi_pyrokinese | B15: 7 | C15: 29 | D15: 100 | E15: 3390° | Wolfram | +484°/s | F15: Pyrokinese | G15: Der Zauber erhitzt eine Kugel mit Radius (M) x 2 mm³. Gegenstände innerhalb der Kugel brennen nur weiter, wenn sie auch natürlich brennen würden. | H15: Aurabann | I15: Gegenstand | J15: Int | K15: (M) x m | L15: 1 | M15: ST sec | N15: ST sec | O15: 15 | P15: St | Q15: PSI_Magie_Zaubertabelle_1_421.xlsx
A16: psi_kryokinese | B16: 1 | C16: 4 | D16: 10 | E16: -15° | -15°/s | F16: Kryokinese | G16: Der Zauber erhitzt eine Kugel mit Radius (M) x 2 mm³. Gegenstände innerhalb der Kugel bleiben gefroren, tauen aber natürlich auf. | H16: Aurabann | I16: Gegenstand | J16: Int | K16: (M) x m | L16: 1 | M16: ST sec | N16: ST sec | O16: 10 | P16: St | Q16: PSI_Magie_Zaubertabelle_1_421.xlsx
A17: psi_kryokinese | B17: 2 | C17: 7 | D17: 20 | E17: -40° | -20°/s | F17: Kryokinese | G17: Der Zauber erhitzt eine Kugel mit Radius (M) x 2 mm³. Gegenstände innerhalb der Kugel bleiben gefroren, tauen aber natürlich auf. | H17: Aurabann | I17: Gegenstand | J17: Int | K17: (M) x m | L17: 1 | M17: ST sec | N17: ST sec | O17: 10 | P17: St | Q17: PSI_Magie_Zaubertabelle_1_421.xlsx
A18: psi_kryokinese | B18: 3 | C18: 10 | D18: 30 | E18: -60° | -20°/s | F18: Kryokinese | G18: Der Zauber erhitzt eine Kugel mit Radius (M) x 2 mm³. Gegenstände innerhalb der Kugel bleiben gefroren, tauen aber natürlich auf. | H18: Aurabann | I18: Gegenstand | J18: Int | K18: (M) x m | L18: 1 | M18: ST sec | N18: ST sec | O18: 10 | P18: St | Q18: PSI_Magie_Zaubertabelle_1_421.xlsx
A19: psi_kryokinese | B19: 4 | C19: 14 | D19: 45 | E19: -85° | -21°/s | F19: Kryokinese | G19: Der Zauber erhitzt eine Kugel mit Radius (M) x 2 mm³. Gegenstände innerhalb der Kugel bleiben gefroren, tauen aber natürlich auf. | H19: Aurabann | I19: Gegenstand | J19: Int | K19: (M) x m | L19: 1 | M19: ST sec | N19: ST sec | O19: 10 | P19: St | Q19: PSI_Magie_Zaubertabelle_1_421.xlsx
A20: psi_kryokinese | B20: 5 | C20: 18 | D20: 60 | E20: -110° | -22°/s | F20: Kryokinese | G20: Der Zauber erhitzt eine Kugel mit Radius (M) x 2 mm³. Gegenstände innerhalb der Kugel bleiben gefroren, tauen aber natürlich auf. | H20: Aurabann | I20: Gegenstand | J20: Int | K20: (M) x m | L20: 1 | M20: ST sec | N20: ST sec | O20: 10 | P20: St | Q20: PSI_Magie_Zaubertabelle_1_421.xlsx
... A29: psi_destruktion | B29: 7 | C29: 23 | D29: 115 | E29: Diamant | F29: Destruktion | G29: Auf 1 Unbel. Geg/ nur kleinere Dinge, Bei großen =ST+1. Bei Fremdaura FK-TZW | H29: Kein Aurabann | I29: Aura | J29: Will | K29: (M)*m | L29: 1 | M29: sofort | N29: permanent | O29: 20 | P29: St*5 | Q29: PSI_Magie_Zaubertabelle_1_421.xlsx
A30: psi_geschosse_ablenken | B30: 1 | C30: 2 | D30: 7 | F30: Geschosse ablenken | G30: Der Magus kann Geschosse ablenken, die er sieht oder deren Abwurf/Abschuss/Mündungsfeuer er gesehen hat. Die AW oder Glück-Probe ist um ST x 3 erleichtert. | H30: Kein Aurabann | I30: Selbst | J30: Sch | K30: Selbst | L30: 1 | M30: sofort | N30: permanent | O30: 2 | P30: St*5 | Q30: PSI_Magie_Zaubertabelle_1_421.xlsx
A31: psi_geschosse_ablenken | B31: 2 | C31: 5 | D31: 14 | F31: Geschosse ablenken | G31: Der Magus kann Geschosse ablenken, die er sieht oder deren Abwurf/Abschuss/Mündungsfeuer er gesehen hat. Die AW oder Glück-Probe ist um ST x 3 erleichtert. | H31: Kein Aurabann | I31: Selbst | J31: Sch | K31: Selbst | L31: 1 | M31: sofort | N31: permanent | O31: 2 | P31: St*5 | Q31: PSI_Magie_Zaubertabelle_1_421.xlsx
A32: psi_geschosse_ablenken | B32: 3 | C32: 8 | D32: 21 | F32: Geschosse ablenken | G32: Der Magus kann Geschosse ablenken, die er sieht oder deren Abwurf/Abschuss/Mündungsfeuer er gesehen hat. Die AW oder Glück-Probe ist um ST x 3 erleichtert. | H32: Kein Aurabann | I32: Selbst | J32: Sch | K32: Selbst | L32: 1 | M32: sofort | N32: permanent | O32: 2 | P32: St*5 | Q32: PSI_Magie_Zaubertabelle_1_421.xlsx
A33: psi_geschosse_ablenken | B33: 4 | C33: 11 | D33: 28 | F33: Geschosse ablenken | G33: Der Magus kann Geschosse ablenken, die er sieht oder deren Abwurf/Abschuss/Mündungsfeuer er gesehen hat. Die AW oder Glück-Probe ist um ST x 3 erleichtert. | H33: Kein Aurabann | I33: Selbst | J33: Sch | K33: Selbst | L33: 1 | M33: sofort | N33: permanent | O33: 2 | P33: St*5 | Q33: PSI_Magie_Zaubertabelle_1_421.xlsx
A34: psi_geschosse_ablenken | B34: 5 | C34: 14 | D34: 35 | F34: Geschosse ablenken | G34: Der Magus kann Geschosse ablenken, die er sieht oder deren Abwurf/Abschuss/Mündungsfeuer er gesehen hat. Die AW oder Glück-Probe ist um ST x 3 erleichtert. | H34: Kein Aurabann | I34: Selbst | J34: Sch | K34: Selbst | L34: 1 | M34: sofort | N34: permanent | O34: 2 | P34: St*5 | Q34: PSI_Magie_Zaubertabelle_1_421.xlsx
A35: psi_geschosse_ablenken | B35: 6 | C35: 17 | D35: 92 | F35: Geschosse ablenken | G35: Der Magus kann Geschosse ablenken, die er sieht oder deren Abwurf/Abschuss/Mündungsfeuer er gesehen hat. Die AW oder Glück-Probe ist um ST x 3 erleichtert. | H35: Kein Aurabann | I35: Selbst | J35: Sch | K35: Selbst | L35: 1 | M35: sofort | N35: permanent | O35: 2 | P35: St*5 | Q35: PSI_Magie_Zaubertabelle_1_421.xlsx
A36: psi_geschosse_ablenken | B36: 7 | C36: 20 | D36: 145 | F36: Geschosse ablenken | G36: Der Magus kann Geschosse ablenken, die er sieht oder deren Abwurf/Abschuss/Mündungsfeuer er gesehen hat. Die AW oder Glück-Probe ist um ST x 3 erleichtert. | H36: Kein Aurabann | I36: Selbst | J36: Sch | K36: Selbst | L36: 1 | M36: sofort | N36: permanent | O36: 2 | P36: St*5 | Q36: PSI_Magie_Zaubertabelle_1_421.xlsx
A37: psi_empathie | B37: 1 | C37: 1 | D37: 5 | F37: Empathie | G37: Der Zauberer bekommt St*2 Punkte und kann sie frei nach der unten gewählten Tabelle einsetzen: 14 Punkte = 1 gesehene Person Gesinnungsbogen Scannen 1 Punkt = 60° zusätzlicher Sichtwinkel 1 Punkt = Personen vorhanden, ja oder nein 3 Punkte = Personen Vorhanden, ja nein; ungefähre Anzahl 5 Punkte = Personen Vorhanden, ja nein; genaue Anzahl 7 Punkte = Personen Vorhanden, ja nein; genaue Anzahl; ungefähre Position 9 Punkte = Personen Vorhanden, ja nein; genaue Anzahl; genaue Position 11 Punkte = Personen Vorhanden, ja/nein; genaue Anzahl; genaue Position; Tier und Mensch unterscheiden. (genaue Position ist +/- 1m) | H37: Kein Aurabann | I37: Aura | J37: Will | K37: (M)*2m | L37: 1 | M37: sofort | N37: (M) sec | O37: 5 | P37: St | Q37: PSI_Magie_Zaubertabelle_1_421.xlsx
A38: psi_empathie | B38: 2 | C38: 4 | D38: 10 | F38: Empathie | G38: Der Zauberer bekommt St*2 Punkte und kann sie frei nach der unten gewählten Tabelle einsetzen: 14 Punkte = 1 gesehene Person Gesinnungsbogen Scannen 1 Punkt = 60° zusätzlicher Sichtwinkel 1 Punkt = Personen vorhanden, ja oder nein 3 Punkte = Personen Vorhanden, ja nein; ungefähre Anzahl 5 Punkte = Personen Vorhanden, ja nein; genaue Anzahl 7 Punkte = Personen Vorhanden, ja nein; genaue Anzahl; ungefähre Position 9 Punkte = Personen Vorhanden, ja nein; genaue Anzahl; genaue Position 11 Punkte = Personen Vorhanden, ja/nein; genaue Anzahl; genaue Position; Tier und Mensch unterscheiden. (genaue Position ist +/- 1m) | H38: Kein Aurabann | I38: Aura | J38: Will | K38: (M)*2m | L38: 1 | M38: sofort | N38: (M) sec | O38: 5 | P38: St | Q38: PSI_Magie_Zaubertabelle_1_421.xlsx
A39: psi_empathie | B39: 3 | C39: 7 | D39: 20 | F39: Empathie | G39: Der Zauberer bekommt St*2 Punkte und kann sie frei nach der unten gewählten Tabelle einsetzen: 14 Punkte = 1 gesehene Person Gesinnungsbogen Scannen 1 Punkt = 60° zusätzlicher Sichtwinkel 1 Punkt = Personen vorhanden, ja oder nein 3 Punkte = Personen Vorhanden, ja nein; ungefähre Anzahl 5 Punkte = Personen Vorhanden, ja nein; genaue Anzahl 7 Punkte = Personen Vorhanden, ja nein; genaue Anzahl; ungefähre Position 9 Punkte = Personen Vorhanden, ja nein; genaue Anzahl; genaue Position 11 Punkte = Personen Vorhanden, ja/nein; genaue Anzahl; genaue Position; Tier und Mensch unterscheiden. (genaue Position ist +/- 1m) | H39: Kein Aurabann | I39: Aura | J39: Will | K39: (M)*2m | L39: 1 | M39: sofort | N39: (M) sec | O39: 5 | P39: St | Q39: PSI_Magie_Zaubertabelle_1_421.xlsx
A40: psi_empathie | B40: 4 | C40: 10 | D40: 30 | F40: Empathie | G40: Der Zauberer bekommt St*2 Punkte und kann sie frei nach der unten gewählten Tabelle einsetzen: 14 Punkte = 1 gesehene Person Gesinnungsbogen Scannen 1 Punkt = 60° zusätzlicher Sichtwinkel 1 Punkt = Personen vorhanden, ja oder nein 3 Punkte = Personen Vorhanden, ja nein; ungefähre Anzahl 5 Punkte = Personen Vorhanden, ja nein; genaue Anzahl 7 Punkte = Personen Vorhanden, ja nein; genaue Anzahl; ungefähre Position 9 Punkte = Personen Vorhanden, ja nein; genaue Anzahl; genaue Position 11 Punkte = Personen Vorhanden, ja/nein; genaue Anzahl; genaue Position; Tier und Mensch unterscheiden. (genaue Position ist +/- 1m) | H40: Kein Aurabann | I40: Aura | J40: Will | K40: (M)*2m | L40: 1 | M40: sofort | N40: (M) sec | O40: 5 | P40: St | Q40: PSI_Magie_Zaubertabelle_1_421.xlsx
A41: psi_empathie | B41: 5 | C41: 13 | D41: 35 | F41: Empathie | G41: Der Zauberer bekommt St*2 Punkte und kann sie frei nach der unten gewählten Tabelle einsetzen: 14 Punkte = 1 gesehene Person Gesinnungsbogen Scannen 1 Punkt = 60° zusätzlicher Sichtwinkel 1 Punkt = Personen vorhanden, ja oder nein 3 Punkte = Personen Vorhanden, ja nein; ungefähre Anzahl 5 Punkte = Personen Vorhanden, ja nein; genaue Anzahl 7 Punkte = Personen Vorhanden, ja nein; genaue Anzahl; ungefähre Position 9 Punkte = Personen Vorhanden, ja nein; genaue Anzahl; genaue Position 11 Punkte = Personen Vorhanden, ja/nein; genaue Anzahl; genaue Position; Tier und Mensch unterscheiden. (genaue Position ist +/- 1m) | H41: Kein Aurabann | I41: Aura | J41: Will | K41: (M)*2m | L41: 1 | M41: sofort | N41: (M) sec | O41: 5 | P41: St | Q41: PSI_Magie_Zaubertabelle_1_421.xlsx
... A106: psi_hoehere_telekinese | B106: 7 | C106: 29 | D106: 150 | F106: Höhere Telekinese | G106: 1 Gegenstand / Nur Unbelebtes/ Aurabann St³ x kg oder Liter/ max. 10m/sec. | H106: Aurabann | I106: Gegenstand | J106: Will | K106: (M)*m | L106: 1 | M106: sofort | N106: (M) min | O106: 20 | P106: St*2 | Q106: PSI_Magie_Zaubertabelle_1_421.xlsx

Sheet KI-Baum-Kanten
A1: Faehigkeit | B1: Vorbedingung | C1: Mindest-TaW
A2: ki_abhaertung | B2: ki_konzentration | C2: 10
A3: ki_dauerlauf | B3: ki_konzentration | C3: 10
A4: ki_ewige_erinnerung | B4: ki_konzentration | C4: 10
A5: ki_froschlunge | B5: ki_konzentration | C5: 10
A6: ki_katzenauge | B6: ki_konzentration | C6: 10
A7: ki_heilender_schlaf | B7: ki_konzentration | C7: 10
A8: ki_ki_schutz | B8: ki_abhaertung | C8: 10
A9: ki_sprint | B9: ki_dauerlauf | C9: 10
A10: ki_kraftakt | B10: ki_froschlunge | C10: 10
A11: ki_fledermausohr_aalnase | B11: ki_katzenauge | C11: 10
A12: ki_erleuchtung | B12: ki_ewige_erinnerung | C12: 10
A13: ki_abwehr | B13: ki_ki_schutz | C13: 15
... A31: ki_konterattacke | B31: ki_paradeserie | C31: 30

Sheet Preisliste
A1: Art | B1: Name | C1: Anzahl | D1: Einheit | E1: Gewicht in kg | F1: Dublonen | H1: WHK | I1: Spezialisierung
A2: Reittiere | B2: Drache, Flug | C2: 1 | D2: Stück | E2: XXX | F2: ------ | G2: Selten | H2: Abrichten | I2: Drache
A3: Reittiere | B3: Greif, Flug | C3: 1 | D3: Stück | E3: XXX | F3: ------ | G3: Selten | H3: Abrichten | I3: Greife
A4: Reittiere | B4: Chocobo, Abgeh, | C4: 1 | D4: Stück | E4: XXX | F4: 470 | G4: Elf | H4: Abrichten | I4: Laufvogel
A5: Reittiere | B5: Chocobo, Alt | C5: 1 | D5: Stück | E5: XXX | F5: 282 | G5: Elf | H5: Abrichten | I5: Laufvogel
A6: Reittiere | B6: Chocobo, Reit | C6: 1 | D6: Stück | E6: XXX | F6: 750 | G6: Elf | H6: Abrichten | I6: Laufvogel
A7: Reittiere | B7: Chocobo, Schlacht | C7: 1 | D7: Stück | E7: XXX | F7: 2250 | G7: Elf | H7: Abrichten | I7: Laufvogel
A8: Reittiere | B8: Chocobo, Vollblut | C8: 1 | D8: Stück | E8: XXX | F8: 3380 | G8: Elf | H8: Abrichten | I8: Laufvogel
A9: Reittiere | B9: Pegasus, Flug | C9: 1 | D9: Stück | E9: XXX | F9: ------ | G9: Selten | H9: Abrichten | I9: Pegasus
A10: Reittiere | B10: Pferd, Abgehalftert | C10: 1 | D10: Stück | E10: XXX | F10: 250 | G10: Indianer, Dalkini | H10: Abrichten | I10: Pferd
A11: Reittiere | B11: Pferd, Alter Gaul | C11: 1 | D11: Stück | E11: XXX | F11: 150 | G11: Indianer, Dalkini | H11: Abrichten | I11: Pferd
A12: Reittiere | B12: Pferd, Reit | C12: 1 | D12: Stück | E12: XXX | F12: 400 | G12: Indianer, Dalkini | H12: Abrichten | I12: Pferd
A13: Reittiere | B13: Pferd, Schlachtross | C13: 1 | D13: Stück | E13: XXX | F13: 1200 | G13: Indianer, Dalkini | H13: Abrichten | I13: Pferd
A14: Reittiere | B14: Pferd, Vollblut | C14: 1 | D14: Stück | E14: XXX | F14: 1800 | G14: Indianer, Dalkini | H14: Abrichten | I14: Pferd
A15: Reittiere | B15: Ratte, Abgehalftert | C15: 1 | D15: Stück | E15: XXX | F15: 190 | G15: Goblin | H15: Abrichten | I15: Ratte
A16: Reittiere | B16: Ratte, Alt | C16: 1 | D16: Stück | E16: XXX | F16: 115 | G16: Goblin | H16: Abrichten | I16: Ratte
A17: Reittiere | B17: Ratte, Gefährlich | C17: 1 | D17: Stück | E17: XXX | F17: 1350 | G17: Goblin | H17: Abrichten | I17: Ratte
A18: Reittiere | B18: Ratte, Reit | C18: 1 | D18: Stück | E18: XXX | F18: 300 | G18: Goblin | H18: Abrichten | I18: Ratte
A19: Reittiere | B19: Ratte, Schlacht | C19: 1 | D19: Stück | E19: XXX | F19: 900 | G19: Goblin | H19: Abrichten | I19: Ratte
A20: Reittiere | B20: Assel, Abgehalftert | C20: 1 | D20: Stück | E20: XXX | F20: 282 | G20: Zwerg | H20: Abrichten | I20: Reitkrebse
A21: Reittiere | B21: Assel, Alt | C21: 1 | D21: Stück | E21: XXX | F21: 169 | G21: Zwerg | H21: Abrichten | I21: Reitkrebse
... A37: Reittiere | B37: Schildkröte, Schnell | C37: 1 | D37: Stück | E37: XXX | F37: 4500 | G37: Gnom | H37: Abrichten | I37: Reitreptilien
A38: Reittiere | B38: Roc, Flug | C38: 1 | D38: Stück | E38: XXX | F38: ------ | G38: Selten | H38: Abrichten | I38: Rok
A39: Reittiere | B39: Rollok, abgehalftert | C39: 1 | D39: Stück | E39: XXX | F39: 532 | G39: Troll | H39: Abrichten | I39: Rollok
A40: Reittiere | B40: Rollok, alt | C40: 1 | D40: Stück | E40: XXX | F40: 319 | G40: Troll | H40: Abrichten | I40: Rollok
A41: Reittiere | B41: Rollok, Reit | C41: 1 | D41: Stück | E41: XXX | F41: 850 | G41: Troll | H41: Abrichten | I41: Rollok
A42: Reittiere | B42: Rollok, Schlacht | C42: 1 | D42: Stück | E42: XXX | F42: 2550 | G42: Troll | H42: Abrichten | I42: Rollok
A43: Reittiere | B43: Rollok, übellaunig | C43: 1 | D43: Stück | E43: XXX | F43: 3850 | G43: Troll | H43: Abrichten | I43: Rollok
A44: Reittiere | B44: Warg, Abgehalftert | C44: 1 | D44: Stück | E44: XXX | F44: 375 | G44: Ork | H44: Abrichten | I44: Warg
A45: Reittiere | B45: Warg, Alt | C45: 1 | D45: Stück | E45: XXX | F45: 225 | G45: Ork | H45: Abrichten | I45: Warg
A46: Reittiere | B46: Warg, Elite | C46: 1 | D46: Stück | E46: XXX | F46: 2700 | G46: Ork | H46: Abrichten | I46: Warg
A47: Reittiere | B47: Warg, Reit | C47: 1 | D47: Stück | E47: XXX | F47: 600 | G47: Ork | H47: Abrichten | I47: Warg
A48: Reittiere | B48: Warg, Schlacht | C48: 1 | D48: Stück | E48: XXX | F48: 1800 | G48: Ork | H48: Abrichten | I48: Warg
A49: Alchemistische Stoffe | B49: Öl, Brand- | C49: 1 | D49: Fass | E49: 5 | F49: 35 | H49: Alchemie | I49: Brandbeschleuniger
A50: Alchemistische Stoffe | B50: Schwarzpulver | C50: 1 | D50: Sack | E50: 1 | F50: 85 | H50: Alchemie | I50: Brandbeschleuniger
A51: Alchemistische Stoffe | B51: Zwergisches Feuer | C51: 1 | D51: Flasche | E51: 1 | F51: 500 | H51: Alchemie | I51: Brandbeschleuniger
A52: Beleuchtung | B52: Streichhölzer 25St, | C52: 1 | D52: Schachtel | E52: 0.2 | F52: 1 | H52: Alchemie | I52: Brandbeschleuniger
A53: Alchemistische Stoffe | B53: Orazal (Lösung) | C53: 1 | D53: Bund | E53: 0.002 | F53: 92 | H53: Alchemie | I53: DSA-Material
A54: Schreibwaren | B54: Tinte | C54: 1 | D54: Phiole | E54: 0.1 | F54: 0.98 | H54: Alchemie | I54: Farbstoffe
A55: Schreibwaren | B55: Tusche | C55: 1 | D55: Phiole | E55: 0.1 | F55: 1.3 | H55: Alchemie | I55: Farbstoffe
A56: Schreibwaren | B56: Tusche, farbig | C56: 1 | D56: Phiole | E56: 0.1 | F56: 3.5 | H56: Alchemie | I56: Farbstoffe
A57: Alchemistische Stoffe | B57: Fett, Salben-, pflanzlich | C57: 1 | D57: Tiegel | E57: 1 | F57: 13 | H57: Alchemie | I57: Fettprodukte
A58: Alchemistische Stoffe | B58: Fett, Salben-, tierisch | C58: 1 | D58: Tiegel | E58: 1 | F58: 13 | H58: Alchemie | I58: Fettprodukte
A59: Körperpflege | B59: Lippenrot | C59: 1 | D59: Tiegel | E59: 0.02 | F59: 4.5 | H59: Alchemie | I59: Fettprodukte
A60: Körperpflege | B60: Seife | C60: 1 | D60: Stück | E60: 0.5 | F60: 0.1 | H60: Alchemie | I60: Fettprodukte
... A92: Nahrungsmittel | B92: Zuckerstange | C92: 1 | D92: Portion | E92: 0.02 | F92: 0.15 | H92: Bäcker | I92: Konditor
A93: Körperpflege | B93: Entlausen | C93: 1 | D93: Besuch | E93: XXX | F93: 0.5 | H93: Barbier | I93: Bader
A94: Körperpflege | B94: Maniküre | C94: 1 | D94: Besuch | E94: XXX | F94: 2 | H94: Barbier | I94: Bader
A95: Körperpflege | B95: Rasur | C95: 1 | D95: Besuch | E95: XXX | F95: 0.75 | H95: Barbier | I95: Bader
A96: Körperpflege | B96: Vollbad im Badehaus | C96: 1 | D96: Besuch | E96: XXX | F96: 1 | H96: Barbier | I96: Bader
A97: Körperpflege | B97: Frisur | C97: 1 | D97: Besuch | E97: XXX | F97: 2 | H97: Barbier | I97: Frisör
A98: Körperpflege | B98: Frisur, Ball- | C98: 1 | D98: Besuch | E98: XXX | F98: 15 | H98: Barbier | I98: Frisör
A99: Körperpflege | B99: Schnitt, Bart- | C99: 1 | D99: Besuch | E99: XXX | F99: 0.9 | H99: Barbier | I99: Frisör
A100: Tierbedarf | B100: Hund färben | C100: 1 | D100: Besuch | E100: XXX | F100: 10 | H100: Barbier | I100: Frisör
A101: Edelsteine | B101: 10 Aquamarin | C101: 1 | D101: Karat | E101: 0.0002 | F101: 3.6 | G101: gebraucht erworben werden können oder die in Einheitsgrößen hergestellt werden, | H101: Bergbau | I101: Edelsteine
A102: Edelsteine | B102: 11 Granat | C102: 1 | D102: Karat | E102: 0.0002 | F102: 1.3 | G102: Der zweitgenannte Preis gilt für Maßanfertigungen bei einem Schneider oder Schuster, | H102: Bergbau | I102: Edelsteine
A103: Edelsteine | B103: 12 Onyx | C103: 1 | D103: Karat | E103: 0.0002 | F103: 2.2 | G103: Der als erstes angegebene Preis bezieht sich bei Kleidungsstücken auf solche, die bei einem Trödler oder Krämer | H103: Bergbau | I103: Edelsteine
A104: Edelsteine | B104: 13 Perle | C104: 1 | D104: Karat | E104: 0.0002 | F104: 3 | H104: Bergbau | I104: Edelsteine
A105: Edelsteine | B105: 14 Turmalin | C105: 1 | D105: Karat | E105: 0.0002 | F105: 4.4 | H105: Bergbau | I105: Edelsteine
A106: Edelsteine | B106: 15 Bernstein | C106: 1 | D106: Karat | E106: 0.0002 | F106: 8 | H106: Bergbau | I106: Edelsteine
A107: Edelsteine | B107: 16 Zirkon | C107: 1 | D107: Karat | E107: 0.0002 | F107: 16 | H107: Bergbau | I107: Edelsteine
A108: Edelsteine | B108: 17 Smaragd | C108: 1 | D108: Karat | E108: 0.0002 | F108: 20 | H108: Bergbau | I108: Edelsteine
A109: Edelsteine | B109: 18 Rubin | C109: 1 | D109: Karat | E109: 0.0002 | F109: 25 | H109: Bergbau | I109: Edelsteine
A110: Edelsteine | B110: 3 Diamant | C110: 1 | D110: Karat | E110: 0.0002 | F110: 27 | G110: Die hier angegebenen Preise beziehen sich auf geschliffene Stücke, Ungeschliffene Steine erbringen höchstens die Hälfte des Preises, | H110: Bergbau | I110: Edelsteine
A111: Edelsteine | B111: 4 Saphir | C111: 1 | D111: Karat | E111: 0.0002 | F111: 22 | G111: Edelsteine von mehr als 50 Karat jedoch auch leicht das Doppelte des hier angegeben Wertes, Mit 3W6 können Sie festlegen, welche Edelsteine sich | H111: Bergbau | I111: Edelsteine
A112: Edelsteine | B112: 5 Opal | C112: 1 | D112: Karat | E112: 0.0002 | F112: 11 | G112: z,B, in einem Schatz befinden, | H112: Bergbau | I112: Edelsteine
A113: Edelsteine | B113: 6 Rohdiamant | C113: 1 | D113: Karat | E113: 0.0002 | F113: 7 | G113: auf 3W6 Edelstein Preis pro Karat (0,2g) | H113: Bergbau | I113: Edelsteine
A114: Edelsteine | B114: 7 Topas | C114: 1 | D114: Karat | E114: 0.0002 | F114: 8 | H114: Bergbau | I114: Edelsteine
A115: Edelsteine | B115: 8 Lapislazuli | C115: 1 | D115: Karat | E115: 0.0002 | F115: 3.5 | G115: Einige weitere Mineralien werden als 'Halbedelsteine' angesehen, Sie kosten ungefähr 9 Dublonen pro 25g, | H115: Bergbau | I115: Edelsteine
A116: Edelsteine | B116: 9 Jade | C116: 1 | D116: Karat | E116: 0.0002 | F116: 1.8 | G116: Zu ihnen gehören: Amethyst, Rosenquarz, Mondstein, Türkis, Malachit, Korallen, Meerschaum und Achat, | H116: Bergbau | I116: Edelsteine
A117: Metall | B117: Diamantspat, ungeprägt | C117: 1 | D117: Barren | E117: 1 | F117: 88 | H117: Bergbau | I117: Edelsteine
A118: Metall | B118: Diamantspat-Metallplatten/drähte | C118: 1 | D118: Bund | E118: 1 | F118: 106 | H118: Bergbau | I118: Edelsteine
A119: Schreibwaren | B119: Kreide, Schreib- | C119: 1 | D119: Schachtel | E119: 0.02 | F119: 0.018 | H119: Bergbau | I119: Gesteine
A120: Schreibwaren | B120: Tafel, Schiefer- | C120: 1 | D120: Stück | E120: 0.5 | F120: 0.78 | H120: Bergbau | I120: Gesteine
A121: Alchemistische Stoffe | B121: Kohle, Zwergen- | C121: 1 | D121: Sack | E121: 1 | F121: 3 | H121: Bergbau | I121: Kohle
A122: Schreibwaren | B122: Stifte, Kohle-, 5 St, | C122: 1 | D122: Satz | E122: 0.05 | F122: 0.005 | H122: Bergbau | I122: Kohle
A123: Alchemistische Stoffe | B123: Öl, Braun-, rauchend | C123: 1 | D123: Flasche | E123: 1 | F123: 52 | H123: Bergbau | I123: Ölprodukte
A124: Alchemistische Stoffe | B124: Pech, Destillations- | C124: 1 | D124: Tiegel | E124: 1 | F124: 8 | H124: Bergbau | I124: Ölprodukte
A125: Alchemistische Stoffe | B125: Salpeter, Salz | C125: 1 | D125: Sack | E125: 1 | F125: 35 | H125: Bergbau | I125: Salze
A126: Alchemistische Stoffe | B126: Schwefel | C126: 1 | D126: Sack | E126: 1 | F126: 125 | H126: Bergbau | I126: Salze
A127: Nahrungsmittel | B127: Salz | C127: 1 | D127: Sack | E127: 0.5 | F127: 0.3 | H127: Bergbau | I127: Salze
A128: Segelschiff | B128: Schiff, Dreimaster | C128: 1 | D128: Stück | E128: XXX | F128: 640000 | H128: Bootsbauer | I128: Dickschiffe
A129: Segelschiff | B129: Schiff, Fünfmaster | C129: 1 | D129: Stück | E129: XXX | F129: 1400000 | H129: Bootsbauer | I129: Dickschiffe
A130: Segelschiff | B130: Schiff, Viermaster | C130: 1 | D130: Stück | E130: XXX | F130: 960000 | H130: Bootsbauer | I130: Dickschiffe
A131: Segelschiff | B131: Schiff, Zweimaster | C131: 1 | D131: Stück | E131: XXX | F131: 420000 | H131: Bootsbauer | I131: Dickschiffe
A132: Segelschiff | B132: Boot, Ruder- klein | C132: 1 | D132: Stück | E132: 50 | F132: 528 | H132: Bootsbauer | I132: Kleine Schiffe
A133: Segelschiff | B133: Boot, Segel- 6m lang | C133: 1 | D133: Stück | E133: 400 | F133: 2860 | H133: Bootsbauer | I133: Kleine Schiffe
A134: Segelschiff | B134: Kanu | C134: 1 | D134: Stück | E134: 50 | F134: 50 | H134: Bootsbauer | I134: Kleine Schiffe
A135: Segelschiff | B135: Schiff, Einmaster | C135: 1 | D135: Stück | E135: XXX | F135: 280000 | H135: Bootsbauer | I135: Kleine Schiffe
A136: Alchemistische Stoffe | B136: Alkohol, rein | C136: 1 | D136: Flasche | E136: 1 | F136: 20 | H136: Brenner | I136: Alchemistische Zutaten
A137: Alchemistische Stoffe | B137: Zwiedestillat | C137: 1 | D137: Flasche | E137: 1 | F137: 13 | H137: Brenner | I137: Alchemistische Zutaten
A138: Alchemistische Stoffe | B138: Schwefelquell Gratenfelser | C138: 1 | D138: Flasche | E138: 1 | F138: 7.5 | H138: Brenner | I138: Alchemistische Zutaten
A139: Nahrungsmittel | B139: Likör | C139: 1 | D139: Flasche | E139: 0.5 | F139: 0.5 | H139: Brenner | I139: Geist
A140: Nahrungsmittel | B140: Schnaps, einfach | C140: 1 | D140: Flasche | E140: 1 | F140: 0.4 | H140: Brenner | I140: Geist
A141: Nahrungsmittel | B141: Wein, Brannt- | C141: 1 | D141: Flasche | E141: 1 | F141: 0.5 | H141: Brenner | I141: Geist
A142: Nahrungsmittel | B142: Wein, Brannt-, gut | C142: 1 | D142: Flasche | E142: 1 | F142: 50 | H142: Brenner | I142: Geist
A143: Körperpflege | B143: Wein, Franzbrannt- | C143: 1 | D143: Flasche | E143: 0.25 | F143: 2.8 | H143: Brenner | I143: Kräutergeist
A144: Körperpflege | B144: Wein, Kräuterbrannt- | C144: 1 | D144: Flasche | E144: 0.25 | F144: 3 | H144: Brenner | I144: Kräutergeist
A145: Schreibwaren | B145: Buch, Tage-, Papier | C145: 1 | D145: Stück | E145: 0.5 | F145: 15.4 | H145: Drucker | I145: Buchbinder
A146: Schreibwaren | B146: Papier, 10 Bögen | C146: 1 | D146: Schachtel | E146: 0.08 | F146: 1.3 | H146: Drucker | I146: Papierherstellung
...

Sheet Alchemika
A1: Kategorie | B1: magisch_y_n | C1: Name | D1: Potenz | E1: Dosierbar | F1: Zufuhr | G1: ZbS (Zeit bis Symptom) | H1: ZbW (Zeit bis Wirkung) | I1: Wirkungsdauer | J1: Wirkung | K1: Legalität | L1: Char_Unterwelt_Mod | M1: Verfügb | N1: Zutaten_Preis_in_D | O1: Kaufpreis_in_D | P1: Rezept-Erschwerung
A2: Gifte | B2: profan | C2: Leichtes Regigift | D2: 5 | E2: J | F2: Körper | G2: Sofort | H2: Sofort | I2: 12h | J2: Regenerationsklasse -2, leichter Schlaf | K2: 3 | L2: 0 | M2: 1 | N2: 0.25 | O2: =N2*(K2+L2) -> 0.75 | P2: 4
A3: Gifte | B3: profan | C3: Regigift | D3: 15 | E3: J | F3: Körper | G3: Sofort | H3: Sofort | I3: 12h | J3: Regenerationsklasse -4, leichter Schlaf | K3: 4 | L3: 0 | M3: 2 | N3: 0.5 | O3: =N3*(K3+L3) -> 2 | P3: 6
A4: Gifte | B4: profan | C4: Starkes Regigift | D4: 30 | E4: J | F4: Körper | G4: Sofort | H4: Sofort | I4: 12h | J4: Regenerationsklasse -7, leichter Schlaf | K4: 5 | L4: 0 | M4: 3 | N4: 1 | O4: =N4*(K4+L4) -> 5 | P4: 10
A5: Gifte | B5: profan | C5: Hässlichkeitsgift | D5: 15 | E5: J | F5: Körper | G5: Sofort | H5: Sofort | I5: 1d | J5: Alle Grundfertigkeits-, Sprach-, Kulur- und WHK-Proben auf Ausstrahlung um 10 erschwert | K5: 4 | L5: 0 | M5: 5 | N5: 50 | O5: =N5*(K5+L5) -> 200 | P5: 30
A6: Gifte | B6: profan | C6: Starkes Hässlichkeitsgift | D6: 30 | E6: J | F6: Körper | G6: Sofort | H6: Sofort | I6: 1d | J6: Alle Grundfertigkeits-, Sprach-, Kulur- und WHK-Proben auf Ausstrahlung um 15 erschwert | K6: 5 | L6: 0 | M6: 6 | N6: 150 | O6: =N6*(K6+L6) -> 750 | P6: 48
A7: Gifte | B7: profan | C7: Leichtes Hässlichkeitsgift | D7: 5 | E7: J | F7: Körper | G7: Sofort | H7: Sofort | I7: 1d | J7: Alle Grundfertigkeits-, Sprach-, Kulur- und WHK-Proben auf Ausstrahlung um 5 erschwert | K7: 3 | L7: 0 | M7: 4 | N7: 25 | O7: =N7*(K7+L7) -> 75 | P7: 18
A8: Gifte | B8: profan | C8: Leichtes Zungengift | D8: 5 | E8: J | F8: Körper | G8: 1 KR | H8: 3 KR | I8: 1h | J8: Artikuliertes Sprechen unmöglich | K8: 2 | L8: 0 | M8: 2 | N8: 1 | O8: =N8*(K8+L8) -> 2 | P8: 12
A9: Gifte | B9: profan | C9: Zungengift | D9: 15 | E9: J | F9: Körper | G9: 1 KR | H9: 3 KR | I9: 1h | J9: Artikuliertes Sprechen unmöglich | K9: 3 | L9: 0 | M9: 3 | N9: 2 | O9: =N9*(K9+L9) -> 6 | P9: 18
A10: Gifte | B10: profan | C10: Starkes Zungengift | D10: 30 | E10: J | F10: Körper | G10: 1 KR | H10: 3 KR | I10: 1h | J10: Artikuliertes Sprechen unmöglich | K10: 4 | L10: 0 | M10: 4 | N10: 4 | O10: =N10*(K10+L10) -> 16 | P10: 30
A11: Gifte | B11: profan | C11: Leichtes Taubheitsgift | D11: 5 | E11: J | F11: Körper | G11: 1 KR | H11: 3 KR | I11: 1h | J11: BE 2, Gefahrensinn -12 | K11: 2 | L11: 0 | M11: 2 | N11: 1 | O11: =N11*(K11+L11) -> 2 | P11: 12
A12: Gifte | B12: profan | C12: Taubheitsgift | D12: 15 | E12: J | F12: Körper | G12: 1 KR | H12: 3 KR | I12: 1h | J12: BE 2, Gefahrensinn -12 | K12: 3 | L12: 0 | M12: 3 | N12: 2 | O12: =N12*(K12+L12) -> 6 | P12: 18
A13: Gifte | B13: profan | C13: Starkes Taubheitsgift | D13: 30 | E13: J | F13: Körper | G13: 1 KR | H13: 3 KR | I13: 1h | J13: BE 2, Gefahrensinn -12 | K13: 4 | L13: 0 | M13: 4 | N13: 4 | O13: =N13*(K13+L13) -> 16 | P13: 30
... A119: Zustandstränke | B119: profan | C119: Geruchslossalbe | D119: 75 | E119: N | F119: Kontakt | G119: 2 KR | H119: 5 KR | I119: 6h | J119: Man verliert seinen Geruch komplett | K119: 2 | L119: 0 | M119: 5 | N119: 25 | O119: =N119*(K119+L119) -> 50 | P119: 12

Sheet Ruestungstabelle
B1: Kopf | C1: Verarbeitung | D1: Anpassung | E1: RS | F1: BE | G1: Preis | H1: NW | I1: AW
A2: Lage 1 | B2: Stoffrüstung | C2: Meisterarbeit | D2: angepasst | E2: 3 | F2: 1 | G2: 227 | H2: 3 | I2: 2
A3: Lage 2 | B3: Leichte Lederrüstung | C3: Meisterarbeit | D3: angepasst | E3: 4 | F3: 2 | G3: 274 | H3: 3 | I3: 2
A4: Lage 3 | B4: Stahl-Kettenpanzer | C4: Meisterarbeit | D4: angepasst | E4: 6 | F4: 3 | G4: 1830 | H4: 3 | I4: 2
A5: Lage 4 | B5: Schwerer Lederpanzer | C5: Meisterarbeit | D5: angepasst | E5: 6 | F5: 4 | G5: 562 | H5: 3 | I5: 2
A6: Lage 5 | B6: Keine Rüstung | E6: 0 | F6: 0 | G6: 0 | H6: 0 | I6: 0
C7: Kopf | D7: Gesamt: | E7: 19 | F7: 10 | G7: 2893
B8: Torso | C8: Verarbeitung | D8: Anpassung | E8: RS | F8: BE | G8: Preis | H8: NW | I8: AW
A9: Lage 1 | B9: Stoffrüstung | C9: Großmeisterarbeit | D9: perfekt angepasst | E9: 4 | F9: 1 | G9: 387 | H9: 5 | I9: 3
A10: Lage 2 | B10: Leichte Lederrüstung | C10: Gesellenarbeit | D10: angepasst | E10: 3 | F10: 2 | G10: 38 | H10: 3 | I10: 2
A11: Lage 3 | B11: Eisen-Kettenpanzer | C11: Gesellenarbeit | D11: angepasst | E11: 4 | F11: 3 | G11: 372 | H11: 3 | I11: 2
A12: Lage 4 | B12: Schwerer Faltstahlpanzer | C12: Einzelstück | D12: perfekt angepasst | E12: 14 | F12: 7 | G12: 6495 | H12: 7 | I12: 7
A13: Lage 5 | B13: Keine Rüstung | E13: 0 | F13: 0 | G13: 0 | H13: 0 | I13: 0
C14: Torso | D14: Gesamt: | E14: 25 | F14: 13 | G14: 7292
B15: Arme | C15: Verarbeitung | D15: Anpassung | E15: RS | F15: BE | G15: Preis | H15: NW | I15: AW
A16: Lage 1 | B16: Stoffrüstung | C16: Gesellenarbeit | D16: angepasst | E16: 2 | F16: 1 | G16: 50 | H16: 3 | I16: 2
A17: Lage 2 | B17: Leichte Lederrüstung | C17: Gesellenarbeit | D17: angepasst | E17: 3 | F17: 2 | G17: 38 | H17: 3 | I17: 2
A18: Lage 3 | B18: Eisen-Kettenpanzer | C18: Gesellenarbeit | D18: angepasst | E18: 4 | F18: 3 | G18: 372 | H18: 3 | I18: 2
A19: Lage 4 | B19: Schwerer Lederpanzer | C19: Gesellenarbeit | D19: angepasst | E19: 5 | F19: 4 | G19: 208 | H19: 3 | I19: 2
A20: Lage 5 | B20: Keine Rüstung | E20: 0 | F20: 0 | G20: 0 | H20: 0 | I20: 0
C21: Arme | D21: Gesamt: | E21: 14 | F21: 10 | G21: 668
B22: Beine | C22: Verarbeitung | D22: Anpassung | E22: RS | F22: BE | G22: Preis | H22: NW | I22: AW
A23: Lage 1 | B23: Stoffrüstung | C23: Gesellenarbeit | D23: angepasst | E23: 2 | F23: 1 | G23: 50 | H23: 3 | I23: 2
A24: Lage 2 | B24: Leichte Lederrüstung | C24: Gesellenarbeit | D24: angepasst | E24: 3 | F24: 2 | G24: 38 | H24: 3 | I24: 2
A25: Lage 3 | B25: Eisen-Kettenpanzer | C25: Gesellenarbeit | D25: angepasst | E25: 4 | F25: 3 | G25: 372 | H25: 3 | I25: 2
A26: Lage 4 | B26: Schwerer Lederpanzer | C26: Gesellenarbeit | D26: angepasst | E26: 5 | F26: 4 | G26: 208 | H26: 3 | I26: 2
A27: Lage 5 | B27: Keine Rüstung | E27: 0 | F27: 0 | G27: 0 | H27: 0 | I27: 0
C28: Beine | D28: Gesamt: | E28: 14 | F28: 10 | G28: 668
F29: BE | G29: Preis
C30: Rüstung | D30: Gesamt: | F30: 43 | G30: 11521
A31: Legende:
A32: Hals, Schultergelenk, Ellenbogen, Hände, Knie und Füße werden nur mit halbem RS geschützt. Augen werden nicht geschützt.Für alle nicht genannten kritischen Trefferzonen gilt der volle Rüstungswert.
A33: Jedes Rüstungsteil kann durch Verarbeitung und Anpassung einmalig modifiziert werden.
A34: Jedes Rüstungsteil hat seine Lage als Mindest-RBE. Lage 5 (Umhänge, Aufpanzerungen) sind hiervon ausgenommen.
A35: Drachenschuppen und andere Aufpanzerungen verfügen über bestimmte Boni, die derzeit noch in der alten Waffentabelle aufgeführt sind...
A36: Rüstung | B36: Lage | C36: RS | D36: BE | F36: Verfügbarkeit NW | G36: Verfügbarkeit AW | H36: Materialkosten | I36: Arbeitszeit/d
A37: Keine Rüstung
A38: Leichte Stoffrüstung | B38: 1 | C38: 1 | D38: 1 | F38: 1 | G38: 1 | H38: 16 | I38: 1
A39: Stoffrüstung | B39: 1 | C39: 2 | D39: 2 | F39: 1 | G39: 1 | H39: 32 | I39: 1
A40: Schwere Stoffrüstung | B40: 1 | C40: 3 | D40: 3 | F40: 1 | G40: 1 | H40: 48 | I40: 1
A41: Keine Rüstung | B41: 1 | F41: 1
A42: Leichte Lederrüstung | B42: 2 | C42: 3 | D42: 3 | F42: 1 | G42: 1 | H42: 14 | I42: 2
A43: Lederrüstung | B43: 2 | C43: 4 | D43: 4 | F43: 1 | G43: 1 | H43: 28 | I43: 2
A44: Schwere Lederrüstung | B44: 2 | C44: 5 | D44: 5 | F44: 1 | G44: 1 | H44: 48 | I44: 2
A45: Keine Rüstung | B45: 2 | F45: 1
A46: Eisen-Kettenpanzer | B46: 3 | C46: 4 | D46: 4 | F46: 1 | G46: 1 | H46: 300 | I46: 10
A47: Stahl-Kettenpanzer | B47: 3 | C47: 5 | D47: 4 | F47: 2 | G47: 1 | H47: 1050 | I47: 10
A48: Schwerer Eisen-Kettenpanzer | B48: 3 | C48: 6 | D48: 5 | F48: 1 | G48: 1 | H48: 480 | I48: 15
A49: Faltstahl-Kettenpanzer | B49: 3 | C49: 7 | D49: 5 | F49: 5 | G49: 3 | H49: 1500 | I49: 10
A50: Schwerer Stahl-Kettenpanzer | B50: 3 | C50: 8 | D50: 6 | F50: 2 | G50: 1 | H50: 1680 | I50: 15
A51: Schwerer Faltstahl-Kettenpanzer | B51: 3 | C51: 9 | D51: 6 | F51: 6 | G51: 4 | H51: 2400 | I51: 15
A52: Keine Rüstung | B52: 3 | F52: 1
A53: Lederpanzer | B53: 4 | C53: 4 | D53: 4 | F53: 2 | G53: 2 | H53: 130 | I53: 3
A54: Schwerer Lederpanzer | B54: 4 | C54: 5 | D54: 5 | F54: 2 | G54: 2 | H54: 172 | I54: 4
A55: Eisenpanzer | B55: 4 | C55: 6 | D55: 6 | F55: 1 | G55: 1 | H55: 607 | I55: 7
A56: Stahlpanzer | B56: 4 | C56: 7 | D56: 7 | F56: 2 | G56: 1 | H56: 2107 | I56: 7
A57: Schwerer Eisenpanzer | B57: 4 | C57: 8 | D57: 8 | F57: 1 | G57: 1 | H57: 907 | I57: 10
A58: Schwerer Stahlpanzer | B58: 4 | C58: 9 | D58: 8 | F58: 2 | G58: 1 | H58: 3157 | I58: 10
A59: Faltstahlpanzer | B59: 4 | C59: 10 | D59: 8 | F59: 5 | G59: 3 | H59: 3007 | I59: 7
A60: Schwerer Faltstahlpanzer | B60: 4 | C60: 12 | D60: 10 | F60: 6 | G60: 4 | H60: 4507 | I60: 10
A61: Keine Rüstung | B61: 5 | F61: 1

Sheet NK-Material
A1: Waffe | B1: Stä-Malus | C1: AT- | D1: PA- | E1: WK | F1: 1H min.Stä | G1: 2H min.Stä | H1: Preis | I1: Klingen-Brecher | J1: Klingen-Schutz | L1: Art/Specials | M1: Rezept-Mod | N1: Verfuegbarkeit-AW | O1: Verfuegbarkeit-NW
A2: Eisen | F2: 1 | G2: 1 | H2: 50 | K2: Dalkini, Draw, Elfen, Goblins, Orks, Trolle, Zentauren, Zwerge | M2: 10 | N2: 1 | O2: 1
A3: Stahl | B3: 1 | D3: 1 | E3: -0.5 | F3: 0.9 | G3: 0.9 | H3: 125 | I3: 1 | J3: 1 | K3: Dalkini, Draw, Elfen, Goblins, Orks, Trolle, Zwerge | M3: 12 | N3: 1 | O3: 2
A4: Qualitätsstahl | B4: 1 | D4: 1 | E4: -0.5 | F4: 0.9 | G4: 0.9 | H4: 175 | I4: 2 | J4: 2 | K4: Dalkini, Draw, Elfen, Goblins, Orks, Zwerge | M4: 18 | N4: 2 | O4: 4
A5: Faltstahl | B5: 2 | D5: 1 | E5: -0.5 | F5: 0.8 | G5: 0.8 | H5: 250 | I5: 3 | J5: 3 | K5: Dalkini, Draw, Elfen, Goblins, Orks, Zwerge | M5: 30 | N5: 3 | O5: 5
A6: Mithril | B6: -1 | D6: 2 | E6: -2 | F6: 0.5 | G6: 0.5 | H6: 1250 | I6: 0 | J6: 2 | K6: Elfen, Zwerge | M6: 20 | N6: 7 | O6: 7
A7: Kolharz | B7: -1 | C7: 1 | D7: 2 | E7: -1 | F7: 0.5 | G7: 0.5 | H7: 1500 | I7: 0 | J7: 0 | K7: Zentauren | M7: 5 | N7: 5 | O7: 7
A8: Alchemistensilber | B8: 0 | C8: -1 | F8: 1 | G8: 1 | H8: 1500 | I8: -1 | J8: -1 | K8: Dalkini, Elfen, Goblins, Orks, Zwerge | M8: 8 | N8: 5 | O8: 6
A9: Nasium | B9: 0 | C9: -1 | D9: -1 | E9: -1 | F9: 1.2 | G9: 1.2 | H9: 1500 | I9: -1 | J9: -1 | K9: Elfen, Zwerge | M9: 7 | N9: 7 | O9: 7
A10: Diamantspat | B10: 3 | D10: 1 | E10: -0.5 | F10: 0.8 | G10: 0.8 | H10: 88 | I10: 3 | J10: 3 | K10: Draw | L10: Zerfällt bei kontakt mit Sonnenlicht zu Staub | M10: 12 | N10: 7 | O10: 7
A11: Adamandit | B11: 3 | D11: 1 | E11: -0.5 | F11: 0.8 | G11: 0.8 | H11: 250000 | I11: 3 | J11: 6 | K11: Draw, Elfen, Goblins, Orks, Zwerge | M11: 120 | N11: M | O11: M
A12: Holz | B12: -3 | C12: 2 | D12: 2 | E12: -1.5 | F12: 0.5 | G12: 0.5 | H12: 0.1 | I12: -11 | J12: -7 | K12: ALLE | M12: 0 | N12: 1 | O12: 1
A13: Knochen | B13: 0 | C13: 1 | D13: 2 | E13: -1 | F13: 0.5 | G13: 0.5 | H13: 0.1 | I13: -4 | J13: -5 | K13: ALLE | M13: 2 | N13: 1 | O13: 1
A14: Stein | B14: 0 | C14: -3 | D14: -2 | E14: 1 | F14: 1.3 | G14: 1.3 | H14: 0.1 | I14: -2 | J14: -3 | K14: Indianer | M14: 5 | N14: 1 | O14: 1
A15: Schwarzfels | B15: 0 | C15: -2 | D15: -1 | E15: 1 | F15: 1.1 | G15: 1.1 | H15: 0.25 | I15: -2 | J15: -2 | K15: Indianer, Katzen | M15: 4 | N15: 5 | O15: 1
A16: Leder | B16: 0 | E16: 0 | F16: 1 | G16: 1 | H16: 0.3 | K16: ALLE | M16: 5 | N16: 1 | O16: 1
A17: Hartholz | B17: -2 | C17: 1 | D17: 2 | E17: -1 | F17: 0.7 | G17: 0.7 | H17: 3 | I17: -7 | J17: -5 | K17: ALLE | L17: Der Schaden wird zur hälfte auf Ausdauer verteielt | M17: 3 | N17: 2 | O17: 2
A18: Vulkanglas | B18: -1 | C18: -3 | D18: -2 | E18: -1 | F18: 1.1 | G18: 1.1 | H18: 3 | I18: -4 | J18: -5 | K18: Indianer, Katzen | M18: 5 | N18: 7 | O18: 3
A19: Chitin | B19: 0 | C19: -1 | D19: 2 | E19: -1 | F19: 0.5 | G19: 0.5 | H19: 20 | I19: -2 | K19: Katzen, Draw, Zwerge, Indianer | M19: 3 | N19: 5 | O19: 2
A20: Bronze | B20: -1 | C20: -1 | E20: 0.5 | F20: 1.1 | G20: 1.1 | H20: 25 | I20: -2 | J20: -2 | K20: Katzen, Indianer | M20: 5 | N20: 1 | O20: 1

Sheet NK-Anpassung
A1: Anpassung | B1: Stä-Malus | C1: AT- | D1: PA- | E1: WK | F1: Min.Stä. 1H | G1: Min.Stä. 2H | H1: Preis | I1: Klingen Brecher | J1: Klingen Schutz | K1: Volk | L1: Art/Specials | N1: Arbeitszeit/d | O1: Verfuegbarkeit-AW | P1: Verfuegbarkeit-NW
A2: Von der Stange | H2: 1 | K2: Standard | M2: 0 | N2: 0 | O2: 1 | P2: 1
A3: angepasst | C3: 1 | D3: 1 | G3: -2 | H3: 2 | K3: ALLE | M3: 6 | N3: 1 | O3: 2 | P3: 3
A4: Perfekt angepasst | C4: 2 | D4: 2 | G4: -4 | H4: 5 | K4: ALLE | M4: 12 | N4: 2 | O4: 3 | P4: 5

Sheet NK-Schaftmaterial
A1: Verstärkung des Schafts | B1: Stä-Malus | C1: AT- | D1: PA- | E1: WK | F1: Min.Stä. 1H | G1: Min.Stä. 2H | H1: Preis/m | I1: Klingen Brecher | J1: Klingen Schutz | K1: Volk | L1: Art/Specials | O1: Verfuegbarkeit-AW | P1: Verfuegbarkeit-NW
A2: Standard | K2: ALLE | M2: 0 | O2: 1 | P2: 1
A3: Eisen Verstärkt | C3: -1 | D3: -1 | G3: 2 | H3: 37.5 | J3: 2 | K3: Dalkini, Draw, Elfen, Goblins, Orks, Trolle, Zentauren, Zwerge | M3: 10 | N3: 0.5 | O3: 1 | P3: 1
A4: Eisen Voll | C4: -2 | D4: -2 | G4: 3 | H4: 275 | J4: 3 | K4: Dalkini, Draw, Elfen, Goblins, Orks, Trolle, Zentauren, Zwerge | M4: 10 | N4: 0.5 | O4: 1 | P4: 1
A5: Stahl Verstärkt | C5: -1 | D5: -1 | G5: 2 | H5: 93.75 | J5: 3 | K5: Dalkini, Draw, Elfen, Goblins, Orks, Trolle, Zwerge | M5: 12 | N5: 0.5 | O5: 1 | P5: 2
A6: Stahl Voll | C6: -2 | D6: -2 | G6: 3 | H6: 687.5 | J6: 4 | K6: Dalkini, Draw, Elfen, Goblins, Orks, Trolle, Zwerge | M6: 12 | N6: 0.5 | O6: 1 | P6: 2
A7: Qualitätsstahl | C7: -1 | D7: -1 | G7: 2 | H7: 131.25 | J7: 4 | K7: Dalkini, Draw, Elfen, Goblins, Orks, Zwerge | M7: 18 | N7: 0.5 | O7: 2 | P7: 4
A8: Qualitätsstahl Voll | C8: -2 | D8: -2 | G8: 3 | H8: 962.5 | J8: 5 | K8: Dalkini, Draw, Elfen, Goblins, Orks, Zwerge | M8: 18 | N8: 0.5 | O8: 2 | P8: 4
A9: Faltstahl Verstärkt | C9: -1 | D9: -1 | G9: 2 | H9: 187.5 | J9: 5 | K9: Dalkini, Draw, Elfen, Goblins, Orks, Zwerge | M9: 30 | N9: 0.5 | O9: 3 | P9: 5
A10: Faltstahl Voll | C10: -2 | D10: -2 | G10: 3 | H10: 1375 | J10: 6 | K10: Dalkini, Draw, Elfen, Goblins, Orks, Zwerge | M10: 30 | N10: 0.5 | O10: 3 | P10: 5
A11: Mithril Verstärkt | C11: 0 | D11: -1 | G11: 1 | H11: 1875 | J11: 2 | K11: Elfen, Zwerge | M11: 20 | N11: 0.5 | O11: 7 | P11: 7
A12: Mithril Voll | C12: -1 | D12: -1 | G12: 1 | H12: 13750 | J12: 3 | K12: Elfen, Zwerge | M12: 20 | N12: 0.5 | O12: 7 | P12: 7
A13: Adamandit Verstärkt | C13: -1 | D13: -1 | G13: 2 | H13: 187500 | J13: 6 | K13: Draw, Elfen, Goblins, Orks, Zwerge | M13: 120 | N13: 0.5 | O13: M | P13: M
A14: Adamandit Voll | C14: -2 | D14: -2 | G14: 3 | H14: 137500 | J14: 7 | K14: Draw, Elfen, Goblins, Orks, Zwerge | M14: 120 | N14: 0.5 | O14: M | P14: M
A15: Bronze Verstärkt | C15: -1 | D15: -1 | G15: 2 | H15: 18.75 | J15: 1 | K15: Katzen, Indianer | M15: 5 | N15: 0.5 | O15: 1 | P15: 1
A16: Bronze Voll | C16: -2 | D16: -2 | G16: 3 | H16: 137.5 | J16: 2 | K16: Katzen, Indianer | M16: 5 | N16: 0.5 | O16: 1 | P16: 1

Sheet NK-Fertigung
A1: Fertigung | B1: Stä-Malus | C1: AT- | D1: PA- | E1: WK | F1: Min.Stä. 1H | G1: Min.Stä. 2H | H1: Preis | I1: Klingen Brecher | J1: Klingen Schutz | K1: Volk | L1: Art/Specials | N1: Verfuegbarkeit-AW | O1: Verfuegbarkeit-NW
A2: Ausschuss | H2: 1.5 | I2: -3 | J2: -6 | K2: ALLE | M2: -6 | N2: 1 | O2: 1
A3: Goblin Massenfab. | H3: 2 | I3: -2 | J3: -3 | K3: Goblin | M3: -4 | N3: 1 | O3: 1
A4: Massenfabrikation | H4: 4 | I4: -1 | J4: -1 | K4: ALLE | M4: -3 | N4: 1 | O4: 1
A5: Gesellenarbeit | H5: 6 | K5: Standard | M5: 0 | N5: 1 | O5: 1
A6: Meisterarbeit | H6: 65 | I6: 1 | J6: 1 | K6: ALLE | M6: 6 | N6: 2 | O6: 3
A7: Großmeisterarbeit | H7: 71 | I7: 2 | J7: 2 | K7: ALLE | M7: 12 | N7: 3 | O7: 5
A8: Einzelstück | H8: 142 | I8: 3 | J8: 3 | K8: ALLE | M8: 24 | N8: 7 | O8: 7

Sheet NK-Waffen-Basis
A1: Hauptfertigkeit | B1: Spezialisierung | C1: Waffe | D1: Ini | E1: WK-Basis | F1: Schadenswuerfel-1 | G1: Schadenswuerfel-2 | H1: Staerke-Teiler | I1: Staerke-Malus-Basis | J1: RB | K1: AT-Basis | L1: PA-Basis | M1: Min-Staerke-1H-Basis | N1: Min-Staerke-2H-Basis | O1: Laenge-m | P1: Tarnung | Q1: Art-Specials | R1: Klingenbrecher-Basis | S1: Klingenschutz-Basis | T1: Rezept-Mod-Basis | U1: Materialpreis-Faktor | V1: Arbeitszeit-Tag-Basis | W1: Volk | X1: RS-Basis | Y1: Preis-Basis | Z1: Verfuegbarkeit-AW | AA1: Verfuegbarkeit-NW
A2: Unbewaffnet | B2: Armklingen | C2: Armklingen | D2: 5 | E2: 3 | F2: W10 | G2: W6 | H2: 3 | I2: -6 | J2: 0 | K2: -2 | L2: -4 | M2: 8 | O2: 0.5 | P2: 0 | Q2: Schnell | R2: 12 | S2: 14 | T2: 10 | U2: 0.7 | V2: 3 | Z2: 1 | AA2: 1
A3: Stichwaffen | B3: Fechtwaffen | C3: Armklingen | D3: 5 | E3: 3 | F3: W10 | G3: W6 | H3: 3 | I3: -6 | J3: 0 | K3: -2 | L3: -4 | M3: 8 | O3: 0.5 | P3: 0 | Q3: Schnell | R3: 12 | S3: 14 | T3: 10 | U3: 0.7 | V3: 3 | Z3: 1 | AA3: 1
A4: Unbewaffnet | B4: Armklingen | C4: Armklingen elfisch | D4: 5 | E4: 2.5 | F4: W12 | G4: W4 | H4: 3 | I4: -6 | J4: 0 | K4: -2 | L4: -3 | M4: 7 | O4: 0.5 | P4: 0 | Q4: Schnell | R4: 12 | S4: 13 | T4: 12 | U4: 0.6 | V4: 4 | W4: Elfen | Z4: 1 | AA4: 1
A5: Hiebwaffen | B5: Äxte | C5: Axt | D5: 7 | E5: 6 | F5: W20 | H5: 2 | I5: -6 | J5: 0 | K5: -4 | L5: -5 | M5: 17 | N5: 10 | O5: 0.72 | P5: 3 | Q5: Holzschaft | R5: 17 | S5: 7 | T5: 8 | U5: 1.8 | V5: 1.5 | Z5: 1 | AA5: 1
A6: Stichwaffen | B6: Fechtwaffen | C6: Bajonett abgepflanzt | D6: 6 | E6: 3 | F6: W12 | G6: W4 | H6: 5 | I6: -3 | J6: 0 | K6: -3 | L6: -5 | M6: 7 | N6: 5 | O6: 0.6 | P6: 4 | R6: 9 | S6: 15 | T6: 5 | U6: 0.6 | V6: 1 | Z6: 1 | AA6: 1
A7: Stangenwaffen | B7: Speere | C7: Bajonett aufgepflanzt | D7: 21 | E7: 3 | F7: W12 | G7: W4 | H7: 5 | I7: -4 | J7: 0 | K7: -5 | L7: -5 | M7: wie Feuerwaffe*2 | N7: wie Feuerwaffe | O7: 2 | P7: 4 | R7: 3 | S7: 8 | T7: 5 | U7: 0.6 | V7: 1 | Z7: 1 | AA7: 1
A8: Hiebwaffen | B8: Beidhand-Hiebwaffen | C8: Barbarendoppelaxt | D8: 14 | E8: 8 | F8: W20 | G8: [2W12] | H8: 1.5 | I8: -16 | J8: 0 | K8: -7 | L8: -7 | M8: 36 | N8: 20 | O8: 1.4 | P8: -- | Q8: Holzschaft | R8: 23 | S8: 8 | T8: 24 | U8: 3.5 | V8: 2.5 | Z8: 1 | AA8: 1
A9: Klingenwaffen | B9: Schwerter | C9: Barbarenschwert | D9: 11 | E9: 6 | F9: W10 | G9: W8 | H9: 2 | I9: -5 | J9: 0 | K9: -5 | L9: -5 | M9: 16 | N9: 12 | O9: 1.1 | P9: -- | R9: 14 | S9: 15 | T9: 16 | U9: 1.5 | V9: 4 | Z9: 1 | AA9: 1
A10: Klingenwaffen | B10: Zweihänder | C10: Barbarenschwert | D10: 11 | E10: 6 | F10: W10 | G10: W8 | H10: 2 | I10: -5 | J10: 0 | K10: -5 | L10: -5 | M10: 16 | N10: 12 | O10: 1.1 | P10: -- | R10: 14 | S10: 15 | T10: 16 | U10: 1.5 | V10: 4 | Z10: 1 | AA10: 1
A11: Klingenwaffen | B11: Schwerter | C11: Bastardschwert | D11: 13 | E11: 6 | F11: W15 | G11: W10 | H11: 2 | I11: -8 | J11: 0 | K11: -5 | L11: -4 | M11: 20 | N11: 13 | O11: 1.3 | P11: -- | R11: 14 | S11: 15 | T11: 19 | U11: 2 | V11: 4 | Z11: 1 | AA11: 1
A12: Klingenwaffen | B12: Zweihänder | C12: Bastardschwert | D12: 13 | E12: 6 | F12: W15 | G12: W10 | H12: 2 | I12: -8 | J12: 0 | K12: -5 | L12: -4 | M12: 20 | N12: 13 | O12: 1.3 | P12: -- | R12: 14 | S12: 15 | T12: 19 | U12: 2 | V12: 4 | Z12: 1 | AA12: 1
A13: Klingenwaffen | B13: Zweihänder | C13: Bat'leth orkisch | D13: 11 | E13: 5.5 | F13: W10 | G13: W10 | H13: 2 | I13: -8 | J13: 0 | K13: -3 | L13: -3 | M13: 15 | N13: 9 | O13: 1.16 | P13: -- | Q13: Schnell | R13: 14 | S13: 14 | T13: 24 | U13: 3 | V13: 8 | W13: Orks | Z13: 1 | AA13: 1
A14: Stangenwaffen | B14: Stäbe | C14: Bat'leth kurz | D14: 10 | E14: 4 | F14: W12 | G14: W6 | H14: 2 | I14: -8 | J14: 0 | K14: -3 | L14: -4 | M14: 13 | N14: 8 | O14: 1 | P14: 0 | R14: 14 | S14: 14 | T14: 20 | U14: 2 | V14: 8 | Z14: 1 | AA14: 1
A15: Klingenwaffen | B15: Zweihänder | C15: Bat'leth kurz | D15: 10 | E15: 4 | F15: W12 | G15: W6 | H15: 2 | I15: -8 | J15: 0 | K15: -3 | L15: -4 | M15: 13 | N15: 8 | O15: 1 | P15: 0 | R15: 14 | S15: 14 | T15: 20 | U15: 2 | V15: 8 | Z15: 1 | AA15: 1
A16: Hiebwaffen | B16: Äxte | C16: Beil | D16: 4 | E16: 5 | F16: W20 | H16: 3 | I16: -5 | J16: 0 | K16: -5 | L16: -5 | M16: 12 | N16: 8 | O16: 0.4 | P16: 6 | Q16: Holzschaft | R16: 16 | S16: 7 | T16: 6 | U16: 0.6 | V16: 1 | Z16: 1 | AA16: 1
A17: Hiebwaffen | B17: Beidhand-Hiebwaffen | C17: Berdysch | D17: 13 | E17: 6.5 | F17: W20 | G17: W6 | H17: 2 | I17: -8 | J17: 0 | K17: -6 | L17: -5 | M17: 24 | N17: 14 | O17: 1.4 | P17: -- | Q17: Holzschaft | R17: 18 | S17: 7 | T17: 18 | U17: 2 | V17: 2 | Z17: 1 | AA17: 1
A18: Stangenwaffen | B18: Hellebarden | C18: Berdysch | D18: 13 | E18: 6.5 | F18: W20 | G18: W6 | H18: 2 | I18: -8 | J18: 0 | K18: -6 | L18: -5 | M18: 24 | N18: 14 | O18: 1.4 | P18: -- | Q18: Holzschaft | R18: 18 | S18: 7 | T18: 18 | U18: 2 | V18: 2 | Z18: 1 | AA18: 1
A19: Klingenwaffen | B19: Schwerter | C19: Breitschwert | D19: 9 | E19: 6 | F19: W10 | G19: W10 | H19: 3 | I19: -4 | J19: 0 | K19: -4 | L19: -4 | M19: 14 | N19: 10 | O19: 0.9 | P19: 2 | R19: 16 | S19: 15 | T19: 14 | U19: 1 | V19: 4 | Z19: 1 | AA19: 1
A20: Klingenwaffen | B20: Zweihänder | C20: Claymore | D20: 16 | E20: 7.5 | F20: W15 | G20: W12 | H20: 1.5 | I20: -11 | J20: 0 | K20: -7 | L20: -6 | M20: 28 | N20: 16 | O20: 1.6 | P20: -- | R20: 17 | S20: 13 | T20: 24 | U20: 2.5 | V20: 5 | Z20: 1 | AA20: 1
A21: Klingenwaffen | B21: Zweihänder | C21: Dai Katana | D21: 14 | E21: 6.5 | F21: 2W12 | H21: 2 | I21: -8 | J21: 0 | K21: -4 | L21: -4 | M21: 22 | N21: 13 | O21: 1.35 | P21: -- | R21: 16 | S21: 14 | T21: 25 | U21: 1.2 | V21: 5 | Z21: 1 | AA21: 1
A22: Stichwaffen | B22: Fechtwaffen | C22: Degen | D22: 13 | E22: 3.5 | F22: W15 | H22: 7 | I22: -2 | J22: 0 | K22: -2 | L22: 0 | M22: 9 | N22: 6 | O22: 1.2 | P22: 1 | R22: 7 | S22: 14 | T22: 18 | U22: 0.75 | V22: 4 | Z22: 1 | AA22: 1
A23: Stichwaffen | B23: Dolche | C23: Dolch | D23: 3 | E23: 2 | F23: W15 | H23: 5 | I23: -3 | J23: 0 | K23: -1 | L23: -6 | M23: 6 | N23: 4 | O23: 0.3 | P23: 8 | R23: 12 | S23: 17 | T23: 5 | U23: 0.3 | V23: 1 | Z23: 1 | AA23: 1
A24: Stichwaffen | B24: Dolche | C24: Dolch ork, Blutrinne | D24: 3 | E24: 1 | F24: W15 | H24: 6 | I24: -3 | J24: 0 | K24: -1 | L24: -6 | M24: 6 | N24: 4 | O24: 0.3 | P24: 8 | Q24: Starke Blutung (x2) | R24: 12 | S24: 15 | T24: 7 | U24: 0.4 | V24: 2 | W24: Orks | Z24: 1 | AA24: 1
A25: Stichwaffen | B25: Dolche | C25: Dolch orkisch, breit | D25: 3 | E25: 2 | F25: W15 | H25: 4 | I25: -4 | J25: 0 | K25: -2 | L25: -5 | M25: 7 | N25: 5 | O25: 0.3 | P25: 7 | R25: 12 | S25: 18 | T25: 5 | U25: 0.4 | V25: 1 | W25: Orks | Z25: 1 | AA25: 1
A26: Stichwaffen | B26: Dolche | C26: Dolch orkisch, mit 3 eingedrehten Klingen | D26: 3 | E26: 3 | F26: W20 | H26: 3 | I26: -7 | J26: 0 | K26: -2 | L26: -5 | M26: 10 | N26: 8 | O26: 0.35 | P26: 4 | R26: 13 | S26: 18 | T26: 15 | U26: 0.5 | V26: 4 | W26: Orks | Z26: 1 | AA26: 1
A27: Hiebwaffen | B27: Äxte | C27: Doppelaxt leicht | D27: 8 | E27: 6 | F27: W20 | H27: 3 | I27: -4 | J27: 0 | K27: -5 | L27: -6 | M27: 20 | N27: 14 | O27: 0.8 | P27: 0 | Q27: Holzschaft | R27: 17 | S27: 8 | T27: 15 | U27: 2.2 | V27: 2.5 | Z27: 1 | AA27: 1
A28: Hiebwaffen | B28: Äxte | C28: Doppelaxt zwergisch | D28: 9 | E28: 7.5 | F28: W20 | G28: W15 | H28: 2 | I28: -12 | J28: 0 | K28: -7 | L28: -6 | M28: 28 | N28: 16 | O28: 0.9 | P28: -- | Q28: Holzschaft | R28: 22 | S28: 8 | T28: 19 | U28: 2.5 | V28: 3 | W28: Zwerge | Z28: 1 | AA28: 1
A29: Hiebwaffen | B29: Äxte | C29: Doppelbeil Zw. kurz | D29: 5 | E29: 6 | F29: W20 | G29: [2W10] | H29: 3 | I29: -11 | J29: 0 | K29: -5 | L29: -4 | M29: 18 | N29: 12 | O29: 0.55 | P29: 3 | Q29: Holzschaft | R29: 18 | S29: 8 | T29: 19 | U29: 1.5 | V29: 3 | W29: Zwerge | Z29: 1 | AA29: 1
A30: Stangenwaffen | B30: Hellebarden | C30: Doppelblatthellebarde | D30: 18 | E30: 7 | F30: W20 | G30: W4 | H30: 2 | I30: -9 | J30: 0 | K30: -6 | L30: -6 | M30: 36 | N30: 16 | O30: 1.8 | P30: -- | Q30: Holzschaft | R30: 17 | S30: 7 | T30: 19 | U30: 3 | V30: 5 | Z30: 1 | AA30: 1
A31: Stangenwaffen | B31: Stäbe | C31: Doppelhellebarde (Kampfstab 2 Hellebarden) | D31: 10 | E31: 6 | F31: W15 | G31: W8 | H31: 3 | I31: -7 | J31: 0 | K31: -4 | L31: -4 | M31: 46 | N31: 18 | O31: 1.8 | P31: -- | Q31: Holzschaft | R31: 16 | S31: 7 | T31: 16 | U31: 3 | V31: 5 | Z31: 1 | AA31: 1
A32: Stangenwaffen | B32: Hellebarden | C32: Doppelsense | D32: 10 | E32: 5 | F32: W15 | G32: W6 | H32: 4 | I32: -6 | J32: 0 | K32: -5 | L32: -5 | M32: 33 | N32: 11 | O32: 1.8 | P32: -- | Q32: Holzschaft, Schnell | R32: 12 | S32: 6 | T32: 12 | U32: 1 | V32: 1 | Z32: 1 | AA32: 1
A33: Klingenwaffen | B33: Zweihänder | C33: Doppelsense | D33: 10 | E33: 5 | F33: W15 | G33: W6 | H33: 4 | I33: -6 | J33: 0 | K33: -5 | L33: -5 | M33: 33 | N33: 11 | O33: 1.8 | P33: -- | Q33: Holzschaft, Schnell | R33: 12 | S33: 6 | T33: 12 | U33: 1 | V33: 1 | Z33: 1 | AA33: 1
A34: Hiebwaffen | B34: Beidhand-Hiebwaffen | C34: Dornenkeule troll, | D34: 16 | E34: 8 | F34: W15 | G34: W12 | H34: 1.5 | I34: -11 | J34: 2 | K34: -6 | L34: -7 | M34: 35 | N34: 20 | O34: 1.8 | P34: -- | Q34: Holzschaft | R34: 14 | S34: 11 | T34: 1 | U34: 0.25 | V34: 1 | W34: Trolle | Z34: 1 | AA34: 1
A35: Unbewaffnet | B35: Peitschen | C35: Dornenpeitsche | D35: 28 | E35: 0 | F35: W4 | G35: W4 | H35: 5 | I35: -1 | J35: 0 | K35: -7 | L35: -15 | M35: 10 | N35: 7 | O35: 3 | P35: 6 | R35: 1 | S35: 7 | T35: 7 | U35: 0.1 | V35: 0.5 | Z35: 1 | AA35: 1
A36: Unbewaffnet | B36: Schild | C36: Drachenschild | E36: 11 | F36: 2W8 | H36: 3 | I36: -5 | J36: 0 | K36: -7 | L36: 9 | M36: 19 | P36: -- | R36: 15 | S36: 13 | T36: 15 | X36: 17 | Y36: 600 | Z36: 1 | AA36: 1
A37: Unbewaffnet | B37: Armklingen | C37: Drei Langklauen | D37: 4 | E37: 3 | F37: W8 | G37: W6 | H37: 3 | I37: -5 | J37: 0 | K37: -3 | L37: -6 | M37: 8 | O37: 0.4 | P37: 0 | R37: 7 | S37: 11 | T37: 8 | U37: 0.4 | V37: 1 | Z37: 1 | AA37: 1
A38: Unbewaffnet | B38: Schild | C38: Dreiecksschild | E38: 8 | F38: W8 | G38: W6 | H38: 3 | I38: -5 | J38: 0 | K38: -6 | L38: 7 | M38: 17 | P38: -- | R38: 15 | S38: 15 | T38: 15 | X38: 16 | Y38: 400 | Z38: 1 | AA38: 1
A39: Unbewaffnet | B39: Schild | C39: Dreiecksschild klein | E39: 6 | F39: W8 | G39: W6 | H39: 3 | I39: -5 | J39: 0 | K39: -5 | L39: 6 | M39: 15 | P39: -- | R39: 15 | S39: 15 | T39: 15 | X39: 15 | Y39: 300 | Z39: 1 | AA39: 1
A40: Stangenwaffen | B40: Speere | C40: Dreizack | D40: 18 | E40: 5 | F40: W12 | G40: W8 | H40: 3 | I40: -6 | J40: 0 | K40: -5 | L40: -3 | M40: 22 | N40: 12 | O40: 1.8 | P40: -- | Q40: Holzschaft | R40: 7 | S40: 7 | T40: 5 | U40: 1 | V40: 1.5 | Z40: 1 | AA40: 1
A41: Hiebwaffen | B41: Stumpfe Hiebwaffen | C41: Dreschflegel eisenbeschlagen | D41: 16 | E41: 4.5 | F41: W10 | G41: W6 | H41: 3 | I41: -3 | J41: 0 | K41: -6 | L41: -7 | M41: 30 | N41: 10 | O41: 1.6 | P41: -- | Q41: Holzschaft | R41: 3 | S41: 6 | T41: 4 | U41: 0.2 | V41: 1 | Z41: 1 | AA41: 1
A42: Klingenwaffen | B42: Schwerter | C42: Eineinhalbhänder | D42: 12 | E42: 6 | F42: W12 | G42: W10 | H42: 2 | I42: -8 | J42: 0 | K42: -5 | L42: -3 | M42: 15 | N42: 11 | O42: 1.2 | P42: 0 | R42: 15 | S42: 14 | T42: 19 | U42: 1.5 | V42: 4 | Z42: 1 | AA42: 1
A43: Klingenwaffen | B43: Zweihänder | C43: Eineinhalbhänder | D43: 12 | E43: 6 | F43: W12 | G43: W10 | H43: 2 | I43: -8 | J43: 0 | K43: -5 | L43: -3 | M43: 15 | N43: 11 | O43: 1.2 | P43: 0 | R43: 15 | S43: 14 | T43: 19 | U43: 1.5 | V43: 4 | Z43: 1 | AA43: 1
A44: Unbewaffnet | B44: Unbewaffnet | C44: Eisenkappenstiefel | D44: 0 | E44: 0 | F44: W6 | G44: W4 | H44: 3 | I44: -5 | J44: 0 | K44: -3 | L44: -11 | M44: 5 | O44: 0.02 | P44: 5 | R44: 5 | S44: 30 | T44: X | U44: x | V44: x | Z44: 1 | AA44: 1
A45: Hiebwaffen | B45: Stumpfe Hiebwaffen | C45: Eisenkeule schwer | D45: 14 | E45: 8 | F45: W12 | G45: W12 | H45: 1.5 | I45: -10 | J45: 0 | K45: -6 | L45: -7 | M45: 32 | N45: 18 | O45: 1.5 | P45: -- | Q45: Holzschaft | R45: 14 | S45: 11 | T45: 4 | U45: 1 | V45: 1 | Z45: 1 | AA45: 1
A46: Hiebwaffen | B46: Stumpfe Hiebwaffen | C46: Eisenkugelstab | D46: 7 | E46: 3 | F46: W6 | G46: W6 | H46: 3 | I46: -4 | J46: 0 | K46: -4 | L46: -4 | M46: 9 | N46: 6 | O46: 0.7 | P46: 4 | Q46: Holzschaft | R46: 7 | S46: 6 | T46: 4 | U46: 1 | V46: 1 | Z46: 1 | AA46: 1
A47: Hiebwaffen | B47: Stumpfe Hiebwaffen | C47: Eisenschlegel | D47: 14 | E47: 6 | F47: W10 | G47: W10 | H47: 2 | I47: -7 | J47: 0 | K47: -6 | L47: -6 | M47: 26 | N47: 16 | O47: 1.4 | P47: -- | Q47: Holzschaft | R47: 12 | S47: 8 | T47: 4 | U47: 1.5 | V47: 1.5 | Z47: 1 | AA47: 1
A48: Hiebwaffen | B48: Stumpfe Hiebwaffen | C48: Eisenstange | D48: 7 | E48: 4 | F48: W6 | G48: W6 | H48: 3 | I48: -4 | J48: 0 | K48: -4 | L48: -4 | M48: 11 | N48: 8 | O48: 0.7 | P48: 4 | R48: 7 | S48: 10 | T48: 0 | U48: 0.7 | V48: 0.1 | Z48: 1 | AA48: 1
A49: Hiebwaffen | B49: Äxte | C49: Enterbeil | D49: 7 | E49: 4 | F49: [2W12] | G49: W6 | H49: 4 | I49: -6 | J49: 0 | K49: -4 | L49: -4 | M49: 10 | N49: 7 | O49: 0.76 | P49: 3 | Q49: Holzschaft | R49: 16 | S49: 7 | T49: 7 | U49: 0.65 | V49: 1 | Z49: 1 | AA49: 1
A50: Hiebwaffen | B50: Kettenwaffen | C50: Enterhaken am Seil | D50: 10 | E50: 5 | F50: W8 | G50: W4 | H50: 4 | I50: -5 | J50: 0 | K50: -8 | L50: -15 | M50: 13 | N50: 10 | O50: 1.5 | P50: 0 | R50: 2 | S50: 4 | T50: 5 | U50: 2 | V50: 0.5 | Z50: 1 | AA50: 1
A51: Hiebwaffen | B51: Äxte | C51: Enterhaken ohne Seil | D51: 2 | E51: 5 | F51: W8 | G51: W4 | H51: 4 | I51: -5 | J51: 0 | K51: -5 | L51: -8 | M51: 11 | N51: 8 | O51: 0.2 | P51: 0 | R51: 7 | S51: 10 | T51: 5 | U51: 2 | V51: 0.5 | Z51: 1 | AA51: 1
A52: Unbewaffnet | B52: Messer | C52: Enterhaken ohne Seil | D52: 2 | E52: 5 | F52: W8 | G52: W4 | H52: 4 | I52: -5 | J52: 0 | K52: -5 | L52: -8 | M52: 11 | N52: 8 | O52: 0.2 | P52: 0 | R52: 7 | S52: 10 | T52: 5 | U52: 2 | V52: 0.5 | Z52: 1 | AA52: 1
A53: Klingenwaffen | B53: Kurzschwerter | C53: Entermesser | D53: 8 | E53: 4 | F53: W8 | G53: W8 | H53: 3 | I53: -4 | J53: 0 | K53: -2 | L53: -3 | M53: 9 | N53: 6 | O53: 0.8 | P53: 4 | R53: 14 | S53: 14 | T53: 12 | U53: 0.8 | V53: 3 | Z53: 1 | AA53: 1
A54: Klingenwaffen | B54: Schwerter | C54: Entermesser | D54: 8 | E54: 4 | F54: W8 | G54: W8 | H54: 3 | I54: -4 | J54: 0 | K54: -2 | L54: -3 | M54: 9 | N54: 6 | O54: 0.8 | P54: 4 | R54: 14 | S54: 14 | T54: 12 | U54: 0.8 | V54: 3 | Z54: 1 | AA54: 1
A55: Unbewaffnet | B55: Schild | C55: Faustschild/Buckler | E55: 4 | F55: W8 | G55: W4 | H55: 2 | I55: -8 | K55: -2 | L55: 2 | M55: 13 | P55: -- | Q55: Keine FK-Parade | R55: 14 | S55: 16 | T55: 15 | X55: 12 | Y55: 100 | Z55: 1 | AA55: 1
A56: Klingenwaffen | B56: Zweihänder | C56: Flamberge | D56: 17 | E56: 8 | F56: 2W15 | H56: 1.5 | I56: -12 | J56: 0 | K56: -7 | L56: -7 | M56: 36 | N56: 18 | O56: 1.8 | P56: -- | R56: 17 | S56: 13 | T56: 28 | U56: 2.5 | V56: 8 | Z56: 1 | AA56: 1
A57: Hiebwaffen | B57: Äxte | C57: Fleischerbeil | D57: 4 | E57: 3.5 | F57: W20 | H57: 4 | I57: -5 | J57: 0 | K57: -6 | L57: -6 | M57: 7 | N57: 3 | O57: 0.4 | P57: 6 | Q57: Holzschaft | R57: 13 | S57: 6 | T57: 5 | U57: 0.6 | V57: 0.5 | Z57: 1 | AA57: 1
A58: Stichwaffen | B58: Fechtwaffen | C58: Florett | D58: 13 | E58: 2 | F58: W8 | G58: W4 | H58: 20 | I58: -1 | J58: 0 | K58: -1 | L58: 1 | M58: 6 | O58: 1.1 | P58: 2 | Q58: Schnell | R58: 0 | S58: 20 | T58: 18 | U58: 0.7 | V58: 4 | Z58: 1 | AA58: 1
A59: Stichwaffen | B59: Fechtwaffen | C59: Gladius | D59: 8 | E59: 4 | F59: W12 | G59: W4 | H59: 4 | I59: -4 | J59: 0 | K59: -3 | L59: -4 | M59: 8 | N59: 6 | O59: 0.75 | P59: 5 | R59: 15 | S59: 15 | T59: 10 | U59: 0.75 | V59: 3 | Z59: 1 | AA59: 1
A60: Klingenwaffen | B60: Kurzschwerter | C60: Gladius | D60: 8 | E60: 4 | F60: W12 | G60: W4 | H60: 4 | I60: -4 | J60: 0 | K60: -3 | L60: -4 | M60: 8 | N60: 6 | O60: 0.75 | P60: 5 | R60: 15 | S60: 15 | T60: 10 | U60: 0.75 | V60: 3 | Z60: 1 | AA60: 1
A61: Stichwaffen | B61: Fechtwaffen | C61: Gladius mit Griffkorb | D61: 7 | E61: 4 | F61: W12 | G61: W4 | H61: 4 | I61: -4 | J61: 0 | K61: -3 | L61: -3 | M61: 9 | N61: 6 | O61: 0.75 | P61: 3 | R61: 15 | S61: 15 | T61: 11 | U61: 0.8 | V61: 3.5 | Z61: 1 | AA61: 1
A62: Klingenwaffen | B62: Kurzschwerter | C62: Gladius mit Griffkorb | D62: 7 | E62: 4 | F62: W12 | G62: W4 | H62: 4 | I62: -4 | J62: 0 | K62: -3 | L62: -3 | M62: 9 | N62: 6 | O62: 0.75 | P62: 3 | R62: 15 | S62: 15 | T62: 11 | U62: 0.8 | V62: 3.5 | Z62: 1 | AA62: 1
A63: Stichwaffen | B63: Fechtwaffen | C63: Gladius kurz | D63: 4 | E63: 3 | F63: W12 | G63: W4 | H63: 4 | I63: -4 | J63: 0 | K63: -2 | L63: -5 | M63: 8 | N63: 5 | O63: 0.45 | P63: 6 | R63: 13 | S63: 18 | T63: 9 | U63: 0.5 | V63: 3 | Z63: 1 | AA63: 1
A64: Klingenwaffen | B64: Kurzschwerter | C64: Gladius kurz | D64: 4 | E64: 3 | F64: W12 | G64: W4 | H64: 4 | I64: -4 | J64: 0 | K64: -2 | L64: -5 | M64: 8 | N64: 5 | O64: 0.45 | P64: 6 | R64: 13 | S64: 18 | T64: 9 | U64: 0.5 | V64: 3 | Z64: 1 | AA64: 1
A65: Stangenwaffen | B65: Speere | C65: Glefe | D65: 29 | E65: 6 | F65: W15 | G65: W10 | H65: 3 | I65: -7 | J65: 0 | K65: -7 | L65: -5 | M65: 26 | N65: 14 | O65: 2.7 | P65: -- | Q65: Holzschaft | R65: 16 | S65: 7 | T65: 16 | U65: 1.1 | V65: 3.5 | Z65: 1 | AA65: 1
A66: Hiebwaffen | B66: Äxte | C66: Hacke | D66: 14 | E66: 4.5 | F66: W15 | G66: W4 | H66: 3 | I66: -5 | J66: 2 | K66: -7 | L66: -7 | M66: 14 | N66: 8 | O66: 1.4 | P66: 0 | Q66: Holzschaft | R66: 10 | S66: 4 | T66: 3 | U66: 0.3 | V66: 0.25 | Z66: 1 | AA66: 1
A67: Stangenwaffen | B67: Stäbe | C67: Hacke | D67: 14 | E67: 4.5 | F67: W15 | G67: W4 | H67: 3 | I67: -5 | J67: 2 | K67: -7 | L67: -7 | M67: 14 | N67: 8 | O67: 1.4 | P67: 0 | Q67: Holzschaft | R67: 10 | S67: 4 | T67: 3 | U67: 0.3 | V67: 0.25 | Z67: 1 | AA67: 1
A68: Stichwaffen | B68: Dolche | C68: Hakendolch | D68: 3 | E68: 2 | F68: W12 | H68: 5 | I68: -2 | J68: 0 | K68: -1 | L68: -6 | M68: 6 | N68: 4 | O68: 0.35 | P68: 6 | R68: 12 | S68: 17 | T68: 7 | U68: 0.3 | V68: 1 | Z68: 1 | AA68: 1
A69: Hiebwaffen | B69: Stumpfe Hiebwaffen | C69: Hammer groß | D69: 3 | E69: 5 | F69: W10 | G69: W6 | H69: 2 | I69: -7 | J69: 0 | K69: -5 | L69: -8 | M69: 10 | N69: 7 | O69: 0.3 | P69: 7 | Q69: Holzschaft | R69: 9 | S69: 6 | T69: 4 | U69: 0.7 | V69: 0.25 | Z69: 1 | AA69: 1
A70: Hiebwaffen | B70: Stumpfe Hiebwaffen | C70: Hammer klein | D70: 2 | E70: 2.5 | F70: W8 | G70: W4 | H70: 3 | I70: -5 | J70: 0 | K70: -6 | L70: -9 | M70: 6 | O70: 0.25 | P70: 8 | Q70: Holzschaft | R70: 8 | S70: 5 | T70: 3 | U70: 0.4 | V70: 0.25 | Z70: 1 | AA70: 1
A71: Stangenwaffen | B71: Hellebarden | C71: Handhellebarde | D71: 13 | E71: 5 | F71: W20 | G71: W6 | H71: 3 | I71: -8 | J71: 0 | K71: -5 | L71: -4 | M71: 25 | N71: 11 | O71: 1.2 | P71: -- | Q71: Holzschaft | R71: 17 | S71: 7 | T71: 16 | U71: 1.5 | V71: 4 | Z71: 1 | AA71: 1
A72: Klingenwaffen | B72: Kurzschwerter | C72: Haumesser | D72: 5 | E72: 2.5 | F72: W6 | G72: W6 | H72: 4 | I72: -2 | J72: 0 | K72: -1 | L72: -5 | M72: 6 | N72: 4 | O72: 0.5 | P72: 6 | R72: 14 | S72: 11 | T72: 10 | U72: 0.8 | V72: 3 | Z72: 1 | AA72: 1
A73: Stangenwaffen | B73: Hellebarden | C73: Hellebarde lang, 3m | D73: 32 | E73: 6 | F73: W20 | G73: W12 | H73: 2 | I73: -14 | J73: 0 | K73: -8 | L73: -7 | M73: 32 | N73: 14 | O73: 3 | P73: -- | Q73: Holzschaft | R73: 17 | S73: 7 | T73: 16 | U73: 1.5 | V73: 4 | Z73: 1 | AA73: 1
A74: Stangenwaffen | B74: Hellebarden | C74: Hellebarde leicht, 2m | D74: 22 | E74: 5 | F74: W15 | G74: W8 | H74: 3 | I74: -7 | J74: 0 | K74: -5 | L74: -5 | M74: 26 | N74: 12 | O74: 2 | P74: -- | Q74: Holzschaft | R74: 17 | S74: 7 | T74: 16 | U74: 1.5 | V74: 4 | Z74: 1 | AA74: 1
A75: Stichwaffen | B75: Dolche | C75: Hiebdolch schwer | D75: 3 | E75: 2 | F75: W10 | G75: W4 | H75: 5 | I75: -3 | J75: 0 | K75: -1 | L75: -5 | M75: 6 | N75: 4 | O75: 0.35 | P75: 6 | R75: 13 | S75: 18 | T75: 5 | U75: 0.4 | V75: 1 | Z75: 1 | AA75: 1
A76: Stichwaffen | B76: Dolche | C76: Hiebdolch kurz | D76: 3 | E76: 1 | F76: W10 | G76: W4 | H76: 5 | I76: -4 | J76: 0 | K76: -1 | L76: -6 | M76: 5 | N76: 3 | O76: 0.25 | P76: 9 | R76: 12 | S76: 18 | T76: 5 | U76: 0.25 | V76: 1 | Z76: 1 | AA76: 1
A77: Unbewaffnet | B77: Messer | C77: Hiebdolch kurz | D77: 3 | E77: 1 | F77: W10 | G77: W4 | H77: 5 | I77: -4 | J77: 0 | K77: -1 | L77: -6 | M77: 5 | N77: 3 | O77: 0.25 | P77: 9 | R77: 12 | S77: 18 | T77: 5 | U77: 0.25 | V77: 1 | Z77: 1 | AA77: 1
A78: Stichwaffen | B78: Fechtwaffen | C78: Hirschfänger (rapierartig) | D78: 8 | E78: 4 | F78: W15 | G78: W4 | H78: 4 | I78: -5 | J78: 0 | K78: -2 | L78: -3 | M78: 8 | N78: 6 | O78: 0.7 | P78: 4 | R78: 14 | S78: 16 | T78: 18 | U78: 0.8 | V78: 4 | Z78: 1 | AA78: 1
A79: Hiebwaffen | B79: Äxte | C79: Holzfälleraxt | D79: 8 | E79: 7 | F79: W20 | G79: W4 | H79: 1.5 | I79: -11 | J79: 0 | K79: -5 | L79: -5 | M79: 28 | N79: 12 | O79: 0.8 | P79: 0 | Q79: Holzschaft | R79: 17 | S79: 6 | T79: 8 | U79: 2 | V79: 1.5 | Z79: 1 | AA79: 1
A80: Stichwaffen | B80: Dolche | C80: Jagdmesser | D80: 3 | E80: 0 | F80: W10 | H80: 6 | I80: -2 | J80: 0 | K80: -1 | L80: -8 | M80: 3 | O80: 0.3 | P80: 11 | R80: 11 | S80: 16 | T80: 4 | U80: 0.3 | V80: 1 | Z80: 1 | AA80: 1
A81: Unbewaffnet | B81: Messer | C81: Jagdmesser | D81: 3 | E81: 0 | F81: W10 | H81: 6 | I81: -2 | J81: 0 | K81: -1 | L81: -8 | M81: 3 | O81: 0.3 | P81: 11 | R81: 11 | S81: 16 | T81: 4 | U81: 0.3 | V81: 1 | Z81: 1 | AA81: 1
A82: Hiebwaffen | B82: Beidhand-Hiebwaffen | C82: junge Birke aus Eisen (KEINE Listenwaffe) | D82: 28 | E82: 15 | F82: W30 | G82: W30 | H82: 1 | I82: -36 | J82: 0 | K82: -9 | L82: -9 | M82: 128 | N82: 64 | O82: 3 | P82: -- | Q82: Holzschaft | R82: 32 | S82: 32 | T82: 10 | U82: 7000 | V82: 4 | Z82: 1 | AA82: 1
A83: Stichwaffen | B83: Dolche | C83: Kampfmesser | D83: 3 | E83: 1 | F83: W12 | H83: 6 | I83: -2 | J83: 0 | K83: -1 | L83: -7 | M83: 4 | O83: 0.28 | P83: 10 | R83: 11 | S83: 17 | T83: 4 | U83: 0.4 | V83: 1 | Z83: 1 | AA83: 1
A84: Unbewaffnet | B84: Messer | C84: Kampfmesser | D84: 3 | E84: 1 | F84: W12 | H84: 6 | I84: -2 | J84: 0 | K84: -1 | L84: -7 | M84: 4 | O84: 0.28 | P84: 10 | R84: 11 | S84: 17 | T84: 4 | U84: 0.4 | V84: 1 | Z84: 1 | AA84: 1
A85: Stangenwaffen | B85: Stäbe | C85: Kampfstab eisenbeschlagen | D85: 11 | E85: 3.5 | F85: W8 | G85: W4 | H85: 4 | I85: -2 | J85: 0 | K85: -2 | L85: -2 | M85: 18 | N85: 7 | O85: 1.8 | P85: -- | Q85: Holzschaft, Schnell | R85: 2 | S85: 7 | T85: 3 | U85: 0.5 | V85: 0.25 | Z85: 1 | AA85: 1
A86: Stangenwaffen | B86: Stäbe | C86: Kampfstab Eisenkolben | D86: 11 | E86: 4 | F86: W8 | G86: W6 | H86: 4 | I86: -2 | J86: 0 | K86: -3 | L86: -3 | M86: 22 | N86: 11 | O86: 1.8 | P86: -- | Q86: Holzschaft, Schnell | R86: 3 | S86: 7 | T86: 4 | U86: 1 | V86: 1 | Z86: 1 | AA86: 1
A87: Stangenwaffen | B87: Stäbe | C87: Kampfstab Eisenspitzen | D87: 11 | E87: 4 | F87: W10 | G87: W4 | H87: 5 | I87: -2 | J87: 0 | K87: -3 | L87: -3 | M87: 20 | N87: 9 | O87: 1.8 | P87: -- | Q87: Holzschaft, Schnell | R87: 3 | S87: 7 | T87: 3 | U87: 0.5 | V87: 1 | Z87: 1 | AA87: 1
A88: Stangenwaffen | B88: Stäbe | C88: Kampfstab kurz eisenb. | D88: 8 | E88: 3 | F88: W6 | G88: W6 | H88: 4 | I88: -2 | J88: 0 | K88: -2 | L88: -1 | M88: 10 | N88: 6 | O88: 1.4 | P88: -- | Q88: Holzschaft, Schnell | R88: 2 | S88: 7 | T88: 2 | U88: 0.5 | V88: 0.25 | Z88: 1 | AA88: 1
A89: Klingenwaffen | B89: Schwerter | C89: Katana 1½-händig | D89: 11 | E89: 5 | F89: W12 | G89: W8 | H89: 3 | I89: -6 | J89: 0 | K89: -3 | L89: -2 | M89: 11 | N89: 8 | O89: 1 | P89: 2 | R89: 15 | S89: 13 | T89: 19 | U89: 1 | V89: 5 | Z89: 1 | AA89: 1
A90: Klingenwaffen | B90: Zweihänder | C90: Katana 1½-händig | D90: 11 | E90: 5 | F90: W12 | G90: W8 | H90: 3 | I90: -6 | J90: 0 | K90: -3 | L90: -2 | M90: 11 | N90: 8 | O90: 1 | P90: 2 | R90: 15 | S90: 13 | T90: 19 | U90: 1 | V90: 5 | Z90: 1 | AA90: 1
A91: Klingenwaffen | B91: Schwerter | C91: Kavalleriesäbel | D91: 10 | E91: 4 | F91: W10 | G91: W6 | H91: 4 | I91: -3 | J91: 0 | K91: -2 | L91: -2 | M91: 9 | N91: 6 | O91: 1 | P91: 1 | R91: 13 | S91: 15 | T91: 16 | U91: 1 | V91: 4 | Z91: 1 | AA91: 1
A92: Hiebwaffen | B92: Kettenwaffen | C92: Kette | D92: 7 | E92: 0 | F92: W4 | G92: W4 | H92: 3 | I92: -4 | J92: 0 | K92: -7 | L92: -15 | M92: 10 | N92: 6 | O92: 1 | P92: 6 | R92: 1 | S92: 12 | T92: 6 | U92: 2 | V92: 1 | Z92: 1 | AA92: 1
A93: Unbewaffnet | B93: Peitschen | C93: Kettenpeitsche | D93: 14 | E93: 7 | F93: W10 | G93: W6 | H93: 2 | I93: -4 | J93: 0 | K93: -7 | L93: -15 | M93: 14 | N93: 11 | O93: 1.5 | P93: 3 | R93: 2 | S93: 7 | T93: 6 | U93: 3 | V93: 1.5 | Z93: 1 | AA93: 1
A94: Hiebwaffen | B94: Stumpfe Hiebwaffen | C94: Keule eisenbeschlagen | D94: 9 | E94: 4 | F94: W6 | G94: W6 | H94: 3 | I94: -4 | J94: 0 | K94: -4 | L94: -5 | M94: 9 | N94: 7 | O94: 1 | P94: 0 | Q94: Holzschaft | R94: 12 | S94: 7 | T94: 3 | U94: 0.5 | V94: 0.25 | Z94: 1 | AA94: 1
A95: Hiebwaffen | B95: Beidhand-Hiebwaffen | C95: Keule troll,, eisenbeschlagen | D95: 15 | E95: 8 | F95: 2W12 | H95: 1.5 | I95: -13 | J95: 0 | K95: -6 | L95: -7 | M95: 34 | N95: 19 | O95: 1.7 | P95: -- | Q95: Holzschaft | R95: 14 | S95: 11 | T95: 10 | U95: 1 | V95: 0.25 | W95: Trolle | Z95: 1 | AA95: 1
A96: Unbewaffnet | B96: Armklingen | C96: Klaue | D96: 2 | E96: 2 | F96: W10 | G96: W6 | H96: 3 | I96: -6 | J96: 0 | K96: -2 | L96: -6 | M96: 6 | O96: 0.2 | P96: 3 | R96: 7 | S96: 12 | T96: 6 | U96: 0.4 | V96: 1 | Z96: 1 | AA96: 1
A97: Hiebwaffen | B97: Äxte | C97: Kriegsbeil | D97: 6 | E97: 4.5 | F97: [2W12] | G97: W12 | H97: 3 | I97: -10 | J97: 0 | K97: -3 | L97: -4 | M97: 12 | N97: 7 | O97: 0.6 | P97: 4 | Q97: Holzschaft | R97: 18 | S97: 7 | T97: 10 | U97: 0.7 | V97: 4 | Z97: 1 | AA97: 1
A98: Hiebwaffen | B98: Äxte | C98: Kriegsbeil orkisch | D98: 9 | E98: 6 | F98: [2W15] | G98: W12 | H98: 3 | I98: -10 | J98: 0 | K98: -5 | L98: -4 | M98: 19 | N98: 12 | O98: 0.9 | P98: 0 | Q98: Holzschaft | R98: 18 | S98: 7 | T98: 8 | U98: 1.2 | V98: 4 | W98: Orks | Z98: 1 | AA98: 1
A99: Hiebwaffen | B99: Beidhand-Hiebwaffen | C99: Kriegshammer (Hammer) | D99: 13 | E99: 7 | F99: W12 | G99: W12 | H99: 2 | I99: -11 | J99: 0 | K99: -7 | L99: -7 | M99: 28 | N99: 16 | O99: 1.4 | P99: -- | Q99: Holzschaft | R99: 19 | S99: 9 | T99: 9 | U99: 1.4 | V99: 5 | Z99: 1 | AA99: 1
A100: Hiebwaffen | B100: Beidhand-Hiebwaffen | C100: Kriegshammer (Schnabel) | D100: 13 | E100: 7 | F100: W30 | H100: 2 | I100: -11 | J100: 4 | K100: -7 | L100: -7 | M100: 28 | N100: 16 | O100: 1.4 | P100: -- | Q100: Holzschaft | R100: 19 | S100: 9 | T100: 9 | U100: 1.4 | V100: 5 | Z100: 1 | AA100: 1
...

Sheet Entwickeln
A1: Bereich | B1: Thema | C1: Beschreibung | D1: Status | E1: Hinzugefuegt
A2: Ausruestung/Schilde | B2: Schild-Preise/Rezept/Materialpreis | C2: 14 Schildzeilen mit #WERT!-Fehlern in NK-Waffen-Basis: Preis/Rezeptschwierigkeit/Materialpreis nicht uebernommen. Die Schilde-Quelltabelle (NN Schilde v0.1.xlsx) hat Materialpreis/Arbeitszeit/Rezept-Mod-Basis komplett unausgefuellt ('x'/'X'), und ihre Basiswerte gelten teils mit Holz statt Eisen als Grundmaterial, nicht kompatibel mit dem NK-Waffen-Materialsystem. Zeilen sind uebernommen, aber als 'aktuell nicht ausruestbar' markiert. Muss von Grund auf neu entwickelt werden (eigenes Material-/Preissystem fuer Schilde, ggf. eigene Normalisierung auf ein einheitliches Basismaterial). -- GELOEST 2026-07-16: 'Schilde v1.4.docx' vom Nutzer bereitgestellt, enthaelt saubere Preis-Basis (100D-1200D) je Schild sowie eigene Material-/Fertigungs-/Bespannungs-Tabellen (multiplikatives Preissystem, siehe Sheets Schild-Material/Schild-Fertigung/Schild-Bespannung). Ausserdem dabei einen Vorzeichenfehler gefunden und korrigiert: 11 der 12 Schilde hatten Staerke-Malus-Basis=+5 statt korrekt -5 in NK-Waffen-Basis. | D2: Geloest | E2: 2026-07-16
A3: Ausruestung/Ruestung | B3: Panzerhandschuhe, Panzerschienen, Eisenkappenstiefel, Orkischer Kampfhandschuh | C3: Ruestungswerte fehlen fuer diese vier Gegenstaende in der Ruestungstabelle (es existiert kein Haende-/Fuesse-Slot, nur Kopf/Torso/Arme/Beine). Rezept-Mod-Basis/Materialpreis-Faktor/Arbeitszeit-Tag-Basis in NK-Waffen-Basis daher = X/x/x. Braucht: (a) Ruestungswerte-System fuer Haende/Fuesse allgemein, (b) konkrete Werte fuer diese 4 Items. | D3: Offen | E3: 2026-07-16
A4: Ausruestung/Ruestung | B4: Ruestungsmodifikatoren/Ruestungsteile-System | C4: Es existiert kein Pendant zu NK-Material/NK-Fertigung/NK-Anpassung/NK-Schaftmaterial fuer Ruestung. Muss komplett neu entwickelt werden, analog zur NK-Waffen-Modifikatorkette. -- GELOEST 2026-07-16: System steckte bereits vollstaendig in NN NPC-Rechner 0.76.xlsx, Sheet 'RS-Sheet' (Nutzerhinweis). Als Sheets Ruestung-Basis (20 Ruestungsteile), Ruestung-Addons (4 Aufpanzerungen, Lage 5), Ruestung-Verarbeitung (4 Stufen), Ruestung-Anpassung (4 Stufen) umgesetzt. Formel (RS = Basis + Verarbeitung; BE = MAX(Lage; Basis+Verarbeitung+Anpassung); Preis = Materialkosten + Lohn*(Arbeitszeit+Zusatztage); Verfuegbarkeit = MAX ueber alle 3 Komponenten) gegen das bestehende Beispiel-Set in Sheet Ruestungstabelle verifiziert (Stoffruestung+Meisterarbeit+angepasst -> RS=3/BE=1/Preis=227/NW=3/AW=2, alle 5 Werte exakt reproduziert). | D4: Geloest | E4: 2026-07-16
A5: Ausruestung/Waffen | B5: Ork'sche (FK/NK-Hybrid) | C5: Pistole/Muskete, die gleichzeitig als Nahkampfwaffe zaehlt. Nur ueber Fertigung/Anpassung modifizierbar, Preis stammt aus der FK-Tabelle; die NK-Version wird beim Kauf der FK-Waffe automatisch mitgeliefert. Grenzfall zwischen FK- und NK-System, noch nicht in NK-Waffen-Basis integriert. | D5: Offen | E5: 2026-07-16
A6: Ausruestung/NK-Waffen | B6: Rezeptschwierigkeit generell | C6: 14 Zeilen mit Rezept-Mod-Basis=X: Wert in der Originalquelle (NN NK-Waffentabelle v1.12) nie ausgefuellt. Korrelation Rezeptschwierigkeit vs. Preis rechnerisch getestet (r=0.007) - kein statistischer Zusammenhang, kann nicht aus dem Preis rekonstruiert werden. Bleibt offen, bis eine inhaltliche Einschaetzung (Spielleitung) vorliegt. | D6: Offen | E6: 2026-07-16
A7: Nahkampf/Unbewaffnet | B7: Voelkerbeschraenkungen bei Unbewaffnet-Kampfstilen | C7: Boxen (Dalkini/Zwerg/Ork), Elfische Kunst der Selbstverteidigung (Elf), Goblinische Kampfkunst (Goblin), Katzenmenschen Kampfkunst (Katzenmensch), Orkisch' Raufen (Ork), Schattenkampf (Drow) sind laut Quelle (Nahkampftabelle Unbewaffnet.doc, 2004) an bestimmte Voelker gebunden. Diese Beschraenkung ist inhaltlich nicht geprueft/nachvollzogen (Nutzer: 'sehe ich persoenlich nicht ein') und sollte ueberarbeitet werden - ebenso die Kampfstile/Faehigkeiten selbst generell (Balance, Aktualitaet, Formulierung der Specials). | D7: Offen | E7: 2026-07-16
A8: Nahkampf/Unbewaffnet | B8: Dynamische Schadenswerte (Boxen, Ringen, Elfische Kunst) | C8: Boxen und Ringen haben Schaden/Staerke-Mod = 'wie unbewaffnet' (haengt von der Rasse des Charakters ab, siehe rassenabhaengige Unbewaffnet-Basiswerte in NK-Waffen-Basis). Elfische Kunst der Selbstverteidigung hat Schaden = 'gegnerischer' (spiegelt den Schaden des Gegners). Beides ist aktuell nur als Text in NK-Waffen-Basis hinterlegt, keine Formel - fehlt eine mechanische Aufloesung im Formel-System (Werte-Sheet). | D8: Offen | E8: 2026-07-16
A9: Nahkampf/Unbewaffnet | B9: Fert/Spez-Maximum Mechanik unklar | C9: Die Quelle gibt pro Kampfstil ein 'Fert/Spez-Maximum' an (z.B. 20/20, 25/30, 30/20). Rohwerte wurden 1:1 in NK-Waffen-Basis Spalte 'Fert-Spez-Maximum' uebernommen, aber die Bedeutung/Wirkung ist ungeklaert (Deckelt es nk_unbewaffnet? Die Spezialisierung? Beides getrennt?). | D9: Offen | E9: 2026-07-16
A10: Nahkampf/Unbewaffnet | B10: 'Staerkebonus' vs. 'Staerke-Mod' bei Biss-Angriffen | C10: Bei Ork- und Katzenmensch-Biss wird der Schaden mit '+[Staerkebonus]' angegeben - eine andere Notation als das sonst genutzte Staerke-Teiler/Staerke-Malus-System (z.B. '(Staerke:3)-7' bei Troll-Biss/Zentaur-Huftritt). Unklar, ob 'Staerkebonus' ein bereits vorhandener Wert im System ist oder neu definiert werden muss. | D10: Offen | E10: 2026-07-16
A11: Nahkampf/Unbewaffnet | B11: Vitalitaet als Ruestungsschutz gegen Unbewaffnet-/Fallschaden | C11: Laut Quelle gibt Vitalitaet einen zusaetzlichen Ruestungsschutz (RS) gegen Schaden durch Unbewaffnet-Angriffe oder Sturz/Fall. Noch nicht ins Ruestungs-/Schadenssystem integriert. | D11: Offen | E11: 2026-07-16
A12: Ausruestung/Schilde | B12: Chitin/Kolhartz Preis-Faktor als Spanne | C12: Schild-Material: Chitin ('*2,5 - *4') und Kolhartz ('*0,1 - *1000') geben in Schilde v1.4.docx eine Preis-Spanne statt eines Einzelwerts an (vermutlich abhaengig von Qualitaet/Seltenheit des Rohmaterials, analog zur Waffen-Materialtabelle, wo Chitin ebenfalls '*2,5 - *4' hat). Braucht eine Entscheidung, wie die Spanne genutzt wird (fester Wert? Wuerfelspanne? Spielleiter-Ermessen?). | D12: Offen | E12: 2026-07-16
... A48: NPC/Kleidung | B48: Standardartikel der Grundkleidung | C48: Unterwäsche: Preisliste Zeile 896 (Unterwäsche, gewöhnlich); Strümpfe: Preisliste Zeile 891 (Strümpfe, Wolle, gewöhnlich); Oberteil: Preisliste Zeile 796 (Hemd, Bluse, Leinen, gewöhnlich); Beinkleidung: Preisliste Zeile 784 (Beinkleider, Leinen, gewöhnlich); Schuhe: Preisliste Zeile 553 (Schuhe, Leder, gewöhnlich); Wetterschutz: Preisliste Zeile 821 (Mantel, Wolle, gewöhnlich); Kopfbedeckung: Preisliste Zeile 767 (Hut, Filz, gewöhnlich) | D48: Bestätigt | E48: 2026-09-09
A49: NPC/Kleidung | B49: Katalogpreis Grundkleidung (D) | C49: =SUM(Preisliste!F896,Preisliste!F891,Preisliste!F796,Preisliste!F784,Preisliste!F553,Preisliste!F821,Preisliste!F767) -> 5.195 | D49: Bestätigt | E49: 2026-09-09
A50: NPC/Kleidung | B50: Anschaffungsbudget Kleidung (D, auf Cent) | C50: =ROUNDUP(C49,2) -> 5.2 | D50: Bestätigt | E50: 2026-09-09
A51: NPC/Kleidung | B51: Kataloggewicht Grundkleidung (kg) | C51: =SUM(Preisliste!E896,Preisliste!E891,Preisliste!E796,Preisliste!E784,Preisliste!E553,Preisliste!E821,Preisliste!E767) -> 4.55 | D51: Bestätigt | E51: 2026-09-09
A52: NPC/Kleidung | B52: Referenz-NPCs und Budget | C52: Neue Vorschauen ergänzen ausschließlich fehlende Bekleidungsbereiche. Der Bauer besitzt bereits vollständige Kleidung. Fünf weitere Referenzen erhalten fehlende Grundkleidung. Das provisorische Anschaffungsbudget der Referenzen wird um die tatsächlichen Ergänzungskosten, auf Cent aufgerundet, erweitert. Keine allgemeine Geldzuteilung für den künftigen Generator. Gespeicherte Charaktere und historische Referenzdateien werden nicht automatisch verändert. | D52: Bestätigt | E52: 2026-09-09
A53: NPC/Kleidung | B53: Beruf und Klima | C53: Reiten: Reiterstiefel P559 statt Schuhe, Reitmantel P819 statt Wollmantel. Seefahrt: Teerjacke P804 nach Bedarf. Schmiede/Mechanik: Lederschürze D066. Wirt/Arzt/Heiler/Alchemist: Leinenschürze D067. Bergmann: Grubenhelm D014 statt Hut. Wache/Soldat: Uniformschnitt und D002. Künstler: passende Auftrittskleidung. Alle übrigen Berufe erhalten die Grundkleidung, angepasst an Klima, Körperbau und Lebenswelt. | D53: Bestätigt | E53: 2026-09-09
A54: NPC/Ausrüstung | B54: Qualität, Besitz, Mengen | C54: Professionsgüte bestimmt weder Qualität noch Besitz. Persönliche, dienstliche, geliehene und betriebliche Ausrüstung unterscheiden. Optionen nach Schwerpunkt wählen. Geteilte Werkzeuge aus Zweitberuf/Lebenswelt nicht doppelt kaufen. Verbrauchsmengen nach Auftrag und Dauer festlegen. Transport, Zuladung, Tiere, Geschirr und Futter zusammen prüfen. Preise bestehender Artikel unverändert übernehmen. | D54: Bestätigt | E54: 2026-09-09
A55: NPC/Ausrüstung | B55: Vorhandene Waren weiterverwenden | C55: Tierfutter P441/P446/P447, Reisebedarf, Lebensmittel, Brennstoff, Fahrzeuge, Geschirre, Waffen und Munition sind bereits vorhanden. P446 umfasst sieben Tage. Keine allgemeine Patrone oder pauschale Heil-/Magiewirkung einführen. Fehlende Gewichte sind nicht null. Regelabhängige Pflanzen, Schulen, Rezepte und Waffenmechaniken nach Auftrag bestimmen. | D55: Bestätigt | E55: 2026-09-09
A56: NPC/Ausrüstung | B56: Verfügbarkeit und Datenpflege | C56: AW/NW-Verfügbarkeit und Völkerzuweisung der neuen Artikel sind noch offen und dürfen nicht als 0 behandelt werden. Die Stück/Paar-Bezeichnungen von Strümpfen und Stiefeln sind vor endgültiger Mengenkalkulation zu prüfen. Der auffällige Preis P800 Lederjacke (0,0018 D) bleibt unverändert und wird nicht für die Grundkleidung verwendet. | D56: Offen | E56: 2026-09-09
A57: NPC/Artikel | B57: D001: Handschellen mit zwei Schlüsseln | C57: Preisliste Zeile 974. Für: Wache, Kopfgeldjäger. Umfang: Passende Handgelenkgröße wählen; keine neue Fesselregel. Preisbegründung: Kurzes Kettenstück mit zwei präzisen Schlössern; Größenordnung des Dietrichsatzes. Preisanker: P701 (140 D); P682 (52.8 D). Regelreferenz: whk_spez_schmied_feinschmied. | D57: Bestätigt | E57: 2026-09-09
A58: NPC/Artikel | B58: D002: Dienstabzeichen, geprägt | C58: Preisliste Zeile 975. Für: Wache, Soldat, Verwalter. Umfang: Blanko oder autorisierte Prägung; Besitz verleiht keine Amtsbefugnisse. Preisbegründung: Kleines Metallteil mit einfacher Prägung unter dem Preis eines Gravurwerkzeugs. Preisanker: P676 (8 D); P677 (1.3 D). Regelreferenz: whk_spez_schmied_feinschmied. | D58: Bestätigt | E58: 2026-09-09
A59: NPC/Artikel | B59: D003: Fahndungsblatt, gedruckt | C59: Preisliste Zeile 976. Für: Wache, Kopfgeldjäger, Journalist. Umfang: Druck eines vorhandenen Texts; Recherche und Belohnung nicht enthalten. Preisbegründung: Papierbogen plus einfacher Druck; Auflage vorausgesetzt. Preisanker: P146 (1.3 D). Regelreferenz: whk_spez_drucker_lithograf. | D59: Bestätigt | E59: 2026-09-09
A60: NPC/Artikel | B60: D004: Revolverholster, Gürtelmontage | C60: Preisliste Zeile 977. Für: Revolverheld, Soldat, Wache, Kopfgeldjäger. Umfang: Für eine konkret gewählte Waffe; Gürtel und Waffe separat. Preisbegründung: Kleines angepasstes Lederbehältnis unter dem Patronengürtel. Preisanker: P567 (5 D); P525 (0.98 D). Regelreferenz: whk_spez_lederbearbeitung_sattler. | D60: Bestätigt | E60: 2026-09-09
A61: NPC/Artikel | B61: D005: Landkarte, Region | C61: Preisliste Zeile 978. Für: Kundschafter, Prospektor, Fuhrmann, Schmuggler, Gelehrter. Umfang: Veröffentlichte Karte, keine aktuelle Geheimaufklärung. Preisbegründung: Mehrere Druck- und Zeichenarbeiten; unter einem gebundenen Tagebuch. Preisanker: P145 (15.4 D); P146 (1.3 D). Regelreferenz: whk_spez_geografie_kartografie. | D61: Bestätigt | E61: 2026-09-09
A62: NPC/Artikel | B62: D006: Seekarte, Küstenabschnitt | C62: Preisliste Zeile 979. Für: Matrose, Schmuggler, Gelehrter. Umfang: Bekannter Küstenabschnitt; Aktualität und Region festlegen. Preisbegründung: Fachliche Kartierung über dem Tagebuch, unter dem Quadranten. Preisanker: P145 (15.4 D); P197 (32 D). Regelreferenz: whk_spez_geografie_kartografie. | D62: Bestätigt | E62: 2026-09-09
A63: NPC/Artikel | B63: D007: Jagdfalle, kleine Kastenfalle | C63: Preisliste Zeile 980. Für: Jäger. Umfang: Für Kleinwild; keine automatisch festgelegten Fang- oder Schadenswerte. Preisbegründung: Stabile kleine Holzkonstruktion mit einfacher Auslösung. Preisanker: P275 (0.89 D); P278 (13 D). Regelreferenz: whk_spez_holzbearbeitung_tischler. | D63: Bestätigt | E63: 2026-09-09
... A123: NPC/Artikel | B123: D067: Arbeitsschürze, Leinen | C123: Preisliste Zeile 1040. Für: Wirt, Heiler, Arzt, Alchemist. Umfang: Waschbare Arbeitsschürze, keine Schutzwirkung gegen Chemikalien zugesichert. Preisbegründung: Einfacher Zuschnitt zwischen Hemd und Hose. Preisanker: P796 (0.2 D); P784 (0.5 D). Regelreferenz: whk_spez_schneider_konfektionsschneider. | D123: Bestätigt | E123: 2026-09-09

Sheet Schild-Material
A1: Material | B1: Staerke-Malus-Mod | C1: AT-Mod | D1: PA-Mod | E1: WK-Mod | F1: Klingenbrecher-Mod | G1: Klingenschutz-Mod | H1: RS-Mod | I1: Min-Staerke-Faktor | J1: Preis-Faktor | K1: Art-Specials | L1: Verfuegbarkeit-AW | M1: Verfuegbarkeit-NW | N1: Volk
A2: Holz | B2: -3 | C2: 2 | D2: 2 | E2: -1.5 | F2: -11 | G2: -10 | H2: -5 | I2: 0.5 | J2: 0.2 | L2: 1 | M2: 1
A3: Hart Holz | B3: -2 | C3: 1 | D3: 2 | E3: -1 | F3: -4 | G3: -5 | H3: -3 | I3: 0.7 | J3: 0.3 | L3: 2 | M3: 2
A4: Leder | B4: 0 | C4: 3 | D4: 3 | E4: 0 | F4: -20 | G4: -15 | H4: -7 | I4: 0.45 | J4: 0.1 | L4: 1 | M4: 1
A5: Spinnenwebe | B5: -6 | C5: 3 | D5: 4 | E5: -2 | F5: -11 | G5: -5 | H5: 3 | I5: 0.4 | J5: 6 | K5: Nur Fernkampf-RS | L5: 4 | M5: 4 | N5: Draw
A6: Chitin | B6: 0 | C6: 1 | D6: 2 | E6: -1 | F6: -2 | G6: 0 | H6: -4 | I6: 0.5 | J6: 3 | L6: 5 | M6: 2 | N6: Katzen, Draw, Zwerge, Indianer
A7: Drachensch. | B7: 0 | C7: 1 | D7: 2 | E7: -1 | F7: -2 | G7: 0 | H7: -3 | I7: 0.5 | J7: Meister (individuell durch Spielleitung) | L7: M | M7: M
A8: Stein | B8: 0 | C8: -3 | D8: -2 | E8: 1 | F8: -2 | G8: -3 | H8: -3 | I8: 1.3 | J8: 0.25 | L8: 1 | M8: 1 | N8: Indianer
A9: Schwarzfels | B9: 0 | C9: -2 | D9: -1 | E9: 1 | F9: -2 | G9: -2 | H9: -1 | I9: 1.1 | J9: 0.5 | L9: 5 | M9: 1 | N9: Indianer, Katzen
A10: Diamantspat | B10: 3 | C10: 0 | D10: 1 | E10: -0.5 | F10: 3 | G10: 3 | H10: 6 | I10: 0.8 | J10: 1.75 | K10: 2 Wuerfe beim Bruchtest | L10: 7 | M10: 7 | N10: Draw
A11: Bronze | B11: -1 | C11: -1 | D11: 0 | E11: 0.5 | F11: -2 | G11: -2 | H11: -2 | I11: 1.1 | J11: 0.5 | L11: 1 | M11: 1 | N11: Katzen, Indianer
A12: Eisen | B12: 0 | C12: -1 | D12: 0 | E12: 0 | F12: -1 | G12: -1 | H12: -1 | I12: 1.1 | J12: 0.75 | L12: 1 | M12: 1 | N12: Dalkini, Draw, Elfen, Goblins, Orks, Trolle, Zentauren, Zwerge
A13: Feineisen | B13: 0 | C13: 0 | D13: 0 | E13: 0 | F13: 0 | G13: 0 | H13: 0 | I13: 1 | J13: 1 | K13: Standard (Referenzmaterial) | L13: 1 | M13: 1 | N13: Dalkini, Draw, Elfen, Goblins, Orks, Trolle, Zentauren, Zwerge
A14: Stahl | B14: 1 | C14: 0 | D14: 1 | E14: -0.5 | F14: 1 | G14: 1 | H14: 2 | I14: 0.9 | J14: 2.5 | L14: 1 | M14: 2 | N14: Dalkini, Draw, Elfen, Goblins, Orks, Trolle, Zwerge
A15: Qualitaetsstahl | B15: 1 | C15: 0 | D15: 1 | E15: -0.5 | F15: 2 | G15: 2 | H15: 3 | I15: 0.9 | J15: 3.5 | L15: 2 | M15: 4 | N15: Dalkini, Draw, Elfen, Goblins, Orks, Zwerge
A16: Faltstahl | B16: 2 | C16: 0 | D16: 1 | E16: -0.5 | F16: 3 | G16: 3 | H16: 5 | I16: 0.8 | J16: 5 | K16: 2 Wuerfe beim Bruchtest | L16: 3 | M16: 5 | N16: Dalkini, Draw, Elfen, Goblins, Orks, Zwerge
A17: Mithril | B17: -1 | C17: 1 | D17: 2 | E17: -2 | F17: 0 | G17: 2 | H17: 2 | I17: 0.5 | J17: 25 | L17: 7 | M17: 7 | N17: Elfen, Zwerge
A18: Adamandit | B18: 3 | C18: 0 | D18: 1 | E18: -0.5 | F18: 3 | G18: +50% (so in Quelle - Bruch mit Format der Spalte, vermutlich Tippfehler statt Flachwert, siehe Entwickeln) | H18: 7 | I18: 0.8 | J18: 5000 | K18: 3 Wuerfe beim Bruchtest | L18: M | M18: M | N18: Draw, Elfen, Goblins, Orks, Zwerge
A19: Alchemistensilber | B19: 0 | C19: -1 | D19: 0 | E19: 0 | F19: -1 | G19: -1 | H19: -1 | I19: 1 | J19: 3.5 | L19: 5 | M19: 6 | N19: Dalkini, Elfen, Goblins, Orks, Zwerge
A20: Vulkanglas | B20: -1 | C20: -3 | D20: -2 | E20: -1 | F20: -4 | G20: -5 | H20: -1 | I20: 1.1 | J20: 3.5 | L20: 7 | M20: 3 | N20: Indianer, Katzen
A21: Nasium | B21: 0 | C21: -1 | D21: -1 | E21: -1 | F21: -1 | G21: -1 | H21: -1 | I21: 1.2 | J21: 30 | L21: 7 | M21: 7 | N21: Elfen, Zwerge
A22: Knochen | B22: 0 | C22: 1 | D22: 2 | E22: -1 | F22: -4 | G22: -5 | H22: -4 | I22: 0.5 | J22: 0.1 | L22: 1 | M22: 1
A23: Kolharz | B23: -1 | C23: 1 | D23: 2 | E23: -1 | F23: 0 | G23: 0 | H23: -1 | I23: 0.5 | J23: 1 | K23: nur auf dem Trollkontinent von Zentauern erhältlich | L23: 5 | M23: 7 | N23: Zentauren

Sheet Schild-Fertigung
A1: Fertigung | B1: Klingenbrecher-Mod | C1: Klingenschutz-Mod | D1: Preis-Faktor | E1: Verfuegbarkeit-AW | F1: Verfuegbarkeit-NW | G1: Volk
A2: Ausschuss | B2: -3 | C2: -6 | D2: 0.3 | E2: 1 | F2: 1
A3: Goblin Massenfab. | B3: -2 | C3: -3 | D3: 0.5 | E3: 1 | F3: 1 | G3: Goblins
A4: Massenfabrikation | B4: -1 | C4: -1 | D4: 0.75 | E4: 1 | F4: 1
A5: Gesellenarbeit | B5: 0 | C5: 0 | D5: 1 | E5: 1 | F5: 1
A6: Meisterarbeit | B6: 1 | C6: 1 | D6: 2 | E6: 2 | F6: 3
A7: Großmeisterarbeit | B7: 2 | C7: 2 | D7: 5 | E7: 3 | F7: 5
A8: Einzelstück | B8: 3 | C8: 3 | D8: 10 | E8: 7 | F8: 7

Sheet Schild-Bespannung
A1: Bespannung | B1: Klingenbrecher-Mod | C1: Klingenschutz-Mod | D1: RS-Mod | E1: Min-Staerke-Faktor | F1: Preis | G1: Art-Specials | H1: Verfuegbarkeit-AW | I1: Verfuegbarkeit-NW | J1: Volk
A2: Stoff | B2: 0 | C2: 0 | F2: 20 | H2: 1 | I2: 1
A3: Spinnenwebe | B3: 0 | C3: 1 | D3: 3 | E3: 1.05 | F3: 600 | G3: Nur FK | H3: 4 | I3: 4 | J3: Draw
A4: Leder | B4: 0 | C4: 2 | D4: 1 | E4: 1.1 | F4: 25 | H4: 1 | I4: 1
A5: Drachenschuppe | B5: 1 | C5: 2 | D5: 4 | E5: 1.2 | F5: Meister (individuell durch Spielleitung) | G5: -50% Einzelelement-Schaden | H5: M | I5: M
A6: Kohlharz | B6: 2 | C6: 3 | D6: 5 | E6: 1.4 | F6: 10 | G6: nur bei Zentauren auf dem Trollkontinent erhältlich. | H6: 4 | I6: 4 | J6: Zentauren

Sheet Schild-Verplatung
A1: Material | B1: Klingenbrecher-Mod | C1: Klingenschutz-Mod | D1: RS-Mod | E1: Min-Staerke-Faktor | F1: Preis-Faktor | G1: Flag
A2: Schwarzfells | G2: Keine Werte in Quelle vorhanden - nur Materialliste, siehe Entwickeln
A3: Diamantspart | G3: Keine Werte in Quelle vorhanden - nur Materialliste, siehe Entwickeln
A4: Bronze | G4: Keine Werte in Quelle vorhanden - nur Materialliste, siehe Entwickeln
A5: Eisen | G5: Keine Werte in Quelle vorhanden - nur Materialliste, siehe Entwickeln
A6: Feineisen | G6: Keine Werte in Quelle vorhanden - nur Materialliste, siehe Entwickeln
A7: Stahl | G7: Keine Werte in Quelle vorhanden - nur Materialliste, siehe Entwickeln
A8: Qualitaetsstahl | G8: Keine Werte in Quelle vorhanden - nur Materialliste, siehe Entwickeln
A9: Faltstahl | G9: Keine Werte in Quelle vorhanden - nur Materialliste, siehe Entwickeln
A10: Mithril | G10: Keine Werte in Quelle vorhanden - nur Materialliste, siehe Entwickeln
A11: Adamandit | G11: Keine Werte in Quelle vorhanden - nur Materialliste, siehe Entwickeln
A12: Alchemistensilb. | G12: Keine Werte in Quelle vorhanden - nur Materialliste, siehe Entwickeln
A13: Vulkanglas | G13: Keine Werte in Quelle vorhanden - nur Materialliste, siehe Entwickeln
A14: Nasium | G14: Keine Werte in Quelle vorhanden - nur Materialliste, siehe Entwickeln

Sheet Artefakt-Magus-Faehigkeiten
A1: Rang | B1: Name | C1: Max-Zaubergrad-Wirkungsstufe | D1: Gehalt | E1: Dublonen-pro-Mana | F1: Angenommene-M | G1: Verfuegbarkeit
A2: 1 | B2: - | C2: 2 | D2: 11 | E2: 0.5 | F2: 5 | G2: 1
A3: 2 | B3: - | C3: 2 | D3: 22 | E3: 1 | F3: 10 | G3: 2
A4: 3 | B4: Magus | C4: 2 | D4: 44 | E4: 2 | F4: 20 | G4: 3
A5: 4 | B5: Magus Magister | C5: 3 | D5: 60 | E5: 6 | F5: 25 | G5: 4
A6: 5 | B6: Magus Major | C6: 4 | D6: 90 | E6: 18 | F6: 30 | G6: 5
A7: 6 | B7: Magus Superior | C7: 5 | D7: 150 | E7: 54 | F7: 35 | G7: 6
A8: 7 | B8: Magus Archus | C8: 6 | D8: 600 | E8: 162 | F8: 40 | G8: 7
A9: 8 | B9: Magus Legendarius | C9: 7 | D9: 1500 | E9: 486 | F9: 45 | G9: 8
A10: 9 | B10: Magus Semi-Deus | C10: 8 | D10: 5000 | E10: 1458 | F10: 50 | G10: 9
A11: 10 | B11: Avatar | C11: 9 | D11: 15000 | E11: 4374 | F11: 55 | G11: 10
A12: 11 | B12: Gott | C12: 10 | D12: 45000 | E12: 13122 | F12: 60 | G12: 11

Sheet Artefakt-Seelensteine
A1: Zauberstufe | B1: Karat-pro-Mana | C1: Dublonen-pro-Mana
A2: 1 | B2: 0.6 | C2: 5
A3: 2 | B3: 0.5 | C3: 10
A4: 3 | B4: 0.4 | C4: 17
A5: 4 | B5: 0.3 | C5: 26
A6: 5 | B6: 0.2 | C6: 37
A7: 6 | B7: 0.1 | C7: 50
A8: 7 | B8: 0.05 | C8: 65
A9: 8 | B9: 0.05 | C9: 82
A10: 9 | B10: 0.05 | C10: 101
A11: 10 | B11: 0.05 | C11: 123

Sheet Artefakt-Manamultiplikator
A1: Differenz | B1: Manamultiplikator
A2: 1 | B2: 0.66666667
A3: 2 | B3: 0.44444444
A4: 3 | B4: 0.2962963
A5: 4 | B5: 0.19753086
A6: 5 | B6: 0.13168724
A7: 6 | B7: 0.087791495
A8: 7 | B8: 0.058527663
A9: 8 | B9: 0.039018442
A10: 9 | B10: 0.026012295
A11: 10 | B11: 0.01734153

Sheet Artefakt-Basis
A1: Referenz | B1: Name | C1: Beschreibung | D1: Zaubergrad | E1: Mana-Basis | F1: Vorbereitungszeit-sec | G1: Effektdauer-sec | H1: Wirkungsdauer-Basis | I1: Wirkungsdauer-Einheit | J1: Wirkung-Basis | K1: Wirkung-Einheit | L1: Eigenschaft | M1: Element | N1: Wirkungsstufe-Offset | O1: Zusatzwert-Art | P1: Schadenselement | Q1: Namenspraefix
A2: artefakt_licht | B2: Licht | C2: Das Artefakt beginnt zu leuchten. Bei Erschaffung muss die Strahlart festgelegt werden: Rundumlicht, Strahl oder Kegel. Das Artefakt leuchtet so hell wie: | D2: 1 | E2: 10 | F2: 1 | G2: sofort | H2: 5 | I2: min | J2: 40 | K2: Fackeln
A3: artefakt_magisches_makeover | B3: Magisches Makeover | C3: Der Magus kann seine Kleidung, seine Nägel und sein Haar in den gewünschten Zustand versetzen. Sämtliche Verunreinigungen oder unangenehmen Gerüche werden entfernt. Verwundungen und Vergiftungen werden hiervon nicht beeinflusst. | D3: 1 | E3: 20 | F3: 1 | G3: 30 | H3: permanent | J3: 40 | K3: %
A4: artefakt_in_nahrung_verwandeln | B4: In Nahrung verwandeln | C4: Der Träger kann unbelebte Materie, die er mit dem Artefakt berührt, in Nahrung verwandeln. Diese Nahrung ist nahezu geschmacklos, deckt aber alle Bedürfnisse des Organismus ab. Es ist möglich, sich ausschließlich von magischer Nahrung zu ernähren. | D4: 1 | E4: 42 | F4: 1 | G4: 60 | H4: permanent | J4: 700 | K4: Gramm
A5: artefakt_whk_talentwert_erhoehen | B5: WHK-Talentwert erhöhen | C5: Der Wert einer festgelegten Handwerks-, Wissens- oder Kultur- Talentes erhöht sich auf magische Weise. Der Wert muss vorher mindestens 4 betragen haben. | D5: 1 | E5: 15 | F5: 1 | G5: sofort | H5: 7 | I5: h | J5: 14 | K5: TaW
A6: artefakt_wasserwandeln | B6: Wasserwandeln | C6: Träger kann auf allen Oberflächen, die zu min. 50% aus Wasser bestehen, wie auf festem Boden gehen. | D6: 1 | E6: 28 | F6: 1 | G6: sofort | H6: 7 | I6: min
A7: artefakt_grundfertigkeit_erhoehen | B7: Grundfertigkeit erhöhen | C7: Eine bei Erschaffung fest gewählte spezialisierbare Grundfertigkeit wird erhöht. Der Wert muss vorher mindestens 4 betragen haben. | D7: 1 | E7: 15 | F7: 1 | G7: sofort | H7: 40 | I7: min | J7: 13 | K7: TaW
A8: artefakt_ausstrahlung_erhoehen | B8: Ausstrahlung erhöhen | C8: Die Ausstrahlung des Trägers wird auf magische Weise erhöht. | D8: 1 | E8: 12 | F8: 1 | G8: sofort | H8: 40 | I8: min | J8: Aus + | K8: 13 | L8: Ausstrahlung
A9: artefakt_waffe_erschaffen | B9: Waffe erschaffen | C9: In den Händen des Magus erscheint eine bei Erschaffung fest definierte beliebige normale Listen-Nahkampfwaffe oder ein beliebiger Listen-Schild, der vollständig aus Eisen besteht. Am Ende der Wirkungsdauer zerfällt die Waffe zu Staub, das ursprüngliche Artefakt bleibt erhalten. Während der Effektdauer hat die Waffe normale Werte, aber AT/PA-Klasse -1. Der Seelenstein ist integrativer Bestandteil des Gegenstands. | D9: 2 | E9: 15 | F9: 2 | G9: 2 | H9: 5 | I9: min
A10: artefakt_athletik_erhoehen | B10: Athletik erhöhen | C10: Athletik des Trägers wird auf magische Weise erhöht. (Aufgeteilt aus 'Körperliche Eigenschaft erhöhen': Eine bei Erschaffung fest gewählte körperliche Eigenschaft (Ath, Ges, Kon, Sch, Stä) wird auf magische Weise erhöht.) | D10: 2 | E10: 18 | F10: 2 | G10: sofort | H10: 40 | I10: min | J10: Eig + | K10: 13 | L10: Athletik
A11: artefakt_geschicklichkeit_erhoehen | B11: Geschicklichkeit erhöhen | C11: Geschicklichkeit des Trägers wird auf magische Weise erhöht. (Aufgeteilt aus 'Körperliche Eigenschaft erhöhen': Eine bei Erschaffung fest gewählte körperliche Eigenschaft (Ath, Ges, Kon, Sch, Stä) wird auf magische Weise erhöht.) | D11: 2 | E11: 18 | F11: 2 | G11: sofort | H11: 40 | I11: min | J11: Eig + | K11: 13 | L11: Geschicklichkeit
A12: artefakt_konstitution_erhoehen | B12: Konstitution erhöhen | C12: Konstitution des Trägers wird auf magische Weise erhöht. (Aufgeteilt aus 'Körperliche Eigenschaft erhöhen': Eine bei Erschaffung fest gewählte körperliche Eigenschaft (Ath, Ges, Kon, Sch, Stä) wird auf magische Weise erhöht.) | D12: 2 | E12: 18 | F12: 2 | G12: sofort | H12: 40 | I12: min | J12: Eig + | K12: 13 | L12: Konstitution
A13: artefakt_schnelligkeit_erhoehen | B13: Schnelligkeit erhöhen | C13: Schnelligkeit des Trägers wird auf magische Weise erhöht. (Aufgeteilt aus 'Körperliche Eigenschaft erhöhen': Eine bei Erschaffung fest gewählte körperliche Eigenschaft (Ath, Ges, Kon, Sch, Stä) wird auf magische Weise erhöht.) | D13: 2 | E13: 18 | F13: 2 | G13: sofort | H13: 40 | I13: min | J13: Eig + | K13: 13 | L13: Schnelligkeit
A14: artefakt_staerke_erhoehen | B14: Staerke erhöhen | C14: Staerke des Trägers wird auf magische Weise erhöht. (Aufgeteilt aus 'Körperliche Eigenschaft erhöhen': Eine bei Erschaffung fest gewählte körperliche Eigenschaft (Ath, Ges, Kon, Sch, Stä) wird auf magische Weise erhöht.) | D14: 2 | E14: 18 | F14: 2 | G14: sofort | H14: 40 | I14: min | J14: Eig + | K14: 13 | L14: Staerke
A15: artefakt_kiemen | B15: Kiemen | C15: Auf den Halsschlagadern bilden sich Kiemen. Dies ist ein schmerzhafter Prozess, bei dem eine um 5 erscwerte Selbstbeherrschungsprobe abgelegt werden muss. Nach dem Ende der Effektdauer kann unter Wasser durch die Kiemen geatmet werden. Atmet er in die Lunge, ertrinkt er. Giftstoffe im Wasser dringen über die Kiemen in den Blutkreislauf ein | D15: 2 | E15: 18 | F15: 2 | G15: 15 | H15: 120 | I15: min
A16: artefakt_stimme_veraendern | B16: Stimme verändern | C16: Die Stimme des Magiers verändert sich auf eine festgelgte Art und Weise. Es ist nicht möglich, die Stimme eines anderen exakt zu reproduzieren. Akzente und Mundarten werden hierdurch nicht simuliert, dafür benötigt der Magier die entsprechenden Sprachfertigkeiten. Während der Effektdauer ist der Magier im Stimmbruch. Wahl: Andere Stimme (Stufe 2, hier angegeben), Laute Stimme (*2: Stufe 3, *3: Stufe vier...); min. Seelenstein- & Wirkungs- Stufe 2 | D16: 2 | E16: 9 | F16: 2 | G16: 5 | H16: 7 | I16: min
A17: artefakt_flammen_pfeil | B17: Flammen - Pfeil | C17: Der Pfeil verursacht zusätzlichen elementaren Schaden. Die Wirkung endet in der Kampfrunde nach dem Aufprall. | D17: 3 | E17: 4 | F17: 3 | G17: sofort | H17: 40 | I17: sec | J17: W30
A18: artefakt_frost_pfeil | B18: Frost - Pfeil | C18: Der Pfeil verursacht zusätzlichen elementaren Schaden. Die Wirkung endet in der Kampfrunde nach dem Aufprall. Pro volle 5 TP erleidet das Opfer eine zusätzliche BE von 1. | D18: 3 | E18: 4 | F18: 3 | G18: sofort | H18: 40 | I18: sec | J18: W20
A19: artefakt_sturm_pfeil | B19: Sturm - Pfeil | C19: Der Pfeil verursacht zusätzlichen elementaren Schaden. Die Wirkung endet in der Kampfrunde nach dem Aufprall. Das Ziel wird TP*m weggeschleudert; Ath-Probe erschwert um TP, sonst zusätzlich W8 Sturzschaden auf FK-TZ (W30). | D19: 3 | E19: 4 | F19: 3 | G19: sofort | H19: 40 | I19: sec | J19: W20
A20: artefakt_splitter_pfeil | B20: Splitter - Pfeil | C20: Der Pfeil verursacht zusätzlichen elementaren Schaden. Die Wirkung endet in der Kampfrunde nach dem Aufprall. Der Splitter - Pfeil kann Rüstungen leichter durchdringen. | D20: 3 | E20: 4 | F20: 3 | G20: sofort | H20: 40 | I20: sec | J20: W20 | K20: RB 8
A21: artefakt_schock_pfeil | B21: Schock - Pfeil | C21: Der Pfeil verursacht zusätzlichen elementaren Schaden. Die Wirkung endet in der Kampfrunde nach dem Aufprall. Sobald das Ziel 1 SP erleidet, muss es eine SB-Probe ablegen, die immer zusätzlich um den angegeben Wert erschwert ist. | D21: 3 | E21: 4 | F21: 3 | G21: sofort | H21: 40 | I21: sec | J21: W20 | K21: SB 13
A22: artefakt_flammen_klinge | B22: Flammen - Klinge | C22: Die Klinge verursacht zusätzlichen elementaren Schaden. | D22: 3 | E22: 26 | F22: 3 | G22: sofort | H22: 40 | I22: min | J22: W30 | M22: Flamme | N22: 1 | P22: Flamme | Q22: Flammen
A23: artefakt_frost_klinge | B23: Frost - Klinge | C23: Die Klinge verursacht zusätzlichen elementaren Schaden. Pro volle 5 TP erleidet das Opfer eine zusätzliche BE von 1. | D23: 3 | E23: 26 | F23: 3 | G23: sofort | H23: 40 | I23: min | J23: W20 | M23: Frost | N23: 0 | P23: Frost | Q23: Frost
A24: artefakt_sturm_klinge | B24: Sturm - Klinge | C24: Die Klinge verursacht zusätzlichen elementaren Schaden. Das Ziel wird TP*m weggeschleudert; Ath-Probe erschwert um TP, sonst zusätzlich W8 Sturzschaden auf FK-TZ (W30). | D24: 3 | E24: 26 | F24: 3 | G24: sofort | H24: 40 | I24: min | J24: W20 | M24: Sturm | N24: 0 | P24: Sturm | Q24: Sturm
A25: artefakt_splitter_klinge | B25: Splitter - Klinge | C25: Die Klinge verursacht zusätzlichen elementaren Schaden. Die Splitter - Klinge kann Rüstungen leichter durchdringen. | D25: 3 | E25: 26 | F25: 3 | G25: sofort | H25: 40 | I25: min | J25: W20 | K25: RB 8 | M25: Splitter | N25: 0 | O25: RB | P25: Erde | Q25: Splitter
A26: artefakt_schock_klinge | B26: Schock - Klinge | C26: Die Klinge verursacht zusätzlichen elementaren Schaden. Sobald das Ziel 1 SP erleidet, muss es eine SB-Probe ablegen, die immer zusätzlich um den angegeben Wert erschwert ist. | D26: 3 | E26: 26 | F26: 3 | G26: sofort | H26: 40 | I26: min | J26: W20 | K26: SB 13 | M26: Schock | N26: 0 | O26: SB | P26: Schock | Q26: Schock
A27: artefakt_material_verstaerken | B27: Material verstärken | C27: Klingenschutz und Klingenbrecher des verzauberten Gegenstandes erhöhen sich. | D27: 3 | E27: 80 | F27: 3 | G27: sofort | H27: 40 | I27: min | J27: 8 | K27: KS/KB
A28: artefakt_intelligenz_erhoehen | B28: Intelligenz erhöhen | C28: Intelligenz des Trägers wird auf magische Weise erhöht. (Aufgeteilt aus 'Geistige Eigenschaft erhöhen': Eine geistige Eigenschaft (Int, Mut, Sin, Wil) wird magisch erhöht.) | D28: 3 | E28: 18 | F28: 3 | G28: sofort | H28: 40 | I28: min | J28: Eig + | K28: 13 | L28: Intelligenz
A29: artefakt_mut_erhoehen | B29: Mut erhöhen | C29: Mut des Trägers wird auf magische Weise erhöht. (Aufgeteilt aus 'Geistige Eigenschaft erhöhen': Eine geistige Eigenschaft (Int, Mut, Sin, Wil) wird magisch erhöht.) | D29: 3 | E29: 18 | F29: 3 | G29: sofort | H29: 40 | I29: min | J29: Eig + | K29: 13 | L29: Mut
A30: artefakt_sinnesschaerfe_erhoehen | B30: Sinnesschaerfe erhöhen | C30: Sinnesschaerfe des Trägers wird auf magische Weise erhöht. (Aufgeteilt aus 'Geistige Eigenschaft erhöhen': Eine geistige Eigenschaft (Int, Mut, Sin, Wil) wird magisch erhöht.) | D30: 3 | E30: 18 | F30: 3 | G30: sofort | H30: 40 | I30: min | J30: Eig + | K30: 13 | L30: Sinnesschaerfe
A31: artefakt_willenskraft_erhoehen | B31: Willenskraft erhöhen | C31: Willenskraft des Trägers wird auf magische Weise erhöht. (Aufgeteilt aus 'Geistige Eigenschaft erhöhen': Eine geistige Eigenschaft (Int, Mut, Sin, Wil) wird magisch erhöht.) | D31: 3 | E31: 18 | F31: 3 | G31: sofort | H31: 40 | I31: min | J31: Eig + | K31: 13 | L31: Willenskraft
A32: artefakt_sinne_verbessern | B32: Sinne verbessern | C32: Entweder der Geruchssinn, der Geschmackssinn, das Gehör, das Sehvermögen oder der Tastsinn werden verbessert. Sinnesschärfen-Proben, die der Meister verlangen könnte, sind um (M):2 erleichtert (entspricht der Wirkungsdauer). Der verbesserte Sinn muss bei Erschaffung des Artefaktes festgelegt werden. | D32: 3 | E32: 92 | F32: 3 | G32: sofort | H32: 20 | I32: min | J32: Sin + | K32: 20
A33: artefakt_in_pflanze_verwandeln | B33: In Pflanze verwandeln | C33: Der Träger sowie alle Ausrüstung in seiner Aura verwandeln sich in eine festgelegte Pflanze und erleidet während der Effektdauer starke Schmerzen, kann aber nicht bewusstlos werden. Während der Wirkungsdauer hat das Ziel die Wahrnehmung der Pflanze, kann also nicht sprechen oder zaubern. Die Wirkung kann nur durch Antimagie vorzeitig beendet werden. Nach Ende der Wirkungsdauer findet eine Rückverwandlung statt, die genauso lange dauert wie die Effektdauer. Die Masse der zu verwandelnden Person bleibt gleich! Während der Wirkungsdauer verfügt der Träger über die folgenden LE/RS - Werte: | D33: 3 | E33: 1800 | F33: 3 | G33: 180 | H33: 40 | I33: h | J33: 400 | K33: 7
A34: artefakt_langsamer_fall | B34: Langsamer Fall | C34: Ein Lebewesen wird durch diesen Zauber so weit verlangsamt, dass es keinen Sturzschaden erfahren kann. | D34: 4 | E34: 130 | F34: 4 | G34: sofort | H34: 20 | I34: sec
A35: artefakt_in_tier_verwandeln | B35: In [Tier] verwandeln | C35: Der Träger wird in ein fest ausgewähltes Tier verwandelt. Dieses Tier verfügt über die selben Werte wie der Träger. In Tierform können keinerlei Zauber gewirkt werden, Sprachfertigkeiten entsprechen den Fähigkeiten des Tieres. Die Umwandlung ist äußerst schmerzhaft und kann nicht vor Ablauf der Wirkungsdauer beendet werden (außer durch Antimagie). Die Masse des Ziels bleibt gleich! | D35: 4 | E35: 1400 | F35: 4 | G35: 60 | H35: 40 | I35: min
A36: artefakt_gecko | B36: Gecko | C36: Der Träger kann mit Händen und Füßen an jeder beliebigen festen Oberfläche haften und dabei seine Maximallast tragen. Klettern-Proben sind erleichtert. | D36: 5 | E36: 88 | F36: 5 | G36: sofort | H36: 40 | I36: min | J36: 20 | K36: Klettern
A37: artefakt_chamaeleon | B37: Chamäleon | C37: Der Träger und alle Gegenstände, die sich innerhalb seiner Aura befinden, werden durchsichtig.Um das Ziel zu Erkennen, ist eine um Wirkungsstufe * 3 erschwerte Sinnesschärfe-Probe nötig. Schleicht/geht/läuft/sprintet/attackiert das Ziel, sind Sinnesschärfe-Proben um Wirkungsstufe*3/2/1/0,5/0,25 erschwert. | D37: 5 | E37: 336 | F37: 5 | G37: 3 | H37: 20 | I37: min | J37: 21 | K37: Sin
A38: artefakt_warp | B38: Warp | C38: Der Träger teleportiert zu einem Punkt, den er sieht. Er löst sich von Fuß zum Kopf hin in Dampf auf, genauso materialisiert er wieder. Er materialisiert immer stehend, Arme angelegt. Abweichung vom Zielpunkt: (Distanz in m/10) = Wx; Wx –Wirkungsstufe =Abweichung in m; Abw. immer horizontal, nicht in Gegenstände hinein, sondern auf/neben ihnen. Patzer: Pech-Probe erschw. um Distanz/10. ->pro 1 Punkt Pech: 1W20 auf alle TZ verteilt, alles ignorierend. Der Magus befindet sich während der Reise 1 sec in der Astralsphäre und benötigt 1 sec um wieder zu materialisieren. | D38: 5 | E38: 22 | F38: 5 | G38: 1 | H38: 1 | I38: sec | J38: 200 | K38: m RW
A39: artefakt_verwandlung | B39: Verwandlung | C39: Der Träger verändert sein Aussehen, je nachdem wie der Artefaktmagier es in das Artefakt gebannt hat. Dies schließt biometrische Merkmale außer der DNA ein. Das Ziel muss während der gesamten Effektdauer bewegungslos bleiben, sonst fällt der Zauber und verursacht unter Umständen ein grauenhaftes Resultat (Ausstrahlungs-Malus von 3 pro min). Die Verwandlung ist ein äußerst schmerzhafter und anstrengender Prozess, bei dem pro min Effektdauer eine SB-Probe erschwert um 15 abzulegen ist. Die Masse bleibt gleich. | D39: 5 | E39: 960 | F39: 5 | G39: 180 | H39: 240 | I39: min
A40: artefakt_last_des_alters | B40: Last des Alters | C40: Der Träger altert um maximal Wirkungsstufe*5 Jahre (entspricht der Wirkungsdauer) und erfährt die Leiden des Alters in voller Stärke. Das Erscheinungsbild, die Beweglichkeit und die Wahrnehmung erleiden die Einbußen, die das Opfer bei natürlicher Alterung erleiden würde. Auf Vitalfunktionen hat dieser Zauber keinerlei Einfluss. Am Ende der Wirkungsdauer verwandelt sich das Opfer in seinen Ursprungszustand zurück. Beide Effektdauern sind äußerst schmerzhaft. | D40: 6 | E40: 600 | F40: 6 | G40: 180 | H40: 200 | I40: min
A41: artefakt_unauffindbarkeit | B41: Unauffindbarkeit | C41: Der Träger und Ausrüstung in seiner Aura verursachen keinerlei Geräusche, hinterlassen keine Spuren und erzeugen keinerlei Gerüche. Optisch, astral und mit Wärmesicht ist das Ziel unmodifiziert zu entdecken. Erleichterung Schleichen&Tarnung/Erschwerung Sinnesschärfe zur Wahrehmung | D41: 6 | E41: 258 | F41: 6 | G41: sofort | H41: 40 | I41: min | J41: 21 | K41: 14
A42: artefakt_unsichtbarkeit | B42: Unsichtbarkeit | C42: Der Träger und alle Ausrüstung in seiner Aura sind vollkommen unsichtbar und weder astral, optisch oder mit Wärmesicht zu entdecken. Bewegt sich das Ziel schneller als gehend oder beginnt es, an einem Kampf teilzunehmen oder zu zaubern, fällt der Zauber. | D42: 6 | E42: 320 | F42: 6 | G42: sofort | H42: 20 | I42: min
A43: artefakt_verjuengung | B43: Verjüngung | C43: Der Träger verjüngt sich und erfährt die Jugend in voller Stärke. Das Erscheinungsbild, die Beweglichkeit und die Wahrnehmung entsprechen dem erzielten Lebensalter. Auf Vitalfunktionen hat dieser Zauber keinerlei Einfluss. Am Ende der Wirkungsdauer verwandelt sich das Opfer in seinen Ursprungszustand zurück. Beide Effektdauern sind äußerst schmerzhaft. Es ist nicht möglich, ein Entwicklungsstadium vor der Geburt zu erzielen. Die Masse bleibt gleich! | D43: 7 | E43: 800 | F43: 7 | G43: 180 | H43: 200 | I43: min | J43: 35 | K43: Jahre
A44: artefakt_artefakt_analysieren | B44: Artefakt analysieren | C44: Magische Gegenstände analysieren bis Grad/erforderliche Magietheorie | D44: 1 | E44: 17 | F44: 1 | G44: 21 | H44: permanent | J44: 7 | K44: 35
A45: artefakt_dammerungssicht | B45: Dammerungssicht | C45: Restlichtverstärker | D45: 1 | E45: 120 | F45: 1 | G45: sofort | H45: 120 | I45: min
A46: artefakt_waermesicht | B46: Wärmesicht | C46: Infrarotsicht | D46: 2 | E46: 40 | F46: 2 | G46: sofort | H46: 20 | I46: min
A47: artefakt_magische_reinigung | B47: Magische Reinigung | C47: Alle anhaltenden und bipolaren Zauber, die auf die Aure des Trägers wirken, werden beendet. | D47: 2 | E47: 6 | F47: 2 | G47: sofort | H47: 2 | I47: sec | J47: Grad | K47: 7
A48: artefakt_magische_sicht | B48: Magische Sicht | C48: Magische Sicht | D48: 3 | E48: 160 | F48: 3 | G48: sofort | H48: 80 | I48: min
A49: artefakt_magischer_schild | B49: Magischer Schild | C49: Die Aura des Zieles wird von einem unsichtbaren Schild geschützt. Es kann pro KR maximal (M):2 TP und insgesamt (M) TP abhalten. RS/LE | D49: 3 | E49: 40 | F49: 3 | G49: sofort | H49: 40 | I49: min | J49: 20 | K49: 40
A50: artefakt_korpi_ignorieren | B50: Korpi ignorieren | C50: Der Magus ermöglicht es einem Gegenstand, magische Korpi zu ignorieren. So ist es dem Gegenstand möglich, durch jede Art von Barriere zu dringen, als wäre sie nicht existent. Diese Gegenstände können von Magiekorpi nicht wahrgenommen werden. Grad 1 „Manaschild“ wird nicht ignoriert (gilt nicht als Magiekorpus), Angriffe auf beseelte Magie-Korpi wie z.B. (Elementar-)Geister und Artefakte unmöglich. | D50: 5 | E50: 72 | F50: 5 | G50: sofort | H50: 40 | I50: min
A51: artefakt_kampfmaschine | B51: Kampfmaschine | C51: Der Träger verschmilzt mit der Artefakt-Waffe. Dies führt zu einer Erleichterung auf alle kampfrelevanten Proben, bei denen die Waffe zum Einsatz kommt. | D51: 6 | E51: 400 | F51: 6 | G51: sofort | H51: 40 | I51: sec | J51: Bonus | K51: 7
A52: artefakt_attributs_artefakt_aura | B52: Attributs-Artefakt (Aura) | C52: Aura wird fuer einen magischen Tag magisch erhoeht. Nur permanent (kein Einmal-Artefakt), Verfuegbarkeit nur ueber den Spielleiter, nicht regulaer erwerbbar. Bezieht sich auf das Attribut 'att_aura' im Werte-Sheet (Kategorie 'Attribute': Aura/Essenz/Glueck/Karma/Magie/Vitalitaet/Weisheit - NICHT die 10 Eigenschaften Athletik...Willenskraft). | D52: 4 | E52: 24 | F52: 4 | G52: sofort | H52: 24 | I52: h | J52: Att + | L52: att_aura
A53: #artefakt_attributs_artefakt_essenz | B53: Attributs-Artefakt (Essenz) | C53: Essenz wird fuer einen magischen Tag magisch erhoeht. Nur permanent (kein Einmal-Artefakt), Verfuegbarkeit nur ueber den Spielleiter, nicht regulaer erwerbbar. Bezieht sich auf das Attribut 'att_essenz' im Werte-Sheet (Kategorie 'Attribute': Aura/Essenz/Glueck/Karma/Magie/Vitalitaet/Weisheit - NICHT die 10 Eigenschaften Athletik...Willenskraft). | D53: 4 | E53: 24 | F53: 4 | G53: sofort | H53: 24 | I53: h | J53: Att + | L53: att_essenz
A54: artefakt_attributs_artefakt_glueck | B54: Attributs-Artefakt (Glück) | C54: Glück wird fuer einen magischen Tag magisch erhoeht. Nur permanent (kein Einmal-Artefakt), Verfuegbarkeit nur ueber den Spielleiter, nicht regulaer erwerbbar. Bezieht sich auf das Attribut 'att_glueck' im Werte-Sheet (Kategorie 'Attribute': Aura/Essenz/Glueck/Karma/Magie/Vitalitaet/Weisheit - NICHT die 10 Eigenschaften Athletik...Willenskraft). | D54: 4 | E54: 24 | F54: 4 | G54: sofort | H54: 24 | I54: h | J54: Att + | L54: att_glueck
A55: artefakt_attributs_artefakt_karma | B55: Attributs-Artefakt (Karma) | C55: Karma wird fuer einen magischen Tag magisch erhoeht. Nur permanent (kein Einmal-Artefakt), Verfuegbarkeit nur ueber den Spielleiter, nicht regulaer erwerbbar. Bezieht sich auf das Attribut 'att_karma' im Werte-Sheet (Kategorie 'Attribute': Aura/Essenz/Glueck/Karma/Magie/Vitalitaet/Weisheit - NICHT die 10 Eigenschaften Athletik...Willenskraft). | D55: 4 | E55: 24 | F55: 4 | G55: sofort | H55: 24 | I55: h | J55: Att + | L55: att_karma
A56: artefakt_attributs_artefakt_magie | B56: Attributs-Artefakt (Magie) | C56: Magie wird fuer einen magischen Tag magisch erhoeht. Nur permanent (kein Einmal-Artefakt), Verfuegbarkeit nur ueber den Spielleiter, nicht regulaer erwerbbar. Bezieht sich auf das Attribut 'att_magie' im Werte-Sheet (Kategorie 'Attribute': Aura/Essenz/Glueck/Karma/Magie/Vitalitaet/Weisheit - NICHT die 10 Eigenschaften Athletik...Willenskraft). | D56: 4 | E56: 24 | F56: 4 | G56: sofort | H56: 24 | I56: h | J56: Att + | L56: att_magie
A57: artefakt_attributs_artefakt_vitalitaet | B57: Attributs-Artefakt (Vitalität) | C57: Vitalität wird fuer einen magischen Tag magisch erhoeht. Nur permanent (kein Einmal-Artefakt), Verfuegbarkeit nur ueber den Spielleiter, nicht regulaer erwerbbar. Bezieht sich auf das Attribut 'att_vitalitaet' im Werte-Sheet (Kategorie 'Attribute': Aura/Essenz/Glueck/Karma/Magie/Vitalitaet/Weisheit - NICHT die 10 Eigenschaften Athletik...Willenskraft). | D57: 4 | E57: 24 | F57: 4 | G57: sofort | H57: 24 | I57: h | J57: Att + | L57: att_vitalitaet
A58: artefakt_attributs_artefakt_weisheit | B58: Attributs-Artefakt (Weisheit) | C58: Weisheit wird fuer einen magischen Tag magisch erhoeht. Nur permanent (kein Einmal-Artefakt), Verfuegbarkeit nur ueber den Spielleiter, nicht regulaer erwerbbar. Bezieht sich auf das Attribut 'att_weisheit' im Werte-Sheet (Kategorie 'Attribute': Aura/Essenz/Glueck/Karma/Magie/Vitalitaet/Weisheit - NICHT die 10 Eigenschaften Athletik...Willenskraft). | D58: 4 | E58: 24 | F58: 4 | G58: sofort | H58: 24 | I58: h | J58: Att + | L58: att_weisheit
A59: artefakt_eigenschafts_artefakt_athletik | B59: Eigenschafts-Artefakt (Athletik) | C59: Athletik wird fuer einen magischen Tag magisch erhoeht. Nur permanent (kein Einmal-Artefakt). Bezieht sich auf die Eigenschaft 'Athletik' im Werte-Sheet (Kategorie 'Eigenschaften': Athletik/Ausstrahlung/Geschicklichkeit/Intelligenz/Konstitution/Mut/Schnelligkeit/Sinnesschaerfe/Staerke/Willenskraft). | D59: 4 | E59: 24 | F59: 4 | G59: sofort | H59: 24 | I59: h | J59: Eig + | L59: Athletik
A60: artefakt_eigenschafts_artefakt_ausstrahlung | B60: Eigenschafts-Artefakt (Ausstrahlung) | C60: Ausstrahlung wird fuer einen magischen Tag magisch erhoeht. Nur permanent (kein Einmal-Artefakt). Bezieht sich auf die Eigenschaft 'Ausstrahlung' im Werte-Sheet (Kategorie 'Eigenschaften': Athletik/Ausstrahlung/Geschicklichkeit/Intelligenz/Konstitution/Mut/Schnelligkeit/Sinnesschaerfe/Staerke/Willenskraft). | D60: 4 | E60: 24 | F60: 4 | G60: sofort | H60: 24 | I60: h | J60: Eig + | L60: Ausstrahlung
A61: artefakt_eigenschafts_artefakt_geschicklichkeit | B61: Eigenschafts-Artefakt (Geschicklichkeit) | C61: Geschicklichkeit wird fuer einen magischen Tag magisch erhoeht. Nur permanent (kein Einmal-Artefakt). Bezieht sich auf die Eigenschaft 'Geschicklichkeit' im Werte-Sheet (Kategorie 'Eigenschaften': Athletik/Ausstrahlung/Geschicklichkeit/Intelligenz/Konstitution/Mut/Schnelligkeit/Sinnesschaerfe/Staerke/Willenskraft). | D61: 4 | E61: 24 | F61: 4 | G61: sofort | H61: 24 | I61: h | J61: Eig + | L61: Geschicklichkeit
A62: artefakt_eigenschafts_artefakt_intelligenz | B62: Eigenschafts-Artefakt (Intelligenz) | C62: Intelligenz wird fuer einen magischen Tag magisch erhoeht. Nur permanent (kein Einmal-Artefakt). Bezieht sich auf die Eigenschaft 'Intelligenz' im Werte-Sheet (Kategorie 'Eigenschaften': Athletik/Ausstrahlung/Geschicklichkeit/Intelligenz/Konstitution/Mut/Schnelligkeit/Sinnesschaerfe/Staerke/Willenskraft). | D62: 4 | E62: 24 | F62: 4 | G62: sofort | H62: 24 | I62: h | J62: Eig + | L62: Intelligenz
A63: artefakt_eigenschafts_artefakt_konstitution | B63: Eigenschafts-Artefakt (Konstitution) | C63: Konstitution wird fuer einen magischen Tag magisch erhoeht. Nur permanent (kein Einmal-Artefakt). Bezieht sich auf die Eigenschaft 'Konstitution' im Werte-Sheet (Kategorie 'Eigenschaften': Athletik/Ausstrahlung/Geschicklichkeit/Intelligenz/Konstitution/Mut/Schnelligkeit/Sinnesschaerfe/Staerke/Willenskraft). | D63: 4 | E63: 24 | F63: 4 | G63: sofort | H63: 24 | I63: h | J63: Eig + | L63: Konstitution
... A68: artefakt_eigenschafts_artefakt_willenskraft | B68: Eigenschafts-Artefakt (Willenskraft) | C68: Willenskraft wird fuer einen magischen Tag magisch erhoeht. Nur permanent (kein Einmal-Artefakt). Bezieht sich auf die Eigenschaft 'Willenskraft' im Werte-Sheet (Kategorie 'Eigenschaften': Athletik/Ausstrahlung/Geschicklichkeit/Intelligenz/Konstitution/Mut/Schnelligkeit/Sinnesschaerfe/Staerke/Willenskraft). | D68: 4 | E68: 24 | F68: 4 | G68: sofort | H68: 24 | I68: h | J68: Eig + | L68: Willenskraft
A69: artefakt_grosser_funkentanz | B69: Grosser Funkentanz | C69: Der Traeger erzeugt viele kleine Lichtfunken, die um seinen eigenen Koerper fliegen. Dadurch wird es fuer jeden Gegner schwerer, ihn mit einer Nahkampf- oder Fernkampf-Attacke zu treffen, um: | D69: 4 | E69: 20 | F69: 7 | G69: sofort | H69: 20 | I69: sec | J69: 4 | K69: Erschwerung (NK/FK)
A70: artefakt_magische_verkleidung | B70: Magische Verkleidung | C70: Bei der Erschaffung wird eine feste Verkleidung festgelegt (gewuenschter Zustand von Kleidung, Naegeln und Haar). Der Traeger erscheint fuer die Wirkungsdauer in dieser Verkleidung - es handelt sich um eine reine optische Illusion, keine tatsaechliche Veraenderung. | D70: 1 | E70: 10 | F70: 7 | G70: 30 | H70: 40 | I70: min
A71: artefakt_manaspende | B71: Manaspende | C71: Nach Ablauf der Effektdauer wird dem Traeger einmalig Mana gutgeschrieben, auch ueber dessen Maximum hinaus, in Hoehe von: | D71: 1 | E71: 14 | F71: 7 | G71: 5 | H71: permanent | J71: 40 | K71: Mana
A72: artefakt_durchsichtiger_gegenstand | B72: Durchsichtiger Gegenstand | C72: Ein Gegenstand wird durchsichtig, bis zu einem Volumen von maximal (in Liter): Aus bestimmten Blickwinkeln kann er mit einer um Wirkungsgrad x 2 erschwerten Sinnesschaerfe-Probe entdeckt werden; wird er bewegt, sinkt die Erschwerung auf aufgerundet(Wirkungsgrad : 2). | D72: 3 | E72: 89 | F72: 7 | G72: sofort | H72: 20 | I72: h | J72: 20 | K72: l

Sheet Artefakt-Kosten
A1: Referenz | B1: Name | C1: Wirkungsgrad | D1: Kosten-einmalig | E1: Verfuegbarkeit-einmalig | F1: Kosten-permanent | G1: Verfuegbarkeit-permanent
A2: artefakt_licht | B2: Licht | C2: 1 | D2: 76 | E2: 3 | F2: 525 | G2: 5
A3: artefakt_licht | B3: Licht | C3: 2 | D3: 218 | E3: 3 | F3: 975 | G3: 5
A4: artefakt_licht | B4: Licht | C4: 3 | D4: 552 | E4: 3 | F4: 1730 | G4: 5
A5: artefakt_licht | B5: Licht | C5: 4 | D5: 920 | E5: 4 | F5: 2368 | G5: 5
A6: artefakt_licht | B6: Licht | C6: 5 | D6: 1590 | E6: 5 | F6: 3450 | G6: 5
A7: artefakt_licht | B7: Licht | C7: 6 | D7: 3020 | E7: 6 | F7: 5860 | G7: 6
A8: artefakt_licht | B8: Licht | C8: 7 | D8: 8780 | E8: 7 | F8: 14080 | G8: 7
A9: artefakt_magisches_makeover | B9: Magisches Makeover | C9: 1 | D9: 120 | E9: 3 | F9: 645 | G9: 5
A10: artefakt_magisches_makeover | B10: Magisches Makeover | C10: 2 | D10: 372 | E10: 3 | F10: 1275 | G10: 5
A11: artefakt_magisches_makeover | B11: Magisches Makeover | C11: 3 | D11: 932 | E11: 3 | F11: 2322 | G11: 5
A12: artefakt_magisches_makeover | B12: Magisches Makeover | C12: 4 | D12: 1480 | E12: 4 | F12: 3656 | G12: 5
A13: artefakt_magisches_makeover | B13: Magisches Makeover | C13: 5 | D13: 2370 | E13: 5 | F13: 5730 | G13: 5
... A351: artefakt_kampfmaschine | B351: Kampfmaschine | C351: 7 | D351: 61040 | E351: 7 | F351: 146680 | G351: 7
A352: artefakt_attributs_artefakt_aura | B352: Attributs-Artefakt (Aura) | C352: 1 | F352: 705 | G352: Meister
A353: artefakt_attributs_artefakt_aura | B353: Attributs-Artefakt (Aura) | C353: 2 | F353: 1475 | G353: Meister
A354: artefakt_attributs_artefakt_aura | B354: Attributs-Artefakt (Aura) | C354: 3 | F354: 2618 | G354: Meister
A355: artefakt_attributs_artefakt_aura | B355: Attributs-Artefakt (Aura) | C355: 4 | F355: 4024 | G355: Meister
A356: artefakt_attributs_artefakt_aura | B356: Attributs-Artefakt (Aura) | C356: 5 | F356: 6642 | G356: Meister
A357: artefakt_attributs_artefakt_aura | B357: Attributs-Artefakt (Aura) | C357: 6 | F357: 9780 | G357: Meister
A358: artefakt_attributs_artefakt_aura | B358: Attributs-Artefakt (Aura) | C358: 7 | F358: 18840 | G358: Meister
A359: #artefakt_attributs_artefakt_essenz | B359: Attributs-Artefakt (Essenz) | C359: 1 | F359: 705 | G359: Meister
A360: #artefakt_attributs_artefakt_essenz | B360: Attributs-Artefakt (Essenz) | C360: 2 | F360: 1475 | G360: Meister
A361: #artefakt_attributs_artefakt_essenz | B361: Attributs-Artefakt (Essenz) | C361: 3 | F361: 2618 | G361: Meister
A362: #artefakt_attributs_artefakt_essenz | B362: Attributs-Artefakt (Essenz) | C362: 4 | F362: 4024 | G362: Meister
A363: #artefakt_attributs_artefakt_essenz | B363: Attributs-Artefakt (Essenz) | C363: 5 | F363: 6642 | G363: Meister
... A400: artefakt_attributs_artefakt_weisheit | B400: Attributs-Artefakt (Weisheit) | C400: 7 | F400: 18840 | G400: Meister
A401: artefakt_eigenschafts_artefakt_athletik | B401: Eigenschafts-Artefakt (Athletik) | C401: 1 | F401: 705 | G401: 5
A402: artefakt_eigenschafts_artefakt_athletik | B402: Eigenschafts-Artefakt (Athletik) | C402: 2 | F402: 1408 | G402: 5
A403: artefakt_eigenschafts_artefakt_athletik | B403: Eigenschafts-Artefakt (Athletik) | C403: 3 | F403: 2438 | G403: 5
A404: artefakt_eigenschafts_artefakt_athletik | B404: Eigenschafts-Artefakt (Athletik) | C404: 4 | F404: 3754 | G404: 5
A405: artefakt_eigenschafts_artefakt_athletik | B405: Eigenschafts-Artefakt (Athletik) | C405: 5 | F405: 6282 | G405: 5
A406: artefakt_eigenschafts_artefakt_athletik | B406: Eigenschafts-Artefakt (Athletik) | C406: 6 | F406: 9030 | G406: 6
A407: artefakt_eigenschafts_artefakt_athletik | B407: Eigenschafts-Artefakt (Athletik) | C407: 7 | F407: 15240 | G407: 7
A408: artefakt_eigenschafts_artefakt_ausstrahlung | B408: Eigenschafts-Artefakt (Ausstrahlung) | C408: 1 | F408: 705 | G408: 5
A409: artefakt_eigenschafts_artefakt_ausstrahlung | B409: Eigenschafts-Artefakt (Ausstrahlung) | C409: 2 | F409: 1408 | G409: 5
A410: artefakt_eigenschafts_artefakt_ausstrahlung | B410: Eigenschafts-Artefakt (Ausstrahlung) | C410: 3 | F410: 2438 | G410: 5
A411: artefakt_eigenschafts_artefakt_ausstrahlung | B411: Eigenschafts-Artefakt (Ausstrahlung) | C411: 4 | F411: 3754 | G411: 5
A412: artefakt_eigenschafts_artefakt_ausstrahlung | B412: Eigenschafts-Artefakt (Ausstrahlung) | C412: 5 | F412: 6282 | G412: 5
... A470: artefakt_eigenschafts_artefakt_willenskraft | B470: Eigenschafts-Artefakt (Willenskraft) | C470: 7 | F470: 15240 | G470: 7
A471: artefakt_grosser_funkentanz | B471: Grosser Funkentanz | C471: 1 | D471: 120 | E471: 3 | F471: 501 | G471: 5
A472: artefakt_grosser_funkentanz | B472: Grosser Funkentanz | C472: 2 | D472: 372 | E472: 3 | F472: 951 | G472: 5
A473: artefakt_grosser_funkentanz | B473: Grosser Funkentanz | C473: 3 | D473: 932 | E473: 3 | F473: 1674 | G473: 5
A474: artefakt_grosser_funkentanz | B474: Grosser Funkentanz | C474: 4 | D474: 1480 | E474: 4 | F474: 2648 | G474: 5
A475: artefakt_grosser_funkentanz | B475: Grosser Funkentanz | C475: 5 | D475: 2370 | E475: 5 | F475: 4290 | G475: 5
A476: artefakt_grosser_funkentanz | B476: Grosser Funkentanz | C476: 6 | D476: 4060 | E476: 6 | F476: 7220 | G476: 6
A477: artefakt_grosser_funkentanz | B477: Grosser Funkentanz | C477: 7 | D477: 10120 | E477: 7 | F477: 16040 | G477: 7
A478: artefakt_magische_verkleidung | B478: Magische Verkleidung | C478: 1 | D478: 76 | E478: 3 | F478: 525 | G478: 5
A479: artefakt_magische_verkleidung | B479: Magische Verkleidung | C479: 2 | D479: 218 | E479: 3 | F479: 975 | G479: 5
A480: artefakt_magische_verkleidung | B480: Magische Verkleidung | C480: 3 | D480: 552 | E480: 3 | F480: 1730 | G480: 5
A481: artefakt_magische_verkleidung | B481: Magische Verkleidung | C481: 4 | D481: 920 | E481: 4 | F481: 2368 | G481: 5
A482: artefakt_magische_verkleidung | B482: Magische Verkleidung | C482: 5 | D482: 1590 | E482: 5 | F482: 3450 | G482: 5
... A498: artefakt_durchsichtiger_gegenstand | B498: Durchsichtiger Gegenstand | C498: 7 | D498: 19366 | E498: 7 | F498: 34532 | G498: 7

Sheet Verfuegbarkeit-Modifikatoren
A1: Kategorie | B1: Auspraegung | C1: Faktor
A2: Herstellungsort | B2: Import, wird nicht hergestellt | C2: 0.5
A3: Herstellungsort | B3: Teilweiser Import, Herstellung im Reich | C3: 0.75
A4: Herstellungsort | B4: Herstellung im Reich | C4: 1
A5: Herstellungsort | B5: Herstellung in der Region | C5: 1.5
A6: Herstellungsort | B6: Herstellung direkt vor Ort | C6: 2
A7: Siedlungsgroesse | B7: Wildnis | C7: 0
A8: Siedlungsgroesse | B8: Siedlung | C8: 0.4
A9: Siedlungsgroesse | B9: Dorf | C9: 0.7
A10: Siedlungsgroesse | B10: Kleinstadt | C10: 1
A11: Siedlungsgroesse | B11: Stadt | C11: 1.1
A12: Siedlungsgroesse | B12: Grossstadt | C12: 1.25
A13: Siedlungsgroesse | B13: Metropole | C13: 1.4
... A26: Haendler | B26: Grosser spezialisierter Haendler | C26: 1.5
A28: Grund-Verfuegbarkeit (Legende) | B28: Grund-Verfuegbarkeit (Legende) | C28: Grund-Verfuegbarkeit (Legende)
A29: Wert | B29: Bedeutung | C29: Optionaler Wuerfelwurf (falls Meister unschluessig)
A30: 1 | B30: Immer | C30: 1-29
A31: 2 | B31: Fast immer | C31: 1-20
A32: 3 | B32: Haeufig | C32: 1-14
A33: 4 | B33: Selten | C33: 1-7
A34: 5 | B34: Fast nie | C34: 1-3
A35: 6 | B35: Nie | C35: 21 (exakt)
A36: 7 | B36: Einzigartig | C36: 29 zwei mal hintereinander

Sheet Ruestung-Basis
A1: Ruestungsteil | B1: Lage | C1: RS-Basis | D1: BE-Basis | E1: Verfuegbarkeit-NW | F1: Verfuegbarkeit-AW | G1: Materialkosten | H1: Arbeitszeit-Tag-Basis | I1: Volk
A2: Leichte Stoffrüstung | B2: 1 | C2: 1 | D2: 1 | E2: 1 | F2: 1 | G2: 16 | H2: 1
A3: Stoffrüstung | B3: 1 | C3: 2 | D3: 2 | E3: 1 | F3: 1 | G3: 32 | H3: 1
A4: Schwere Stoffrüstung | B4: 1 | C4: 3 | D4: 3 | E4: 1 | F4: 1 | G4: 48 | H4: 1
A5: Leichte Lederrüstung | B5: 2 | C5: 3 | D5: 3 | E5: 1 | F5: 1 | G5: 14 | H5: 2
A6: Lederrüstung | B6: 2 | C6: 4 | D6: 4 | E6: 1 | F6: 1 | G6: 28 | H6: 2
A7: Schwere Lederrüstung | B7: 2 | C7: 5 | D7: 5 | E7: 1 | F7: 1 | G7: 48 | H7: 2
A8: Eisen-Kettenpanzer | B8: 3 | C8: 4 | D8: 4 | E8: 1 | F8: 1 | G8: 300 | H8: 10 | I8: Dalkini, Draw, Elfen, Goblins, Orks, Zwerge
A9: Stahl-Kettenpanzer | B9: 3 | C9: 5 | D9: 4 | E9: 2 | F9: 1 | G9: 1050 | H9: 10 | I9: Dalkini, Draw, Elfen, Goblins, Orks, Zwerge
A10: Schwerer Eisen-Kettenpanzer | B10: 3 | C10: 6 | D10: 5 | E10: 1 | F10: 1 | G10: 480 | H10: 15 | I10: Dalkini, Draw, Elfen, Goblins, Orks, Zwerge
A11: Faltstahl-Kettenpanzer | B11: 3 | C11: 7 | D11: 5 | E11: 5 | F11: 3 | G11: 1500 | H11: 10 | I11: Dalkini, Draw, Elfen, Goblins, Orks, Zwerge
A12: Schwerer Stahl-Kettenpanzer | B12: 3 | C12: 8 | D12: 6 | E12: 2 | F12: 1 | G12: 1680 | H12: 15 | I12: Dalkini, Draw, Elfen, Goblins, Orks, Zwerge
A13: Schwerer Faltstahl-Kettenpanzer | B13: 3 | C13: 9 | D13: 6 | E13: 6 | F13: 4 | G13: 2400 | H13: 15 | I13: Dalkini, Draw, Elfen, Goblins, Orks, Zwerge
A14: Lederpanzer | B14: 4 | C14: 4 | D14: 4 | E14: 2 | F14: 2 | G14: 130 | H14: 3
A15: Schwerer Lederpanzer | B15: 4 | C15: 5 | D15: 5 | E15: 2 | F15: 2 | G15: 172 | H15: 4
A16: Eisenpanzer | B16: 4 | C16: 6 | D16: 6 | E16: 1 | F16: 1 | G16: 607 | H16: 7 | I16: Dalkini, Draw, Elfen, Goblins, Orks, Trolle, Zwerge
A17: Stahlpanzer | B17: 4 | C17: 7 | D17: 7 | E17: 2 | F17: 1 | G17: 2107 | H17: 7 | I17: Dalkini, Draw, Elfen, Goblins, Orks, Trolle, Zwerge
A18: Schwerer Eisenpanzer | B18: 4 | C18: 8 | D18: 8 | E18: 1 | F18: 1 | G18: 907 | H18: 10 | I18: Dalkini, Draw, Elfen, Goblins, Orks, Trolle, Zwerge
A19: Schwerer Stahlpanzer | B19: 4 | C19: 9 | D19: 8 | E19: 2 | F19: 1 | G19: 3157 | H19: 10 | I19: Dalkini, Draw, Elfen, Goblins, Orks, Trolle, Zwerge
A20: Faltstahlpanzer | B20: 4 | C20: 10 | D20: 8 | E20: 5 | F20: 3 | G20: 3007 | H20: 7 | I20: Dalkini, Draw, Elfen, Goblins, Orks, Trolle, Zwerge
A21: Schwerer Faltstahlpanzer | B21: 4 | C21: 12 | D21: 10 | E21: 6 | F21: 4 | G21: 4507 | H21: 10 | I21: Dalkini, Draw, Elfen, Goblins, Orks, Trolle, Zwerge

Sheet Ruestung-Addons
A1: Addon | B1: Lage | C1: RS | D1: BE | E1: Verfuegbarkeit-NW | F1: Verfuegbarkeit-AW
A2: Leichte Drachenschuppen | B2: 5 | C2: 3 | D2: 2 | E2: 6 | F2: 6
A3: Drachenschuppen | B3: 5 | C3: 5 | D3: 4 | E3: 6 | F3: 6
A4: Schwere Drachenschuppen | B4: 5 | C4: 7 | D4: 6 | E4: 6 | F4: 6
A5: Spinnweben | B5: 5 | C5: 0 | D5: 0 | E5: 7 | F5: 7

Sheet Ruestung-Verarbeitung
A1: Verarbeitung | B1: RS-Mod | C1: BE-Mod | D1: Verfuegbarkeit-NW | E1: Verfuegbarkeit-AW | F1: Lohn-pro-Tag
A2: Gesellenarbeit | D2: 1 | E2: 1 | F2: 6
A3: Meisterarbeit | B3: 1 | D3: 3 | E3: 2 | F3: 65
A4: Großmeisterarbeit | B4: 2 | D4: 5 | E4: 3 | F4: 71
A5: Einzelstück | B5: 2 | C5: -1 | D5: 7 | E5: 7 | F5: 142

Sheet Ruestung-Anpassung
A1: Anpassung | B1: RS-Mod | C1: BE-Mod | D1: Verfuegbarkeit-NW | E1: Verfuegbarkeit-AW | F1: Zusaetzliche-Tage
A2: völlig unpassend | C2: 2 | D2: 1 | E2: 1 | F2: 0
A3: von der Stange | C3: 0 | D3: 1 | E3: 1 | F3: 0
A4: angepasst | C4: -1 | D4: 3 | E4: 2 | F4: 2
A5: perfekt angepasst | C5: -2 | D5: 5 | E5: 3 | F5: 4

Sheet Munition-Feuerwaffen
A1: Geeignet für | B1: Art | C1: Kaliber | D1: Preis (1Schuss) | E1: Preis-10-Schuss | F1: Preis-50-Schuss | G1: Preis-100-Schuss | H1: Preis-500-Schuss | I1: Preis-1000-Schuss | J1: Besonderheiten
A2: Vorderlader | B2: S.P.&Blei | C2: 12 | D2: 0.366912 | E2: 3.6691 | F2: 18.3456 | G2: 36.6912 | H2: 183.456 | I2: 366.912
A3: Vorderlader | B3: S.P.&Blei | C3: 13 | D3: 0.374556 | E3: 3.7456 | F3: 18.7278 | G3: 37.4556 | H3: 187.278 | I3: 374.556
A4: Vorderlader | B4: S.P.&Blei | C4: 14 | D4: 0.3822 | E4: 3.822 | F4: 19.11 | G4: 38.22 | H4: 191.1 | I4: 382.2
A5: Vorderlader | B5: S.P.&Blei | C5: 15 | D5: 0.389844 | E5: 3.8984 | F5: 19.4922 | G5: 38.9844 | H5: 194.922 | I5: 389.844
A6: Vorderlader | B6: S.P.&Blei | C6: 16 | D6: 0.397488 | E6: 3.9749 | F6: 19.8744 | G6: 39.7488 | H6: 198.744 | I6: 397.488
A7: Vorderlader | B7: S.P.&Blei | C7: 17 | D7: 0.405132 | E7: 4.0513 | F7: 20.2566 | G7: 40.5132 | H7: 202.566 | I7: 405.132
A8: Vorderlader | B8: S.P.&Blei | C8: 18 | D8: 0.412776 | E8: 4.1278 | F8: 20.6388 | G8: 41.2776 | H8: 206.388 | I8: 412.776
A9: Vorderlader | B9: S.P.&Blei | C9: 19 | D9: 0.42042 | E9: 4.2042 | F9: 21.021 | G9: 42.042 | H9: 210.21 | I9: 420.42
A10: Vorderlader | B10: S.P.&Blei | C10: 20 | D10: 0.428064 | E10: 4.2806 | F10: 21.4032 | G10: 42.8064 | H10: 214.032 | I10: 428.064
A11: Vorderlader | B11: S.P.&Blei | C11: 21 | D11: 0.435708 | E11: 4.3571 | F11: 21.7854 | G11: 43.5708 | H11: 217.854 | I11: 435.708
A12: Vorderlader | B12: S.P.&Blei | C12: 22 | D12: 0.443352 | E12: 4.4335 | F12: 22.1676 | G12: 44.3352 | H12: 221.676 | I12: 443.352
A13: Vorderlader | B13: S.P.&Blei | C13: 23 | D13: 0.450996 | E13: 4.51 | F13: 22.5498 | G13: 45.0996 | H13: 225.498 | I13: 450.996
A14: Vorderlader | B14: VL. Papierpatrone | C14: 12 | D14: 0.408855 | E14: 4.0886 | F14: 20.4428 | G14: 40.8855 | H14: 204.4275 | I14: 408.855 | J14: Reduziert die Nachladezeit um 5 Sekunden
A15: Vorderlader | B15: VL. Papierpatrone | C15: 13 | D15: 0.4151775 | E15: 4.1518 | F15: 20.7589 | G15: 41.5178 | H15: 207.5888 | I15: 415.1775 | J15: Reduziert die Nachladezeit um 5 Sekunden
A16: Vorderlader | B16: VL. Papierpatrone | C16: 14 | D16: 0.4215 | E16: 4.215 | F16: 21.075 | G16: 42.15 | H16: 210.75 | I16: 421.5 | J16: Reduziert die Nachladezeit um 5 Sekunden
A17: Vorderlader | B17: VL. Papierpatrone | C17: 15 | D17: 0.4278225 | E17: 4.2782 | F17: 21.3911 | G17: 42.7822 | H17: 213.9112 | I17: 427.8225 | J17: Reduziert die Nachladezeit um 5 Sekunden
A18: Vorderlader | B18: VL. Papierpatrone | C18: 16 | D18: 0.434145 | E18: 4.3415 | F18: 21.7073 | G18: 43.4145 | H18: 217.0725 | I18: 434.145 | J18: Reduziert die Nachladezeit um 5 Sekunden
A19: Vorderlader | B19: VL. Papierpatrone | C19: 17 | D19: 0.4404675 | E19: 4.4047 | F19: 22.0234 | G19: 44.0468 | H19: 220.2338 | I19: 440.4675 | J19: Reduziert die Nachladezeit um 5 Sekunden
A20: Vorderlader | B20: VL. Papierpatrone | C20: 18 | D20: 0.44679 | E20: 4.4679 | F20: 22.3395 | G20: 44.679 | H20: 223.395 | I20: 446.79 | J20: Reduziert die Nachladezeit um 5 Sekunden
A21: Vorderlader | B21: VL. Papierpatrone | C21: 19 | D21: 0.4531125 | E21: 4.5311 | F21: 22.6556 | G21: 45.3113 | H21: 226.5563 | I21: 453.1125 | J21: Reduziert die Nachladezeit um 5 Sekunden
A22: Vorderlader | B22: VL. Papierpatrone | C22: 20 | D22: 0.459435 | E22: 4.5944 | F22: 22.9718 | G22: 45.9435 | H22: 229.7175 | I22: 459.435 | J22: Reduziert die Nachladezeit um 5 Sekunden
A23: Vorderlader | B23: VL. Papierpatrone | C23: 21 | D23: 0.4657575 | E23: 4.6576 | F23: 23.2879 | G23: 46.5758 | H23: 232.8788 | I23: 465.7575 | J23: Reduziert die Nachladezeit um 5 Sekunden
A24: Vorderlader | B24: VL. Papierpatrone | C24: 22 | D24: 0.47208 | E24: 4.7208 | F24: 23.604 | G24: 47.208 | H24: 236.04 | I24: 472.08 | J24: Reduziert die Nachladezeit um 5 Sekunden
A25: Vorderlader | B25: VL. Papierpatrone | C25: 23 | D25: 0.4784025 | E25: 4.784 | F25: 23.9201 | G25: 47.8403 | H25: 239.2013 | I25: 478.4025 | J25: Reduziert die Nachladezeit um 5 Sekunden
A26: Hinterlader | B26: Papierpatrone | C26: 16 | D26: 0.68066667 | E26: 6.8067 | F26: 34.0333 | G26: 68.0667 | H26: 340.3333 | I26: 680.6667
A27: Hinterlader | B27: Papierpatrone | C27: 17 | D27: 0.70108667 | E27: 7.0109 | F27: 35.0543 | G27: 70.1087 | H27: 350.5433 | I27: 701.0867
A28: Hinterlader | B28: Papierpatrone | C28: 18 | D28: 0.72150667 | E28: 7.2151 | F28: 36.0753 | G28: 72.1507 | H28: 360.7533 | I28: 721.5067
A29: Hinterlader | B29: Papierpatrone | C29: 19 | D29: 0.74192667 | E29: 7.4193 | F29: 37.0963 | G29: 74.1927 | H29: 370.9633 | I29: 741.9267
A30: Patronenwaffen | B30: Messingpatrone | C30: 5 | D30: 0.4036032 | E30: 7.814 | F30: 39.07 | G30: 78.14 | H30: 390.7 | I30: 781.4
A31: Patronenwaffen | B31: Messingpatrone | C31: 6 | D31: 0.445104 | E31: 8.2516 | F31: 41.2579 | G31: 82.5158 | H31: 412.5792 | I31: 825.1584
A32: Patronenwaffen | B32: Messingpatrone | C32: 7 | D32: 0.718784 | E32: 8.6892 | F32: 43.4458 | G32: 86.8917 | H32: 434.4584 | I32: 868.9168
A33: Patronenwaffen | B33: Messingpatrone | C33: 8 | D33: 0.8251584 | E33: 9.1268 | F33: 45.6338 | G33: 91.2675 | H33: 456.3376 | I33: 912.6752
A34: Patronenwaffen | B34: Messingpatrone | C34: 9 | D34: 0.8689168 | E34: 9.5643 | F34: 47.8217 | G34: 95.6434 | H34: 478.2168 | I34: 956.4336
A35: Patronenwaffen | B35: Messingpatrone | C35: 10 | D35: 0.9126752 | E35: 10.0019 | F35: 50.0096 | G35: 100.0192 | H35: 500.096 | I35: 1000.192
A36: Patronenwaffen | B36: Messingpatrone | C36: 11 | D36: 0.9564336
A37: Patronenwaffen | B37: Messingpatrone | C37: 12 | D37: 1.000192
A38: Harpunengewehr | B38: Harpune | C38: 16 | D38: 6.88384
A39: Harpunengewehr | B39: Harpune | C39: 17 | D39: 6.88384

Sheet Munition-Ressourcen
A1: Material | B1: Dublonen-pro-KG | C1: Massenfabrikation-Dublonen-pro-KG
A2: Messing | B2: 32 | C2: 25.6
A3: Blei | B3: 12 | C3: 9.6
A4: Schwarzpulver | B4: 85 | C4: 68
A5: Papier | B5: 15 | C5: 12
A7: Handwerker/Anlage | B7: Dublonen-pro-Tag | C7: Hinweis
A8: Kugelgießer | B8: 1
A9: (Schwarz-)Pulvermischer | B9: 1.5
A10: Munitionsmanufaktur (Pauschale/Tag) | B10: 20 | C10: Beinhaltet Manufakturkosten und 3 Vorarbeiter
A11: Komplette Manufaktur | B11: 38 | C11: Beinhaltet Manufakturkosten, 3 Vorarbeiter, 6 (Schwarz-)Pulvermischer, 9 Kugelgiesser
A13: Patronentyp | B13: Schwarzpulver-kg | C13: Blei-kg | D13: Papier-kg | E13: Messing-kg | F13: Gesamtgewicht-kg | G13: Manufaktur-Ausstoss-pro-Tag | H13: Herstellungskosten-pro-Schuss | I13: Materialkosten-pro-Schuss | J13: Gesamtkosten-pro-Schuss
A14: Blei (+Schwarzpulver) | B14: 0.005 | C14: 0.004 | F14: 0.009 | G14: 10000 | H14: 0.0038 | I14: 0.3784 | J14: 0.3822
A15: VL. Papierpatrone | B15: 0.005 | C15: 0.004 | D15: 0.002 | F15: 0.011 | G15: 4000 | H15: 0.0095 | I15: 0.412 | J15: 0.4215
A16: Papierpatrone | B16: 0.005 | C16: 0.005 | D16: 0.002 | E16: 0.01 | F16: 0.022 | G16: 3000 | H16: 0.012667 | I16: 0.668 | J16: 0.680667
A17: Messingpatrone | B17: 0.005 | C17: 0.004 | E17: 0.015 | F17: 0.024 | G17: 2000 | H17: 0.019 | I17: 0.7624 | J17: 0.7814

Sheet Boegen-Basis
A1: Name | B1: Volk | C1: Material | D1: Min-Staerke | E1: Schaden | F1: RB | G1: Modifikatoren-roh | H1: RW-m | I1: Ladezeit-sec | J1: Nachlade-Teiler | K1: Preis | L1: Verfuegbarkeit-NW | M1: Verfuegbarkeit-AW | N1: Verfuegbarkeit-Volk
A2: Improvisierter Bogen | B2: Alle | C2: Holz | D2: 7 | E2: 1W4 | F2: 0 | G2: +4/0/-15/x/x | H2: 15m | I2: 6 | J2: 9 | K2: 0.001 | L2: 1 | M2: 1 | N2: 1
A3: Kurzbogen | B3: Goblin | C3: Holz | D3: 5 | E3: 1W4+1 | F3: 1 | G3: +8/+2/-13/-25/x/x | H3: 15m | I3: 6 | J3: 9 | K3: 50 | L3: 3 | M3: 4 | N3: 1
A4: Jagdbogen | B4: Goblin | C4: Holz | D4: 7 | E4: 1W6+1 | F4: 2 | G4: +6/+2/-8/-22/x/x | H4: 20m | I4: 6 | J4: 9 | K4: 60 | L4: 3 | M4: 4 | N4: 1
A5: Langbogen | B5: Goblin | C5: Holz | D5: 10 | E5: 1W6+1 | F5: 3 | G5: +5/+2/-8/-20/-30 | H5: 60m | I5: 7 | J5: 9 | K5: 100 | L5: 3 | M5: 4 | N5: 1
A6: Froggler-Bogen | B6: Goblin | C6: Holz | D6: 7 | E6: 1W6 | F6: 1 | G6: +6/+2/-8/-22/x/x | H6: 25m | I6: 7 | J6: 9 | K6: 55 | L6: 2 | M6: 3 | N6: 1
A7: Bogen | B7: Indianer | C7: Holz | D7: 9 | E7: 1W6+1 | F7: 2 | G7: +7/+2/-8/-23/x | H7: 25m | I7: 6 | J7: 9 | K7: 1 | L7: 5 | M7: 6 | N7: 1
A8: Langbogen | B8: Indianer | C8: Holz | D8: 12 | E8: 1W6+1 | F8: 3 | G8: +6/+2/-8/-21/x | H8: 75m | I8: 7 | J8: 9 | K8: 2 | L8: 6 | M8: 6 | N8: 4
A9: Schwarzfels-Bogen | B9: Indianer | C9: Holz, Schwarzfels, Seil, Leim | D9: 15 | E9: 1W8+1 | F9: 3 | G9: +6/+2/-7/-22/x | H9: 40m | I9: 9 | J9: 9 | K9: 1500 | L9: 6 | M9: 6 | N9: 6
A10: Kurzbogen | B10: Daikini | C10: Holz | D10: 9 | E10: 1W4+1 | F10: 2 | G10: +7/+2/-11/-25/x | H10: 20m | I10: 6 | J10: 9 | K10: 60 | L10: 6 | M10: 6 | N10: 1
A11: Jagdbogen | B11: Daikini | C11: Holz | D11: 11 | E11: 1W6+1 | F11: 2 | G11: +6/+2/-8/-22/x | H11: 27m | I11: 6 | J11: 9 | K11: 80 | L11: 6 | M11: 6 | N11: 1
A12: Langbogen | B12: Daikini | C12: Holz | D12: 12 | E12: 1W6+1 | F12: 3 | G12: +5/+2/-8/-20/-30 | H12: 50m | I12: 7 | J12: 9 | K12: 125 | L12: 6 | M12: 6 | N12: 2
A13: Asymmetrischer Bogen | B13: Daikini | C13: Holz | D13: 13 | E13: 1W6+1 | F13: 3 | G13: +7/+2/-8/-20/-30 | H13: 75m | I13: 6 | J13: 9 | K13: 1000 | L13: 6 | M13: 6 | N13: 6
... A42: Drachenbogen | B42: Spezial/Legendaer | C42: Holz, Kaiserdrachen-Bein, Leim | D42: 21 | E42: 1W12+1 | F42: 3 | G42: +6/+1/-13/-29/x/x | H42: 25m | I42: 8 | J42: 9 | K42: 1000000 | L42: 7 | M42: 7 | N42: 7

Sheet Pfeile-Basis
A1: Name | B1: Schaden-Mod | C1: RB-Mod | D1: RW-Mod-Spalte1 | E1: RW-Mod-Spalte2 | F1: Preis | G1: Verfuegbarkeit-NW | H1: Verfuegbarkeit-AW | I1: Verfuegbarkeit-Volk | J1: BE | K1: Spezialitaeten
A2: Improvisierter-Pfeil | B2: +1W4 | C2: 0 | D2: -15m | E2: -15m | F2: nichts | J2: 1
A3: Holzspitzen-Pfeil | B3: +1W6 | C3: 0 | D3: -7m | E3: -7m | F3: 50 FZ | G3: 1 | H3: 5 | J3: 1
A4: Knochenspitzen-Pfeil | B4: +1W6 | C4: 0 | D4: 0 | E4: 0 | F4: 100FZ | G4: 4 | H4: 4 | J4: 1
A5: Steinspitzen-Pfeil | B5: +1W8 | C5: 0 | D5: 0 | E5: 0 | F5: 200 FZ | G5: 1 | H5: 4 | J5: 1
A6: Diamantspatspitzen-Pfeil | B6: +1W8 | C6: +6 | D6: 0 | E6: 0 | F6: 1,5D | G6: 7 | H6: 7 | I6: 2 | J6: 1 | K6: Wird durch UV-Strahlung zersetzt
A7: Bronzespitzen-Pfeil | B7: +1W8 | C7: +1 | D7: 0 | E7: 0 | F7: 300 FZ | G7: 4 | H7: 3 | J7: 1
A8: Eisenspitzen-Pfeil | B8: +1W8 | C8: +2 | D8: 0 | E8: 0 | F8: 500 FZ | G8: 3 | H8: 1 | J8: 1
A9: Stahlspitzen-Pfeil | B9: +1W8 | C9: +3 | D9: 0 | E9: 0 | F9: 1D | G9: 4 | H9: 3 | J9: 1
A10: Edelstahlspitzen-Pfeil | B10: +1W8 | C10: +4 | D10: 0 | E10: 0 | F10: 2,5D | G10: 5 | H10: 4 | J10: 1
A11: Faltstahlspitzen-Pfeil | B11: +1W8 | C11: +5 | D11: 0 | E11: 0 | F11: 5D | G11: 5 | H11: 4 | J11: 1
A12: Nasiumspitzen-Pfeil | B12: +1W8 | C12: +2 | D12: 0 | E12: 0 | F12: 100D | G12: 6 | H12: 5 | J12: 1 | K12: Verzauberungskosten werden stark verringert
A13: Adamantitspitzen-Pfeil | B13: +1W8 | C13: +7 | D13: 0 | E13: 0 | F13: 1000D | G13: 7 | H13: 6 | J13: 1
A14: Diamantspitzen-Pfeil | B14: +1W8 | C14: +5 | D14: 0 | E14: 0 | F14: 100D | G14: 5 | H14: 5 | J14: 1
A15: Silberspitzen-Pfeil | B15: +1W6 | C15: -2 | D15: 0 | E15: 0 | F15: 2,5D | G15: 5 | H15: 5 | J15: 1 | K15: Man sagt es gaebe Wesen die nur mit Silber verletzt oder getoetet werden koennen
A16: Glasspitzen-Pfeil | B16: +1W8 | C16: -2 | D16: 0 | E16: 0 | F16: 10D | G16: 5 | H16: 5 | J16: 2 | K16: Die Spitze zersplittert beim Aufprall, die Splitter bohren sich bei jeder Bewegung ins Fleisch
A17: Breitkopfspitzen-Pfeil | B17: +3 | C17: -1 | D17: -1 | E17: +10m | F17: +2D | G17: 4 | H17: 3 | J17: 2
A18: Hohlspitzen-Pfeil | B18: +2 | C18: +3 | D18: +3 | E18: +5m | F18: +10D | G18: 4 | H18: 4 | J18: 1 | K18: Moderner Arme-Pfeil: wird nur an staatlich Befugte weitergegeben
A19: Widerhaken-Pfeil | B19: 0 | C19: +1 | D19: +1 | E19: -5m | F19: +2D | G19: 4 | H19: 3 | J19: 1 | K19: Ges+Medizin erschwert um 15 beim Rausziehen, sonst 1W8+2 SP direkt auf die TZ
A20: Kanuelen-Pfeil | B20: -2 | C20: +1 | D20: +1 | E20: -5m | F20: +3D | G20: 5 | H20: 4 | J20: 1 | K20: Kann eine groessere Menge Gift transportieren (2 statt 1 Anwendung)
A21: Halbmond-Pfeil | B21: +2 | C21: -3 | D21: -3 | E21: 0 | F21: +2D | G21: 3 | H21: 2 | J21: 2 | K21: Man kann damit Seile durchschiessen
A22: Dornspitzen-Pfeil | B22: -2 | C22: +7 | D22: +7 | E22: 0 | F22: +1D | G22: 3 | H22: 3 | J22: 1
A23: Hohlkoerper-Pfeil | B23: 0 | C23: -2 | D23: -2 | E23: -10m | F23: +5D | G23: 6 | H23: 5 | J23: 1 | K23: In einer Tonkugel an der Spitze kann z.B. Zwergisches Feuer untergebracht werden
A24: (Trolle) Trollbogen-Pfeil | B24: +1W15 | C24: 0 | D24: 0 | E24: 0 | F24: 5D | G24: 7 | H24: 7 | I24: 6 | J24: 10 | K24: Kann nur mit dem Trollbogen abgeschossen werden
A25: (Drow) Elbenbein-Pfeil | B25: +1W8+1 | C25: +1 | D25: 0 | E25: 0 | F25: 4D | G25: 7 | H25: 7 | I25: 4 | J25: 1 | K25: Traditioneller Drow-Pfeil
