Workbook
Name test1: #REF!
Name test2: #REF!

Sheet Werte
A1: Referenz | B1: Kategorie | C1: Beschreibung | D1: Abkürzung | E1: Info | F1: Parent | G1: Art | H1: Formel | I1: Pool | J1: Flag | K1: Grad | L1: Kosten | M1: Verfuegbarkeit | O1: Mindest-TaW | P1: Eig-Bonus | Q1: Wirkung
A2: spruchmagie_erdbeschwoerung_1_splitterwand | B2: Spruchmagie | C2: Splitterwand | F2: Erdbeschwörung | G2: Wert | J2: ACHTUNG: In der Quelle (NN_Spruchmagie_0.57) gibt es mehrere Zeilen mit gleichem Schule+Grad+Name aber abweichendem Wirkungstext (vermutlich alte+neue Version nebeneinander stehen geblieben) - hier wurde die letzte Version uebernommen, bitte pruefen. | K2: 1 | L2: WENN(wert=0;0;10+(wert-1)*grad) | P2: eig_bonus_k_staerke | Q2: Der Magier erschafft eine Wand aus Erde. Die Wahrnehmung durch diese Wand ist stark erschwert bis unmöglich: Alle FK-Attacken sind um Aura*2 erschwert. Wer versucht, die Wand zu durchdringen, erleidet Elementarschaden auf jeder TZ. Während der Effektdauer entfaltet die Wand nur die halbe Wirkung. Schaden: W4+Magie, RB 6 auf jede TZ.
A3: spruchmagie_erdbeschwoerung_2_splitterstrahl | B3: Spruchmagie | C3: Splitterstrahl | F3: Erdbeschwörung | G3: Wert | J3: ACHTUNG: In der Quelle (NN_Spruchmagie_0.57) gibt es mehrere Zeilen mit gleichem Schule+Grad+Name aber abweichendem Wirkungstext (vermutlich alte+neue Version nebeneinander stehen geblieben) - hier wurde die letzte Version uebernommen, bitte pruefen. | K3: 2 | L3: WENN(wert=0;0;10+(wert-1)*grad) | P3: eig_bonus_k_staerke | Q3: Aus der Handfläche des Magiers schießt ein (M) cm dicker Strahl aus Erde. Schaden: W10+Magie, RB 3, pro sec, Treffer auf eine FK-TZ mit 1 zusätzlichen TZ-Reroll.
A4: spruchmagie_erdbeschwoerung_3_steinschlag | B4: Spruchmagie | C4: Steinschlag | F4: Erdbeschwörung | G4: Wert | J4: ACHTUNG: In der Quelle (NN_Spruchmagie_0.57) gibt es mehrere Zeilen mit gleichem Schule+Grad+Name aber abweichendem Wirkungstext (vermutlich alte+neue Version nebeneinander stehen geblieben) - hier wurde die letzte Version uebernommen, bitte pruefen. | K4: 3 | L4: WENN(wert=0;0;10+(wert-1)*grad) | P4: eig_bonus_k_staerke | Q4: Der Magus erschafft um das Opfer eine Kugel aus Erde. Treffer auf FK-TZ mit 2 TZ-Rerolls auf die gewünschte Trefferzone. Schaden: 2W6 + Magie, RB 6.
A5: spruchmagie_erdbeschwoerung_4_grosse_splitterwand | B5: Spruchmagie | C5: Große Splitterwand | F5: Erdbeschwörung | G5: Wert | J5: ACHTUNG: In der Quelle (NN_Spruchmagie_0.57) gibt es mehrere Zeilen mit gleichem Schule+Grad+Name aber abweichendem Wirkungstext (vermutlich alte+neue Version nebeneinander stehen geblieben) - hier wurde die letzte Version uebernommen, bitte pruefen. | K5: 4 | L5: WENN(wert=0;0;10+(wert-1)*grad) | P5: eig_bonus_k_staerke | Q5: Der Magier erschafft eine Wand aus Erde. Die Wahrnehmung durch diese Wand ist stark erschwert bis unmöglich: Alle FK-Attacken sind um Aura*2 erschwert. Wer versucht, die Wand zu durchdringen, erleidet Elementarschaden auf jeder TZ. Während der Effektdauer entfaltet die Wand nur die halbe Wirkung. Schaden: 2W6 + Magie, RB 6. Länge max. (M) m, Breite max. (M)*5cm
A6: spruchmagie_erdbeschwoerung_5_grosse_splitteraura | B6: Spruchmagie | C6: Große Splitteraura | F6: Erdbeschwörung | G6: Wert | J6: ACHTUNG: In der Quelle (NN_Spruchmagie_0.57) gibt es mehrere Zeilen mit gleichem Schule+Grad+Name aber abweichendem Wirkungstext (vermutlich alte+neue Version nebeneinander stehen geblieben) - hier wurde die letzte Version uebernommen, bitte pruefen. | K6: 5 | L6: WENN(wert=0;0;10+(wert-1)*grad) | P6: eig_bonus_k_staerke | Q6: Der Magus hüllt sich in eine kugelförmige Aura aus Erde. Wer sich in die Aura begibt, erleidet auf jeder TZ innerhalb dieses Gebietes Elementarschaden. Der Magier kann aus der Aura heraus normal zielen, FK-Angriffe sind um Aura*2 erschwert. Feindliche Magie ist mit Ziel Aura hiervon nicht betroffen. Schaden: 2W6+Magie, RB 6, auf jede TZ.
A7: spruchmagie_erdbeschwoerung_5_grosser_steinschuss | B7: Spruchmagie | C7: Großer Steinschuss | F7: Erdbeschwörung | G7: Wert | J7: ACHTUNG: In der Quelle (NN_Spruchmagie_0.57) gibt es mehrere Zeilen mit gleichem Schule+Grad+Name aber abweichendem Wirkungstext (vermutlich alte+neue Version nebeneinander stehen geblieben) - hier wurde die letzte Version uebernommen, bitte pruefen. | K7: 5 | L7: WENN(wert=0;0;10+(wert-1)*grad) | P7: eig_bonus_k_staerke | Q7: Der Magus erschafft einen Bolzen aus Erde. Treffer auf FK-TZ. Schaden: 2W10 + Magie; RB: 6 + (M)/2
A8: spruchmagie_erdbeschwoerung_5_splittersturm | B8: Spruchmagie | C8: Splittersturm | F8: Erdbeschwörung | G8: Wert | J8: ACHTUNG: In der Quelle (NN_Spruchmagie_0.57) gibt es mehrere Zeilen mit gleichem Schule+Grad+Name aber abweichendem Wirkungstext (vermutlich alte+neue Version nebeneinander stehen geblieben) - hier wurde die letzte Version uebernommen, bitte pruefen. | K8: 5 | L8: WENN(wert=0;0;10+(wert-1)*grad) | P8: eig_bonus_k_staerke | Q8: Eine vom Magus ausgehende kugelförmige Explosion verursacht Elementarschaden. Es ist unmöglich, dem Schaden zu entgehen. Jede TZ wird getroffen. Schaden: W8 + Magie, RB 3.
A9: spruchmagie_erdbeschwoerung_6_grosser_splitterstrahl | B9: Spruchmagie | C9: Großer Splitterstrahl | F9: Erdbeschwörung | G9: Wert | J9: ACHTUNG: In der Quelle (NN_Spruchmagie_0.57) gibt es mehrere Zeilen mit gleichem Schule+Grad+Name aber abweichendem Wirkungstext (vermutlich alte+neue Version nebeneinander stehen geblieben) - hier wurde die letzte Version uebernommen, bitte pruefen. | K9: 6 | L9: WENN(wert=0;0;10+(wert-1)*grad) | P9: eig_bonus_k_staerke | Q9: Aus der Handfläche des Magiers schießt ein (M) cm dicker Strahl aus Erde. Schaden: 2W10 + Magie, RB 6, pro sec, Treffer auf eine FK-TZ mit 1 zusätzlichen TZ-Reroll.
A10: spruchmagie_erdbeschwoerung_6_grosser_steinschlag | B10: Spruchmagie | C10: Großer Steinschlag | F10: Erdbeschwörung | G10: Wert | J10: ACHTUNG: In der Quelle (NN_Spruchmagie_0.57) gibt es mehrere Zeilen mit gleichem Schule+Grad+Name aber abweichendem Wirkungstext (vermutlich alte+neue Version nebeneinander stehen geblieben) - hier wurde die letzte Version uebernommen, bitte pruefen. | K10: 6 | L10: WENN(wert=0;0;10+(wert-1)*grad) | P10: eig_bonus_k_staerke | Q10: Der Magus erschafft um das Opfer eine Kugel aus Erde. Treffer auf FK-TZ mit 2 TZ-Rerolls auf die gewünschte Trefferzone. Schaden: 2W12 + Magie, RB 9.
A11: spruchmagie_erdbeschwoerung_7_grosser_splittersturm | B11: Spruchmagie | C11: Großer Splittersturm | F11: Erdbeschwörung | G11: Wert | J11: ACHTUNG: In der Quelle (NN_Spruchmagie_0.57) gibt es mehrere Zeilen mit gleichem Schule+Grad+Name aber abweichendem Wirkungstext (vermutlich alte+neue Version nebeneinander stehen geblieben) - hier wurde die letzte Version uebernommen, bitte pruefen. | K11: 7 | L11: WENN(wert=0;0;10+(wert-1)*grad) | P11: eig_bonus_k_staerke | Q11: Eine vom Magus ausgehende kugelförmige Explosion verursacht Elementarschaden. Es ist unmöglich, dem Schaden zu entgehen. Jede TZ wird getroffen. Schaden: 2W15 + Magie, RB 15.
A12: spruchmagie_feuerbeschwoerung_1_flammenwand | B12: Spruchmagie | C12: Flammenwand | F12: Feuerbeschwörung | G12: Wert | J12: ACHTUNG: In der Quelle (NN_Spruchmagie_0.57) gibt es mehrere Zeilen mit gleichem Schule+Grad+Name aber abweichendem Wirkungstext (vermutlich alte+neue Version nebeneinander stehen geblieben) - hier wurde die letzte Version uebernommen, bitte pruefen. | K12: 1 | L12: WENN(wert=0;0;10+(wert-1)*grad) | P12: eig_bonus_g_mut | Q12: Der Magier erschafft eine Wand aus Feuer. Die Wahrnehmung durch diese Wand ist stark erschwert bis unmöglich: Alle FK-Attacken sind um Aura*2 erschwert. Wer versucht, die Wand zu durchdringen, erleidet Elementarschaden auf jeder TZ. Während der Effektdauer entfaltet die Wand nur die halbe Wirkung. Schaden: W6+Magie auf jede TZ.
A13: spruchmagie_feuerbeschwoerung_2_flammenaura | B13: Spruchmagie | C13: Flammenaura | F13: Feuerbeschwörung | G13: Wert | J13: ACHTUNG: In der Quelle (NN_Spruchmagie_0.57) gibt es mehrere Zeilen mit gleichem Schule+Grad+Name aber abweichendem Wirkungstext (vermutlich alte+neue Version nebeneinander stehen geblieben) - hier wurde die letzte Version uebernommen, bitte pruefen. | K13: 2 | L13: WENN(wert=0;0;10+(wert-1)*grad) | P13: eig_bonus_g_mut | Q13: Der Magus hüllt sich in eine kugelförmige Aura aus Feuer. Wer sich in die Aura begibt, erleidet auf jeder TZ innerhalb dieses Gebietes Elementarschaden. Der Magier kann aus der Aura heraus normal zielen, FK-Angriffe sind um Aura*2 erschwert. Feindliche Magie ist mit Ziel Aura hiervon nicht betroffen. Schaden: W6+Magie auf jede TZ.
... A71: spruchmagie_wasserbeschwoerung_7_grosse_frostbolzen_salve | B71: Spruchmagie | C71: Große Frostbolzen-Salve | F71: Wasserbeschwörung | G71: Wert | J71: ACHTUNG: In der Quelle (NN_Spruchmagie_0.57) gibt es mehrere Zeilen mit gleichem Schule+Grad+Name aber abweichendem Wirkungstext (vermutlich alte+neue Version nebeneinander stehen geblieben) - hier wurde die letzte Version uebernommen, bitte pruefen. | Referenz enthielt Bindestrich (mehrdeutig mit Subtraktion) - zu Unterstrich normalisiert. | K71: 7 | L71: WENN(wert=0;0;10+(wert-1)*grad) | P71: eig_bonus_k_athletik | Q71: Der Magus erschafft Magie/2 Bolzen aus Wasser. Jeweils Treffer auf FK-TZ. Schaden: 2W10 + Magie; RB: (M)/2. Pro 5 TP erleidet das Opfer zusätzliche BE 1, nur die höchste so erzielte BE zählt.
A72: ep_abenteuer | B72: Charakterwerte | C72: EP zum Abenteuerende | E72: S.1 | G72: Formel | H72: ep_gesamt-ep_start
A73: le_leberschutz | B73: Kampf | C73: Leberschutz | E73: S.3 | G73: Pool
A74: ep_gesamt | B74: Charakterwerte | C74: Gesamte Erfahrungspunke | E74: S.1 | G74: Wert
A75: ep_start | B75: Charakterwerte | C75: EP bei Abenteuerbeginn | E75: S.1 | G75: Wert
A76: whk_spez_kaufmann_gastwirt | B76: WHK | C76: -> Gastwirt | F76: Kaufmann | G76: Wert | L76: SVERWEIS(wert;'WHK-Spez-Kosten';3;1)
A77: whk_spez_kaufmann_sklavenhaendler | B77: WHK | C77: -> Sklavenhändler | F77: Kaufmann | G77: Wert | L77: SVERWEIS(wert;'WHK-Spez-Kosten';3;1)
A78: whk_spez_abrichten_drache | B78: WHK | C78: -> Drache | F78: Abrichten | G78: Wert | L78: SVERWEIS(wert;'WHK-Spez-Kosten';3;1)
A79: whk_spez_abrichten_laufvogel | B79: WHK | C79: -> Laufvogel | F79: Abrichten | G79: Wert | L79: SVERWEIS(wert;'WHK-Spez-Kosten';3;1)
A80: whk_spez_abrichten_reitkrebse | B80: WHK | C80: -> Reitkrebse | F80: Abrichten | G80: Wert | L80: SVERWEIS(wert;'WHK-Spez-Kosten';3;1)
A81: whk_spez_abrichten_reitreptilien | B81: WHK | C81: -> Reitreptilien | F81: Abrichten | G81: Wert | L81: SVERWEIS(wert;'WHK-Spez-Kosten';3;1)
A82: whk_spez_abrichten_rok | B82: WHK | C82: -> Rok | F82: Abrichten | G82: Wert | L82: SVERWEIS(wert;'WHK-Spez-Kosten';3;1)
A83: whk_spez_abrichten_warg | B83: WHK | C83: -> Warg | F83: Abrichten | G83: Wert | L83: SVERWEIS(wert;'WHK-Spez-Kosten';3;1)
A84: whk_spez_ruestungsschmied_tierruestungen | B84: WHK | C84: -> Tierrüstungen | F84: Rüstungsschmied | G84: Wert | L84: SVERWEIS(wert;'WHK-Spez-Kosten';3;1)
A85: bewegung_f_schnell_schwimmen | B85: Bewegung | C85: Schnell Schwimmen | E85: Meisterscreen S.3 | G85: Formel | H85: (eig_k_konstitution+eig_k_athletik+gr_schwimmen)/30
A86: bewegung_f_sprinten | B86: Bewegung | C86: Sprinten | E86: Meisterscreen S.3 | G86: Formel | H86: (eig_k_athletik+eig_k_schnelligkeit+gr_sprinten)/7+4
A87: spruchmagie_beherrschung_4_einschlaefern | B87: Spruchmagie | C87: Einschläfern | F87: Beherrschung | G87: Wert | K87: 4 | L87: WENN(wert=0;0;10+(wert-1)*grad) | P87: eig_bonus_k_ausstrahlung | Q87: Das Opfer schläft ein. Der Schlaf ist, wenn auch unnatürlich tief, wie normaler schlaf zu Behandeln. Sollte das Opfer also gerade stehen, so fällt es um und wacht durch den Sturz natürlich wieder auf. Auch das abfeuern einer Feuerwaffe in seiner nähe wird wohl, ohne Probe, zum Aufwachen führen. Gewohnte Geräusche gehören natürlich nicht dazu. Ein Heizer einer Dampfmaschine wird durch eben jene nicht Aufwachen.
A88: spruchmagie_beherrschung_7_maechtige_f_daemonen_herrschaft | B88: Spruchmagie | C88: Mächtige f.Dämonen Herrschaft | F88: Beherrschung | G88: Wert | K88: 7 | L88: WENN(wert=0;0;10+(wert-1)*grad) | P88: eig_bonus_k_ausstrahlung | Q88: Ein freier (nicht von einem anderen Magus beherrschter) Dämon hat eine Willenskraft-Probe erschwert um die Differenz von der (M) des Margus (Macht x2) und des Opfers (Macht x1). Und alle 24 Stunden eine weitere. Wenn sie gelingt fällt der Zauber.1 und 29 sind immer ein Erfolg. Ansonsten wird der Dämon zu einem Willenskraftenlosen Sklaven des Magus. Es wird aufs Wort hören, ganz so als währe es ein Absolut untertäniger Diner. Der Dämon weis zwar immer genau was der Magus von ihm Willenskraft ist aber nicht Intelligenzelligenter als vorher oder verfügt nicht über neue Fertigkeiten. Eine Stroh dummer Dämon wird es wohl nicht schaffen den Banksafe ohne Gewalt zu öffnen.
A89: spruchmagie_beherrschung_5_massen_besaenftigung | B89: Spruchmagie | C89: Massen Besänftigung | F89: Beherrschung | G89: Wert | K89: 5 | L89: WENN(wert=0;0;10+(wert-1)*grad) | P89: eig_bonus_k_ausstrahlung | Q89: Die Opfer werden ruhig und gelassen, sie verlieren jeglichen drang zu Töten (außer Einer ist ein Sadist und macht es aus Spaß). Sie wissen zwar noch alles, es ist aber nicht mehr so Dramatisch für Sie. Nach dem der Zauber vorbei ist, sind die Opfer immer noch ruhig, es hält Sie aber nichts davon ab wieder Wütend zu werden. Was natürlich auch sofort geschehen kann aber nicht muss, wenn sie sich daran erinnern dass man gerade ihr Dorf nieder gebrannt hat.
A90: spruchmagie_beherrschung_3_schmerzt_unterdruecken | B90: Spruchmagie | C90: Schmerzt unterdrücken | F90: Beherrschung | G90: Wert | K90: 3 | L90: WENN(wert=0;0;10+(wert-1)*grad) | P90: eig_bonus_g_willenskraft | Q90: Die Gefühle und Schmerzen des Opfers werden unterdrückt. Das Opfer fühlt sich so als würde es unter dem Einfluss eines Betäubungsmittels stehen. Es bekommt eine Generelle Behinderung von 1. Seine TS steigt um das 4 fache an und alle Behinderungen die das Opfer durch Kampfschäden bekommt oder bekommen hat sind gleich null.
A91: spruchmagie_beherrschung_2_zoegern | B91: Spruchmagie | C91: Zögern | F91: Beherrschung | G91: Wert | K91: 2 | L91: WENN(wert=0;0;10+(wert-1)*grad) | P91: eig_bonus_g_intelligenz | Q91: Das Opfer zögert, das zu tun, was es gerade wollte. Es greift nicht mehr an, sondern verteidigt sich nur noch. Sollte gerade keine Kampf Situation sein so bleibt es sehn und hält inne um seinen nächsten schritt noch mal zu überdenken. Das Opfer zögert maximal 1W4+Magie Sekunden lang.
A92: vn_angst_magie_10 | B92: Vor- und Nachteile | C92: Nervosität: Magie | E92: Auswahlgruppe angst_magie; maximal 1 Stufe; Angstwert 10; direkte Konfrontation: bei jeder erneuten direkten Konfrontation; bloße Gegenwart: BE -1. | F92: Angst: Magie | G92: Auswahl | J92: EP-Rate für 'magie' aus NN NPC-Rechner 0.75, Sheet 'NPC-Rechner' Formel '=AOxx*-10' (Zeile 52ff). Kosten = Stufenwert(10) * Rate(-10). | EXKLUSIV_ANGST=angst_magie | ANGST_INTERVALL=NEUE_KONFRONTATION | ANGST_DIREKTE_KONFRONTATION=1 | ANGST_BE=-1 | K92: 10 | L92: -100 | M92: S | Q92: Der Charakter reagiert auf alle Magie mit Nervosität und ist nicht in der Lage, irgendeine Form von Magie außer KI zu wirken. Bei direkter Konfrontation mit Magie, insbesondere wenn er gegen einen Magiewirker vorgeht, muss er bei jeder erneuten direkten Konfrontation eine um 10 erschwerte Mut-Probe bestehen, um handlungsfähig zu bleiben. Um Verzauberungen oder magische Heilung zuzulassen, ein Artefakt zu benutzen oder bewusst mit Magie zu interagieren, muss er einmalig eine um 10 erschwerte Willenskraft-Probe bestehen. Ist Magie zwar gegenwärtig, aber weder direkter Gegner noch Gegenstand, Wesen oder sonstiges Ziel, mit dem sich der Charakter aktuell befasst, sind keine Angst-Proben erforderlich; der Charakter erhält BE -1.
A93: vn_angst_magie_15 | B93: Vor- und Nachteile | C93: Furcht: Magie | E93: Auswahlgruppe angst_magie; maximal 1 Stufe; Angstwert 15; direkte Konfrontation: sofort, danach alle 10 KR; bloße Gegenwart: BE -2. | F93: Angst: Magie | G93: Auswahl | J93: EP-Rate für 'magie' aus NN NPC-Rechner 0.75, Sheet 'NPC-Rechner' Formel '=AOxx*-10' (Zeile 52ff). Kosten = Stufenwert(15) * Rate(-10). | EXKLUSIV_ANGST=angst_magie | ANGST_INTERVALL=10_KR | ANGST_DIREKTE_KONFRONTATION=1 | ANGST_BE=-2 | K93: 15 | L93: -150 | M93: S | Q93: Der Charakter reagiert auf alle Magie mit Furcht und ist nicht in der Lage, irgendeine Form von Magie außer KI zu wirken. Bei direkter Konfrontation mit Magie, insbesondere wenn er gegen einen Magiewirker vorgeht, muss er sofort, danach alle 10 KR eine um 15 erschwerte Mut-Probe bestehen, um handlungsfähig zu bleiben. Um Verzauberungen oder magische Heilung zuzulassen, ein Artefakt zu benutzen oder bewusst mit Magie zu interagieren, muss er einmalig eine um 15 erschwerte Willenskraft-Probe bestehen. Ist Magie zwar gegenwärtig, aber weder direkter Gegner noch Gegenstand, Wesen oder sonstiges Ziel, mit dem sich der Charakter aktuell befasst, sind keine Angst-Proben erforderlich; der Charakter erhält BE -2.
A94: vn_angst_magie_20 | B94: Vor- und Nachteile | C94: Angst: Magie | E94: Auswahlgruppe angst_magie; maximal 1 Stufe; Angstwert 20; direkte Konfrontation: sofort, danach alle 5 KR; bloße Gegenwart: BE -3. | F94: Angst: Magie | G94: Auswahl | J94: EP-Rate für 'magie' aus NN NPC-Rechner 0.75, Sheet 'NPC-Rechner' Formel '=AOxx*-10' (Zeile 52ff). Kosten = Stufenwert(20) * Rate(-10). | EXKLUSIV_ANGST=angst_magie | ANGST_INTERVALL=5_KR | ANGST_DIREKTE_KONFRONTATION=1 | ANGST_BE=-3 | K94: 20 | L94: -200 | M94: S | Q94: Der Charakter reagiert auf alle Magie mit Angst und ist nicht in der Lage, irgendeine Form von Magie außer KI zu wirken. Bei direkter Konfrontation mit Magie, insbesondere wenn er gegen einen Magiewirker vorgeht, muss er sofort, danach alle 5 KR eine um 20 erschwerte Mut-Probe bestehen, um handlungsfähig zu bleiben. Um Verzauberungen oder magische Heilung zuzulassen, ein Artefakt zu benutzen oder bewusst mit Magie zu interagieren, muss er einmalig eine um 20 erschwerte Willenskraft-Probe bestehen. Ist Magie zwar gegenwärtig, aber weder direkter Gegner noch Gegenstand, Wesen oder sonstiges Ziel, mit dem sich der Charakter aktuell befasst, sind keine Angst-Proben erforderlich; der Charakter erhält BE -3.
A95: vn_angst_magie_30 | B95: Vor- und Nachteile | C95: Phobie: Magie | E95: Auswahlgruppe angst_magie; maximal 1 Stufe; Angstwert 30; direkte Konfrontation: sofort, danach jede KR; bloße Gegenwart: BE -5. | F95: Angst: Magie | G95: Auswahl | J95: EP-Rate für 'magie' aus NN NPC-Rechner 0.75, Sheet 'NPC-Rechner' Formel '=AOxx*-10' (Zeile 52ff). Kosten = Stufenwert(30) * Rate(-10). | EXKLUSIV_ANGST=angst_magie | ANGST_INTERVALL=1_KR | ANGST_DIREKTE_KONFRONTATION=1 | ANGST_BE=-5 | K95: 30 | L95: -300 | M95: S | Q95: Der Charakter leidet unter einer Phobie gegenüber aller Magie und ist nicht in der Lage, irgendeine Form von Magie außer KI zu wirken. Bei direkter Konfrontation mit Magie, insbesondere wenn er gegen einen Magiewirker vorgeht, muss er sofort, danach jede KR eine um 30 erschwerte Mut-Probe bestehen, um handlungsfähig zu bleiben. Um Verzauberungen oder magische Heilung zuzulassen, ein Artefakt zu benutzen oder bewusst mit Magie zu interagieren, muss er einmalig eine um 30 erschwerte Willenskraft-Probe bestehen. Ist Magie zwar gegenwärtig, aber weder direkter Gegner noch Gegenstand, Wesen oder sonstiges Ziel, mit dem sich der Charakter aktuell befasst, sind keine Angst-Proben erforderlich; der Charakter erhält BE -5.
A96: vn_angst_magie_5 | B96: Vor- und Nachteile | C96: Unbehagen: Magie | E96: Auswahlgruppe angst_magie; maximal 1 Stufe; Angstwert 5; direkte Konfrontation: einmal pro Situation; bloße Gegenwart: BE 0. | F96: Angst: Magie | G96: Auswahl | J96: EP-Rate für 'magie' aus NN NPC-Rechner 0.75, Sheet 'NPC-Rechner' Formel '=AOxx*-10' (Zeile 52ff). Kosten = Stufenwert(5) * Rate(-10). | EXKLUSIV_ANGST=angst_magie | ANGST_INTERVALL=SITUATION | ANGST_DIREKTE_KONFRONTATION=1 | ANGST_BE=0 | K96: 5 | L96: -50 | M96: S | Q96: Der Charakter empfindet Unbehagen gegenüber aller Magie und ist nicht in der Lage, irgendeine Form von Magie außer KI zu wirken. Bei direkter Konfrontation mit Magie, insbesondere wenn er gegen einen Magiewirker vorgeht, muss er einmal pro Situation eine um 5 erschwerte Mut-Probe bestehen, um handlungsfähig zu bleiben. Um Verzauberungen oder magische Heilung zuzulassen, ein Artefakt zu benutzen oder bewusst mit Magie zu interagieren, muss er einmalig eine um 5 erschwerte Willenskraft-Probe bestehen.
A97: vn_schlechte_eigenschaft_ausstrahlung | B97: Vor- und Nachteile | C97: Schlechte Eigenschaft: Ausstrahlung | E97: Max=9 (ab Kreis 3); Erstellungs-Max=7; nicht uebersteigerbar | G97: Auswahl | J97: Ersetzt die normale Voelker-Maxima-Tabelle fuer diese Eigenschaft komplett (nicht MIN() mit dem Volkswert - die Regel ignoriert explizit die Erstellungs-/Kreis-3-Minima/Maxima und setzt eigene feste Werte). | L97: -200 | M97: E
A98: vn_schlechte_eigenschaft_intelligenz | B98: Vor- und Nachteile | C98: Schlechte Eigenschaft: Intelligenz | E98: Max=9 (ab Kreis 3); Erstellungs-Max=7; nicht uebersteigerbar | G98: Auswahl | J98: Ersetzt die normale Voelker-Maxima-Tabelle fuer diese Eigenschaft komplett (nicht MIN() mit dem Volkswert - die Regel ignoriert explizit die Erstellungs-/Kreis-3-Minima/Maxima und setzt eigene feste Werte). | L98: -200 | M98: E
A99: vn_schlechte_eigenschaft_mut | B99: Vor- und Nachteile | C99: Schlechte Eigenschaft: Mut | E99: Max=9 (ab Kreis 3); Erstellungs-Max=7; nicht uebersteigerbar | G99: Auswahl | J99: Ersetzt die normale Voelker-Maxima-Tabelle fuer diese Eigenschaft komplett (nicht MIN() mit dem Volkswert - die Regel ignoriert explizit die Erstellungs-/Kreis-3-Minima/Maxima und setzt eigene feste Werte). | L99: -200 | M99: E
A100: vn_schlechte_eigenschaft_sinnesschaerfe | B100: Vor- und Nachteile | C100: Schlechte Eigenschaft: Sinnesschaerfe | E100: Max=9 (ab Kreis 3); Erstellungs-Max=7; nicht uebersteigerbar | G100: Auswahl | J100: Ersetzt die normale Voelker-Maxima-Tabelle fuer diese Eigenschaft komplett (nicht MIN() mit dem Volkswert - die Regel ignoriert explizit die Erstellungs-/Kreis-3-Minima/Maxima und setzt eigene feste Werte). | L100: -200 | M100: E
A101: vn_schlechte_eigenschaft_willenskraft | B101: Vor- und Nachteile | C101: Schlechte Eigenschaft: Willenskraft | E101: Max=9 (ab Kreis 3); Erstellungs-Max=7; nicht uebersteigerbar | G101: Auswahl | J101: Ersetzt die normale Voelker-Maxima-Tabelle fuer diese Eigenschaft komplett (nicht MIN() mit dem Volkswert - die Regel ignoriert explizit die Erstellungs-/Kreis-3-Minima/Maxima und setzt eigene feste Werte). | L101: -200 | M101: E
A102: vn_schlechte_eigenschaft_athletik | B102: Vor- und Nachteile | C102: Schlechte Eigenschaft: Athletik | E102: Max=9 (ab Kreis 3); Erstellungs-Max=7; nicht uebersteigerbar | G102: Auswahl | J102: Ersetzt die normale Voelker-Maxima-Tabelle fuer diese Eigenschaft komplett (nicht MIN() mit dem Volkswert - die Regel ignoriert explizit die Erstellungs-/Kreis-3-Minima/Maxima und setzt eigene feste Werte). | L102: -200 | M102: E
A103: vn_schlechte_eigenschaft_geschicklichkeit | B103: Vor- und Nachteile | C103: Schlechte Eigenschaft: Geschicklichkeit | E103: Max=9 (ab Kreis 3); Erstellungs-Max=7; nicht uebersteigerbar | G103: Auswahl | J103: Ersetzt die normale Voelker-Maxima-Tabelle fuer diese Eigenschaft komplett (nicht MIN() mit dem Volkswert - die Regel ignoriert explizit die Erstellungs-/Kreis-3-Minima/Maxima und setzt eigene feste Werte). | L103: -200 | M103: E
A104: vn_schlechte_eigenschaft_konstitution | B104: Vor- und Nachteile | C104: Schlechte Eigenschaft: Konstitution | E104: Max=9 (ab Kreis 3); Erstellungs-Max=7; nicht uebersteigerbar | G104: Auswahl | J104: Ersetzt die normale Voelker-Maxima-Tabelle fuer diese Eigenschaft komplett (nicht MIN() mit dem Volkswert - die Regel ignoriert explizit die Erstellungs-/Kreis-3-Minima/Maxima und setzt eigene feste Werte). | L104: -200 | M104: E
A105: vn_schlechte_eigenschaft_schnelligkeit | B105: Vor- und Nachteile | C105: Schlechte Eigenschaft: Schnelligkeit | E105: Max=9 (ab Kreis 3); Erstellungs-Max=7; nicht uebersteigerbar | G105: Auswahl | J105: Ersetzt die normale Voelker-Maxima-Tabelle fuer diese Eigenschaft komplett (nicht MIN() mit dem Volkswert - die Regel ignoriert explizit die Erstellungs-/Kreis-3-Minima/Maxima und setzt eigene feste Werte). | L105: -200 | M105: E
A106: vn_schlechte_eigenschaft_staerke | B106: Vor- und Nachteile | C106: Schlechte Eigenschaft: Staerke | E106: Max=9 (ab Kreis 3); Erstellungs-Max=7; nicht uebersteigerbar | G106: Auswahl | J106: Ersetzt die normale Voelker-Maxima-Tabelle fuer diese Eigenschaft komplett (nicht MIN() mit dem Volkswert - die Regel ignoriert explizit die Erstellungs-/Kreis-3-Minima/Maxima und setzt eigene feste Werte). | L106: -200 | M106: E
A107: nk_pool_unbewaffnet | B107: Nahkampf | C107: Pool Unbewaffnet | G107: Pool | I107: MAX(0;(eig_g_mut+eig_k_schnelligkeit+nk_unbewaffnet)/3-20)+MAX(0;(eig_k_athletik+eig_k_schnelligkeit+nk_unbewaffnet)/3-20) | J107: Formel hatte nur den Attacke-seitigen MAX-Term. Alle anderen 'Pool <Gruppe>'-Zeilen (198,203,207,212) kombinieren Attacke- und Parade-seitigen Überschuss - fehlenden Parade-Term ergänzt.
A108: f_ausdauer | B108: Charakterwerte | C108: Ausdauer | D108: Ausd. | E108: S.2 | G108: Formel | H108: eig_k_athletik+2*eig_k_konstitution+(eig_k_staerke/2)+3*att_vitalitaet+stufe | J108: Formel referenzierte 'att_vitalität' (alte Umlautschreibweise) statt der aktuellen Referenz 'att_vitalitaet' - korrigiert.
A109: f_alchemieresistenz | B109: Charakterwerte | C109: Alchemieresistenz | D109: AR | G109: Formel | H109: eig_k_konstitution+3*att_vitalitaet+sf_alchemieresistenz | J109: Formel referenzierte 'att_vitalität' (alte Umlautschreibweise) statt der aktuellen Referenz 'att_vitalitaet' - korrigiert. | Formel referenzierte veraltete Gro�-/Kleinschreibung (sf_Alchemieresistenz) - an aktuelle (kleingeschriebene) Referenz angepasst.
A110: selbstbeherrschung | B110: Charakterwerte | C110: Selbstbeherrschung | D110: SB | E110: S.2 | G110: Formel | H110: (eig_g_mut+eig_g_willenskraft+eig_k_konstitution+eig_k_staerke+sf_selbstbeherrschung)/7+att_vitalitaet+12 | J110: Formel referenzierte 'att_vitalität' (alte Umlautschreibweise) statt der aktuellen Referenz 'att_vitalitaet' - korrigiert. | Formel referenzierte veraltete Gro�-/Kleinschreibung (sf_Selbstbeherrschung) - an aktuelle (kleingeschriebene) Referenz angepasst.
A111: fk_basis_blasrohre | B111: Fernkampf | C111: Fernkampf-Basis-Wert Blasrohre | G111: Formel | H111: (eig_g_sinneschaerfe+eig_k_geschicklichkeit+fk_blasrohre)/4 | J111: Formel referenzierte veraltete Gro�-/Kleinschreibung (fk_blasrohre) - an aktuelle (kleingeschriebene) Referenz angepasst.
A112: fk_basis_spez_blasrohre_blasrohre | B112: Fernkampf | C112: Fernkampf-Spezialisierungs-Wert Blasrohre | G112: Formel | H112: (eig_g_sinneschaerfe+eig_k_geschicklichkeit+fk_blasrohre+fk_spez_blasrohre_blasrohre)/4 | J112: Formel referenzierte veraltete Gro�-/Kleinschreibung (fk_spez_Blasrohre_blasrohre, fk_blasrohre) - an aktuelle (kleingeschriebene) Referenz angepasst.
A113: aw_def_normal | B113: Kampf | C113: Defensives Ausweichen | D113: def. nAW | E113: S.2 | G113: Formel | H113: (eig_k_athletik+eig_k_schnelligkeit+att_glueck+sf_ausweichen)/5+6-gewichtsbelastung | J113: Formel referenzierte veraltete Gro�-/Kleinschreibung (Gewichtsbelastung, sf_Ausweichen) - an aktuelle (kleingeschriebene) Referenz angepasst.
A114: aw_off_normal | B114: Kampf | C114: Offensives Ausweichen | D114: off. nAW | E114: S.2 | G114: Formel | H114: (eig_k_athletik+eig_k_schnelligkeit+att_glueck+sf_ausweichen)/5+2-gewichtsbelastung | J114: Formel referenzierte veraltete Gro�-/Kleinschreibung (Gewichtsbelastung, sf_Ausweichen) - an aktuelle (kleingeschriebene) Referenz angepasst.
A115: aw_gut | B115: Kampf | C115: Gutes Ausweichen | D115: gAW | E115: S.2 | G115: Formel | H115: (eig_bonus_k_athletik+sf_gutes_aw)/5+1 | J115: Formel referenzierte veraltete Gro�-/Kleinschreibung (sf_Gutes_AW) - an aktuelle (kleingeschriebene) Referenz angepasst.
A116: mana | B116: Charakterwerte | C116: Mana | E116: S.1 | G116: Formel | H116: att_aura*7+att_magie*3+3*eig_g_willenskraft-30+eig_bonus_g_intelligenz*att_weisheit+stufe+sf_mana_talent*2 | J116: Formel referenzierte veraltete Gro�-/Kleinschreibung (sf_Mana_Talent) - an aktuelle (kleingeschriebene) Referenz angepasst.
A117: aw_meisterlich | B117: Kampf | C117: Meisterliches Ausweichen | D117: mAW | E117: S.2 | G117: Formel | H117: (eig_bonus_k_schnelligkeit+sf_meisterliches_ausweichen)/5+21 | J117: Formel referenzierte veraltete Gro�-/Kleinschreibung (sf_Meisterliches_ausweichen) - an aktuelle (kleingeschriebene) Referenz angepasst.
A118: gbe_ausgeruestet | B118: Gewichtsbelastung | C118: Ausgerüstet | G118: Formel | H118: eig_k_staerke+sf_tragen*1,5 | J118: Formel referenzierte veraltete Gro�-/Kleinschreibung (sf_Tragen) - an aktuelle (kleingeschriebene) Referenz angepasst.
A119: gbe_leichtes_marschgepaeck | B119: Gewichtsbelastung | C119: Leichtes Marschgepäck | G119: Formel | H119: eig_k_staerke+sf_tragen*3 | J119: Formel referenzierte veraltete Gro�-/Kleinschreibung (sf_Tragen) - an aktuelle (kleingeschriebene) Referenz angepasst.
A120: gbe_max_hebelast | B120: Gewichtsbelastung | C120: max. Hebelast | G120: Formel | H120: eig_k_staerke+sf_tragen*15 | J120: Formel referenzierte veraltete Gro�-/Kleinschreibung (sf_Tragen) - an aktuelle (kleingeschriebene) Referenz angepasst.
A121: gbe_mittel_ueberladen | B121: Gewichtsbelastung | C121: Mittel Überladen | G121: Formel | H121: eig_k_staerke+sf_tragen*7 | J121: Formel referenzierte veraltete Gro�-/Kleinschreibung (sf_Tragen) - an aktuelle (kleingeschriebene) Referenz angepasst.
A122: gbe_schwer_schleppend | B122: Gewichtsbelastung | C122: Schwer schleppend | G122: Formel | H122: eig_k_staerke+sf_tragen*11 | J122: Formel referenzierte veraltete Gro�-/Kleinschreibung (sf_Tragen) - an aktuelle (kleingeschriebene) Referenz angepasst.
A123: gbe_schweres_marschgepaeck | B123: Gewichtsbelastung | C123: Schweres Marschgepäck | G123: Formel | H123: eig_k_staerke+sf_tragen*5 | J123: Formel referenzierte veraltete Gro�-/Kleinschreibung (sf_Tragen) - an aktuelle (kleingeschriebene) Referenz angepasst.
A124: gbe_unbelastet | B124: Gewichtsbelastung | C124: Unbelastet | G124: Formel | H124: eig_k_staerke+sf_tragen*0,5 | J124: Formel referenzierte veraltete Gro�-/Kleinschreibung (sf_Tragen) - an aktuelle (kleingeschriebene) Referenz angepasst.
A125: fk_gute_spez_schusswaffen_armbrust | B125: Fernkampf | C125: Fernkampf-Spezialisierungs-Gute-Wert Armbrust | E125: Diese Formel geht von der VOLLSTAENDIGEN Probe aus (Basiswert + Waffen-Modifikator + Entfernungs-Modifikator, siehe Waffentabellen z.B. NN_Feuerwaffen_1.1.xlsx). Die Berechnung dieser vollstaendigen Probe sowie die Sonderregel bei Probe<=0 (nur Meisterlich=normaler Treffer bzw. Froehlich=guter Treffer moeglich) gehoeren ins zukuenftige Kampfmodul, nicht in den Charakterbogen - hier steht nur der Basismechanismus. | G125: Formel | H125: WENN(talente_fernkampfgeschick_stufe_2>0;1+AUFRUNDEN(fk_basis_spez_schusswaffen_armbrust/3;0);WENN(talente_fernkampfgeschick_stufe_1>0;1+AUFRUNDEN(fk_basis_spez_schusswaffen_armbrust/4;0);1)) | J125: Gleiches Muster wie fk_gute_* (Basiswaffe), nur auf den Spezialisierungs-Basiswert angewandt - Nutzerbestaetigung: 'Spezialisierungen sollten als simples +Spez in der /4 Formel gefuehrt sein'.
A126: fk_gute_spez_blasrohre_blasrohre | B126: Fernkampf | C126: Fernkampf-Spezialisierungs-Gute-Wert Blasrohre | E126: Diese Formel geht von der VOLLSTAENDIGEN Probe aus (Basiswert + Waffen-Modifikator + Entfernungs-Modifikator, siehe Waffentabellen z.B. NN_Feuerwaffen_1.1.xlsx). Die Berechnung dieser vollstaendigen Probe sowie die Sonderregel bei Probe<=0 (nur Meisterlich=normaler Treffer bzw. Froehlich=guter Treffer moeglich) gehoeren ins zukuenftige Kampfmodul, nicht in den Charakterbogen - hier steht nur der Basismechanismus. | G126: Formel | H126: WENN(talente_fernkampfgeschick_stufe_2>0;1+AUFRUNDEN(fk_basis_spez_blasrohre_blasrohre/3;0);WENN(talente_fernkampfgeschick_stufe_1>0;1+AUFRUNDEN(fk_basis_spez_blasrohre_blasrohre/4;0);1)) | J126: Gleiches Muster wie fk_gute_* (Basiswaffe), nur auf den Spezialisierungs-Basiswert angewandt - Nutzerbestaetigung: 'Spezialisierungen sollten als simples +Spez in der /4 Formel gefuehrt sein'.
A127: fk_gute_spez_schusswaffen_musketen | B127: Fernkampf | C127: Fernkampf-Spezialisierungs-Gute-Wert Musketen | E127: Diese Formel geht von der VOLLSTAENDIGEN Probe aus (Basiswert + Waffen-Modifikator + Entfernungs-Modifikator, siehe Waffentabellen z.B. NN_Feuerwaffen_1.1.xlsx). Die Berechnung dieser vollstaendigen Probe sowie die Sonderregel bei Probe<=0 (nur Meisterlich=normaler Treffer bzw. Froehlich=guter Treffer moeglich) gehoeren ins zukuenftige Kampfmodul, nicht in den Charakterbogen - hier steht nur der Basismechanismus. | G127: Formel | H127: WENN(talente_fernkampfgeschick_stufe_2>0;1+AUFRUNDEN(fk_basis_spez_schusswaffen_musketen/3;0);WENN(talente_fernkampfgeschick_stufe_1>0;1+AUFRUNDEN(fk_basis_spez_schusswaffen_musketen/4;0);1)) | J127: Gleiches Muster wie fk_gute_* (Basiswaffe), nur auf den Spezialisierungs-Basiswert angewandt - Nutzerbestaetigung: 'Spezialisierungen sollten als simples +Spez in der /4 Formel gefuehrt sein'.
A128: fk_gute_spez_schusswaffen_pistolen | B128: Fernkampf | C128: Fernkampf-Spezialisierungs-Gute-Wert Pistolen | E128: Diese Formel geht von der VOLLSTAENDIGEN Probe aus (Basiswert + Waffen-Modifikator + Entfernungs-Modifikator, siehe Waffentabellen z.B. NN_Feuerwaffen_1.1.xlsx). Die Berechnung dieser vollstaendigen Probe sowie die Sonderregel bei Probe<=0 (nur Meisterlich=normaler Treffer bzw. Froehlich=guter Treffer moeglich) gehoeren ins zukuenftige Kampfmodul, nicht in den Charakterbogen - hier steht nur der Basismechanismus. | G128: Formel | H128: WENN(talente_fernkampfgeschick_stufe_2>0;1+AUFRUNDEN(fk_basis_spez_schusswaffen_pistolen/3;0);WENN(talente_fernkampfgeschick_stufe_1>0;1+AUFRUNDEN(fk_basis_spez_schusswaffen_pistolen/4;0);1)) | J128: Gleiches Muster wie fk_gute_* (Basiswaffe), nur auf den Spezialisierungs-Basiswert angewandt - Nutzerbestaetigung: 'Spezialisierungen sollten als simples +Spez in der /4 Formel gefuehrt sein'.
A129: fk_gute_spez_boegen_boegen | B129: Fernkampf | C129: Fernkampf-Spezialisierungs-Gute-Wert Bögen | E129: Diese Formel geht von der VOLLSTAENDIGEN Probe aus (Basiswert + Waffen-Modifikator + Entfernungs-Modifikator, siehe Waffentabellen z.B. NN_Feuerwaffen_1.1.xlsx). Die Berechnung dieser vollstaendigen Probe sowie die Sonderregel bei Probe<=0 (nur Meisterlich=normaler Treffer bzw. Froehlich=guter Treffer moeglich) gehoeren ins zukuenftige Kampfmodul, nicht in den Charakterbogen - hier steht nur der Basismechanismus. | G129: Formel | H129: WENN(talente_fernkampfgeschick_stufe_2>0;1+AUFRUNDEN(fk_basis_spez_boegen_boegen/3;0);WENN(talente_fernkampfgeschick_stufe_1>0;1+AUFRUNDEN(fk_basis_spez_boegen_boegen/4;0);1)) | J129: Gleiches Muster wie fk_gute_* (Basiswaffe), nur auf den Spezialisierungs-Basiswert angewandt - Nutzerbestaetigung: 'Spezialisierungen sollten als simples +Spez in der /4 Formel gefuehrt sein'.
A130: fk_meisterlich_spez_schusswaffen_armbrust | B130: Fernkampf | C130: Fernkampf-Spezialisierungs-Meisterliche-Wert Armbrust | E130: Diese Formel geht von der VOLLSTAENDIGEN Probe aus (Basiswert + Waffen-Modifikator + Entfernungs-Modifikator, siehe Waffentabellen z.B. NN_Feuerwaffen_1.1.xlsx). Die Berechnung dieser vollstaendigen Probe sowie die Sonderregel bei Probe<=0 (nur Meisterlich=normaler Treffer bzw. Froehlich=guter Treffer moeglich) gehoeren ins zukuenftige Kampfmodul, nicht in den Charakterbogen - hier steht nur der Basismechanismus. | G130: Formel | H130: WENN(talente_fernkampfgeschick_stufe_3>0;21+AUFRUNDEN(fk_basis_spez_schusswaffen_armbrust/20;0);21) | J130: Gleiches Muster wie fk_meisterlich_* (Basiswaffe), nur auf den Spezialisierungs-Basiswert angewandt.
A131: fk_meisterlich_spez_blasrohre_blasrohre | B131: Fernkampf | C131: Fernkampf-Spezialisierungs-Meisterliche-Wert Blasrohre | E131: Diese Formel geht von der VOLLSTAENDIGEN Probe aus (Basiswert + Waffen-Modifikator + Entfernungs-Modifikator, siehe Waffentabellen z.B. NN_Feuerwaffen_1.1.xlsx). Die Berechnung dieser vollstaendigen Probe sowie die Sonderregel bei Probe<=0 (nur Meisterlich=normaler Treffer bzw. Froehlich=guter Treffer moeglich) gehoeren ins zukuenftige Kampfmodul, nicht in den Charakterbogen - hier steht nur der Basismechanismus. | G131: Formel | H131: WENN(talente_fernkampfgeschick_stufe_3>0;21+AUFRUNDEN(fk_basis_spez_blasrohre_blasrohre/20;0);21) | J131: Gleiches Muster wie fk_meisterlich_* (Basiswaffe), nur auf den Spezialisierungs-Basiswert angewandt.
A132: fk_meisterlich_spez_schusswaffen_musketen | B132: Fernkampf | C132: Fernkampf-Spezialisierungs-Meisterliche-Wert Musketen | E132: Diese Formel geht von der VOLLSTAENDIGEN Probe aus (Basiswert + Waffen-Modifikator + Entfernungs-Modifikator, siehe Waffentabellen z.B. NN_Feuerwaffen_1.1.xlsx). Die Berechnung dieser vollstaendigen Probe sowie die Sonderregel bei Probe<=0 (nur Meisterlich=normaler Treffer bzw. Froehlich=guter Treffer moeglich) gehoeren ins zukuenftige Kampfmodul, nicht in den Charakterbogen - hier steht nur der Basismechanismus. | G132: Formel | H132: WENN(talente_fernkampfgeschick_stufe_3>0;21+AUFRUNDEN(fk_basis_spez_schusswaffen_musketen/20;0);21) | J132: Gleiches Muster wie fk_meisterlich_* (Basiswaffe), nur auf den Spezialisierungs-Basiswert angewandt.
A133: fk_meisterlich_spez_schusswaffen_pistolen | B133: Fernkampf | C133: Fernkampf-Spezialisierungs-Meisterliche-Wert Pistolen | E133: Diese Formel geht von der VOLLSTAENDIGEN Probe aus (Basiswert + Waffen-Modifikator + Entfernungs-Modifikator, siehe Waffentabellen z.B. NN_Feuerwaffen_1.1.xlsx). Die Berechnung dieser vollstaendigen Probe sowie die Sonderregel bei Probe<=0 (nur Meisterlich=normaler Treffer bzw. Froehlich=guter Treffer moeglich) gehoeren ins zukuenftige Kampfmodul, nicht in den Charakterbogen - hier steht nur der Basismechanismus. | G133: Formel | H133: WENN(talente_fernkampfgeschick_stufe_3>0;21+AUFRUNDEN(fk_basis_spez_schusswaffen_pistolen/20;0);21) | J133: Gleiches Muster wie fk_meisterlich_* (Basiswaffe), nur auf den Spezialisierungs-Basiswert angewandt.
A134: fk_meisterlich_spez_boegen_boegen | B134: Fernkampf | C134: Fernkampf-Spezialisierungs-Meisterliche-Wert Bögen | E134: Diese Formel geht von der VOLLSTAENDIGEN Probe aus (Basiswert + Waffen-Modifikator + Entfernungs-Modifikator, siehe Waffentabellen z.B. NN_Feuerwaffen_1.1.xlsx). Die Berechnung dieser vollstaendigen Probe sowie die Sonderregel bei Probe<=0 (nur Meisterlich=normaler Treffer bzw. Froehlich=guter Treffer moeglich) gehoeren ins zukuenftige Kampfmodul, nicht in den Charakterbogen - hier steht nur der Basismechanismus. | G134: Formel | H134: WENN(talente_fernkampfgeschick_stufe_3>0;21+AUFRUNDEN(fk_basis_spez_boegen_boegen/20;0);21) | J134: Gleiches Muster wie fk_meisterlich_* (Basiswaffe), nur auf den Spezialisierungs-Basiswert angewandt.
A135: rs_arme | B135: Kampf | C135: Rüstungsschutz Arme | E135: S.2 | G135: Formel | H135: SUMME(RS der 5 Ruestungslagen in Zone arme) | J135: Jede Koerperzone hat 5 Lagen (Stoff/Leder/Kette/Platte/Addon, siehe Sheets Ruestung-Basis/-Verarbeitung/-Anpassung/-Addons), deren RS sich aufaddieren (Nutzerangabe 2026-07-16, bestaetigt durch das Beispiel-Set in Sheet Ruestungstabelle: Kopf RS = 3+4+6+6+0 = 19). Einzel-Lagen-RS = RS-Basis(Ruestungsteil) + RS-Mod(Verarbeitung) [Anpassung wirkt nie auf RS, siehe Ruestung-Basis-Formel]. Welche Ruestung pro Lage/Zone gewaehlt ist, ist noch keine Referenz in diesem Sheet (keine Auswahl-Mechanik vorhanden) - Aufloesung der SUMME(...) obliegt der App/Charakterbogen-Logik, siehe Entwickeln.
A136: rs_beine | B136: Kampf | C136: Rüstungsschutz Beine | E136: S.2 | G136: Formel | H136: SUMME(RS der 5 Ruestungslagen in Zone beine) | J136: Jede Koerperzone hat 5 Lagen (Stoff/Leder/Kette/Platte/Addon, siehe Sheets Ruestung-Basis/-Verarbeitung/-Anpassung/-Addons), deren RS sich aufaddieren (Nutzerangabe 2026-07-16, bestaetigt durch das Beispiel-Set in Sheet Ruestungstabelle: Kopf RS = 3+4+6+6+0 = 19). Einzel-Lagen-RS = RS-Basis(Ruestungsteil) + RS-Mod(Verarbeitung) [Anpassung wirkt nie auf RS, siehe Ruestung-Basis-Formel]. Welche Ruestung pro Lage/Zone gewaehlt ist, ist noch keine Referenz in diesem Sheet (keine Auswahl-Mechanik vorhanden) - Aufloesung der SUMME(...) obliegt der App/Charakterbogen-Logik, siehe Entwickeln.
... A138: rs_torso | B138: Kampf | C138: Rüstungsschutz Torso | E138: S.2 | G138: Formel | H138: SUMME(RS der 5 Ruestungslagen in Zone torso) | J138: Jede Koerperzone hat 5 Lagen (Stoff/Leder/Kette/Platte/Addon, siehe Sheets Ruestung-Basis/-Verarbeitung/-Anpassung/-Addons), deren RS sich aufaddieren (Nutzerangabe 2026-07-16, bestaetigt durch das Beispiel-Set in Sheet Ruestungstabelle: Kopf RS = 3+4+6+6+0 = 19). Einzel-Lagen-RS = RS-Basis(Ruestungsteil) + RS-Mod(Verarbeitung) [Anpassung wirkt nie auf RS, siehe Ruestung-Basis-Formel]. Welche Ruestung pro Lage/Zone gewaehlt ist, ist noch keine Referenz in diesem Sheet (keine Auswahl-Mechanik vorhanden) - Aufloesung der SUMME(...) obliegt der App/Charakterbogen-Logik, siehe Entwickeln.
A139: talente_gefahrensinn | B139: Talente | C139: Gefahrensinn | F139: Abenteurer | G139: Auswahl | J139: Kein exakter Namenstreffer in NN NPC-Rechner 0.75/Talente - dort heißt das Talent 'Gefahreninstinkt' (Kategorie=Abenteurer). Vermutlich dasselbe Talent unter leicht anderem Namen, Parent trotzdem gesetzt. | L139: 2
A140: bewegung_f_leiter_steigen_schnell | B140: Bewegung | C140: Leiter steigen schnell | E140: Meisterscreen S.3 | G140: Formel | H140: FEHLT | J140: kein Formeltext vorhanden
A141: bewegung_f_seil_hochklettern | B141: Bewegung | C141: Seil hochklettern | E141: Meisterscreen S.3 | G141: Formel | H141: FEHLT | J141: kein Formeltext vorhanden
A142: f_gefahreninstinkt | B142: Charakterwerte | C142: Gefahreninstinkt | D142: GI | E142: S.2 | G142: Formel | H142: eig_g_sinneschaerfe+sf_gefahreninstinkt | J142: kein Formeltext vorhanden | Formel = Sinnesschaerfe + SF Gefahreninstinkt (Nutzerangabe 2026-07-16). Einfache Probe, Probenwert = diese Formel, kann vom Meister situativ erschwert werden. Standard-Offsets fuer evtl. spaetere Gute/Meisterliche-Varianten waeren 1 bzw. 21 (Systemstandard, siehe aw_gut/aw_meisterlich), hier aber keine Sonderwerte noetig.
A143: bewegung_f_lesegeschwindigkeit | B143: Bewegung | C143: Lesegeschwindigkeit (Wörter/min) | E143: Meisterscreen S.3 | G143: Formel | H143: FEHLT | J143: kein Formeltext vorhanden | Referenz (Spalte G) enthält Klammern und Schrägstrich '(.../...)' unverändert aus der Beschreibung übernommen.
A144: ep_verbraucht | B144: Charakterwerte | C144: Verbrauchte EP | E144: S.1 | G144: Formel | H144: SUMME(Kosten aller gewaehlten Werte) | J144: Kein normaler Zeilen-Verweis wie sonst ueblich, sondern eine Summe UEBER DEN GESAMTEN Charakterbogen: alle Kosten-Werte jeder Zeile, die der Spieler tatsaechlich gewaehlt/erhoeht hat (Eigenschaften, Attribute, Grundfertigkeiten, Talente, Vor-/Nachteile, Spruchmagie, ...). Muss von der App als aggregierte Summe berechnet werden, nicht als einzelne Referenz aufloesbar.
A145: startbudget_ausruestung | B145: Charakterwerte | C145: Startbudget Ausruestung | E145: In Dublonen. 1 Dublone = 1000 Fuffzisch. Meister kann Kosten mit % anpassen (App-Verhalten, nicht Formel). | G145: Fixwert | H145: 5000 | J145: KORRIGIERT 2026-07-16 (Nutzerangabe): 5000 Dublonen Startbudget fuer Ausruestung bei Erschaffung (vorher faelschlich 4000 eingetragen).
A146: gr_betoeren | B146: Grundfertigkeit | C146: Betören | G146: Wert | J146: Kosten = statisch 9 EP/Punkt (Nutzerangabe). | L146: wert*9
A147: gr_dauerlauf | B147: Grundfertigkeit | C147: Dauerlauf | G147: Wert | J147: Kosten = statisch 9 EP/Punkt (Nutzerangabe). | L147: wert*9
A148: gr_einschuechtern | B148: Grundfertigkeit | C148: Einschüchtern | G148: Wert | J148: Kosten = statisch 9 EP/Punkt (Nutzerangabe). | L148: wert*9
A149: gr_faehrtensuche | B149: Grundfertigkeit | C149: Fährtensuche | G149: Wert | J149: Kosten = statisch 9 EP/Punkt (Nutzerangabe). | L149: wert*9
A150: gr_fliegen | B150: Grundfertigkeit | C150: Fliegen | G150: Wert | J150: Kosten = statisch 9 EP/Punkt (Nutzerangabe). | L150: wert*9
A151: gr_klettern | B151: Grundfertigkeit | C151: Klettern | G151: Wert | J151: Kosten = statisch 9 EP/Punkt (Nutzerangabe). | L151: wert*9
A152: gr_koerperbeherrschung | B152: Grundfertigkeit | C152: Körperbeherrschung | D152: KB | G152: Wert | J152: Kosten = statisch 9 EP/Punkt (Nutzerangabe). | L152: wert*9
A153: gr_laufen | B153: Grundfertigkeit | C153: Laufen | G153: Wert | J153: Kosten = statisch 9 EP/Punkt (Nutzerangabe). | L153: wert*9
A154: gr_luft_anhalten | B154: Grundfertigkeit | C154: Luft anhalten | G154: Wert | J154: Kosten = statisch 9 EP/Punkt (Nutzerangabe). | L154: wert*9
A155: gr_luegen | B155: Grundfertigkeit | C155: Lügen | G155: Wert | J155: Kosten = statisch 9 EP/Punkt (Nutzerangabe). | L155: wert*9
A156: gr_menschenkenntnis | B156: Grundfertigkeit | C156: Menschenkenntnis | G156: Wert | J156: Kosten = statisch 9 EP/Punkt (Nutzerangabe). | L156: wert*9
A157: gr_orientierung | B157: Grundfertigkeit | C157: Orientierung | G157: Wert | J157: Kosten = statisch 9 EP/Punkt (Nutzerangabe). | L157: wert*9
A158: gr_reiten | B158: Grundfertigkeit | C158: Reiten | G158: Wert | J158: Kosten = statisch 9 EP/Punkt (Nutzerangabe). | L158: wert*9
...

Sheet EP-Stufe-Kreis
A1: EP ab | B1: Stufe | C1: Kreis
A2: 0 | B2: 0 | C2: 0
A3: 20 | B3: 1 | C3: 1
A4: 60 | B4: 2 | C4: 1
A5: 120 | B5: 3 | C5: 1
A6: 200 | B6: 4 | C6: 2
A7: 300 | B7: 5 | C7: 2
A8: 400 | B8: 6 | C8: 2
A9: 500 | B9: 7 | C9: 2
A10: 600 | B10: 8 | C10: 2
A11: 700 | B11: 9 | C11: 3
A12: 850 | B12: 10 | C12: 3
A13: 1000 | B13: 11 | C13: 3
... A65: 15150 | B65: 63 | C65: 7

Sheet WHK-Spez-Kosten
A1: Wert | B1: EP-Kosten (Schritt) | C1: Gesamt-EP
A2: 0 | B2: 0 | C2: 0
A3: 1 | B3: 4 | C3: 4
A4: 2 | B4: 1 | C4: 5
A5: 3 | B5: 1 | C5: 6
A6: 4 | B6: 1 | C6: 7
A7: 5 | B7: 2 | C7: 9
A8: 6 | B8: 2 | C8: 11
A9: 7 | B9: 2 | C9: 13
A10: 8 | B10: 3 | C10: 16
A11: 9 | B11: 3 | C11: 19
A12: 10 | B12: 3 | C12: 22
A13: 11 | B13: 4 | C13: 26
... A41: 39 | B41: 13 | C41: 264

Sheet Eigenschaften-Kosten
A1: Wert | B1: Gesamt-EP | C1: EP-Kosten (Schritt)
A2: 0 | B2: 0 | C2: 0
A3: 1 | B3: 30 | C3: 30
A4: 2 | B4: 60 | C4: 30
A5: 3 | B5: 90 | C5: 30
A6: 4 | B6: 120 | C6: 30
A7: 5 | B7: 150 | C7: 30
A8: 6 | B8: 180 | C8: 30
A9: 7 | B9: 210 | C9: 30
A10: 8 | B10: 240 | C10: 30
A11: 9 | B11: 270 | C11: 30
A12: 10 | B12: 300 | C12: 30
A13: 11 | B13: 330 | C13: 30
... A66: 64 | B66: 6213 | C66: 189

Sheet Voelker-Maxima
A1: Volk | B1: Eigenschaft | C1: Erstellungs-Min | D1: Erstellungs-Max | E1: Max (ab Kreis 3)
A2: Dalkini | B2: Ausstrahlung | C2: 9 | D2: 21 | E2: 31
A3: Dalkini | B3: Intelligenz | C3: 9 | D3: 21 | E3: 31
A4: Dalkini | B4: Mut | C4: 10 | D4: 22 | E4: 31
A5: Dalkini | B5: Sinnesschaerfe | C5: 9 | D5: 21 | E5: 31
A6: Dalkini | B6: Willenskraft | C6: 15 | D6: 27 | E6: 31
A7: Dalkini | B7: Athletik | C7: 10 | D7: 22 | E7: 31
A8: Dalkini | B8: Geschicklichkeit | C8: 10 | D8: 22 | E8: 31
A9: Dalkini | B9: Konstitution | C9: 11 | D9: 23 | E9: 31
A10: Dalkini | B10: Schnelligkeit | C10: 10 | D10: 22 | E10: 31
A11: Dalkini | B11: Staerke | C11: 11 | D11: 23 | E11: 31
A12: Draw | B12: Ausstrahlung | C12: 11 | D12: 23 | E12: 31
A13: Draw | B13: Intelligenz | C13: 12 | D13: 24 | E13: 31
... A111: Zwerge | B111: Staerke | C111: 12 | D111: 24 | E111: 31

Sheet PSI-Zauberstufen
A1: Referenz | B1: Stufe | C1: Erschwerung | D1: ASP-Kosten
A2: psi_telekinese | B2: 1 | C2: 3 | D2: 10
A3: psi_telekinese | B3: 2 | C3: 6 | D3: 15
A4: psi_telekinese | B4: 3 | C4: 9 | D4: 25
A5: psi_telekinese | B5: 4 | C5: 12 | D5: 40
A6: psi_telekinese | B6: 5 | C6: 15 | D6: 60
A7: psi_telekinese | B7: 6 | C7: 18 | D7: 80
A8: psi_telekinese | B8: 7 | C8: 21 | D8: 105
A9: psi_telekinese_griff | B9: 1 | C9: 4 | D9: 20
A10: psi_telekinese_griff | B10: 2 | C10: 7 | D10: 30
A11: psi_telekinese_griff | B11: 3 | C11: 10 | D11: 40
A12: psi_telekinese_griff | B12: 4 | C12: 14 | D12: 55
A13: psi_telekinese_griff | B13: 5 | C13: 18 | D13: 75
... A106: psi_kryokinese | B106: 7 | C106: 29 | D106: 100

Sheet KI-Baum-Kanten
A1: Faehigkeit | B1: Vorbedingung | C1: Mindest-TaW
A2: ki_ki-schutz | B2: ki_abhaertung | C2: 10
A3: ki_geschossen_ausweichen | B3: ki_abwehr | C3: 15
A4: ki_geschossen_ausweichen | B4: ki_adlerauge | C4: 30
A5: ki_magie_aufspueren | B5: ki_adlerauge | C5: 20
A6: ki_erleuchtung | B6: ki_charisma | C6: 15
A7: ki_sprint | B7: ki_dauerlauf | C7: 10
A8: ki_heilender_schlaf | B8: ki_erleuchtung | C8: 10
A9: ki_adlerauge | B9: ki_fledermausohr_aalnase | C9: 15
A10: ki_kraftakt | B10: ki_froschlunge | C10: 10
A11: ki_paradeserie | B11: ki_geschossen_ausweichen | C11: 25
A12: ki_geschossen_ausweichen | B12: ki_gleichgewicht_&_feingefuehl | C12: 30
A13: ki_fledermausohr_aalnase | B13: ki_katzenauge | C13: 10
... A30: ki_katzenauge | B30: ki_konzentration | C30: 10

Sheet Preisliste
A1: Art | B1: Name | C1: Anzahl | D1: Einheit | E1: Gewicht in kg | F1: Dublonen | H1: WHK | I1: Spezialisierung
A2: Reittiere | B2: Drache, Flug | C2: 1 | D2: Stück | E2: XXX | F2: ------ | G2: Selten | H2: Abrichten | I2: Drache
A3: Reittiere | B3: Greif, Flug | C3: 1 | D3: Stück | E3: XXX | F3: ------ | G3: Selten | H3: Abrichten | I3: Greife
A4: Reittiere | B4: Chocobo, Abgeh, | C4: 1 | D4: Stück | E4: XXX | F4: 470 | G4: Elf | H4: Abrichten | I4: Laufvogel
A5: Reittiere | B5: Chocobo, Alt | C5: 1 | D5: Stück | E5: XXX | F5: 282 | G5: Elf | H5: Abrichten | I5: Laufvogel
A6: Reittiere | B6: Chocobo, Reit | C6: 1 | D6: Stück | E6: XXX | F6: 750 | G6: Elf | H6: Abrichten | I6: Laufvogel
A7: Reittiere | B7: Chocobo, Schlacht | C7: 1 | D7: Stück | E7: XXX | F7: 2250 | G7: Elf | H7: Abrichten | I7: Laufvogel
A8: Reittiere | B8: Chocobo, Vollblut | C8: 1 | D8: Stück | E8: XXX | F8: 3380 | G8: Elf | H8: Abrichten | I8: Laufvogel
A9: Reittiere | B9: Pegasus, Flug | C9: 1 | D9: Stück | E9: XXX | F9: ------ | G9: Selten | H9: Abrichten | I9: Pegasus
A10: Reittiere | B10: Pferd, Abgehalftert | C10: 1 | D10: Stück | E10: XXX | F10: 250 | G10: Indianer, Dalkini | H10: Abrichten | I10: Pferd
A11: Reittiere | B11: Pferd, Alter Gaul | C11: 1 | D11: Stück | E11: XXX | F11: 150 | G11: Indianer, Dalkini | H11: Abrichten | I11: Pferd
A12: Reittiere | B12: Pferd, Reit | C12: 1 | D12: Stück | E12: XXX | F12: 400 | G12: Indianer, Dalkini | H12: Abrichten | I12: Pferd
A13: Reittiere | B13: Pferd, Schlachtross | C13: 1 | D13: Stück | E13: XXX | F13: 1200 | G13: Indianer, Dalkini | H13: Abrichten | I13: Pferd
A14: Reittiere | B14: Pferd, Vollblut | C14: 1 | D14: Stück | E14: XXX | F14: 1800 | G14: Indianer, Dalkini | H14: Abrichten | I14: Pferd
A15: Reittiere | B15: Ratte, Abgehalftert | C15: 1 | D15: Stück | E15: XXX | F15: 190 | G15: Goblin | H15: Abrichten | I15: Ratte
A16: Reittiere | B16: Ratte, Alt | C16: 1 | D16: Stück | E16: XXX | F16: 115 | G16: Goblin | H16: Abrichten | I16: Ratte
A17: Reittiere | B17: Ratte, Gefährlich | C17: 1 | D17: Stück | E17: XXX | F17: 1350 | G17: Goblin | H17: Abrichten | I17: Ratte
A18: Reittiere | B18: Ratte, Reit | C18: 1 | D18: Stück | E18: XXX | F18: 300 | G18: Goblin | H18: Abrichten | I18: Ratte
A19: Reittiere | B19: Ratte, Schlacht | C19: 1 | D19: Stück | E19: XXX | F19: 900 | G19: Goblin | H19: Abrichten | I19: Ratte
A20: Reittiere | B20: Assel, Abgehalftert | C20: 1 | D20: Stück | E20: XXX | F20: 282 | G20: Zwerg | H20: Abrichten | I20: Reitkrebse
A21: Reittiere | B21: Assel, Alt | C21: 1 | D21: Stück | E21: XXX | F21: 169 | G21: Zwerg | H21: Abrichten | I21: Reitkrebse
... A37: Reittiere | B37: Schildkröte, Schnell | C37: 1 | D37: Stück | E37: XXX | F37: 4500 | G37: Gnom | H37: Abrichten | I37: Reitreptilien
A38: Reittiere | B38: Roc, Flug | C38: 1 | D38: Stück | E38: XXX | F38: ------ | G38: Selten | H38: Abrichten | I38: Rok
A39: Reittiere | B39: Rollok, abgehalftert | C39: 1 | D39: Stück | E39: XXX | F39: 532 | G39: Troll | H39: Abrichten | I39: Rollok
A40: Reittiere | B40: Rollok, alt | C40: 1 | D40: Stück | E40: XXX | F40: 319 | G40: Troll | H40: Abrichten | I40: Rollok
A41: Reittiere | B41: Rollok, Reit | C41: 1 | D41: Stück | E41: XXX | F41: 850 | G41: Troll | H41: Abrichten | I41: Rollok
A42: Reittiere | B42: Rollok, Schlacht | C42: 1 | D42: Stück | E42: XXX | F42: 2550 | G42: Troll | H42: Abrichten | I42: Rollok
A43: Reittiere | B43: Rollok, übellaunig | C43: 1 | D43: Stück | E43: XXX | F43: 3850 | G43: Troll | H43: Abrichten | I43: Rollok
A44: Reittiere | B44: Warg, Abgehalftert | C44: 1 | D44: Stück | E44: XXX | F44: 375 | G44: Ork | H44: Abrichten | I44: Warg
A45: Reittiere | B45: Warg, Alt | C45: 1 | D45: Stück | E45: XXX | F45: 225 | G45: Ork | H45: Abrichten | I45: Warg
A46: Reittiere | B46: Warg, Elite | C46: 1 | D46: Stück | E46: XXX | F46: 2700 | G46: Ork | H46: Abrichten | I46: Warg
A47: Reittiere | B47: Warg, Reit | C47: 1 | D47: Stück | E47: XXX | F47: 600 | G47: Ork | H47: Abrichten | I47: Warg
A48: Reittiere | B48: Warg, Schlacht | C48: 1 | D48: Stück | E48: XXX | F48: 1800 | G48: Ork | H48: Abrichten | I48: Warg
A49: Alchemistische Stoffe | B49: Öl, Brand- | C49: 1 | D49: Fass | E49: 5 | F49: 35 | H49: Alchemie | I49: Brandbeschleuniger
A50: Alchemistische Stoffe | B50: Schwarzpulver | C50: 1 | D50: Sack | E50: 1 | F50: 85 | H50: Alchemie | I50: Brandbeschleuniger
A51: Alchemistische Stoffe | B51: Zwergisches Feuer | C51: 1 | D51: Flasche | E51: 1 | F51: 500 | H51: Alchemie | I51: Brandbeschleuniger
A52: Beleuchtung | B52: Streichhölzer 25St, | C52: 1 | D52: Schachtel | E52: 0.2 | F52: 1 | H52: Alchemie | I52: Brandbeschleuniger
A53: Alchemistische Stoffe | B53: Orazal (Lösung) | C53: 1 | D53: Bund | E53: 0.002 | F53: 92 | H53: Alchemie | I53: DSA-Material
A54: Schreibwaren | B54: Tinte | C54: 1 | D54: Phiole | E54: 0.1 | F54: 0.98 | H54: Alchemie | I54: Farbstoffe
A55: Schreibwaren | B55: Tusche | C55: 1 | D55: Phiole | E55: 0.1 | F55: 1.3 | H55: Alchemie | I55: Farbstoffe
A56: Schreibwaren | B56: Tusche, farbig | C56: 1 | D56: Phiole | E56: 0.1 | F56: 3.5 | H56: Alchemie | I56: Farbstoffe
A57: Alchemistische Stoffe | B57: Fett, Salben-, pflanzlich | C57: 1 | D57: Tiegel | E57: 1 | F57: 13 | H57: Alchemie | I57: Fettprodukte
A58: Alchemistische Stoffe | B58: Fett, Salben-, tierisch | C58: 1 | D58: Tiegel | E58: 1 | F58: 13 | H58: Alchemie | I58: Fettprodukte
A59: Körperpflege | B59: Lippenrot | C59: 1 | D59: Tiegel | E59: 0.02 | F59: 4.5 | H59: Alchemie | I59: Fettprodukte
A60: Körperpflege | B60: Seife | C60: 1 | D60: Stück | E60: 0.5 | F60: 0.1 | H60: Alchemie | I60: Fettprodukte
... A92: Nahrungsmittel | B92: Zuckerstange | C92: 1 | D92: Portion | E92: 0.02 | F92: 0.15 | H92: Bäcker | I92: Konditor
A93: Körperpflege | B93: Entlausen | C93: 1 | D93: Besuch | E93: XXX | F93: 0.5 | H93: Barbier | I93: Bader
A94: Körperpflege | B94: Maniküre | C94: 1 | D94: Besuch | E94: XXX | F94: 2 | H94: Barbier | I94: Bader
A95: Körperpflege | B95: Rasur | C95: 1 | D95: Besuch | E95: XXX | F95: 0.75 | H95: Barbier | I95: Bader
A96: Körperpflege | B96: Vollbad im Badehaus | C96: 1 | D96: Besuch | E96: XXX | F96: 1 | H96: Barbier | I96: Bader
A97: Körperpflege | B97: Frisur | C97: 1 | D97: Besuch | E97: XXX | F97: 2 | H97: Barbier | I97: Frisör
A98: Körperpflege | B98: Frisur, Ball- | C98: 1 | D98: Besuch | E98: XXX | F98: 15 | H98: Barbier | I98: Frisör
A99: Körperpflege | B99: Schnitt, Bart- | C99: 1 | D99: Besuch | E99: XXX | F99: 0.9 | H99: Barbier | I99: Frisör
A100: Tierbedarf | B100: Hund färben | C100: 1 | D100: Besuch | E100: XXX | F100: 10 | H100: Barbier | I100: Frisör
A101: Edelsteine | B101: 10 Aquamarin | C101: 1 | D101: Karat | E101: 0.0002 | F101: 3.6 | G101: gebraucht erworben werden können oder die in Einheitsgrößen hergestellt werden, | H101: Bergbau | I101: Edelsteine
A102: Edelsteine | B102: 11 Granat | C102: 1 | D102: Karat | E102: 0.0002 | F102: 1.3 | G102: Der zweitgenannte Preis gilt für Maßanfertigungen bei einem Schneider oder Schuster, | H102: Bergbau | I102: Edelsteine
A103: Edelsteine | B103: 12 Onyx | C103: 1 | D103: Karat | E103: 0.0002 | F103: 2.2 | G103: Der als erstes angegebene Preis bezieht sich bei Kleidungsstücken auf solche, die bei einem Trödler oder Krämer | H103: Bergbau | I103: Edelsteine
A104: Edelsteine | B104: 13 Perle | C104: 1 | D104: Karat | E104: 0.0002 | F104: 3 | H104: Bergbau | I104: Edelsteine
A105: Edelsteine | B105: 14 Turmalin | C105: 1 | D105: Karat | E105: 0.0002 | F105: 4.4 | H105: Bergbau | I105: Edelsteine
A106: Edelsteine | B106: 15 Bernstein | C106: 1 | D106: Karat | E106: 0.0002 | F106: 8 | H106: Bergbau | I106: Edelsteine
A107: Edelsteine | B107: 16 Zirkon | C107: 1 | D107: Karat | E107: 0.0002 | F107: 16 | H107: Bergbau | I107: Edelsteine
A108: Edelsteine | B108: 17 Smaragd | C108: 1 | D108: Karat | E108: 0.0002 | F108: 20 | H108: Bergbau | I108: Edelsteine
A109: Edelsteine | B109: 18 Rubin | C109: 1 | D109: Karat | E109: 0.0002 | F109: 25 | H109: Bergbau | I109: Edelsteine
A110: Edelsteine | B110: 3 Diamant | C110: 1 | D110: Karat | E110: 0.0002 | F110: 27 | G110: Die hier angegebenen Preise beziehen sich auf geschliffene Stücke, Ungeschliffene Steine erbringen höchstens die Hälfte des Preises, | H110: Bergbau | I110: Edelsteine
A111: Edelsteine | B111: 4 Saphir | C111: 1 | D111: Karat | E111: 0.0002 | F111: 22 | G111: Edelsteine von mehr als 50 Karat jedoch auch leicht das Doppelte des hier angegeben Wertes, Mit 3W6 können Sie festlegen, welche Edelsteine sich | H111: Bergbau | I111: Edelsteine
A112: Edelsteine | B112: 5 Opal | C112: 1 | D112: Karat | E112: 0.0002 | F112: 11 | G112: z,B, in einem Schatz befinden, | H112: Bergbau | I112: Edelsteine
A113: Edelsteine | B113: 6 Rohdiamant | C113: 1 | D113: Karat | E113: 0.0002 | F113: 7 | G113: auf 3W6 Edelstein Preis pro Karat (0,2g) | H113: Bergbau | I113: Edelsteine
A114: Edelsteine | B114: 7 Topas | C114: 1 | D114: Karat | E114: 0.0002 | F114: 8 | H114: Bergbau | I114: Edelsteine
A115: Edelsteine | B115: 8 Lapislazuli | C115: 1 | D115: Karat | E115: 0.0002 | F115: 3.5 | G115: Einige weitere Mineralien werden als 'Halbedelsteine' angesehen, Sie kosten ungefähr 9 Dublonen pro 25g, | H115: Bergbau | I115: Edelsteine
A116: Edelsteine | B116: 9 Jade | C116: 1 | D116: Karat | E116: 0.0002 | F116: 1.8 | G116: Zu ihnen gehören: Amethyst, Rosenquarz, Mondstein, Türkis, Malachit, Korallen, Meerschaum und Achat, | H116: Bergbau | I116: Edelsteine
A117: Metall | B117: Diamantspat, ungeprägt | C117: 1 | D117: Barren | E117: 1 | F117: 88 | H117: Bergbau | I117: Edelsteine
A118: Metall | B118: Diamantspat-Metallplatten/drähte | C118: 1 | D118: Bund | E118: 1 | F118: 106 | H118: Bergbau | I118: Edelsteine
A119: Schreibwaren | B119: Kreide, Schreib- | C119: 1 | D119: Schachtel | E119: 0.02 | F119: 0.018 | H119: Bergbau | I119: Gesteine
A120: Schreibwaren | B120: Tafel, Schiefer- | C120: 1 | D120: Stück | E120: 0.5 | F120: 0.78 | H120: Bergbau | I120: Gesteine
A121: Alchemistische Stoffe | B121: Kohle, Zwergen- | C121: 1 | D121: Sack | E121: 1 | F121: 3 | H121: Bergbau | I121: Kohle
A122: Schreibwaren | B122: Stifte, Kohle-, 5 St, | C122: 1 | D122: Satz | E122: 0.05 | F122: 0.005 | H122: Bergbau | I122: Kohle
A123: Alchemistische Stoffe | B123: Öl, Braun-, rauchend | C123: 1 | D123: Flasche | E123: 1 | F123: 52 | H123: Bergbau | I123: Ölprodukte
A124: Alchemistische Stoffe | B124: Pech, Destillations- | C124: 1 | D124: Tiegel | E124: 1 | F124: 8 | H124: Bergbau | I124: Ölprodukte
A125: Alchemistische Stoffe | B125: Salpeter, Salz | C125: 1 | D125: Sack | E125: 1 | F125: 35 | H125: Bergbau | I125: Salze
A126: Alchemistische Stoffe | B126: Schwefel | C126: 1 | D126: Sack | E126: 1 | F126: 125 | H126: Bergbau | I126: Salze
A127: Nahrungsmittel | B127: Salz | C127: 1 | D127: Sack | E127: 0.5 | F127: 0.3 | H127: Bergbau | I127: Salze
A128: Segelschiff | B128: Schiff, Dreimaster | C128: 1 | D128: Stück | E128: XXX | F128: 640000 | H128: Bootsbauer | I128: Dickschiffe
A129: Segelschiff | B129: Schiff, Fünfmaster | C129: 1 | D129: Stück | E129: XXX | F129: 1400000 | H129: Bootsbauer | I129: Dickschiffe
A130: Segelschiff | B130: Schiff, Viermaster | C130: 1 | D130: Stück | E130: XXX | F130: 960000 | H130: Bootsbauer | I130: Dickschiffe
A131: Segelschiff | B131: Schiff, Zweimaster | C131: 1 | D131: Stück | E131: XXX | F131: 420000 | H131: Bootsbauer | I131: Dickschiffe
A132: Segelschiff | B132: Boot, Ruder- klein | C132: 1 | D132: Stück | E132: 50 | F132: 528 | H132: Bootsbauer | I132: Kleine Schiffe
A133: Segelschiff | B133: Boot, Segel- 6m lang | C133: 1 | D133: Stück | E133: 400 | F133: 2860 | H133: Bootsbauer | I133: Kleine Schiffe
A134: Segelschiff | B134: Kanu | C134: 1 | D134: Stück | E134: 50 | F134: 50 | H134: Bootsbauer | I134: Kleine Schiffe
A135: Segelschiff | B135: Schiff, Einmaster | C135: 1 | D135: Stück | E135: XXX | F135: 280000 | H135: Bootsbauer | I135: Kleine Schiffe
A136: Alchemistische Stoffe | B136: Alkohol, rein | C136: 1 | D136: Flasche | E136: 1 | F136: 20 | H136: Brenner | I136: Alchemistische Zutaten
A137: Alchemistische Stoffe | B137: Zwiedestillat | C137: 1 | D137: Flasche | E137: 1 | F137: 13 | H137: Brenner | I137: Alchemistische Zutaten
A138: Alchemistische Stoffe | B138: Schwefelquell Gratenfelser | C138: 1 | D138: Flasche | E138: 1 | F138: 7.5 | H138: Brenner | I138: Alchemistische Zutaten
A139: Nahrungsmittel | B139: Likör | C139: 1 | D139: Flasche | E139: 0.5 | F139: 0.5 | H139: Brenner | I139: Geist
A140: Nahrungsmittel | B140: Schnaps, einfach | C140: 1 | D140: Flasche | E140: 1 | F140: 0.4 | H140: Brenner | I140: Geist
A141: Nahrungsmittel | B141: Wein, Brannt- | C141: 1 | D141: Flasche | E141: 1 | F141: 0.5 | H141: Brenner | I141: Geist
A142: Nahrungsmittel | B142: Wein, Brannt-, gut | C142: 1 | D142: Flasche | E142: 1 | F142: 50 | H142: Brenner | I142: Geist
A143: Körperpflege | B143: Wein, Franzbrannt- | C143: 1 | D143: Flasche | E143: 0.25 | F143: 2.8 | H143: Brenner | I143: Kräutergeist
A144: Körperpflege | B144: Wein, Kräuterbrannt- | C144: 1 | D144: Flasche | E144: 0.25 | F144: 3 | H144: Brenner | I144: Kräutergeist
A145: Schreibwaren | B145: Buch, Tage-, Papier | C145: 1 | D145: Stück | E145: 0.5 | F145: 15.4 | H145: Drucker | I145: Buchbinder
A146: Schreibwaren | B146: Papier, 10 Bögen | C146: 1 | D146: Schachtel | E146: 0.08 | F146: 1.3 | H146: Drucker | I146: Papierherstellung
...

Sheet Alchemika
A1: Kategorie | B1: magisch_y_n | C1: Name | D1: Potenz | E1: Dosierbar | F1: Zufuhr | G1: ZbS (Zeit bis Symptom) | H1: ZbW (Zeit bis Wirkung) | I1: Wirkungsdauer | J1: Wirkung | K1: Legalität | L1: Char_Unterwelt_Mod | M1: Verfügb | N1: Zutaten_Preis_in_D | O1: Kaufpreis_in_D | P1: Rezept-Erschwerung
A2: Gifte | B2: profan | C2: Leichtes Regigift | D2: 5 | E2: J | F2: Körper | G2: Sofort | H2: Sofort | I2: 12h | J2: Regenerationsklasse -2, leichter Schlaf | K2: 3 | L2: 0 | M2: 1 | N2: 0.25 | O2: =N2*(K2+L2) -> 0.75 | P2: 4
A3: Gifte | B3: profan | C3: Regigift | D3: 15 | E3: J | F3: Körper | G3: Sofort | H3: Sofort | I3: 12h | J3: Regenerationsklasse -4, leichter Schlaf | K3: 4 | L3: 0 | M3: 2 | N3: 0.5 | O3: =N3*(K3+L3) -> 2 | P3: 6
A4: Gifte | B4: profan | C4: Starkes Regigift | D4: 30 | E4: J | F4: Körper | G4: Sofort | H4: Sofort | I4: 12h | J4: Regenerationsklasse -7, leichter Schlaf | K4: 5 | L4: 0 | M4: 3 | N4: 1 | O4: =N4*(K4+L4) -> 5 | P4: 10
A5: Gifte | B5: profan | C5: Hässlichkeitsgift | D5: 15 | E5: J | F5: Körper | G5: Sofort | H5: Sofort | I5: 1d | J5: Alle Grundfertigkeits-, Sprach-, Kulur- und WHK-Proben auf Ausstrahlung um 10 erschwert | K5: 4 | L5: 0 | M5: 5 | N5: 50 | O5: =N5*(K5+L5) -> 200 | P5: 30
A6: Gifte | B6: profan | C6: Starkes Hässlichkeitsgift | D6: 30 | E6: J | F6: Körper | G6: Sofort | H6: Sofort | I6: 1d | J6: Alle Grundfertigkeits-, Sprach-, Kulur- und WHK-Proben auf Ausstrahlung um 15 erschwert | K6: 5 | L6: 0 | M6: 6 | N6: 150 | O6: =N6*(K6+L6) -> 750 | P6: 48
A7: Gifte | B7: profan | C7: Leichtes Hässlichkeitsgift | D7: 5 | E7: J | F7: Körper | G7: Sofort | H7: Sofort | I7: 1d | J7: Alle Grundfertigkeits-, Sprach-, Kulur- und WHK-Proben auf Ausstrahlung um 5 erschwert | K7: 3 | L7: 0 | M7: 4 | N7: 25 | O7: =N7*(K7+L7) -> 75 | P7: 18
A8: Gifte | B8: profan | C8: Leichtes Zungengift | D8: 5 | E8: J | F8: Körper | G8: 1 KR | H8: 3 KR | I8: 1h | J8: Artikuliertes Sprechen unmöglich | K8: 2 | L8: 0 | M8: 2 | N8: 1 | O8: =N8*(K8+L8) -> 2 | P8: 12
A9: Gifte | B9: profan | C9: Zungengift | D9: 15 | E9: J | F9: Körper | G9: 1 KR | H9: 3 KR | I9: 1h | J9: Artikuliertes Sprechen unmöglich | K9: 3 | L9: 0 | M9: 3 | N9: 2 | O9: =N9*(K9+L9) -> 6 | P9: 18
A10: Gifte | B10: profan | C10: Starkes Zungengift | D10: 30 | E10: J | F10: Körper | G10: 1 KR | H10: 3 KR | I10: 1h | J10: Artikuliertes Sprechen unmöglich | K10: 4 | L10: 0 | M10: 4 | N10: 4 | O10: =N10*(K10+L10) -> 16 | P10: 30
A11: Gifte | B11: profan | C11: Leichtes Taubheitsgift | D11: 5 | E11: J | F11: Körper | G11: 1 KR | H11: 3 KR | I11: 1h | J11: BE 2, Gefahrensinn -12 | K11: 2 | L11: 0 | M11: 2 | N11: 1 | O11: =N11*(K11+L11) -> 2 | P11: 12
A12: Gifte | B12: profan | C12: Taubheitsgift | D12: 15 | E12: J | F12: Körper | G12: 1 KR | H12: 3 KR | I12: 1h | J12: BE 2, Gefahrensinn -12 | K12: 3 | L12: 0 | M12: 3 | N12: 2 | O12: =N12*(K12+L12) -> 6 | P12: 18
A13: Gifte | B13: profan | C13: Starkes Taubheitsgift | D13: 30 | E13: J | F13: Körper | G13: 1 KR | H13: 3 KR | I13: 1h | J13: BE 2, Gefahrensinn -12 | K13: 4 | L13: 0 | M13: 4 | N13: 4 | O13: =N13*(K13+L13) -> 16 | P13: 30
... A119: Zustandstränke | B119: profan | C119: Geruchslossalbe | D119: 75 | E119: N | F119: Kontakt | G119: 2 KR | H119: 5 KR | I119: 6h | J119: Man verliert seinen Geruch komplett | K119: 2 | L119: 0 | M119: 5 | N119: 25 | O119: =N119*(K119+L119) -> 50 | P119: 12

Sheet Ruestungstabelle
B1: Kopf | C1: Verarbeitung | D1: Anpassung | E1: RS | F1: BE | G1: Preis | H1: NW | I1: AW
A2: Lage 1 | B2: Stoffrüstung | C2: Meisterarbeit | D2: angepasst | E2: 3 | F2: 1 | G2: 227 | H2: 3 | I2: 2
A3: Lage 2 | B3: Leichte Lederrüstung | C3: Meisterarbeit | D3: angepasst | E3: 4 | F3: 2 | G3: 274 | H3: 3 | I3: 2
A4: Lage 3 | B4: Stahl-Kettenpanzer | C4: Meisterarbeit | D4: angepasst | E4: 6 | F4: 3 | G4: 1830 | H4: 3 | I4: 2
A5: Lage 4 | B5: Schwerer Lederpanzer | C5: Meisterarbeit | D5: angepasst | E5: 6 | F5: 4 | G5: 562 | H5: 3 | I5: 2
A6: Lage 5 | B6: Keine Rüstung | E6: 0 | F6: 0 | G6: 0 | H6: 0 | I6: 0
C7: Kopf | D7: Gesamt: | E7: 19 | F7: 10 | G7: 2893
B8: Torso | C8: Verarbeitung | D8: Anpassung | E8: RS | F8: BE | G8: Preis | H8: NW | I8: AW
A9: Lage 1 | B9: Stoffrüstung | C9: Großmeisterarbeit | D9: perfekt angepasst | E9: 4 | F9: 1 | G9: 387 | H9: 5 | I9: 3
A10: Lage 2 | B10: Leichte Lederrüstung | C10: Gesellenarbeit | D10: angepasst | E10: 3 | F10: 2 | G10: 38 | H10: 3 | I10: 2
A11: Lage 3 | B11: Eisen-Kettenpanzer | C11: Gesellenarbeit | D11: angepasst | E11: 4 | F11: 3 | G11: 372 | H11: 3 | I11: 2
A12: Lage 4 | B12: Schwerer Faltstahlpanzer | C12: Einzelstück | D12: perfekt angepasst | E12: 14 | F12: 7 | G12: 6495 | H12: 7 | I12: 7
A13: Lage 5 | B13: Keine Rüstung | E13: 0 | F13: 0 | G13: 0 | H13: 0 | I13: 0
C14: Torso | D14: Gesamt: | E14: 25 | F14: 13 | G14: 7292
B15: Arme | C15: Verarbeitung | D15: Anpassung | E15: RS | F15: BE | G15: Preis | H15: NW | I15: AW
A16: Lage 1 | B16: Stoffrüstung | C16: Gesellenarbeit | D16: angepasst | E16: 2 | F16: 1 | G16: 50 | H16: 3 | I16: 2
A17: Lage 2 | B17: Leichte Lederrüstung | C17: Gesellenarbeit | D17: angepasst | E17: 3 | F17: 2 | G17: 38 | H17: 3 | I17: 2
A18: Lage 3 | B18: Eisen-Kettenpanzer | C18: Gesellenarbeit | D18: angepasst | E18: 4 | F18: 3 | G18: 372 | H18: 3 | I18: 2
A19: Lage 4 | B19: Schwerer Lederpanzer | C19: Gesellenarbeit | D19: angepasst | E19: 5 | F19: 4 | G19: 208 | H19: 3 | I19: 2
A20: Lage 5 | B20: Keine Rüstung | E20: 0 | F20: 0 | G20: 0 | H20: 0 | I20: 0
C21: Arme | D21: Gesamt: | E21: 14 | F21: 10 | G21: 668
B22: Beine | C22: Verarbeitung | D22: Anpassung | E22: RS | F22: BE | G22: Preis | H22: NW | I22: AW
A23: Lage 1 | B23: Stoffrüstung | C23: Gesellenarbeit | D23: angepasst | E23: 2 | F23: 1 | G23: 50 | H23: 3 | I23: 2
A24: Lage 2 | B24: Leichte Lederrüstung | C24: Gesellenarbeit | D24: angepasst | E24: 3 | F24: 2 | G24: 38 | H24: 3 | I24: 2
A25: Lage 3 | B25: Eisen-Kettenpanzer | C25: Gesellenarbeit | D25: angepasst | E25: 4 | F25: 3 | G25: 372 | H25: 3 | I25: 2
A26: Lage 4 | B26: Schwerer Lederpanzer | C26: Gesellenarbeit | D26: angepasst | E26: 5 | F26: 4 | G26: 208 | H26: 3 | I26: 2
A27: Lage 5 | B27: Keine Rüstung | E27: 0 | F27: 0 | G27: 0 | H27: 0 | I27: 0
C28: Beine | D28: Gesamt: | E28: 14 | F28: 10 | G28: 668
F29: BE | G29: Preis
C30: Rüstung | D30: Gesamt: | F30: 43 | G30: 11521
A31: Legende:
A32: Hals, Schultergelenk, Ellenbogen, Hände, Knie und Füße werden nur mit halbem RS geschützt. Augen werden nicht geschützt.Für alle nicht genannten kritischen Trefferzonen gilt der volle Rüstungswert.
A33: Jedes Rüstungsteil kann durch Verarbeitung und Anpassung einmalig modifiziert werden.
A34: Jedes Rüstungsteil hat seine Lage als Mindest-RBE. Lage 5 (Umhänge, Aufpanzerungen) sind hiervon ausgenommen.
A35: Drachenschuppen und andere Aufpanzerungen verfügen über bestimmte Boni, die derzeit noch in der alten Waffentabelle aufgeführt sind...
A36: Rüstung | B36: Lage | C36: RS | D36: BE | F36: Verfügbarkeit NW | G36: Verfügbarkeit AW | H36: Materialkosten | I36: Arbeitszeit/d
A37: Keine Rüstung
A38: Leichte Stoffrüstung | B38: 1 | C38: 1 | D38: 1 | F38: 1 | G38: 1 | H38: 16 | I38: 1
A39: Stoffrüstung | B39: 1 | C39: 2 | D39: 2 | F39: 1 | G39: 1 | H39: 32 | I39: 1
A40: Schwere Stoffrüstung | B40: 1 | C40: 3 | D40: 3 | F40: 1 | G40: 1 | H40: 48 | I40: 1
A41: Keine Rüstung | B41: 1 | F41: 1
A42: Leichte Lederrüstung | B42: 2 | C42: 3 | D42: 3 | F42: 1 | G42: 1 | H42: 14 | I42: 2
A43: Lederrüstung | B43: 2 | C43: 4 | D43: 4 | F43: 1 | G43: 1 | H43: 28 | I43: 2
A44: Schwere Lederrüstung | B44: 2 | C44: 5 | D44: 5 | F44: 1 | G44: 1 | H44: 48 | I44: 2
A45: Keine Rüstung | B45: 2 | F45: 1
A46: Eisen-Kettenpanzer | B46: 3 | C46: 4 | D46: 4 | F46: 1 | G46: 1 | H46: 300 | I46: 10
A47: Stahl-Kettenpanzer | B47: 3 | C47: 5 | D47: 4 | F47: 2 | G47: 1 | H47: 1050 | I47: 10
A48: Schwerer Eisen-Kettenpanzer | B48: 3 | C48: 6 | D48: 5 | F48: 1 | G48: 1 | H48: 480 | I48: 15
A49: Faltstahl-Kettenpanzer | B49: 3 | C49: 7 | D49: 5 | F49: 5 | G49: 3 | H49: 1500 | I49: 10
A50: Schwerer Stahl-Kettenpanzer | B50: 3 | C50: 8 | D50: 6 | F50: 2 | G50: 1 | H50: 1680 | I50: 15
A51: Schwerer Faltstahl-Kettenpanzer | B51: 3 | C51: 9 | D51: 6 | F51: 6 | G51: 4 | H51: 2400 | I51: 15
A52: Keine Rüstung | B52: 3 | F52: 1
A53: Lederpanzer | B53: 4 | C53: 4 | D53: 4 | F53: 2 | G53: 2 | H53: 130 | I53: 3
A54: Schwerer Lederpanzer | B54: 4 | C54: 5 | D54: 5 | F54: 2 | G54: 2 | H54: 172 | I54: 4
A55: Eisenpanzer | B55: 4 | C55: 6 | D55: 6 | F55: 1 | G55: 1 | H55: 607 | I55: 7
A56: Stahlpanzer | B56: 4 | C56: 7 | D56: 7 | F56: 2 | G56: 1 | H56: 2107 | I56: 7
A57: Schwerer Eisenpanzer | B57: 4 | C57: 8 | D57: 8 | F57: 1 | G57: 1 | H57: 907 | I57: 10
A58: Schwerer Stahlpanzer | B58: 4 | C58: 9 | D58: 8 | F58: 2 | G58: 1 | H58: 3157 | I58: 10
A59: Faltstahlpanzer | B59: 4 | C59: 10 | D59: 8 | F59: 5 | G59: 3 | H59: 3007 | I59: 7
A60: Schwerer Faltstahlpanzer | B60: 4 | C60: 12 | D60: 10 | F60: 6 | G60: 4 | H60: 4507 | I60: 10
A61: Keine Rüstung | B61: 5 | F61: 1

Sheet NK-Material
A1: Waffe | B1: Stä-Malus | C1: AT- | D1: PA- | E1: WK | F1: 1H min.Stä | G1: 2H min.Stä | H1: Preis | I1: Klingen-Brecher | J1: Klingen-Schutz | L1: Art/Specials | M1: Rezept-Mod
A2: Eisen | F2: 1 | G2: 1 | H2: 50 | K2: Standard | M2: 10
A3: Stahl | B3: 1 | D3: 1 | E3: -0.5 | F3: 0.9 | G3: 0.9 | H3: 125 | I3: 1 | J3: 1 | K3: ALLE | M3: 12
A4: Qualitätsstahl | B4: 1 | D4: 1 | E4: -0.5 | F4: 0.9 | G4: 0.9 | H4: 175 | I4: 2 | J4: 2 | K4: ALLE | M4: 18
A5: Faltstahl | B5: 2 | D5: 1 | E5: -0.5 | F5: 0.8 | G5: 0.8 | H5: 250 | I5: 3 | J5: 3 | K5: ALLE | M5: 30
A6: Mithril | B6: -1 | D6: 2 | E6: -2 | F6: 0.5 | G6: 0.5 | H6: 1250 | I6: 0 | J6: 2 | K6: ALLE | M6: 20
A7: Kolhartz | B7: -1 | C7: 1 | D7: 2 | E7: -1 | F7: 0.5 | G7: 0.5 | H7: 1500 | I7: 0 | J7: 0 | K7: Zentauren | M7: 5
A8: Alchemistensilb. | B8: 0 | C8: -1 | F8: 1 | G8: 1 | H8: 1500 | I8: -1 | J8: -1 | K8: ALLE | M8: 8
A9: Nasium | B9: 0 | C9: -1 | D9: -1 | E9: -1 | F9: 1.2 | G9: 1.2 | H9: 1500 | I9: -1 | J9: -1 | K9: ALLE | M9: 7
A10: Diamantspat | B10: 3 | D10: 1 | E10: -0.5 | F10: 0.8 | G10: 0.8 | H10: 88 | I10: 3 | J10: 3 | K10: Drow | L10: Zerfällt bei kontakt mit Sonnenlicht zu Staub | M10: 12
A11: Adamandit | B11: 3 | D11: 1 | E11: -0.5 | F11: 0.8 | G11: 0.8 | H11: 250000 | I11: 3 | J11: 6 | K11: ALLE | M11: 120
A12: Holz | B12: -3 | C12: 2 | D12: 2 | E12: -1.5 | F12: 0.5 | G12: 0.5 | H12: 0.1 | I12: -11 | J12: -7 | K12: ALLE | M12: 0
A13: Knochen | B13: 0 | C13: 1 | D13: 2 | E13: -1 | F13: 0.5 | G13: 0.5 | H13: 0.1 | I13: -4 | J13: -5 | K13: ALLE | M13: 2
A14: Stein | B14: 0 | C14: -3 | D14: -2 | E14: 1 | F14: 1.3 | G14: 1.3 | H14: 0.1 | I14: -2 | J14: -3 | K14: ALLE | M14: 5
A15: Schwarzfells | B15: 0 | C15: -2 | D15: -1 | E15: 1 | F15: 1.1 | G15: 1.1 | H15: 0.25 | I15: -2 | J15: -2 | K15: Indianer | M15: 4
A16: Leder | B16: 0 | E16: 0 | F16: 1 | G16: 1 | H16: 0.3 | K16: ALLE | M16: 5
A17: Hartholz | B17: -2 | C17: 1 | D17: 2 | E17: -1 | F17: 0.7 | G17: 0.7 | H17: 3 | I17: -7 | J17: -5 | K17: ALLE | L17: Der Schaden wird zur hälfte auf Ausdauer verteielt | M17: 3
A18: Vulkanglas | B18: -1 | C18: -3 | D18: -2 | E18: -1 | F18: 1.1 | G18: 1.1 | H18: 3 | I18: -4 | J18: -5 | K18: Indianer | M18: 5
A19: Chitin | B19: 0 | C19: -1 | D19: 2 | E19: -1 | F19: 0.5 | G19: 0.5 | H19: 20 | I19: -2 | K19: ALLE | M19: 3
A20: Bronze | B20: -1 | C20: -1 | E20: 0.5 | F20: 1.1 | G20: 1.1 | H20: 25 | I20: -2 | J20: -2 | K20: ALLE | M20: 5

Sheet NK-Anpassung
A1: Anpassung | B1: Stä-Malus | C1: AT- | D1: PA- | E1: WK | F1: Min.Stä. 1H | G1: Min.Stä. 2H | H1: Preis | I1: Klingen Brecher | J1: Klingen Schutz | K1: Volk | L1: Art/Specials | N1: Arbeitszeit/d
A2: Von der Stange | H2: 1 | K2: Standard | M2: 0 | N2: 0
A3: angepasst | C3: 1 | D3: 1 | G3: -2 | H3: 2 | K3: ALLE | M3: 6 | N3: 1
A4: Perfekt angepasst | C4: 2 | D4: 2 | G4: -4 | H4: 5 | K4: ALLE | M4: 12 | N4: 2

Sheet NK-Schaftmaterial
A1: Verstärkung des Schafts | B1: Stä-Malus | C1: AT- | D1: PA- | E1: WK | F1: Min.Stä. 1H | G1: Min.Stä. 2H | H1: Preis/m | I1: Klingen Brecher | J1: Klingen Schutz | K1: Volk | L1: Art/Specials
A2: Standard | M2: 0
A3: Eisen Verstärkt | C3: -1 | D3: -1 | G3: 2 | H3: 37.5 | J3: 2 | K3: ALLE | M3: 10 | N3: 0.5
A4: Eisen Voll | C4: -2 | D4: -2 | G4: 3 | H4: 275 | J4: 3 | K4: ALLE | M4: 10 | N4: 0.5
A5: Stahl Verstärkt | C5: -1 | D5: -1 | G5: 2 | H5: 93.75 | J5: 3 | K5: ALLE | M5: 12 | N5: 0.5
A6: Stahl Voll | C6: -2 | D6: -2 | G6: 3 | H6: 687.5 | J6: 4 | K6: ALLE | M6: 12 | N6: 0.5
A7: Qualitätsstahl | C7: -1 | D7: -1 | G7: 2 | H7: 131.25 | J7: 4 | K7: ALLE | M7: 18 | N7: 0.5
A8: Qualitätsstahl Voll | C8: -2 | D8: -2 | G8: 3 | H8: 962.5 | J8: 5 | K8: ALLE | M8: 18 | N8: 0.5
A9: Faltstahl Verstärkt | C9: -1 | D9: -1 | G9: 2 | H9: 187.5 | J9: 5 | K9: ALLE | M9: 30 | N9: 0.5
A10: Faltstahl Voll | C10: -2 | D10: -2 | G10: 3 | H10: 1375 | J10: 6 | K10: ALLE | M10: 30 | N10: 0.5
A11: Mithril Verstärkt | C11: 0 | D11: -1 | G11: 1 | H11: 1875 | J11: 2 | K11: ALLE | M11: 20 | N11: 0.5
A12: Mithril Voll | C12: -1 | D12: -1 | G12: 1 | H12: 13750 | J12: 3 | K12: ALLE | M12: 20 | N12: 0.5
A13: Adamandit Verst. | C13: -1 | D13: -1 | G13: 2 | H13: 187500 | J13: 6 | K13: ALLE | M13: 120 | N13: 0.5
A14: Adamantit Voll | C14: -2 | D14: -2 | G14: 3 | H14: 137500 | J14: 7 | K14: ALLE | M14: 120 | N14: 0.5
... A16: Bronze Voll | C16: -2 | D16: -2 | G16: 3 | H16: 137.5 | J16: 2 | K16: ALLE | M16: 5 | N16: 0.5

Sheet NK-Fertigung
A1: Fertigung | B1: Stä-Malus | C1: AT- | D1: PA- | E1: WK | F1: Min.Stä. 1H | G1: Min.Stä. 2H | H1: Preis | I1: Klingen Brecher | J1: Klingen Schutz | K1: Volk | L1: Art/Specials
A2: Ausschuss | H2: 1.5 | I2: -3 | J2: -6 | K2: ALLE | M2: -6
A3: Goblin Massenfab. | H3: 2 | I3: -2 | J3: -3 | K3: Goblin | M3: -4
A4: Massenfabrikation | H4: 4 | I4: -1 | J4: -1 | K4: ALLE | M4: -3
A5: Gesellenarbeit | H5: 6 | K5: Standard | M5: 0
A6: Meisterarbeit | H6: 65 | I6: 1 | J6: 1 | K6: ALLE | M6: 6
A7: Großmeisterarbeit | H7: 71 | I7: 2 | J7: 2 | K7: ALLE | M7: 12
A8: Einzelstück | H8: 142 | I8: 3 | J8: 3 | K8: ALLE | M8: 24

Sheet NK-Waffen-Basis
A1: Hauptfertigkeit | B1: Spezialisierung | C1: Waffe | D1: Ini | E1: WK-Basis | F1: Schadenswuerfel-1 | G1: Schadenswuerfel-2 | H1: Staerke-Teiler | I1: Staerke-Malus-Basis | J1: RB | K1: AT-Basis | L1: PA-Basis | M1: Min-Staerke-1H-Basis | N1: Min-Staerke-2H-Basis | O1: Laenge-m | P1: Tarnung | Q1: Art-Specials | R1: Klingenbrecher-Basis | S1: Klingenschutz-Basis | T1: Rezept-Mod-Basis | U1: Materialpreis-Faktor | V1: Arbeitszeit-Tag-Basis | W1: Volk | X1: Fert-Spez-Maximum | Y1: RS-Basis | Z1: Preis-Basis
A2: Unbewaffnet | B2: Armklingen | C2: Armklingen | D2: 5 | E2: 3 | F2: W10 | G2: W6 | H2: 3 | I2: -6 | J2: 0 | K2: -2 | L2: -4 | M2: 8 | O2: 0.5 | P2: 0 | Q2: Schnell | R2: 12 | S2: 14 | T2: 10 | U2: 0.7 | V2: 3
A3: Stichwaffen | B3: Fechtwaffen | C3: Armklingen | D3: 5 | E3: 3 | F3: W10 | G3: W6 | H3: 3 | I3: -6 | J3: 0 | K3: -2 | L3: -4 | M3: 8 | O3: 0.5 | P3: 0 | Q3: Schnell | R3: 12 | S3: 14 | T3: 10 | U3: 0.7 | V3: 3
A4: Unbewaffnet | B4: Armklingen | C4: Armklingen elfisch | D4: 5 | E4: 2.5 | F4: W12 | G4: W4 | H4: 3 | I4: -6 | J4: 0 | K4: -2 | L4: -3 | M4: 7 | O4: 0.5 | P4: 0 | Q4: Schnell | R4: 12 | S4: 13 | T4: 12 | U4: 0.6 | V4: 4
A5: Hiebwaffen | B5: Äxte | C5: Axt | D5: 7 | E5: 6 | F5: W20 | H5: 2 | I5: -6 | J5: 0 | K5: -4 | L5: -5 | M5: 17 | N5: 10 | O5: 0.72 | P5: 3 | Q5: Holzschaft | R5: 17 | S5: 7 | T5: 8 | U5: 1.8 | V5: 1.5
A6: Stichwaffen | B6: Fechtwaffen | C6: Bajonett abgepflanzt | D6: 6 | E6: 3 | F6: W12 | G6: W4 | H6: 5 | I6: -3 | J6: 0 | K6: -3 | L6: -5 | M6: 7 | N6: 5 | O6: 0.6 | P6: 4 | R6: 9 | S6: 15 | T6: 5 | U6: 0.6 | V6: 1
A7: Stangenwaffen | B7: Speere | C7: Bajonett aufgepflanzt | D7: 21 | E7: 3 | F7: W12 | G7: W4 | H7: 5 | I7: -4 | J7: 0 | K7: -5 | L7: -5 | M7: wie Feuerwaffe*2 | N7: wie Feuerwaffe | O7: 2 | P7: 4 | R7: 3 | S7: 8 | T7: 5 | U7: 0.6 | V7: 1
A8: Hiebwaffen | B8: Beidhand-Hiebwaffen | C8: Barbarendoppelaxt | D8: 14 | E8: 8 | F8: W20 | G8: [2W12] | H8: 1.5 | I8: -16 | J8: 0 | K8: -7 | L8: -7 | M8: 36 | N8: 20 | O8: 1.4 | P8: -- | Q8: Holzschaft | R8: 23 | S8: 8 | T8: 24 | U8: 3.5 | V8: 2.5
A9: Klingenwaffen | B9: Schwerter | C9: Barbarenschwert | D9: 11 | E9: 6 | F9: W10 | G9: W8 | H9: 2 | I9: -5 | J9: 0 | K9: -5 | L9: -5 | M9: 16 | N9: 12 | O9: 1.1 | P9: -- | R9: 14 | S9: 15 | T9: 16 | U9: 1.5 | V9: 4
A10: Klingenwaffen | B10: Zweihänder | C10: Barbarenschwert | D10: 11 | E10: 6 | F10: W10 | G10: W8 | H10: 2 | I10: -5 | J10: 0 | K10: -5 | L10: -5 | M10: 16 | N10: 12 | O10: 1.1 | P10: -- | R10: 14 | S10: 15 | T10: 16 | U10: 1.5 | V10: 4
A11: Klingenwaffen | B11: Schwerter | C11: Bastardschwert | D11: 13 | E11: 6 | F11: W15 | G11: W10 | H11: 2 | I11: -8 | J11: 0 | K11: -5 | L11: -4 | M11: 20 | N11: 13 | O11: 1.3 | P11: -- | R11: 14 | S11: 15 | T11: 19 | U11: 2 | V11: 4
A12: Klingenwaffen | B12: Zweihänder | C12: Bastardschwert | D12: 13 | E12: 6 | F12: W15 | G12: W10 | H12: 2 | I12: -8 | J12: 0 | K12: -5 | L12: -4 | M12: 20 | N12: 13 | O12: 1.3 | P12: -- | R12: 14 | S12: 15 | T12: 19 | U12: 2 | V12: 4
A13: Klingenwaffen | B13: Zweihänder | C13: Bat'leth orkisch | D13: 11 | E13: 5.5 | F13: W10 | G13: W10 | H13: 2 | I13: -8 | J13: 0 | K13: -3 | L13: -3 | M13: 15 | N13: 9 | O13: 1.16 | P13: -- | Q13: Schnell | R13: 14 | S13: 14 | T13: 24 | U13: 3 | V13: 8
A14: Stangenwaffen | B14: Stäbe | C14: Bat'leth kurz | D14: 10 | E14: 4 | F14: W12 | G14: W6 | H14: 2 | I14: -8 | J14: 0 | K14: -3 | L14: -4 | M14: 13 | N14: 8 | O14: 1 | P14: 0 | R14: 14 | S14: 14 | T14: 20 | U14: 2 | V14: 8
A15: Klingenwaffen | B15: Zweihänder | C15: Bat'leth kurz | D15: 10 | E15: 4 | F15: W12 | G15: W6 | H15: 2 | I15: -8 | J15: 0 | K15: -3 | L15: -4 | M15: 13 | N15: 8 | O15: 1 | P15: 0 | R15: 14 | S15: 14 | T15: 20 | U15: 2 | V15: 8
A16: Hiebwaffen | B16: Äxte | C16: Beil | D16: 4 | E16: 5 | F16: W20 | H16: 3 | I16: -5 | J16: 0 | K16: -5 | L16: -5 | M16: 12 | N16: 8 | O16: 0.4 | P16: 6 | Q16: Holzschaft | R16: 16 | S16: 7 | T16: 6 | U16: 0.6 | V16: 1
A17: Hiebwaffen | B17: Beidhand-Hiebwaffen | C17: Berdysch | D17: 13 | E17: 6.5 | F17: W20 | G17: W6 | H17: 2 | I17: -8 | J17: 0 | K17: -6 | L17: -5 | M17: 24 | N17: 14 | O17: 1.4 | P17: -- | Q17: Holzschaft | R17: 18 | S17: 7 | T17: 18 | U17: 2 | V17: 2
A18: Stangenwaffen | B18: Hellebarden | C18: Berdysch | D18: 13 | E18: 6.5 | F18: W20 | G18: W6 | H18: 2 | I18: -8 | J18: 0 | K18: -6 | L18: -5 | M18: 24 | N18: 14 | O18: 1.4 | P18: -- | Q18: Holzschaft | R18: 18 | S18: 7 | T18: 18 | U18: 2 | V18: 2
A19: Klingenwaffen | B19: Schwerter | C19: Breitschwert | D19: 9 | E19: 6 | F19: W10 | G19: W10 | H19: 3 | I19: -4 | J19: 0 | K19: -4 | L19: -4 | M19: 14 | N19: 10 | O19: 0.9 | P19: 2 | R19: 16 | S19: 15 | T19: 14 | U19: 1 | V19: 4
A20: Klingenwaffen | B20: Zweihänder | C20: Claymore | D20: 16 | E20: 7.5 | F20: W15 | G20: W12 | H20: 1.5 | I20: -11 | J20: 0 | K20: -7 | L20: -6 | M20: 28 | N20: 16 | O20: 1.6 | P20: -- | R20: 17 | S20: 13 | T20: 24 | U20: 2.5 | V20: 5
A21: Klingenwaffen | B21: Zweihänder | C21: Dai Katana | D21: 14 | E21: 6.5 | F21: 2W12 | H21: 2 | I21: -8 | J21: 0 | K21: -4 | L21: -4 | M21: 22 | N21: 13 | O21: 1.35 | P21: -- | R21: 16 | S21: 14 | T21: 25 | U21: 1.2 | V21: 5
A22: Stichwaffen | B22: Fechtwaffen | C22: Degen | D22: 13 | E22: 3.5 | F22: W15 | H22: 7 | I22: -2 | J22: 0 | K22: -2 | L22: 0 | M22: 9 | N22: 6 | O22: 1.2 | P22: 1 | R22: 7 | S22: 14 | T22: 18 | U22: 0.75 | V22: 4
A23: Stichwaffen | B23: Dolche | C23: Dolch | D23: 3 | E23: 2 | F23: W15 | H23: 5 | I23: -3 | J23: 0 | K23: -1 | L23: -6 | M23: 6 | N23: 4 | O23: 0.3 | P23: 8 | R23: 12 | S23: 17 | T23: 5 | U23: 0.3 | V23: 1
A24: Stichwaffen | B24: Dolche | C24: Dolch ork, Blutrinne | D24: 3 | E24: 1 | F24: W15 | H24: 6 | I24: -3 | J24: 0 | K24: -1 | L24: -6 | M24: 6 | N24: 4 | O24: 0.3 | P24: 8 | Q24: Starke Blutung (x2) | R24: 12 | S24: 15 | T24: 7 | U24: 0.4 | V24: 2
A25: Stichwaffen | B25: Dolche | C25: Dolch orkisch, breit | D25: 3 | E25: 2 | F25: W15 | H25: 4 | I25: -4 | J25: 0 | K25: -2 | L25: -5 | M25: 7 | N25: 5 | O25: 0.3 | P25: 7 | R25: 12 | S25: 18 | T25: 5 | U25: 0.4 | V25: 1
A26: Stichwaffen | B26: Dolche | C26: Dolch orkisch, mit 3 eingedrehten Klingen | D26: 3 | E26: 3 | F26: W20 | H26: 3 | I26: -7 | J26: 0 | K26: -2 | L26: -5 | M26: 10 | N26: 8 | O26: 0.35 | P26: 4 | R26: 13 | S26: 18 | T26: 15 | U26: 0.5 | V26: 4
A27: Hiebwaffen | B27: Äxte | C27: Doppelaxt leicht | D27: 8 | E27: 6 | F27: W20 | H27: 3 | I27: -4 | J27: 0 | K27: -5 | L27: -6 | M27: 20 | N27: 14 | O27: 0.8 | P27: 0 | Q27: Holzschaft | R27: 17 | S27: 8 | T27: 15 | U27: 2.2 | V27: 2.5
A28: Hiebwaffen | B28: Äxte | C28: Doppelaxt zwergisch | D28: 9 | E28: 7.5 | F28: W20 | G28: W15 | H28: 2 | I28: -12 | J28: 0 | K28: -7 | L28: -6 | M28: 28 | N28: 16 | O28: 0.9 | P28: -- | Q28: Holzschaft | R28: 22 | S28: 8 | T28: 19 | U28: 2.5 | V28: 3
A29: Hiebwaffen | B29: Äxte | C29: Doppelbeil Zw. kurz | D29: 5 | E29: 6 | F29: W20 | G29: [2W10] | H29: 3 | I29: -11 | J29: 0 | K29: -5 | L29: -4 | M29: 18 | N29: 12 | O29: 0.55 | P29: 3 | Q29: Holzschaft | R29: 18 | S29: 8 | T29: 19 | U29: 1.5 | V29: 3
A30: Stangenwaffen | B30: Hellebarden | C30: Doppelblatthellebarde | D30: 18 | E30: 7 | F30: W20 | G30: W4 | H30: 2 | I30: -9 | J30: 0 | K30: -6 | L30: -6 | M30: 36 | N30: 16 | O30: 1.8 | P30: -- | Q30: Holzschaft | R30: 17 | S30: 7 | T30: 19 | U30: 3 | V30: 5
A31: Stangenwaffen | B31: Stäbe | C31: Doppelhellebarde (Kampfstab 2 Hellebarden) | D31: 10 | E31: 6 | F31: W15 | G31: W8 | H31: 3 | I31: -7 | J31: 0 | K31: -4 | L31: -4 | M31: 46 | N31: 18 | O31: 1.8 | P31: -- | Q31: Holzschaft | R31: 16 | S31: 7 | T31: 16 | U31: 3 | V31: 5
A32: Stangenwaffen | B32: Hellebarden | C32: Doppelsense | D32: 10 | E32: 5 | F32: W15 | G32: W6 | H32: 4 | I32: -6 | J32: 0 | K32: -5 | L32: -5 | M32: 33 | N32: 11 | O32: 1.8 | P32: -- | Q32: Holzschaft, Schnell | R32: 12 | S32: 6 | T32: 12 | U32: 1 | V32: 1
A33: Klingenwaffen | B33: Zweihänder | C33: Doppelsense | D33: 10 | E33: 5 | F33: W15 | G33: W6 | H33: 4 | I33: -6 | J33: 0 | K33: -5 | L33: -5 | M33: 33 | N33: 11 | O33: 1.8 | P33: -- | Q33: Holzschaft, Schnell | R33: 12 | S33: 6 | T33: 12 | U33: 1 | V33: 1
A34: Hiebwaffen | B34: Beidhand-Hiebwaffen | C34: Dornenkeule troll, | D34: 16 | E34: 8 | F34: W15 | G34: W12 | H34: 1.5 | I34: -11 | J34: 2 | K34: -6 | L34: -7 | M34: 35 | N34: 20 | O34: 1.8 | P34: -- | Q34: Holzschaft | R34: 14 | S34: 11 | T34: 1 | U34: 0.25 | V34: 1
A35: Unbewaffnet | B35: Peitschen | C35: Dornenpeitsche | D35: 28 | E35: 0 | F35: W4 | G35: W4 | H35: 5 | I35: -1 | J35: 0 | K35: -7 | L35: -15 | M35: 10 | N35: 7 | O35: 3 | P35: 6 | R35: 1 | S35: 7 | T35: 7 | U35: 0.1 | V35: 0.5
A36: Unbewaffnet | B36: Schild | C36: Drachenschild | E36: 11 | F36: 2W8 | H36: 3 | I36: -5 | J36: 0 | K36: -7 | L36: 9 | M36: 19 | P36: -- | R36: 15 | S36: 13 | T36: 15 | Y36: 17 | Z36: 600
A37: Unbewaffnet | B37: Armklingen | C37: Drei Langklauen | D37: 4 | E37: 3 | F37: W8 | G37: W6 | H37: 3 | I37: -5 | J37: 0 | K37: -3 | L37: -6 | M37: 8 | O37: 0.4 | P37: 0 | R37: 7 | S37: 11 | T37: 8 | U37: 0.4 | V37: 1
A38: Unbewaffnet | B38: Schild | C38: Dreiecksschild | E38: 8 | F38: W8 | G38: W6 | H38: 3 | I38: -5 | J38: 0 | K38: -6 | L38: 7 | M38: 17 | P38: -- | R38: 15 | S38: 15 | T38: 15 | Y38: 16 | Z38: 400
A39: Unbewaffnet | B39: Schild | C39: Dreiecksschild klein | E39: 6 | F39: W8 | G39: W6 | H39: 3 | I39: -5 | J39: 0 | K39: -5 | L39: 6 | M39: 15 | P39: -- | R39: 15 | S39: 15 | T39: 15 | Y39: 15 | Z39: 300
A40: Stangenwaffen | B40: Speere | C40: Dreizack | D40: 18 | E40: 5 | F40: W12 | G40: W8 | H40: 3 | I40: -6 | J40: 0 | K40: -5 | L40: -3 | M40: 22 | N40: 12 | O40: 1.8 | P40: -- | Q40: Holzschaft | R40: 7 | S40: 7 | T40: 5 | U40: 1 | V40: 1.5
A41: Hiebwaffen | B41: Stumpfe Hiebwaffen | C41: Dreschflegel eisenbeschlagen | D41: 16 | E41: 4.5 | F41: W10 | G41: W6 | H41: 3 | I41: -3 | J41: 0 | K41: -6 | L41: -7 | M41: 30 | N41: 10 | O41: 1.6 | P41: -- | Q41: Holzschaft | R41: 3 | S41: 6 | T41: 4 | U41: 0.2 | V41: 1
A42: Klingenwaffen | B42: Schwerter | C42: Eineinhalbhänder | D42: 12 | E42: 6 | F42: W12 | G42: W10 | H42: 2 | I42: -8 | J42: 0 | K42: -5 | L42: -3 | M42: 15 | N42: 11 | O42: 1.2 | P42: 0 | R42: 15 | S42: 14 | T42: 19 | U42: 1.5 | V42: 4
A43: Klingenwaffen | B43: Zweihänder | C43: Eineinhalbhänder | D43: 12 | E43: 6 | F43: W12 | G43: W10 | H43: 2 | I43: -8 | J43: 0 | K43: -5 | L43: -3 | M43: 15 | N43: 11 | O43: 1.2 | P43: 0 | R43: 15 | S43: 14 | T43: 19 | U43: 1.5 | V43: 4
A44: Unbewaffnet | B44: Rüstungsmodifikator | C44: Eisenkappenstiefel | D44: 0 | E44: 0 | F44: W6 | G44: W4 | H44: 3 | I44: -5 | J44: 0 | K44: -3 | L44: -11 | M44: 5 | O44: 0.02 | P44: 5 | R44: 5 | S44: 30 | T44: X | U44: x | V44: x
A45: Hiebwaffen | B45: Stumpfe Hiebwaffen | C45: Eisenkeule schwer | D45: 14 | E45: 8 | F45: W12 | G45: W12 | H45: 1.5 | I45: -10 | J45: 0 | K45: -6 | L45: -7 | M45: 32 | N45: 18 | O45: 1.5 | P45: -- | Q45: Holzschaft | R45: 14 | S45: 11 | T45: 4 | U45: 1 | V45: 1
A46: Hiebwaffen | B46: Stumpfe Hiebwaffen | C46: Eisenkugelstab | D46: 7 | E46: 3 | F46: W6 | G46: W6 | H46: 3 | I46: -4 | J46: 0 | K46: -4 | L46: -4 | M46: 9 | N46: 6 | O46: 0.7 | P46: 4 | Q46: Holzschaft | R46: 7 | S46: 6 | T46: 4 | U46: 1 | V46: 1
A47: Hiebwaffen | B47: Stumpfe Hiebwaffen | C47: Eisenschlegel | D47: 14 | E47: 6 | F47: W10 | G47: W10 | H47: 2 | I47: -7 | J47: 0 | K47: -6 | L47: -6 | M47: 26 | N47: 16 | O47: 1.4 | P47: -- | Q47: Holzschaft | R47: 12 | S47: 8 | T47: 4 | U47: 1.5 | V47: 1.5
A48: Hiebwaffen | B48: Stumpfe Hiebwaffen | C48: Eisenstange | D48: 7 | E48: 4 | F48: W6 | G48: W6 | H48: 3 | I48: -4 | J48: 0 | K48: -4 | L48: -4 | M48: 11 | N48: 8 | O48: 0.7 | P48: 4 | R48: 7 | S48: 10 | T48: 0 | U48: 0.7 | V48: 0.1
A49: Hiebwaffen | B49: Äxte | C49: Enterbeil | D49: 7 | E49: 4 | F49: [2W12] | G49: W6 | H49: 4 | I49: -6 | J49: 0 | K49: -4 | L49: -4 | M49: 10 | N49: 7 | O49: 0.76 | P49: 3 | Q49: Holzschaft | R49: 16 | S49: 7 | T49: 7 | U49: 0.65 | V49: 1
A50: Hiebwaffen | B50: Kettenwaffen | C50: Enterhaken am Seil | D50: 10 | E50: 5 | F50: W8 | G50: W4 | H50: 4 | I50: -5 | J50: 0 | K50: -8 | L50: -15 | M50: 13 | N50: 10 | O50: 1.5 | P50: 0 | R50: 2 | S50: 4 | T50: 5 | U50: 2 | V50: 0.5
A51: Hiebwaffen | B51: Äxte | C51: Enterhaken ohne Seil | D51: 2 | E51: 5 | F51: W8 | G51: W4 | H51: 4 | I51: -5 | J51: 0 | K51: -5 | L51: -8 | M51: 11 | N51: 8 | O51: 0.2 | P51: 0 | R51: 7 | S51: 10 | T51: 5 | U51: 2 | V51: 0.5
A52: Unbewaffnet | B52: Messer | C52: Enterhaken ohne Seil | D52: 2 | E52: 5 | F52: W8 | G52: W4 | H52: 4 | I52: -5 | J52: 0 | K52: -5 | L52: -8 | M52: 11 | N52: 8 | O52: 0.2 | P52: 0 | R52: 7 | S52: 10 | T52: 5 | U52: 2 | V52: 0.5
A53: Klingenwaffen | B53: Kurzschwerter | C53: Entermesser | D53: 8 | E53: 4 | F53: W8 | G53: W8 | H53: 3 | I53: -4 | J53: 0 | K53: -2 | L53: -3 | M53: 9 | N53: 6 | O53: 0.8 | P53: 4 | R53: 14 | S53: 14 | T53: 12 | U53: 0.8 | V53: 3
A54: Klingenwaffen | B54: Schwerter | C54: Entermesser | D54: 8 | E54: 4 | F54: W8 | G54: W8 | H54: 3 | I54: -4 | J54: 0 | K54: -2 | L54: -3 | M54: 9 | N54: 6 | O54: 0.8 | P54: 4 | R54: 14 | S54: 14 | T54: 12 | U54: 0.8 | V54: 3
A55: Unbewaffnet | B55: Schild | C55: Faustschild/Buckler | E55: 4 | F55: W8 | G55: W4 | H55: 2 | I55: -8 | K55: -2 | L55: 2 | M55: 13 | P55: -- | Q55: Keine FK-Parade | R55: 14 | S55: 16 | T55: 15 | Y55: 12 | Z55: 100
A56: Klingenwaffen | B56: Zweihänder | C56: Flamberge | D56: 17 | E56: 8 | F56: 2W15 | H56: 1.5 | I56: -12 | J56: 0 | K56: -7 | L56: -7 | M56: 36 | N56: 18 | O56: 1.8 | P56: -- | R56: 17 | S56: 13 | T56: 28 | U56: 2.5 | V56: 8
A57: Hiebwaffen | B57: Äxte | C57: Fleischerbeil | D57: 4 | E57: 3.5 | F57: W20 | H57: 4 | I57: -5 | J57: 0 | K57: -6 | L57: -6 | M57: 7 | N57: 3 | O57: 0.4 | P57: 6 | Q57: Holzschaft | R57: 13 | S57: 6 | T57: 5 | U57: 0.6 | V57: 0.5
A58: Stichwaffen | B58: Fechtwaffen | C58: Florett | D58: 13 | E58: 2 | F58: W8 | G58: W4 | H58: 20 | I58: -1 | J58: 0 | K58: -1 | L58: 1 | M58: 6 | O58: 1.1 | P58: 2 | Q58: Schnell | R58: 0 | S58: 20 | T58: 18 | U58: 0.7 | V58: 4
A59: Stichwaffen | B59: Fechtwaffen | C59: Gladius | D59: 8 | E59: 4 | F59: W12 | G59: W4 | H59: 4 | I59: -4 | J59: 0 | K59: -3 | L59: -4 | M59: 8 | N59: 6 | O59: 0.75 | P59: 5 | R59: 15 | S59: 15 | T59: 10 | U59: 0.75 | V59: 3
A60: Klingenwaffen | B60: Kurzschwerter | C60: Gladius | D60: 8 | E60: 4 | F60: W12 | G60: W4 | H60: 4 | I60: -4 | J60: 0 | K60: -3 | L60: -4 | M60: 8 | N60: 6 | O60: 0.75 | P60: 5 | R60: 15 | S60: 15 | T60: 10 | U60: 0.75 | V60: 3
A61: Stichwaffen | B61: Fechtwaffen | C61: Gladius mit Griffkorb | D61: 7 | E61: 4 | F61: W12 | G61: W4 | H61: 4 | I61: -4 | J61: 0 | K61: -3 | L61: -3 | M61: 9 | N61: 6 | O61: 0.75 | P61: 3 | R61: 15 | S61: 15 | T61: 11 | U61: 0.8 | V61: 3.5
A62: Klingenwaffen | B62: Kurzschwerter | C62: Gladius mit Griffkorb | D62: 7 | E62: 4 | F62: W12 | G62: W4 | H62: 4 | I62: -4 | J62: 0 | K62: -3 | L62: -3 | M62: 9 | N62: 6 | O62: 0.75 | P62: 3 | R62: 15 | S62: 15 | T62: 11 | U62: 0.8 | V62: 3.5
A63: Stichwaffen | B63: Fechtwaffen | C63: Gladius kurz | D63: 4 | E63: 3 | F63: W12 | G63: W4 | H63: 4 | I63: -4 | J63: 0 | K63: -2 | L63: -5 | M63: 8 | N63: 5 | O63: 0.45 | P63: 6 | R63: 13 | S63: 18 | T63: 9 | U63: 0.5 | V63: 3
A64: Klingenwaffen | B64: Kurzschwerter | C64: Gladius kurz | D64: 4 | E64: 3 | F64: W12 | G64: W4 | H64: 4 | I64: -4 | J64: 0 | K64: -2 | L64: -5 | M64: 8 | N64: 5 | O64: 0.45 | P64: 6 | R64: 13 | S64: 18 | T64: 9 | U64: 0.5 | V64: 3
A65: Stangenwaffen | B65: Speere | C65: Glefe | D65: 29 | E65: 6 | F65: W15 | G65: W10 | H65: 3 | I65: -7 | J65: 0 | K65: -7 | L65: -5 | M65: 26 | N65: 14 | O65: 2.7 | P65: -- | Q65: Holzschaft | R65: 16 | S65: 7 | T65: 16 | U65: 1.1 | V65: 3.5
A66: Hiebwaffen | B66: Äxte | C66: Hacke | D66: 14 | E66: 4.5 | F66: W15 | G66: W4 | H66: 3 | I66: -5 | J66: 2 | K66: -7 | L66: -7 | M66: 14 | N66: 8 | O66: 1.4 | P66: 0 | Q66: Holzschaft | R66: 10 | S66: 4 | T66: 3 | U66: 0.3 | V66: 0.25
A67: Stangenwaffen | B67: Stäbe | C67: Hacke | D67: 14 | E67: 4.5 | F67: W15 | G67: W4 | H67: 3 | I67: -5 | J67: 2 | K67: -7 | L67: -7 | M67: 14 | N67: 8 | O67: 1.4 | P67: 0 | Q67: Holzschaft | R67: 10 | S67: 4 | T67: 3 | U67: 0.3 | V67: 0.25
A68: Stichwaffen | B68: Dolche | C68: Hakendolch | D68: 3 | E68: 2 | F68: W12 | H68: 5 | I68: -2 | J68: 0 | K68: -1 | L68: -6 | M68: 6 | N68: 4 | O68: 0.35 | P68: 6 | R68: 12 | S68: 17 | T68: 7 | U68: 0.3 | V68: 1
A69: Hiebwaffen | B69: Stumpfe Hiebwaffen | C69: Hammer groß | D69: 3 | E69: 5 | F69: W10 | G69: W6 | H69: 2 | I69: -7 | J69: 0 | K69: -5 | L69: -8 | M69: 10 | N69: 7 | O69: 0.3 | P69: 7 | Q69: Holzschaft | R69: 9 | S69: 6 | T69: 4 | U69: 0.7 | V69: 0.25
A70: Hiebwaffen | B70: Stumpfe Hiebwaffen | C70: Hammer klein | D70: 2 | E70: 2.5 | F70: W8 | G70: W4 | H70: 3 | I70: -5 | J70: 0 | K70: -6 | L70: -9 | M70: 6 | O70: 0.25 | P70: 8 | Q70: Holzschaft | R70: 8 | S70: 5 | T70: 3 | U70: 0.4 | V70: 0.25
A71: Stangenwaffen | B71: Hellebarden | C71: Handhellebarde | D71: 13 | E71: 5 | F71: W20 | G71: W6 | H71: 3 | I71: -8 | J71: 0 | K71: -5 | L71: -4 | M71: 25 | N71: 11 | O71: 1.2 | P71: -- | Q71: Holzschaft | R71: 17 | S71: 7 | T71: 16 | U71: 1.5 | V71: 4
A72: Klingenwaffen | B72: Kurzschwerter | C72: Haumesser | D72: 5 | E72: 2.5 | F72: W6 | G72: W6 | H72: 4 | I72: -2 | J72: 0 | K72: -1 | L72: -5 | M72: 6 | N72: 4 | O72: 0.5 | P72: 6 | R72: 14 | S72: 11 | T72: 10 | U72: 0.8 | V72: 3
A73: Stangenwaffen | B73: Hellebarden | C73: Hellebarde lang, 3m | D73: 32 | E73: 6 | F73: W20 | G73: W12 | H73: 2 | I73: -14 | J73: 0 | K73: -8 | L73: -7 | M73: 32 | N73: 14 | O73: 3 | P73: -- | Q73: Holzschaft | R73: 17 | S73: 7 | T73: 16 | U73: 1.5 | V73: 4
A74: Stangenwaffen | B74: Hellebarden | C74: Hellebarde leicht, 2m | D74: 22 | E74: 5 | F74: W15 | G74: W8 | H74: 3 | I74: -7 | J74: 0 | K74: -5 | L74: -5 | M74: 26 | N74: 12 | O74: 2 | P74: -- | Q74: Holzschaft | R74: 17 | S74: 7 | T74: 16 | U74: 1.5 | V74: 4
A75: Stichwaffen | B75: Dolche | C75: Hiebdolch schwer | D75: 3 | E75: 2 | F75: W10 | G75: W4 | H75: 5 | I75: -3 | J75: 0 | K75: -1 | L75: -5 | M75: 6 | N75: 4 | O75: 0.35 | P75: 6 | R75: 13 | S75: 18 | T75: 5 | U75: 0.4 | V75: 1
A76: Stichwaffen | B76: Dolche | C76: Hiebdolch kurz | D76: 3 | E76: 1 | F76: W10 | G76: W4 | H76: 5 | I76: -4 | J76: 0 | K76: -1 | L76: -6 | M76: 5 | N76: 3 | O76: 0.25 | P76: 9 | R76: 12 | S76: 18 | T76: 5 | U76: 0.25 | V76: 1
A77: Unbewaffnet | B77: Messer | C77: Hiebdolch kurz | D77: 3 | E77: 1 | F77: W10 | G77: W4 | H77: 5 | I77: -4 | J77: 0 | K77: -1 | L77: -6 | M77: 5 | N77: 3 | O77: 0.25 | P77: 9 | R77: 12 | S77: 18 | T77: 5 | U77: 0.25 | V77: 1
A78: Stichwaffen | B78: Fechtwaffen | C78: Hirschfänger (rapierartig) | D78: 8 | E78: 4 | F78: W15 | G78: W4 | H78: 4 | I78: -5 | J78: 0 | K78: -2 | L78: -3 | M78: 8 | N78: 6 | O78: 0.7 | P78: 4 | R78: 14 | S78: 16 | T78: 18 | U78: 0.8 | V78: 4
A79: Hiebwaffen | B79: Äxte | C79: Holzfälleraxt | D79: 8 | E79: 7 | F79: W20 | G79: W4 | H79: 1.5 | I79: -11 | J79: 0 | K79: -5 | L79: -5 | M79: 28 | N79: 12 | O79: 0.8 | P79: 0 | Q79: Holzschaft | R79: 17 | S79: 6 | T79: 8 | U79: 2 | V79: 1.5
A80: Stichwaffen | B80: Dolche | C80: Jagdmesser | D80: 3 | E80: 0 | F80: W10 | H80: 6 | I80: -2 | J80: 0 | K80: -1 | L80: -8 | M80: 3 | O80: 0.3 | P80: 11 | R80: 11 | S80: 16 | T80: 4 | U80: 0.3 | V80: 1
A81: Unbewaffnet | B81: Messer | C81: Jagdmesser | D81: 3 | E81: 0 | F81: W10 | H81: 6 | I81: -2 | J81: 0 | K81: -1 | L81: -8 | M81: 3 | O81: 0.3 | P81: 11 | R81: 11 | S81: 16 | T81: 4 | U81: 0.3 | V81: 1
A82: Hiebwaffen | B82: Beidhand-Hiebwaffen | C82: junge Birke aus Eisen (KEINE Listenwaffe) | D82: 28 | E82: 15 | F82: W30 | G82: W30 | H82: 1 | I82: -36 | J82: 0 | K82: -9 | L82: -9 | M82: 128 | N82: 64 | O82: 3 | P82: -- | Q82: Holzschaft | R82: 32 | S82: 32 | T82: 10 | U82: 7000 | V82: 4
A83: Stichwaffen | B83: Dolche | C83: Kampfmesser | D83: 3 | E83: 1 | F83: W12 | H83: 6 | I83: -2 | J83: 0 | K83: -1 | L83: -7 | M83: 4 | O83: 0.28 | P83: 10 | R83: 11 | S83: 17 | T83: 4 | U83: 0.4 | V83: 1
A84: Unbewaffnet | B84: Messer | C84: Kampfmesser | D84: 3 | E84: 1 | F84: W12 | H84: 6 | I84: -2 | J84: 0 | K84: -1 | L84: -7 | M84: 4 | O84: 0.28 | P84: 10 | R84: 11 | S84: 17 | T84: 4 | U84: 0.4 | V84: 1
A85: Stangenwaffen | B85: Stäbe | C85: Kampfstab eisenbeschlagen | D85: 11 | E85: 3.5 | F85: W8 | G85: W4 | H85: 4 | I85: -2 | J85: 0 | K85: -2 | L85: -2 | M85: 18 | N85: 7 | O85: 1.8 | P85: -- | Q85: Holzschaft, Schnell | R85: 2 | S85: 7 | T85: 3 | U85: 0.5 | V85: 0.25
A86: Stangenwaffen | B86: Stäbe | C86: Kampfstab Eisenkolben | D86: 11 | E86: 4 | F86: W8 | G86: W6 | H86: 4 | I86: -2 | J86: 0 | K86: -3 | L86: -3 | M86: 22 | N86: 11 | O86: 1.8 | P86: -- | Q86: Holzschaft, Schnell | R86: 3 | S86: 7 | T86: 4 | U86: 1 | V86: 1
A87: Stangenwaffen | B87: Stäbe | C87: Kampfstab Eisenspitzen | D87: 11 | E87: 4 | F87: W10 | G87: W4 | H87: 5 | I87: -2 | J87: 0 | K87: -3 | L87: -3 | M87: 20 | N87: 9 | O87: 1.8 | P87: -- | Q87: Holzschaft, Schnell | R87: 3 | S87: 7 | T87: 3 | U87: 0.5 | V87: 1
A88: Stangenwaffen | B88: Stäbe | C88: Kampfstab kurz eisenb. | D88: 8 | E88: 3 | F88: W6 | G88: W6 | H88: 4 | I88: -2 | J88: 0 | K88: -2 | L88: -1 | M88: 10 | N88: 6 | O88: 1.4 | P88: -- | Q88: Holzschaft, Schnell | R88: 2 | S88: 7 | T88: 2 | U88: 0.5 | V88: 0.25
A89: Klingenwaffen | B89: Schwerter | C89: Katana 1½-händig | D89: 11 | E89: 5 | F89: W12 | G89: W8 | H89: 3 | I89: -6 | J89: 0 | K89: -3 | L89: -2 | M89: 11 | N89: 8 | O89: 1 | P89: 2 | R89: 15 | S89: 13 | T89: 19 | U89: 1 | V89: 5
A90: Klingenwaffen | B90: Zweihänder | C90: Katana 1½-händig | D90: 11 | E90: 5 | F90: W12 | G90: W8 | H90: 3 | I90: -6 | J90: 0 | K90: -3 | L90: -2 | M90: 11 | N90: 8 | O90: 1 | P90: 2 | R90: 15 | S90: 13 | T90: 19 | U90: 1 | V90: 5
A91: Klingenwaffen | B91: Schwerter | C91: Kavalleriesäbel | D91: 10 | E91: 4 | F91: W10 | G91: W6 | H91: 4 | I91: -3 | J91: 0 | K91: -2 | L91: -2 | M91: 9 | N91: 6 | O91: 1 | P91: 1 | R91: 13 | S91: 15 | T91: 16 | U91: 1 | V91: 4
A92: Hiebwaffen | B92: Kettenwaffen | C92: Kette | D92: 7 | E92: 0 | F92: W4 | G92: W4 | H92: 3 | I92: -4 | J92: 0 | K92: -7 | L92: -15 | M92: 10 | N92: 6 | O92: 1 | P92: 6 | R92: 1 | S92: 12 | T92: 6 | U92: 2 | V92: 1
A93: Unbewaffnet | B93: Peitschen | C93: Kettenpeitsche | D93: 14 | E93: 7 | F93: W10 | G93: W6 | H93: 2 | I93: -4 | J93: 0 | K93: -7 | L93: -15 | M93: 14 | N93: 11 | O93: 1.5 | P93: 3 | R93: 2 | S93: 7 | T93: 6 | U93: 3 | V93: 1.5
A94: Hiebwaffen | B94: Stumpfe Hiebwaffen | C94: Keule eisenbeschlagen | D94: 9 | E94: 4 | F94: W6 | G94: W6 | H94: 3 | I94: -4 | J94: 0 | K94: -4 | L94: -5 | M94: 9 | N94: 7 | O94: 1 | P94: 0 | Q94: Holzschaft | R94: 12 | S94: 7 | T94: 3 | U94: 0.5 | V94: 0.25
A95: Hiebwaffen | B95: Beidhand-Hiebwaffen | C95: Keule troll,, eisenbeschlagen | D95: 15 | E95: 8 | F95: 2W12 | H95: 1.5 | I95: -13 | J95: 0 | K95: -6 | L95: -7 | M95: 34 | N95: 19 | O95: 1.7 | P95: -- | Q95: Holzschaft | R95: 14 | S95: 11 | T95: 10 | U95: 1 | V95: 0.25
A96: Unbewaffnet | B96: Armklingen | C96: Klaue | D96: 2 | E96: 2 | F96: W10 | G96: W6 | H96: 3 | I96: -6 | J96: 0 | K96: -2 | L96: -6 | M96: 6 | O96: 0.2 | P96: 3 | R96: 7 | S96: 12 | T96: 6 | U96: 0.4 | V96: 1
A97: Hiebwaffen | B97: Äxte | C97: Kriegsbeil | D97: 6 | E97: 4.5 | F97: [2W12] | G97: W12 | H97: 3 | I97: -10 | J97: 0 | K97: -3 | L97: -4 | M97: 12 | N97: 7 | O97: 0.6 | P97: 4 | Q97: Holzschaft | R97: 18 | S97: 7 | T97: 10 | U97: 0.7 | V97: 4
A98: Hiebwaffen | B98: Äxte | C98: Kriegsbeil orkisch | D98: 9 | E98: 6 | F98: [2W15] | G98: W12 | H98: 3 | I98: -10 | J98: 0 | K98: -5 | L98: -4 | M98: 19 | N98: 12 | O98: 0.9 | P98: 0 | Q98: Holzschaft | R98: 18 | S98: 7 | T98: 8 | U98: 1.2 | V98: 4
A99: Hiebwaffen | B99: Beidhand-Hiebwaffen | C99: Kriegshammer (Hammer) | D99: 13 | E99: 7 | F99: W12 | G99: W12 | H99: 2 | I99: -11 | J99: 0 | K99: -7 | L99: -7 | M99: 28 | N99: 16 | O99: 1.4 | P99: -- | Q99: Holzschaft | R99: 19 | S99: 9 | T99: 9 | U99: 1.4 | V99: 5
A100: Hiebwaffen | B100: Beidhand-Hiebwaffen | C100: Kriegshammer (Schnabel) | D100: 13 | E100: 7 | F100: W30 | H100: 2 | I100: -11 | J100: 4 | K100: -7 | L100: -7 | M100: 28 | N100: 16 | O100: 1.4 | P100: -- | Q100: Holzschaft | R100: 19 | S100: 9 | T100: 9 | U100: 1.4 | V100: 5
...

Sheet Entwickeln
A1: Bereich | B1: Thema | C1: Beschreibung | D1: Status | E1: Hinzugefuegt
A2: Ausruestung/Schilde | B2: Schild-Preise/Rezept/Materialpreis | C2: 14 Schildzeilen mit #WERT!-Fehlern in NK-Waffen-Basis: Preis/Rezeptschwierigkeit/Materialpreis nicht uebernommen. Die Schilde-Quelltabelle (NN Schilde v0.1.xlsx) hat Materialpreis/Arbeitszeit/Rezept-Mod-Basis komplett unausgefuellt ('x'/'X'), und ihre Basiswerte gelten teils mit Holz statt Eisen als Grundmaterial, nicht kompatibel mit dem NK-Waffen-Materialsystem. Zeilen sind uebernommen, aber als 'aktuell nicht ausruestbar' markiert. Muss von Grund auf neu entwickelt werden (eigenes Material-/Preissystem fuer Schilde, ggf. eigene Normalisierung auf ein einheitliches Basismaterial). -- GELOEST 2026-07-16: 'Schilde v1.4.docx' vom Nutzer bereitgestellt, enthaelt saubere Preis-Basis (100D-1200D) je Schild sowie eigene Material-/Fertigungs-/Bespannungs-Tabellen (multiplikatives Preissystem, siehe Sheets Schild-Material/Schild-Fertigung/Schild-Bespannung). Ausserdem dabei einen Vorzeichenfehler gefunden und korrigiert: 11 der 12 Schilde hatten Staerke-Malus-Basis=+5 statt korrekt -5 in NK-Waffen-Basis. | D2: Geloest | E2: 2026-07-16
A3: Ausruestung/Ruestung | B3: Panzerhandschuhe, Panzerschienen, Eisenkappenstiefel, Orkischer Kampfhandschuh | C3: Ruestungswerte fehlen fuer diese vier Gegenstaende in der Ruestungstabelle (es existiert kein Haende-/Fuesse-Slot, nur Kopf/Torso/Arme/Beine). Rezept-Mod-Basis/Materialpreis-Faktor/Arbeitszeit-Tag-Basis in NK-Waffen-Basis daher = X/x/x. Braucht: (a) Ruestungswerte-System fuer Haende/Fuesse allgemein, (b) konkrete Werte fuer diese 4 Items. | D3: Offen | E3: 2026-07-16
A4: Ausruestung/Ruestung | B4: Ruestungsmodifikatoren/Ruestungsteile-System | C4: Es existiert kein Pendant zu NK-Material/NK-Fertigung/NK-Anpassung/NK-Schaftmaterial fuer Ruestung. Muss komplett neu entwickelt werden, analog zur NK-Waffen-Modifikatorkette. -- GELOEST 2026-07-16: System steckte bereits vollstaendig in NN NPC-Rechner 0.76.xlsx, Sheet 'RS-Sheet' (Nutzerhinweis). Als Sheets Ruestung-Basis (20 Ruestungsteile), Ruestung-Addons (4 Aufpanzerungen, Lage 5), Ruestung-Verarbeitung (4 Stufen), Ruestung-Anpassung (4 Stufen) umgesetzt. Formel (RS = Basis + Verarbeitung; BE = MAX(Lage; Basis+Verarbeitung+Anpassung); Preis = Materialkosten + Lohn*(Arbeitszeit+Zusatztage); Verfuegbarkeit = MAX ueber alle 3 Komponenten) gegen das bestehende Beispiel-Set in Sheet Ruestungstabelle verifiziert (Stoffruestung+Meisterarbeit+angepasst -> RS=3/BE=1/Preis=227/NW=3/AW=2, alle 5 Werte exakt reproduziert). | D4: Geloest | E4: 2026-07-16
A5: Ausruestung/Waffen | B5: Ork'sche (FK/NK-Hybrid) | C5: Pistole/Muskete, die gleichzeitig als Nahkampfwaffe zaehlt. Nur ueber Fertigung/Anpassung modifizierbar, Preis stammt aus der FK-Tabelle; die NK-Version wird beim Kauf der FK-Waffe automatisch mitgeliefert. Grenzfall zwischen FK- und NK-System, noch nicht in NK-Waffen-Basis integriert. | D5: Offen | E5: 2026-07-16
A6: Ausruestung/NK-Waffen | B6: Rezeptschwierigkeit generell | C6: 14 Zeilen mit Rezept-Mod-Basis=X: Wert in der Originalquelle (NN NK-Waffentabelle v1.12) nie ausgefuellt. Korrelation Rezeptschwierigkeit vs. Preis rechnerisch getestet (r=0.007) - kein statistischer Zusammenhang, kann nicht aus dem Preis rekonstruiert werden. Bleibt offen, bis eine inhaltliche Einschaetzung (Spielleitung) vorliegt. | D6: Offen | E6: 2026-07-16
A7: Nahkampf/Unbewaffnet | B7: Voelkerbeschraenkungen bei Unbewaffnet-Kampfstilen | C7: Boxen (Dalkini/Zwerg/Ork), Elfische Kunst der Selbstverteidigung (Elf), Goblinische Kampfkunst (Goblin), Katzenmenschen Kampfkunst (Katzenmensch), Orkisch' Raufen (Ork), Schattenkampf (Drow) sind laut Quelle (Nahkampftabelle Unbewaffnet.doc, 2004) an bestimmte Voelker gebunden. Diese Beschraenkung ist inhaltlich nicht geprueft/nachvollzogen (Nutzer: 'sehe ich persoenlich nicht ein') und sollte ueberarbeitet werden - ebenso die Kampfstile/Faehigkeiten selbst generell (Balance, Aktualitaet, Formulierung der Specials). | D7: Offen | E7: 2026-07-16
A8: Nahkampf/Unbewaffnet | B8: Dynamische Schadenswerte (Boxen, Ringen, Elfische Kunst) | C8: Boxen und Ringen haben Schaden/Staerke-Mod = 'wie unbewaffnet' (haengt von der Rasse des Charakters ab, siehe rassenabhaengige Unbewaffnet-Basiswerte in NK-Waffen-Basis). Elfische Kunst der Selbstverteidigung hat Schaden = 'gegnerischer' (spiegelt den Schaden des Gegners). Beides ist aktuell nur als Text in NK-Waffen-Basis hinterlegt, keine Formel - fehlt eine mechanische Aufloesung im Formel-System (Werte-Sheet). | D8: Offen | E8: 2026-07-16
A9: Nahkampf/Unbewaffnet | B9: Fert/Spez-Maximum Mechanik unklar | C9: Die Quelle gibt pro Kampfstil ein 'Fert/Spez-Maximum' an (z.B. 20/20, 25/30, 30/20). Rohwerte wurden 1:1 in NK-Waffen-Basis Spalte 'Fert-Spez-Maximum' uebernommen, aber die Bedeutung/Wirkung ist ungeklaert (Deckelt es nk_unbewaffnet? Die Spezialisierung? Beides getrennt?). | D9: Offen | E9: 2026-07-16
A10: Nahkampf/Unbewaffnet | B10: 'Staerkebonus' vs. 'Staerke-Mod' bei Biss-Angriffen | C10: Bei Ork- und Katzenmensch-Biss wird der Schaden mit '+[Staerkebonus]' angegeben - eine andere Notation als das sonst genutzte Staerke-Teiler/Staerke-Malus-System (z.B. '(Staerke:3)-7' bei Troll-Biss/Zentaur-Huftritt). Unklar, ob 'Staerkebonus' ein bereits vorhandener Wert im System ist oder neu definiert werden muss. | D10: Offen | E10: 2026-07-16
A11: Nahkampf/Unbewaffnet | B11: Vitalitaet als Ruestungsschutz gegen Unbewaffnet-/Fallschaden | C11: Laut Quelle gibt Vitalitaet einen zusaetzlichen Ruestungsschutz (RS) gegen Schaden durch Unbewaffnet-Angriffe oder Sturz/Fall. Noch nicht ins Ruestungs-/Schadenssystem integriert. | D11: Offen | E11: 2026-07-16
A12: Ausruestung/Schilde | B12: Chitin/Kolhartz Preis-Faktor als Spanne | C12: Schild-Material: Chitin ('*2,5 - *4') und Kolhartz ('*0,1 - *1000') geben in Schilde v1.4.docx eine Preis-Spanne statt eines Einzelwerts an (vermutlich abhaengig von Qualitaet/Seltenheit des Rohmaterials, analog zur Waffen-Materialtabelle, wo Chitin ebenfalls '*2,5 - *4' hat). Braucht eine Entscheidung, wie die Spanne genutzt wird (fester Wert? Wuerfelspanne? Spielleiter-Ermessen?). | D12: Offen | E12: 2026-07-16
... A37: Fernkampf/Sonderfertigkeit | B37: Ladeschuetze Schleuder | C37: Ladeschuetze Schleuder existiert als Sonderfertigkeit (sf_ladeschuetze_schleuder) und Talent (talente_ladeschuetze_schleuder), aber die Waffe 'Schleuder' existiert nicht als Fernkampf-Kategorie (nur Boegen/Blasrohre/Schusswaffen/Wurfwaffen existieren dort). Da die Sichtbarkeit der Ladeschuetze-SF im Sonderfertigkeit-Tab jetzt an die zugehoerige fk_*-Fertigkeit>0 gekoppelt ist, waere Ladeschuetze Schleuder nie freischaltbar gewesen. Auf Nutzerentscheidung 2026-07-19 deaktiviert (# vor Referenz in Werte-Sheet Zeile 192/1152 - Konvention siehe generate_data_ts.py read_rules()). | D37: Deaktiviert | E37: 2026-07-19

Sheet Schild-Material
A1: Material | B1: Staerke-Malus-Mod | C1: AT-Mod | D1: PA-Mod | E1: WK-Mod | F1: Klingenbrecher-Mod | G1: Klingenschutz-Mod | H1: RS-Mod | I1: Min-Staerke-Faktor | J1: Preis-Faktor | K1: Art-Specials
A2: Holz | B2: -6 | C2: 2 | D2: 2 | E2: -1.5 | F2: -11 | G2: -10 | H2: -5 | I2: 0.5 | J2: 0.2
A3: Hart Holz | B3: -5 | C3: 1 | D3: 2 | E3: -1 | F3: -4 | G3: -5 | H3: -3 | I3: 0.7 | J3: 3
A4: Leder | B4: 0 | C4: 3 | D4: 3 | E4: 0 | F4: -20 | G4: -15 | H4: -7 | I4: 0.45 | J4: 0.1
A5: Spinnenwebe | B5: -6 | C5: 3 | D5: 4 | E5: -2 | F5: -11 | G5: -5 | H5: 3 | I5: 0.4 | J5: 6 | K5: Nur Fernkampf-RS
A6: Chitin | B6: 0 | C6: 1 | D6: 2 | E6: -1 | F6: -2 | G6: 0 | H6: -4 | I6: 0.5 | J6: 3
A7: Drachensch. | B7: 0 | C7: 1 | D7: 2 | E7: -1 | F7: -2 | G7: 0 | H7: -3 | I7: 0.5 | J7: Meister (individuell durch Spielleitung)
A8: Stein | B8: 0 | C8: -3 | D8: -2 | E8: 1 | F8: -2 | G8: -3 | H8: -3 | I8: 1.3 | J8: 0.25
A9: Schwarzfells | B9: 0 | C9: -2 | D9: -1 | E9: 1 | F9: -2 | G9: -2 | H9: -1 | I9: 1.1 | J9: 0.5
A10: Diamantspart | B10: 3 | C10: 0 | D10: 1 | E10: -0.5 | F10: 3 | G10: 3 | H10: 6 | I10: 0.8 | J10: 1.75 | K10: 2 Wuerfe beim Bruchtest
A11: Bronze | B11: -1 | C11: -1 | D11: 0 | E11: 0.5 | F11: -2 | G11: -2 | H11: -2 | I11: 1.1 | J11: 0.5
A12: Eisen | B12: 0 | C12: -1 | D12: 0 | E12: 0 | F12: -1 | G12: -1 | H12: -1 | I12: 1.1 | J12: 0.75
A13: Feineisen | B13: 0 | C13: 0 | D13: 0 | E13: 0 | F13: 0 | G13: 0 | H13: 0 | I13: 1 | J13: 1 | K13: Standard (Referenzmaterial)
A14: Stahl | B14: 1 | C14: 0 | D14: 1 | E14: -0.5 | F14: 1 | G14: 1 | H14: 2 | I14: 0.9 | J14: 2.5
A15: Qualitaetsstahl | B15: 1 | C15: 0 | D15: 1 | E15: -0.5 | F15: 2 | G15: 2 | H15: 3 | I15: 0.9 | J15: 3.5
A16: Faltstahl | B16: 2 | C16: 0 | D16: 1 | E16: -0.5 | F16: 3 | G16: 3 | H16: 5 | I16: 0.8 | J16: 5 | K16: 2 Wuerfe beim Bruchtest
A17: Mithril | B17: -1 | C17: 1 | D17: 2 | E17: -2 | F17: 0 | G17: 2 | H17: 2 | I17: 0.5 | J17: 25
A18: Adamandit | B18: 3 | C18: 0 | D18: 1 | E18: -0.5 | F18: 3 | G18: +50% (so in Quelle - Bruch mit Format der Spalte, vermutlich Tippfehler statt Flachwert, siehe Entwickeln) | H18: 7 | I18: 0.8 | J18: 5000 | K18: 3 Wuerfe beim Bruchtest
A19: Alchemistensilb. | B19: 0 | C19: -1 | D19: 0 | E19: 0 | F19: -1 | G19: -1 | H19: -1 | I19: 1 | J19: 3.5
A20: Vulkanglas | B20: -1 | C20: -3 | D20: -2 | E20: -1 | F20: -4 | G20: -5 | H20: -1 | I20: 1.1 | J20: 3.5
A21: Nasium | B21: 0 | C21: -1 | D21: -1 | E21: -1 | F21: -1 | G21: -1 | H21: -1 | I21: 1.2 | J21: 30
A22: Knochen | B22: 0 | C22: 1 | D22: 2 | E22: -1 | F22: -4 | G22: -5 | H22: -4 | I22: 0.5 | J22: 0.1
A23: Kolhartz | B23: -1 | C23: 1 | D23: 2 | E23: -1 | F23: 0 | G23: 0 | H23: -1 | I23: 0.5 | J23: 1 | K23: nur auf dem Trollkontinent von Zentauern erhältlich

Sheet Schild-Fertigung
A1: Fertigung | B1: Klingenbrecher-Mod | C1: Klingenschutz-Mod | D1: Preis-Faktor
A2: Ausschuss | B2: -3 | C2: -6 | D2: 0.3
A3: Goblin Massenfab. | B3: -2 | C3: -3 | D3: 0.5
A4: Massenfabrikation | B4: -1 | C4: -1 | D4: 0.75
A5: Gesellenarbeit | B5: 0 | C5: 0 | D5: 1
A6: Meisterarbeit | B6: 1 | C6: 1 | D6: 2
A7: Großmeisterarbeit | B7: 2 | C7: 2 | D7: 5
A8: Einzelstück | B8: 3 | C8: 3 | D8: 10

Sheet Schild-Bespannung
A1: Bespannung | B1: Klingenbrecher-Mod | C1: Klingenschutz-Mod | D1: RS-Mod | E1: Min-Staerke-Faktor | F1: Preis | G1: Art-Specials
A2: Stoff | B2: 0 | C2: 0 | F2: 20
A3: Spinnenwebe | B3: 0 | C3: 1 | D3: 3 | E3: 1.05 | F3: 600 | G3: Nur FK
A4: Leder | B4: 0 | C4: 2 | D4: 1 | E4: 1.1 | F4: 25
A5: Drachenschuppe | B5: 1 | C5: 2 | D5: 4 | E5: 1.2 | F5: Meister (individuell durch Spielleitung) | G5: -50% Einzelelement-Schaden
A6: Kohlharz | B6: 2 | C6: 3 | D6: 5 | E6: 1.4 | F6: 10 | G6: nur bei Zentauren auf dem Trollkontinent erhältlich.

Sheet Schild-Verplatung
A1: Material | B1: Klingenbrecher-Mod | C1: Klingenschutz-Mod | D1: RS-Mod | E1: Min-Staerke-Faktor | F1: Preis-Faktor | G1: Flag
A2: Schwarzfells | G2: Keine Werte in Quelle vorhanden - nur Materialliste, siehe Entwickeln
A3: Diamantspart | G3: Keine Werte in Quelle vorhanden - nur Materialliste, siehe Entwickeln
A4: Bronze | G4: Keine Werte in Quelle vorhanden - nur Materialliste, siehe Entwickeln
A5: Eisen | G5: Keine Werte in Quelle vorhanden - nur Materialliste, siehe Entwickeln
A6: Feineisen | G6: Keine Werte in Quelle vorhanden - nur Materialliste, siehe Entwickeln
A7: Stahl | G7: Keine Werte in Quelle vorhanden - nur Materialliste, siehe Entwickeln
A8: Qualitaetsstahl | G8: Keine Werte in Quelle vorhanden - nur Materialliste, siehe Entwickeln
A9: Faltstahl | G9: Keine Werte in Quelle vorhanden - nur Materialliste, siehe Entwickeln
A10: Mithril | G10: Keine Werte in Quelle vorhanden - nur Materialliste, siehe Entwickeln
A11: Adamandit | G11: Keine Werte in Quelle vorhanden - nur Materialliste, siehe Entwickeln
A12: Alchemistensilb. | G12: Keine Werte in Quelle vorhanden - nur Materialliste, siehe Entwickeln
A13: Vulkanglas | G13: Keine Werte in Quelle vorhanden - nur Materialliste, siehe Entwickeln
A14: Nasium | G14: Keine Werte in Quelle vorhanden - nur Materialliste, siehe Entwickeln

Sheet Artefakt-Magus-Faehigkeiten
A1: Rang | B1: Name | C1: Max-Zaubergrad-Wirkungsstufe | D1: Gehalt | E1: Dublonen-pro-Mana | F1: Angenommene-M | G1: Verfuegbarkeit
A2: 1 | B2: - | C2: 2 | D2: 11 | E2: 0.5 | F2: 5 | G2: 1
A3: 2 | B3: - | C3: 2 | D3: 22 | E3: 1 | F3: 10 | G3: 2
A4: 3 | B4: Magus | C4: 2 | D4: 44 | E4: 2 | F4: 20 | G4: 3
A5: 4 | B5: Magus Magister | C5: 3 | D5: 60 | E5: 6 | F5: 25 | G5: 4
A6: 5 | B6: Magus Major | C6: 4 | D6: 90 | E6: 18 | F6: 30 | G6: 5
A7: 6 | B7: Magus Superior | C7: 5 | D7: 150 | E7: 54 | F7: 35 | G7: 6
A8: 7 | B8: Magus Archus | C8: 6 | D8: 600 | E8: 162 | F8: 40 | G8: 7
A9: 8 | B9: Magus Legendarius | C9: 7 | D9: 1500 | E9: 486 | F9: 45 | G9: 8
A10: 9 | B10: Magus Semi-Deus | C10: 8 | D10: 5000 | E10: 1458 | F10: 50 | G10: 9
A11: 10 | B11: Avatar | C11: 9 | D11: 15000 | E11: 4374 | F11: 55 | G11: 10
A12: 11 | B12: Gott | C12: 10 | D12: 45000 | E12: 13122 | F12: 60 | G12: 11

Sheet Artefakt-Seelensteine
A1: Zauberstufe | B1: Karat-pro-Mana | C1: Dublonen-pro-Mana
A2: 1 | B2: 0.6 | C2: 5
A3: 2 | B3: 0.5 | C3: 10
A4: 3 | B4: 0.4 | C4: 17
A5: 4 | B5: 0.3 | C5: 26
A6: 5 | B6: 0.2 | C6: 37
A7: 6 | B7: 0.1 | C7: 50
A8: 7 | B8: 0.05 | C8: 65
A9: 8 | B9: 0.05 | C9: 82
A10: 9 | B10: 0.05 | C10: 101
A11: 10 | B11: 0.05 | C11: 123

Sheet Artefakt-Manamultiplikator
A1: Differenz | B1: Manamultiplikator
A2: 1 | B2: 0.66666667
A3: 2 | B3: 0.44444444
A4: 3 | B4: 0.2962963
A5: 4 | B5: 0.19753086
A6: 5 | B6: 0.13168724
A7: 6 | B7: 0.087791495
A8: 7 | B8: 0.058527663
A9: 8 | B9: 0.039018442
A10: 9 | B10: 0.026012295
A11: 10 | B11: 0.01734153

Sheet Artefakt-Basis
A1: Referenz | B1: Name | C1: Beschreibung | D1: Zaubergrad | E1: Mana-Basis | F1: Vorbereitungszeit-sec | G1: Effektdauer-sec | H1: Wirkungsdauer-Basis | I1: Wirkungsdauer-Einheit | J1: Wirkung-Basis | K1: Wirkung-Einheit | L1: Eigenschaft
A2: artefakt_licht | B2: Licht | C2: Das Artefakt beginnt zu leuchten. Bei Erschaffung muss die Strahlart festgelegt werden: Rundumlicht, Strahl oder Kegel. Das Artefakt leuchtet so hell wie: | D2: 1 | E2: 10 | F2: 1 | G2: sofort | H2: 5 | I2: min | J2: 40 | K2: Fackeln
A3: artefakt_magisches_makeover | B3: Magisches Makeover | C3: Der Magus kann seine Kleidung, seine Nägel und sein Haar in den gewünschten Zustand versetzen. Sämtliche Verunreinigungen oder unangenehmen Gerüche werden entfernt. Verwundungen und Vergiftungen werden hiervon nicht beeinflusst. | D3: 1 | E3: 20 | F3: 1 | G3: 30 | H3: permanent | J3: 40 | K3: %
A4: artefakt_in_nahrung_verwandeln | B4: In Nahrung verwandeln | C4: Der Träger kann unbelebte Materie, die er mit dem Artefakt berührt, in Nahrung verwandeln. Diese Nahrung ist nahezu geschmacklos, deckt aber alle Bedürfnisse des Organismus ab. Es ist möglich, sich ausschließlich von magischer Nahrung zu ernähren. | D4: 1 | E4: 42 | F4: 1 | G4: 60 | H4: permanent | J4: 700 | K4: Gramm
A5: artefakt_whk_talentwert_erhoehen | B5: WHK-Talentwert erhöhen | C5: Der Wert einer festgelegten Handwerks-, Wissens- oder Kultur- Talentes erhöht sich auf magische Weise. Der Wert muss vorher mindestens 4 betragen haben. | D5: 1 | E5: 15 | F5: 1 | G5: sofort | H5: 7 | I5: h | J5: 14 | K5: TaP
A6: artefakt_wasserwandeln | B6: Wasserwandeln | C6: Träger kann auf allen Oberflächen, die zu min. 50% aus Wasser bestehen, wie auf festem Boden gehen. | D6: 1 | E6: 28 | F6: 1 | G6: sofort | H6: 7 | I6: min
A7: artefakt_grundfertigkeit_erhoehen | B7: Grundfertigkeit erhöhen | C7: Eine bei Erschaffung fest gewählte spezialisierbare Grundfertigkeit wird erhöht. Der Wert muss vorher mindestens 4 betragen haben. | D7: 1 | E7: 15 | F7: 1 | G7: sofort | H7: 40 | I7: min | J7: 13 | K7: TaP
A8: artefakt_ausstrahlung_erhoehen | B8: Ausstrahlung erhöhen | C8: Die Ausstrahlung des Trägers wird auf magische Weise erhöht. | D8: 1 | E8: 12 | F8: 1 | G8: sofort | H8: 40 | I8: min | J8: Aus + | K8: 13 | L8: Ausstrahlung
A9: artefakt_waffe_erschaffen | B9: Waffe erschaffen | C9: In den Händen des Magus erscheint eine bei Erschaffung fest definierte beliebige normale Listen-Nahkampfwaffe oder ein beliebiger Listen-Schild, der vollständig aus Eisen besteht. Am Ende der Wirkungsdauer zerfällt die Waffe zu Staub, das ursprüngliche Artefakt bleibt erhalten. Während der Effektdauer hat die Waffe normale Werte, aber AT/PA-Klasse -1. Der Seelenstein ist integrativer Bestandteil des Gegenstands. | D9: 2 | E9: 15 | F9: 2 | G9: 2 | H9: 5 | I9: min
A10: artefakt_athletik_erhoehen | B10: Athletik erhöhen | C10: Athletik des Trägers wird auf magische Weise erhöht. (Aufgeteilt aus 'Körperliche Eigenschaft erhöhen': Eine bei Erschaffung fest gewählte körperliche Eigenschaft (Ath, Ges, Kon, Sch, Stä) wird auf magische Weise erhöht.) | D10: 2 | E10: 18 | F10: 2 | G10: sofort | H10: 40 | I10: min | J10: Eig + | K10: 13 | L10: Athletik
A11: artefakt_geschicklichkeit_erhoehen | B11: Geschicklichkeit erhöhen | C11: Geschicklichkeit des Trägers wird auf magische Weise erhöht. (Aufgeteilt aus 'Körperliche Eigenschaft erhöhen': Eine bei Erschaffung fest gewählte körperliche Eigenschaft (Ath, Ges, Kon, Sch, Stä) wird auf magische Weise erhöht.) | D11: 2 | E11: 18 | F11: 2 | G11: sofort | H11: 40 | I11: min | J11: Eig + | K11: 13 | L11: Geschicklichkeit
A12: artefakt_konstitution_erhoehen | B12: Konstitution erhöhen | C12: Konstitution des Trägers wird auf magische Weise erhöht. (Aufgeteilt aus 'Körperliche Eigenschaft erhöhen': Eine bei Erschaffung fest gewählte körperliche Eigenschaft (Ath, Ges, Kon, Sch, Stä) wird auf magische Weise erhöht.) | D12: 2 | E12: 18 | F12: 2 | G12: sofort | H12: 40 | I12: min | J12: Eig + | K12: 13 | L12: Konstitution
A13: artefakt_schnelligkeit_erhoehen | B13: Schnelligkeit erhöhen | C13: Schnelligkeit des Trägers wird auf magische Weise erhöht. (Aufgeteilt aus 'Körperliche Eigenschaft erhöhen': Eine bei Erschaffung fest gewählte körperliche Eigenschaft (Ath, Ges, Kon, Sch, Stä) wird auf magische Weise erhöht.) | D13: 2 | E13: 18 | F13: 2 | G13: sofort | H13: 40 | I13: min | J13: Eig + | K13: 13 | L13: Schnelligkeit
A14: artefakt_staerke_erhoehen | B14: Staerke erhöhen | C14: Staerke des Trägers wird auf magische Weise erhöht. (Aufgeteilt aus 'Körperliche Eigenschaft erhöhen': Eine bei Erschaffung fest gewählte körperliche Eigenschaft (Ath, Ges, Kon, Sch, Stä) wird auf magische Weise erhöht.) | D14: 2 | E14: 18 | F14: 2 | G14: sofort | H14: 40 | I14: min | J14: Eig + | K14: 13 | L14: Staerke
A15: artefakt_kiemen | B15: Kiemen | C15: Auf den Halsschlagadern bilden sich Kiemen. Dies ist ein schmerzhafter Prozess, bei dem eine um 5 erscwerte Selbstbeherrschungsprobe abgelegt werden muss. Nach dem Ende der Effektdauer kann unter Wasser durch die Kiemen geatmet werden. Atmet er in die Lunge, ertrinkt er. Giftstoffe im Wasser dringen über die Kiemen in den Blutkreislauf ein | D15: 2 | E15: 18 | F15: 2 | G15: 15 | H15: 120 | I15: min
A16: artefakt_stimme_veraendern | B16: Stimme verändern | C16: Die Stimme des Magiers verändert sich auf eine festgelgte Art und Weise. Es ist nicht möglich, die Stimme eines anderen exakt zu reproduzieren. Akzente und Mundarten werden hierdurch nicht simuliert, dafür benötigt der Magier die entsprechenden Sprachfertigkeiten. Während der Effektdauer ist der Magier im Stimmbruch. Wahl: Andere Stimme (Stufe 2, hier angegeben), Laute Stimme (*2: Stufe 3, *3: Stufe vier...); min. Seelenstein- & Wirkungs- Stufe 2 | D16: 2 | E16: 9 | F16: 2 | G16: 5 | H16: 7 | I16: min
A17: artefakt_flammen_pfeil | B17: Flammen - Pfeil | C17: Der Pfeil verursacht zusätzlichen elementaren Schaden. Die Wirkung endet in der Kampfrunde nach dem Aufprall. | D17: 3 | E17: 4 | F17: 3 | G17: sofort | H17: 40 | I17: sec | J17: W30
A18: artefakt_frost_pfeil | B18: Frost - Pfeil | C18: Der Pfeil verursacht zusätzlichen elementaren Schaden. Die Wirkung endet in der Kampfrunde nach dem Aufprall. Pro volle 5 TP erleidet das Opfer eine zusätzliche BE von 1. | D18: 3 | E18: 4 | F18: 3 | G18: sofort | H18: 40 | I18: sec | J18: W20
A19: artefakt_sturm_pfeil | B19: Sturm - Pfeil | C19: Der Pfeil verursacht zusätzlichen elementaren Schaden. Die Wirkung endet in der Kampfrunde nach dem Aufprall. Das Ziel wird TP*m weggeschleudert; Ath-Probe erschwert um TP, sonst zusätzlich W8 Sturzschaden auf FK-TZ (W30). | D19: 3 | E19: 4 | F19: 3 | G19: sofort | H19: 40 | I19: sec | J19: W20
A20: artefakt_splitter_pfeil | B20: Splitter - Pfeil | C20: Der Pfeil verursacht zusätzlichen elementaren Schaden. Die Wirkung endet in der Kampfrunde nach dem Aufprall. Der Splitter - Pfeil kann Rüstungen leichter durchdringen. | D20: 3 | E20: 4 | F20: 3 | G20: sofort | H20: 40 | I20: sec | J20: W20 | K20: RB 8
A21: artefakt_schock_pfeil | B21: Schock - Pfeil | C21: Der Pfeil verursacht zusätzlichen elementaren Schaden. Die Wirkung endet in der Kampfrunde nach dem Aufprall. Sobald das Ziel 1 SP erleidet, muss es eine SB-Probe ablegen, die immer zusätzlich um den angegeben Wert erschwert ist. | D21: 3 | E21: 4 | F21: 3 | G21: sofort | H21: 40 | I21: sec | J21: W20 | K21: SB 13
A22: artefakt_flammen_klinge | B22: Flammen - Klinge | C22: Die Klinge verursacht zusätzlichen elementaren Schaden. | D22: 3 | E22: 26 | F22: 3 | G22: sofort | H22: 40 | I22: min | J22: W30
A23: artefakt_frost_klinge | B23: Frost - Klinge | C23: Die Klinge verursacht zusätzlichen elementaren Schaden. Pro volle 5 TP erleidet das Opfer eine zusätzliche BE von 1. | D23: 3 | E23: 26 | F23: 3 | G23: sofort | H23: 40 | I23: min | J23: W20
A24: artefakt_sturm_klinge | B24: Sturm - Klinge | C24: Die Klinge verursacht zusätzlichen elementaren Schaden. Das Ziel wird TP*m weggeschleudert; Ath-Probe erschwert um TP, sonst zusätzlich W8 Sturzschaden auf FK-TZ (W30). | D24: 3 | E24: 26 | F24: 3 | G24: sofort | H24: 40 | I24: min | J24: W20
A25: artefakt_splitter_klinge | B25: Splitter - Klinge | C25: Die Klinge verursacht zusätzlichen elementaren Schaden. Die Splitter - Klinge kann Rüstungen leichter durchdringen. | D25: 3 | E25: 26 | F25: 3 | G25: sofort | H25: 40 | I25: min | J25: W20 | K25: RB 8
A26: artefakt_schock_klinge | B26: Schock - Klinge | C26: Die Klinge verursacht zusätzlichen elementaren Schaden. Sobald das Ziel 1 SP erleidet, muss es eine SB-Probe ablegen, die immer zusätzlich um den angegeben Wert erschwert ist. | D26: 3 | E26: 26 | F26: 3 | G26: sofort | H26: 40 | I26: min | J26: W20 | K26: SB 13
A27: artefakt_material_verstaerken | B27: Material verstärken | C27: Klingenschutz und Klingenbrecher des verzauberten Gegenstandes erhöhen sich. | D27: 3 | E27: 80 | F27: 3 | G27: sofort | H27: 40 | I27: min | J27: 8 | K27: KS/KB
A28: artefakt_intelligenz_erhoehen | B28: Intelligenz erhöhen | C28: Intelligenz des Trägers wird auf magische Weise erhöht. (Aufgeteilt aus 'Geistige Eigenschaft erhöhen': Eine geistige Eigenschaft (Int, Mut, Sin, Wil) wird magisch erhöht.) | D28: 3 | E28: 18 | F28: 3 | G28: sofort | H28: 40 | I28: min | J28: Eig + | K28: 13 | L28: Intelligenz
A29: artefakt_mut_erhoehen | B29: Mut erhöhen | C29: Mut des Trägers wird auf magische Weise erhöht. (Aufgeteilt aus 'Geistige Eigenschaft erhöhen': Eine geistige Eigenschaft (Int, Mut, Sin, Wil) wird magisch erhöht.) | D29: 3 | E29: 18 | F29: 3 | G29: sofort | H29: 40 | I29: min | J29: Eig + | K29: 13 | L29: Mut
A30: artefakt_sinnesschaerfe_erhoehen | B30: Sinnesschaerfe erhöhen | C30: Sinnesschaerfe des Trägers wird auf magische Weise erhöht. (Aufgeteilt aus 'Geistige Eigenschaft erhöhen': Eine geistige Eigenschaft (Int, Mut, Sin, Wil) wird magisch erhöht.) | D30: 3 | E30: 18 | F30: 3 | G30: sofort | H30: 40 | I30: min | J30: Eig + | K30: 13 | L30: Sinnesschaerfe
A31: artefakt_willenskraft_erhoehen | B31: Willenskraft erhöhen | C31: Willenskraft des Trägers wird auf magische Weise erhöht. (Aufgeteilt aus 'Geistige Eigenschaft erhöhen': Eine geistige Eigenschaft (Int, Mut, Sin, Wil) wird magisch erhöht.) | D31: 3 | E31: 18 | F31: 3 | G31: sofort | H31: 40 | I31: min | J31: Eig + | K31: 13 | L31: Willenskraft
A32: artefakt_sinne_verbessern | B32: Sinne verbessern | C32: Entweder der Geruchssinn, der Geschmackssinn, das Gehör, das Sehvermögen oder der Tastsinn werden verbessert. Sinnesschärfen-Proben, die der Meister verlangen könnte, sind um (M):2 erleichtert (entspricht der Wirkungsdauer). Der verbesserte Sinn muss bei Erschaffung des Artefaktes festgelegt werden. | D32: 3 | E32: 92 | F32: 3 | G32: sofort | H32: 20 | I32: min | J32: Sin + | K32: 20
A33: artefakt_in_pflanze_verwandeln | B33: In Pflanze verwandeln | C33: Der Träger sowie alle Ausrüstung in seiner Aura verwandeln sich in eine festgelegte Pflanze und erleidet während der Effektdauer starke Schmerzen, kann aber nicht bewusstlos werden. Während der Wirkungsdauer hat das Ziel die Wahrnehmung der Pflanze, kann also nicht sprechen oder zaubern. Die Wirkung kann nur durch Antimagie vorzeitig beendet werden. Nach Ende der Wirkungsdauer findet eine Rückverwandlung statt, die genauso lange dauert wie die Effektdauer. Die Masse der zu verwandelnden Person bleibt gleich! Während der Wirkungsdauer verfügt der Träger über die folgenden LE/RS - Werte: | D33: 3 | E33: 1800 | F33: 3 | G33: 180 | H33: 40 | I33: h | J33: 400 | K33: 7
A34: artefakt_langsamer_fall | B34: Langsamer Fall | C34: Ein Lebewesen wird durch diesen Zauber so weit verlangsamt, dass es keinen Sturzschaden erfahren kann. | D34: 4 | E34: 130 | F34: 4 | G34: sofort | H34: 20 | I34: sec
A35: artefakt_in_tier_verwandeln | B35: In [Tier] verwandeln | C35: Der Träger wird in ein fest ausgewähltes Tier verwandelt. Dieses Tier verfügt über die selben Werte wie der Träger. In Tierform können keinerlei Zauber gewirkt werden, Sprachfertigkeiten entsprechen den Fähigkeiten des Tieres. Die Umwandlung ist äußerst schmerzhaft und kann nicht vor Ablauf der Wirkungsdauer beendet werden (außer durch Antimagie). Die Masse des Ziels bleibt gleich! | D35: 4 | E35: 1400 | F35: 4 | G35: 60 | H35: 40 | I35: min
A36: artefakt_gecko | B36: Gecko | C36: Der Träger kann mit Händen und Füßen an jeder beliebigen festen Oberfläche haften und dabei seine Maximallast tragen. Klettern-Proben sind erleichtert. | D36: 5 | E36: 88 | F36: 5 | G36: sofort | H36: 40 | I36: min | J36: 20 | K36: Klettern
A37: artefakt_chamaeleon | B37: Chamäleon | C37: Der Träger und alle Gegenstände, die sich innerhalb seiner Aura befinden, werden durchsichtig.Um das Ziel zu Erkennen, ist eine um Wirkungsstufe * 3 erschwerte Sinnesschärfe-Probe nötig. Schleicht/geht/läuft/sprintet/attackiert das Ziel, sind Sinnesschärfe-Proben um Wirkungsstufe*3/2/1/0,5/0,25 erschwert. | D37: 5 | E37: 336 | F37: 5 | G37: 3 | H37: 20 | I37: min | J37: 21 | K37: Sin
A38: artefakt_warp | B38: Warp | C38: Der Träger teleportiert zu einem Punkt, den er sieht. Er löst sich von Fuß zum Kopf hin in Dampf auf, genauso materialisiert er wieder. Er materialisiert immer stehend, Arme angelegt. Abweichung vom Zielpunkt: (Distanz in m/10) = Wx; Wx –Wirkungsstufe =Abweichung in m; Abw. immer horizontal, nicht in Gegenstände hinein, sondern auf/neben ihnen. Patzer: Pech-Probe erschw. um Distanz/10. ->pro 1 Punkt Pech: 1W20 auf alle TZ verteilt, alles ignorierend. Der Magus befindet sich während der Reise 1 sec in der Astralsphäre und benötigt 1 sec um wieder zu materialisieren. | D38: 5 | E38: 22 | F38: 5 | G38: 1 | H38: 1 | I38: sec | J38: 200 | K38: m RW
A39: artefakt_verwandlung | B39: Verwandlung | C39: Der Träger verändert sein Aussehen, je nachdem wie der Artefaktmagier es in das Artefakt gebannt hat. Dies schließt biometrische Merkmale außer der DNA ein. Das Ziel muss während der gesamten Effektdauer bewegungslos bleiben, sonst fällt der Zauber und verursacht unter Umständen ein grauenhaftes Resultat (Ausstrahlungs-Malus von 3 pro min). Die Verwandlung ist ein äußerst schmerzhafter und anstrengender Prozess, bei dem pro min Effektdauer eine SB-Probe erschwert um 15 abzulegen ist. Die Masse bleibt gleich. | D39: 5 | E39: 960 | F39: 5 | G39: 180 | H39: 240 | I39: min
A40: artefakt_last_des_alters | B40: Last des Alters | C40: Der Träger altert um maximal Wirkungsstufe*5 Jahre (entspricht der Wirkungsdauer) und erfährt die Leiden des Alters in voller Stärke. Das Erscheinungsbild, die Beweglichkeit und die Wahrnehmung erleiden die Einbußen, die das Opfer bei natürlicher Alterung erleiden würde. Auf Vitalfunktionen hat dieser Zauber keinerlei Einfluss. Am Ende der Wirkungsdauer verwandelt sich das Opfer in seinen Ursprungszustand zurück. Beide Effektdauern sind äußerst schmerzhaft. | D40: 6 | E40: 600 | F40: 6 | G40: 180 | H40: 200 | I40: min
A41: artefakt_unauffindbarkeit | B41: Unauffindbarkeit | C41: Der Träger und Ausrüstung in seiner Aura verursachen keinerlei Geräusche, hinterlassen keine Spuren und erzeugen keinerlei Gerüche. Optisch, astral und mit Wärmesicht ist das Ziel unmodifiziert zu entdecken. Erleichterung Schleichen&Tarnung/Erschwerung Sinnesschärfe zur Wahrehmung | D41: 6 | E41: 258 | F41: 6 | G41: sofort | H41: 40 | I41: min | J41: 21 | K41: 14
A42: artefakt_unsichtbarkeit | B42: Unsichtbarkeit | C42: Der Träger und alle Ausrüstung in seiner Aura sind vollkommen unsichtbar und weder astral, optisch oder mit Wärmesicht zu entdecken. Bewegt sich das Ziel schneller als gehend oder beginnt es, an einem Kampf teilzunehmen oder zu zaubern, fällt der Zauber. | D42: 6 | E42: 320 | F42: 6 | G42: sofort | H42: 20 | I42: min
A43: artefakt_verjuengung | B43: Verjüngung | C43: Der Träger verjüngt sich und erfährt die Jugend in voller Stärke. Das Erscheinungsbild, die Beweglichkeit und die Wahrnehmung entsprechen dem erzielten Lebensalter. Auf Vitalfunktionen hat dieser Zauber keinerlei Einfluss. Am Ende der Wirkungsdauer verwandelt sich das Opfer in seinen Ursprungszustand zurück. Beide Effektdauern sind äußerst schmerzhaft. Es ist nicht möglich, ein Entwicklungsstadium vor der Geburt zu erzielen. Die Masse bleibt gleich! | D43: 7 | E43: 800 | F43: 7 | G43: 180 | H43: 200 | I43: min | J43: 35 | K43: Jahre
A44: artefakt_artefakt_analysieren | B44: Artefakt analysieren | C44: Magische Gegenstände analysieren bis Grad/erforderliche Magietheorie | D44: 1 | E44: 17 | F44: 1 | G44: 21 | H44: permanent | J44: 7 | K44: 35
A45: artefakt_dammerungssicht | B45: Dammerungssicht | C45: Restlichtverstärker | D45: 1 | E45: 120 | F45: 1 | G45: sofort | H45: 120 | I45: min
A46: artefakt_waermesicht | B46: Wärmesicht | C46: Infrarotsicht | D46: 2 | E46: 40 | F46: 2 | G46: sofort | H46: 20 | I46: min
A47: artefakt_magische_reinigung | B47: Magische Reinigung | C47: Alle anhaltenden und bipolaren Zauber, die auf die Aure des Trägers wirken, werden beendet. | D47: 2 | E47: 6 | F47: 2 | G47: sofort | H47: 2 | I47: sec | J47: Grad | K47: 7
A48: artefakt_magische_sicht | B48: Magische Sicht | C48: Magische Sicht | D48: 3 | E48: 160 | F48: 3 | G48: sofort | H48: 80 | I48: min
A49: artefakt_magischer_schild | B49: Magischer Schild | C49: Die Aura des Zieles wird von einem unsichtbaren Schild geschützt. Es kann pro KR maximal (M):2 SP und insgesamt (M) SP abhalten. RS/LE | D49: 3 | E49: 40 | F49: 3 | G49: sofort | H49: 40 | I49: min | J49: 20 | K49: 40
A50: artefakt_korpi_ignorieren | B50: Korpi ignorieren | C50: Der Magus ermöglicht es einem Gegenstand, magische Korpi zu ignorieren. So ist es dem Gegenstand möglich, durch jede Art von Barriere zu dringen, als wäre sie nicht existent. Diese Gegenstände können von Magiekorpi nicht wahrgenommen werden. Grad 1 „Manaschild“ wird nicht ignoriert (gilt nicht als Magiekorpus), Angriffe auf beseelte Magie-Korpi wie z.B. (Elementar-)Geister und Artefakte unmöglich. | D50: 5 | E50: 72 | F50: 5 | G50: sofort | H50: 40 | I50: min
A51: artefakt_kampfmaschine | B51: Kampfmaschine | C51: Der Träger verschmilzt mit der Artefakt-Waffe. Dies führt zu einer Erleichterung auf alle kampfrelevanten Proben, bei denen die Waffe zum Einsatz kommt. | D51: 6 | E51: 400 | F51: 6 | G51: sofort | H51: 40 | I51: sec | J51: Bonus | K51: 7
A52: artefakt_attributs_artefakt_aura | B52: Attributs-Artefakt (Aura) | C52: Aura wird fuer einen magischen Tag magisch erhoeht. Nur permanent (kein Einmal-Artefakt), Verfuegbarkeit nur ueber den Spielleiter, nicht regulaer erwerbbar. Bezieht sich auf das Attribut 'att_aura' im Werte-Sheet (Kategorie 'Attribute': Aura/Essenz/Glueck/Karma/Magie/Vitalitaet/Weisheit - NICHT die 10 Eigenschaften Athletik...Willenskraft). | D52: 4 | E52: 24 | F52: 4 | G52: sofort | H52: 24 | I52: h | J52: Att + | L52: att_aura
A53: artefakt_attributs_artefakt_essenz | B53: Attributs-Artefakt (Essenz) | C53: Essenz wird fuer einen magischen Tag magisch erhoeht. Nur permanent (kein Einmal-Artefakt), Verfuegbarkeit nur ueber den Spielleiter, nicht regulaer erwerbbar. Bezieht sich auf das Attribut 'att_essenz' im Werte-Sheet (Kategorie 'Attribute': Aura/Essenz/Glueck/Karma/Magie/Vitalitaet/Weisheit - NICHT die 10 Eigenschaften Athletik...Willenskraft). | D53: 4 | E53: 24 | F53: 4 | G53: sofort | H53: 24 | I53: h | J53: Att + | L53: att_essenz
A54: artefakt_attributs_artefakt_glueck | B54: Attributs-Artefakt (Glück) | C54: Glück wird fuer einen magischen Tag magisch erhoeht. Nur permanent (kein Einmal-Artefakt), Verfuegbarkeit nur ueber den Spielleiter, nicht regulaer erwerbbar. Bezieht sich auf das Attribut 'att_glueck' im Werte-Sheet (Kategorie 'Attribute': Aura/Essenz/Glueck/Karma/Magie/Vitalitaet/Weisheit - NICHT die 10 Eigenschaften Athletik...Willenskraft). | D54: 4 | E54: 24 | F54: 4 | G54: sofort | H54: 24 | I54: h | J54: Att + | L54: att_glueck
A55: artefakt_attributs_artefakt_karma | B55: Attributs-Artefakt (Karma) | C55: Karma wird fuer einen magischen Tag magisch erhoeht. Nur permanent (kein Einmal-Artefakt), Verfuegbarkeit nur ueber den Spielleiter, nicht regulaer erwerbbar. Bezieht sich auf das Attribut 'att_karma' im Werte-Sheet (Kategorie 'Attribute': Aura/Essenz/Glueck/Karma/Magie/Vitalitaet/Weisheit - NICHT die 10 Eigenschaften Athletik...Willenskraft). | D55: 4 | E55: 24 | F55: 4 | G55: sofort | H55: 24 | I55: h | J55: Att + | L55: att_karma
A56: artefakt_attributs_artefakt_magie | B56: Attributs-Artefakt (Magie) | C56: Magie wird fuer einen magischen Tag magisch erhoeht. Nur permanent (kein Einmal-Artefakt), Verfuegbarkeit nur ueber den Spielleiter, nicht regulaer erwerbbar. Bezieht sich auf das Attribut 'att_magie' im Werte-Sheet (Kategorie 'Attribute': Aura/Essenz/Glueck/Karma/Magie/Vitalitaet/Weisheit - NICHT die 10 Eigenschaften Athletik...Willenskraft). | D56: 4 | E56: 24 | F56: 4 | G56: sofort | H56: 24 | I56: h | J56: Att + | L56: att_magie
A57: artefakt_attributs_artefakt_vitalitaet | B57: Attributs-Artefakt (Vitalität) | C57: Vitalität wird fuer einen magischen Tag magisch erhoeht. Nur permanent (kein Einmal-Artefakt), Verfuegbarkeit nur ueber den Spielleiter, nicht regulaer erwerbbar. Bezieht sich auf das Attribut 'att_vitalitaet' im Werte-Sheet (Kategorie 'Attribute': Aura/Essenz/Glueck/Karma/Magie/Vitalitaet/Weisheit - NICHT die 10 Eigenschaften Athletik...Willenskraft). | D57: 4 | E57: 24 | F57: 4 | G57: sofort | H57: 24 | I57: h | J57: Att + | L57: att_vitalitaet
A58: artefakt_attributs_artefakt_weisheit | B58: Attributs-Artefakt (Weisheit) | C58: Weisheit wird fuer einen magischen Tag magisch erhoeht. Nur permanent (kein Einmal-Artefakt), Verfuegbarkeit nur ueber den Spielleiter, nicht regulaer erwerbbar. Bezieht sich auf das Attribut 'att_weisheit' im Werte-Sheet (Kategorie 'Attribute': Aura/Essenz/Glueck/Karma/Magie/Vitalitaet/Weisheit - NICHT die 10 Eigenschaften Athletik...Willenskraft). | D58: 4 | E58: 24 | F58: 4 | G58: sofort | H58: 24 | I58: h | J58: Att + | L58: att_weisheit
A59: artefakt_eigenschafts_artefakt_athletik | B59: Eigenschafts-Artefakt (Athletik) | C59: Athletik wird fuer einen magischen Tag magisch erhoeht. Nur permanent (kein Einmal-Artefakt). Bezieht sich auf die Eigenschaft 'Athletik' im Werte-Sheet (Kategorie 'Eigenschaften': Athletik/Ausstrahlung/Geschicklichkeit/Intelligenz/Konstitution/Mut/Schnelligkeit/Sinnesschaerfe/Staerke/Willenskraft). | D59: 4 | E59: 24 | F59: 4 | G59: sofort | H59: 24 | I59: h | J59: Eig + | L59: Athletik
A60: artefakt_eigenschafts_artefakt_ausstrahlung | B60: Eigenschafts-Artefakt (Ausstrahlung) | C60: Ausstrahlung wird fuer einen magischen Tag magisch erhoeht. Nur permanent (kein Einmal-Artefakt). Bezieht sich auf die Eigenschaft 'Ausstrahlung' im Werte-Sheet (Kategorie 'Eigenschaften': Athletik/Ausstrahlung/Geschicklichkeit/Intelligenz/Konstitution/Mut/Schnelligkeit/Sinnesschaerfe/Staerke/Willenskraft). | D60: 4 | E60: 24 | F60: 4 | G60: sofort | H60: 24 | I60: h | J60: Eig + | L60: Ausstrahlung
A61: artefakt_eigenschafts_artefakt_geschicklichkeit | B61: Eigenschafts-Artefakt (Geschicklichkeit) | C61: Geschicklichkeit wird fuer einen magischen Tag magisch erhoeht. Nur permanent (kein Einmal-Artefakt). Bezieht sich auf die Eigenschaft 'Geschicklichkeit' im Werte-Sheet (Kategorie 'Eigenschaften': Athletik/Ausstrahlung/Geschicklichkeit/Intelligenz/Konstitution/Mut/Schnelligkeit/Sinnesschaerfe/Staerke/Willenskraft). | D61: 4 | E61: 24 | F61: 4 | G61: sofort | H61: 24 | I61: h | J61: Eig + | L61: Geschicklichkeit
A62: artefakt_eigenschafts_artefakt_intelligenz | B62: Eigenschafts-Artefakt (Intelligenz) | C62: Intelligenz wird fuer einen magischen Tag magisch erhoeht. Nur permanent (kein Einmal-Artefakt). Bezieht sich auf die Eigenschaft 'Intelligenz' im Werte-Sheet (Kategorie 'Eigenschaften': Athletik/Ausstrahlung/Geschicklichkeit/Intelligenz/Konstitution/Mut/Schnelligkeit/Sinnesschaerfe/Staerke/Willenskraft). | D62: 4 | E62: 24 | F62: 4 | G62: sofort | H62: 24 | I62: h | J62: Eig + | L62: Intelligenz
A63: artefakt_eigenschafts_artefakt_konstitution | B63: Eigenschafts-Artefakt (Konstitution) | C63: Konstitution wird fuer einen magischen Tag magisch erhoeht. Nur permanent (kein Einmal-Artefakt). Bezieht sich auf die Eigenschaft 'Konstitution' im Werte-Sheet (Kategorie 'Eigenschaften': Athletik/Ausstrahlung/Geschicklichkeit/Intelligenz/Konstitution/Mut/Schnelligkeit/Sinnesschaerfe/Staerke/Willenskraft). | D63: 4 | E63: 24 | F63: 4 | G63: sofort | H63: 24 | I63: h | J63: Eig + | L63: Konstitution
... A68: artefakt_eigenschafts_artefakt_willenskraft | B68: Eigenschafts-Artefakt (Willenskraft) | C68: Willenskraft wird fuer einen magischen Tag magisch erhoeht. Nur permanent (kein Einmal-Artefakt). Bezieht sich auf die Eigenschaft 'Willenskraft' im Werte-Sheet (Kategorie 'Eigenschaften': Athletik/Ausstrahlung/Geschicklichkeit/Intelligenz/Konstitution/Mut/Schnelligkeit/Sinnesschaerfe/Staerke/Willenskraft). | D68: 4 | E68: 24 | F68: 4 | G68: sofort | H68: 24 | I68: h | J68: Eig + | L68: Willenskraft

Sheet Artefakt-Kosten
A1: Referenz | B1: Name | C1: Artefakt-Grad | D1: Kosten-einmalig | E1: Verfuegbarkeit-einmalig | F1: Kosten-permanent | G1: Verfuegbarkeit-permanent
A2: artefakt_licht | B2: Licht | C2: 1 | D2: 76 | E2: 3 | F2: 525 | G2: 5
A3: artefakt_licht | B3: Licht | C3: 2 | D3: 218 | E3: 3 | F3: 975 | G3: 5
A4: artefakt_licht | B4: Licht | C4: 3 | D4: 552 | E4: 3 | F4: 1730 | G4: 5
A5: artefakt_licht | B5: Licht | C5: 4 | D5: 920 | E5: 4 | F5: 2368 | G5: 5
A6: artefakt_licht | B6: Licht | C6: 5 | D6: 1590 | E6: 5 | F6: 3450 | G6: 5
A7: artefakt_licht | B7: Licht | C7: 6 | D7: 3020 | E7: 6 | F7: 5860 | G7: 6
A8: artefakt_licht | B8: Licht | C8: 7 | D8: 8780 | E8: 7 | F8: 14080 | G8: 7
A9: artefakt_magisches_makeover | B9: Magisches Makeover | C9: 1 | D9: 120 | E9: 3 | F9: 645 | G9: 5
A10: artefakt_magisches_makeover | B10: Magisches Makeover | C10: 2 | D10: 372 | E10: 3 | F10: 1275 | G10: 5
A11: artefakt_magisches_makeover | B11: Magisches Makeover | C11: 3 | D11: 932 | E11: 3 | F11: 2322 | G11: 5
A12: artefakt_magisches_makeover | B12: Magisches Makeover | C12: 4 | D12: 1480 | E12: 4 | F12: 3656 | G12: 5
A13: artefakt_magisches_makeover | B13: Magisches Makeover | C13: 5 | D13: 2370 | E13: 5 | F13: 5730 | G13: 5
... A351: artefakt_kampfmaschine | B351: Kampfmaschine | C351: 7 | D351: 61040 | E351: 7 | F351: 146680 | G351: 7
A352: artefakt_attributs_artefakt_aura | B352: Attributs-Artefakt (Aura) | C352: 1 | F352: 705 | G352: Meister
A353: artefakt_attributs_artefakt_aura | B353: Attributs-Artefakt (Aura) | C353: 2 | F353: 1475 | G353: Meister
A354: artefakt_attributs_artefakt_aura | B354: Attributs-Artefakt (Aura) | C354: 3 | F354: 2618 | G354: Meister
A355: artefakt_attributs_artefakt_aura | B355: Attributs-Artefakt (Aura) | C355: 4 | F355: 4024 | G355: Meister
A356: artefakt_attributs_artefakt_aura | B356: Attributs-Artefakt (Aura) | C356: 5 | F356: 6642 | G356: Meister
A357: artefakt_attributs_artefakt_aura | B357: Attributs-Artefakt (Aura) | C357: 6 | F357: 9780 | G357: Meister
A358: artefakt_attributs_artefakt_aura | B358: Attributs-Artefakt (Aura) | C358: 7 | F358: 18840 | G358: Meister
A359: artefakt_attributs_artefakt_essenz | B359: Attributs-Artefakt (Essenz) | C359: 1 | F359: 705 | G359: Meister
A360: artefakt_attributs_artefakt_essenz | B360: Attributs-Artefakt (Essenz) | C360: 2 | F360: 1475 | G360: Meister
A361: artefakt_attributs_artefakt_essenz | B361: Attributs-Artefakt (Essenz) | C361: 3 | F361: 2618 | G361: Meister
A362: artefakt_attributs_artefakt_essenz | B362: Attributs-Artefakt (Essenz) | C362: 4 | F362: 4024 | G362: Meister
A363: artefakt_attributs_artefakt_essenz | B363: Attributs-Artefakt (Essenz) | C363: 5 | F363: 6642 | G363: Meister
... A400: artefakt_attributs_artefakt_weisheit | B400: Attributs-Artefakt (Weisheit) | C400: 7 | F400: 18840 | G400: Meister
A401: artefakt_eigenschafts_artefakt_athletik | B401: Eigenschafts-Artefakt (Athletik) | C401: 1 | F401: 705 | G401: 5
A402: artefakt_eigenschafts_artefakt_athletik | B402: Eigenschafts-Artefakt (Athletik) | C402: 2 | F402: 1408 | G402: 5
A403: artefakt_eigenschafts_artefakt_athletik | B403: Eigenschafts-Artefakt (Athletik) | C403: 3 | F403: 2438 | G403: 5
A404: artefakt_eigenschafts_artefakt_athletik | B404: Eigenschafts-Artefakt (Athletik) | C404: 4 | F404: 3754 | G404: 5
A405: artefakt_eigenschafts_artefakt_athletik | B405: Eigenschafts-Artefakt (Athletik) | C405: 5 | F405: 6282 | G405: 5
A406: artefakt_eigenschafts_artefakt_athletik | B406: Eigenschafts-Artefakt (Athletik) | C406: 6 | F406: 9030 | G406: 6
A407: artefakt_eigenschafts_artefakt_athletik | B407: Eigenschafts-Artefakt (Athletik) | C407: 7 | F407: 15240 | G407: 7
A408: artefakt_eigenschafts_artefakt_ausstrahlung | B408: Eigenschafts-Artefakt (Ausstrahlung) | C408: 1 | F408: 705 | G408: 5
A409: artefakt_eigenschafts_artefakt_ausstrahlung | B409: Eigenschafts-Artefakt (Ausstrahlung) | C409: 2 | F409: 1408 | G409: 5
A410: artefakt_eigenschafts_artefakt_ausstrahlung | B410: Eigenschafts-Artefakt (Ausstrahlung) | C410: 3 | F410: 2438 | G410: 5
A411: artefakt_eigenschafts_artefakt_ausstrahlung | B411: Eigenschafts-Artefakt (Ausstrahlung) | C411: 4 | F411: 3754 | G411: 5
A412: artefakt_eigenschafts_artefakt_ausstrahlung | B412: Eigenschafts-Artefakt (Ausstrahlung) | C412: 5 | F412: 6282 | G412: 5
... A470: artefakt_eigenschafts_artefakt_willenskraft | B470: Eigenschafts-Artefakt (Willenskraft) | C470: 7 | F470: 15240 | G470: 7

Sheet Verfuegbarkeit-Modifikatoren
A1: Kategorie | B1: Auspraegung | C1: Faktor
A2: Herstellungsort | B2: Import, wird nicht hergestellt | C2: 0.5
A3: Herstellungsort | B3: Teilweiser Import, Herstellung im Reich | C3: 0.75
A4: Herstellungsort | B4: Herstellung im Reich | C4: 1
A5: Herstellungsort | B5: Herstellung in der Region | C5: 1.5
A6: Herstellungsort | B6: Herstellung direkt vor Ort | C6: 2
A7: Siedlungsgroesse | B7: Wildnis | C7: 0
A8: Siedlungsgroesse | B8: Siedlung | C8: 0.4
A9: Siedlungsgroesse | B9: Dorf | C9: 0.7
A10: Siedlungsgroesse | B10: Kleinstadt | C10: 1
A11: Siedlungsgroesse | B11: Stadt | C11: 1.1
A12: Siedlungsgroesse | B12: Grossstadt | C12: 1.25
A13: Siedlungsgroesse | B13: Metropole | C13: 1.4
... A26: Haendler | B26: Grosser spezialisierter Haendler | C26: 1.5
A28: Grund-Verfuegbarkeit (Legende) | B28: Grund-Verfuegbarkeit (Legende) | C28: Grund-Verfuegbarkeit (Legende)
A29: Wert | B29: Bedeutung | C29: Optionaler Wuerfelwurf (falls Meister unschluessig)
A30: 1 | B30: Immer | C30: 1-29
A31: 2 | B31: Fast immer | C31: 1-20
A32: 3 | B32: Haeufig | C32: 1-14
A33: 4 | B33: Selten | C33: 1-7
A34: 5 | B34: Fast nie | C34: 1-3
A35: 6 | B35: Nie | C35: 21 (exakt)
A36: 7 | B36: Einzigartig | C36: 29 zwei mal hintereinander

Sheet Ruestung-Basis
A1: Ruestungsteil | B1: Lage | C1: RS-Basis | D1: BE-Basis | E1: Verfuegbarkeit-NW | F1: Verfuegbarkeit-AW | G1: Materialkosten | H1: Arbeitszeit-Tag-Basis
A2: Leichte Stoffrüstung | B2: 1 | C2: 1 | D2: 1 | E2: 1 | F2: 1 | G2: 16 | H2: 1
A3: Stoffrüstung | B3: 1 | C3: 2 | D3: 2 | E3: 1 | F3: 1 | G3: 32 | H3: 1
A4: Schwere Stoffrüstung | B4: 1 | C4: 3 | D4: 3 | E4: 1 | F4: 1 | G4: 48 | H4: 1
A5: Leichte Lederrüstung | B5: 2 | C5: 3 | D5: 3 | E5: 1 | F5: 1 | G5: 14 | H5: 2
A6: Lederrüstung | B6: 2 | C6: 4 | D6: 4 | E6: 1 | F6: 1 | G6: 28 | H6: 2
A7: Schwere Lederrüstung | B7: 2 | C7: 5 | D7: 5 | E7: 1 | F7: 1 | G7: 48 | H7: 2
A8: Eisen-Kettenpanzer | B8: 3 | C8: 4 | D8: 4 | E8: 1 | F8: 1 | G8: 300 | H8: 10
A9: Stahl-Kettenpanzer | B9: 3 | C9: 5 | D9: 4 | E9: 2 | F9: 1 | G9: 1050 | H9: 10
A10: Schwerer Eisen-Kettenpanzer | B10: 3 | C10: 6 | D10: 5 | E10: 1 | F10: 1 | G10: 480 | H10: 15
A11: Faltstahl-Kettenpanzer | B11: 3 | C11: 7 | D11: 5 | E11: 5 | F11: 3 | G11: 1500 | H11: 10
A12: Schwerer Stahl-Kettenpanzer | B12: 3 | C12: 8 | D12: 6 | E12: 2 | F12: 1 | G12: 1680 | H12: 15
A13: Schwerer Faltstahl-Kettenpanzer | B13: 3 | C13: 9 | D13: 6 | E13: 6 | F13: 4 | G13: 2400 | H13: 15
... A21: Schwerer Faltstahlpanzer | B21: 4 | C21: 12 | D21: 10 | E21: 6 | F21: 4 | G21: 4507 | H21: 10

Sheet Ruestung-Addons
A1: Addon | B1: Lage | C1: RS | D1: BE | E1: Verfuegbarkeit-NW | F1: Verfuegbarkeit-AW
A2: Leichte Drachenschuppen | B2: 5 | C2: 3 | D2: 2 | E2: 6 | F2: 6
A3: Drachenschuppen | B3: 5 | C3: 5 | D3: 4 | E3: 6 | F3: 6
A4: Schwere Drachenschuppen | B4: 5 | C4: 7 | D4: 6 | E4: 6 | F4: 6
A5: Spinnweben | B5: 5 | C5: 0 | D5: 0 | E5: 7 | F5: 7

Sheet Ruestung-Verarbeitung
A1: Verarbeitung | B1: RS-Mod | C1: BE-Mod | D1: Verfuegbarkeit-NW | E1: Verfuegbarkeit-AW | F1: Lohn-pro-Tag
A2: Gesellenarbeit | D2: 1 | E2: 1 | F2: 6
A3: Meisterarbeit | B3: 1 | D3: 3 | E3: 2 | F3: 65
A4: Großmeisterarbeit | B4: 2 | D4: 5 | E4: 3 | F4: 71
A5: Einzelstück | B5: 2 | C5: -1 | D5: 7 | E5: 7 | F5: 142

Sheet Ruestung-Anpassung
A1: Anpassung | B1: RS-Mod | C1: BE-Mod | D1: Verfuegbarkeit-NW | E1: Verfuegbarkeit-AW | F1: Zusaetzliche-Tage
A2: völlig unpassend | C2: 2 | D2: 1 | E2: 1 | F2: 0
A3: von der Stange | C3: 0 | D3: 1 | E3: 1 | F3: 0
A4: angepasst | C4: -1 | D4: 3 | E4: 2 | F4: 2
A5: perfekt angepasst | C5: -2 | D5: 5 | E5: 3 | F5: 4

Sheet Munition-Feuerwaffen
A1: Geeignet für | B1: Art | C1: Kaliber | D1: Preis (1Schuss) | E1: Preis-10-Schuss | F1: Preis-50-Schuss | G1: Preis-100-Schuss | H1: Preis-500-Schuss | I1: Preis-1000-Schuss | J1: Besonderheiten
A2: Vorderlader | B2: S.P.&Blei | C2: 12 | D2: 0.366912 | E2: 3.6691 | F2: 18.3456 | G2: 36.6912 | H2: 183.456 | I2: 366.912
A3: Vorderlader | B3: S.P.&Blei | C3: 13 | D3: 0.374556 | E3: 3.7456 | F3: 18.7278 | G3: 37.4556 | H3: 187.278 | I3: 374.556
A4: Vorderlader | B4: S.P.&Blei | C4: 14 | D4: 0.3822 | E4: 3.822 | F4: 19.11 | G4: 38.22 | H4: 191.1 | I4: 382.2
A5: Vorderlader | B5: S.P.&Blei | C5: 15 | D5: 0.389844 | E5: 3.8984 | F5: 19.4922 | G5: 38.9844 | H5: 194.922 | I5: 389.844
A6: Vorderlader | B6: S.P.&Blei | C6: 16 | D6: 0.397488 | E6: 3.9749 | F6: 19.8744 | G6: 39.7488 | H6: 198.744 | I6: 397.488
A7: Vorderlader | B7: S.P.&Blei | C7: 17 | D7: 0.405132 | E7: 4.0513 | F7: 20.2566 | G7: 40.5132 | H7: 202.566 | I7: 405.132
A8: Vorderlader | B8: S.P.&Blei | C8: 18 | D8: 0.412776 | E8: 4.1278 | F8: 20.6388 | G8: 41.2776 | H8: 206.388 | I8: 412.776
A9: Vorderlader | B9: S.P.&Blei | C9: 19 | D9: 0.42042 | E9: 4.2042 | F9: 21.021 | G9: 42.042 | H9: 210.21 | I9: 420.42
A10: Vorderlader | B10: S.P.&Blei | C10: 20 | D10: 0.428064 | E10: 4.2806 | F10: 21.4032 | G10: 42.8064 | H10: 214.032 | I10: 428.064
A11: Vorderlader | B11: S.P.&Blei | C11: 21 | D11: 0.435708 | E11: 4.3571 | F11: 21.7854 | G11: 43.5708 | H11: 217.854 | I11: 435.708
A12: Vorderlader | B12: S.P.&Blei | C12: 22 | D12: 0.443352 | E12: 4.4335 | F12: 22.1676 | G12: 44.3352 | H12: 221.676 | I12: 443.352
A13: Vorderlader | B13: S.P.&Blei | C13: 23 | D13: 0.450996 | E13: 4.51 | F13: 22.5498 | G13: 45.0996 | H13: 225.498 | I13: 450.996
A14: Vorderlader | B14: VL. Papierpatrone | C14: 12 | D14: 0.408855 | E14: 4.0886 | F14: 20.4428 | G14: 40.8855 | H14: 204.4275 | I14: 408.855 | J14: Reduziert die Nachladezeit um 5 Sekunden
A15: Vorderlader | B15: VL. Papierpatrone | C15: 13 | D15: 0.4151775 | E15: 4.1518 | F15: 20.7589 | G15: 41.5178 | H15: 207.5888 | I15: 415.1775 | J15: Reduziert die Nachladezeit um 5 Sekunden
A16: Vorderlader | B16: VL. Papierpatrone | C16: 14 | D16: 0.4215 | E16: 4.215 | F16: 21.075 | G16: 42.15 | H16: 210.75 | I16: 421.5 | J16: Reduziert die Nachladezeit um 5 Sekunden
A17: Vorderlader | B17: VL. Papierpatrone | C17: 15 | D17: 0.4278225 | E17: 4.2782 | F17: 21.3911 | G17: 42.7822 | H17: 213.9112 | I17: 427.8225 | J17: Reduziert die Nachladezeit um 5 Sekunden
A18: Vorderlader | B18: VL. Papierpatrone | C18: 16 | D18: 0.434145 | E18: 4.3415 | F18: 21.7073 | G18: 43.4145 | H18: 217.0725 | I18: 434.145 | J18: Reduziert die Nachladezeit um 5 Sekunden
A19: Vorderlader | B19: VL. Papierpatrone | C19: 17 | D19: 0.4404675 | E19: 4.4047 | F19: 22.0234 | G19: 44.0468 | H19: 220.2338 | I19: 440.4675 | J19: Reduziert die Nachladezeit um 5 Sekunden
A20: Vorderlader | B20: VL. Papierpatrone | C20: 18 | D20: 0.44679 | E20: 4.4679 | F20: 22.3395 | G20: 44.679 | H20: 223.395 | I20: 446.79 | J20: Reduziert die Nachladezeit um 5 Sekunden
A21: Vorderlader | B21: VL. Papierpatrone | C21: 19 | D21: 0.4531125 | E21: 4.5311 | F21: 22.6556 | G21: 45.3113 | H21: 226.5563 | I21: 453.1125 | J21: Reduziert die Nachladezeit um 5 Sekunden
A22: Vorderlader | B22: VL. Papierpatrone | C22: 20 | D22: 0.459435 | E22: 4.5944 | F22: 22.9718 | G22: 45.9435 | H22: 229.7175 | I22: 459.435 | J22: Reduziert die Nachladezeit um 5 Sekunden
A23: Vorderlader | B23: VL. Papierpatrone | C23: 21 | D23: 0.4657575 | E23: 4.6576 | F23: 23.2879 | G23: 46.5758 | H23: 232.8788 | I23: 465.7575 | J23: Reduziert die Nachladezeit um 5 Sekunden
A24: Vorderlader | B24: VL. Papierpatrone | C24: 22 | D24: 0.47208 | E24: 4.7208 | F24: 23.604 | G24: 47.208 | H24: 236.04 | I24: 472.08 | J24: Reduziert die Nachladezeit um 5 Sekunden
A25: Vorderlader | B25: VL. Papierpatrone | C25: 23 | D25: 0.4784025 | E25: 4.784 | F25: 23.9201 | G25: 47.8403 | H25: 239.2013 | I25: 478.4025 | J25: Reduziert die Nachladezeit um 5 Sekunden
A26: Hinterlader | B26: Papierpatrone | C26: 16 | D26: 0.68066667 | E26: 6.8067 | F26: 34.0333 | G26: 68.0667 | H26: 340.3333 | I26: 680.6667
A27: Hinterlader | B27: Papierpatrone | C27: 17 | D27: 0.70108667 | E27: 7.0109 | F27: 35.0543 | G27: 70.1087 | H27: 350.5433 | I27: 701.0867
A28: Hinterlader | B28: Papierpatrone | C28: 18 | D28: 0.72150667 | E28: 7.2151 | F28: 36.0753 | G28: 72.1507 | H28: 360.7533 | I28: 721.5067
A29: Hinterlader | B29: Papierpatrone | C29: 19 | D29: 0.74192667 | E29: 7.4193 | F29: 37.0963 | G29: 74.1927 | H29: 370.9633 | I29: 741.9267
A30: Patronenwaffen | B30: Messingpatrone | C30: 5 | D30: 0.4036032 | E30: 7.814 | F30: 39.07 | G30: 78.14 | H30: 390.7 | I30: 781.4
A31: Patronenwaffen | B31: Messingpatrone | C31: 6 | D31: 0.445104 | E31: 8.2516 | F31: 41.2579 | G31: 82.5158 | H31: 412.5792 | I31: 825.1584
A32: Patronenwaffen | B32: Messingpatrone | C32: 7 | D32: 0.718784 | E32: 8.6892 | F32: 43.4458 | G32: 86.8917 | H32: 434.4584 | I32: 868.9168
A33: Patronenwaffen | B33: Messingpatrone | C33: 8 | D33: 0.8251584 | E33: 9.1268 | F33: 45.6338 | G33: 91.2675 | H33: 456.3376 | I33: 912.6752
A34: Patronenwaffen | B34: Messingpatrone | C34: 9 | D34: 0.8689168 | E34: 9.5643 | F34: 47.8217 | G34: 95.6434 | H34: 478.2168 | I34: 956.4336
A35: Patronenwaffen | B35: Messingpatrone | C35: 10 | D35: 0.9126752 | E35: 10.0019 | F35: 50.0096 | G35: 100.0192 | H35: 500.096 | I35: 1000.192
A36: Patronenwaffen | B36: Messingpatrone | C36: 11 | D36: 0.9564336
A37: Patronenwaffen | B37: Messingpatrone | C37: 12 | D37: 1.000192
A38: Harpunengewehr | B38: Harpune | C38: 16 | D38: 6.88384
A39: Harpunengewehr | B39: Harpune | C39: 17 | D39: 6.88384

Sheet Munition-Ressourcen
A1: Material | B1: Dublonen-pro-KG | C1: Massenfabrikation-Dublonen-pro-KG
A2: Messing | B2: 32 | C2: 25.6
A3: Blei | B3: 12 | C3: 9.6
A4: Schwarzpulver | B4: 85 | C4: 68
A5: Papier | B5: 15 | C5: 12
A7: Handwerker/Anlage | B7: Dublonen-pro-Tag | C7: Hinweis
A8: Kugelgießer | B8: 1
A9: (Schwarz-)Pulvermischer | B9: 1.5
A10: Munitionsmanufaktur (Pauschale/Tag) | B10: 20 | C10: Beinhaltet Manufakturkosten und 3 Vorarbeiter
A11: Komplette Manufaktur | B11: 38 | C11: Beinhaltet Manufakturkosten, 3 Vorarbeiter, 6 (Schwarz-)Pulvermischer, 9 Kugelgiesser
A13: Patronentyp | B13: Schwarzpulver-kg | C13: Blei-kg | D13: Papier-kg | E13: Messing-kg | F13: Gesamtgewicht-kg | G13: Manufaktur-Ausstoss-pro-Tag | H13: Herstellungskosten-pro-Schuss | I13: Materialkosten-pro-Schuss | J13: Gesamtkosten-pro-Schuss
A14: Blei (+Schwarzpulver) | B14: 0.005 | C14: 0.004 | F14: 0.009 | G14: 10000 | H14: 0.0038 | I14: 0.3784 | J14: 0.3822
A15: VL. Papierpatrone | B15: 0.005 | C15: 0.004 | D15: 0.002 | F15: 0.011 | G15: 4000 | H15: 0.0095 | I15: 0.412 | J15: 0.4215
A16: Papierpatrone | B16: 0.005 | C16: 0.005 | D16: 0.002 | E16: 0.01 | F16: 0.022 | G16: 3000 | H16: 0.012667 | I16: 0.668 | J16: 0.680667
A17: Messingpatrone | B17: 0.005 | C17: 0.004 | E17: 0.015 | F17: 0.024 | G17: 2000 | H17: 0.019 | I17: 0.7624 | J17: 0.7814

Sheet Boegen-Basis
A1: Name | B1: Volk | C1: Material | D1: Min-Staerke | E1: Schaden | F1: RB | G1: Modifikatoren-roh | H1: RW-m | I1: Ladezeit-sec | J1: Nachlade-Teiler | K1: Preis | L1: Verfuegbarkeit-NW | M1: Verfuegbarkeit-AW | N1: Verfuegbarkeit-Volk
A2: Improvisierter Bogen | B2: Alle | C2: Holz | D2: 7 | E2: 1W4 | F2: 0 | G2: +4/0/-15/x/x | H2: 15m | I2: 6 | J2: 9 | K2: 0.001 | L2: 1 | M2: 1 | N2: 1
A3: Kurzbogen | B3: Goblin | C3: Holz | D3: 5 | E3: 1W4+1 | F3: 1 | G3: +8/+2/-13/-25/x/x | H3: 15m | I3: 6 | J3: 9 | K3: 50 | L3: 3 | M3: 4 | N3: 1
A4: Jagdbogen | B4: Goblin | C4: Holz | D4: 7 | E4: 1W6+1 | F4: 2 | G4: +6/+2/-8/-22/x/x | H4: 20m | I4: 6 | J4: 9 | K4: 60 | L4: 3 | M4: 4 | N4: 1
A5: Langbogen | B5: Goblin | C5: Holz | D5: 10 | E5: 1W6+1 | F5: 3 | G5: +5/+2/-8/-20/-30 | H5: 60m | I5: 7 | J5: 9 | K5: 100 | L5: 3 | M5: 4 | N5: 1
A6: Froggler-Bogen | B6: Goblin | C6: Holz | D6: 7 | E6: 1W6 | F6: 1 | G6: +6/+2/-8/-22/x/x | H6: 25m | I6: 7 | J6: 9 | K6: 55 | L6: 2 | M6: 3 | N6: 1
A7: Bogen | B7: Indianer | C7: Holz | D7: 9 | E7: 1W6+1 | F7: 2 | G7: +7/+2/-8/-23/x | H7: 25m | I7: 6 | J7: 9 | K7: 1 | L7: 5 | M7: 6 | N7: 1
A8: Langbogen | B8: Indianer | C8: Holz | D8: 12 | E8: 1W6+1 | F8: 3 | G8: +6/+2/-8/-21/x | H8: 75m | I8: 7 | J8: 9 | K8: 2 | L8: 6 | M8: 6 | N8: 4
A9: Schwarzfels-Bogen | B9: Indianer | C9: Holz, Schwarzfels, Seil, Leim | D9: 15 | E9: 1W8+1 | F9: 3 | G9: +6/+2/-7/-22/x | H9: 40m | I9: 9 | J9: 9 | K9: 1500 | L9: 6 | M9: 6 | N9: 6
A10: Kurzbogen | B10: Daikini | C10: Holz | D10: 9 | E10: 1W4+1 | F10: 2 | G10: +7/+2/-11/-25/x | H10: 20m | I10: 6 | J10: 9 | K10: 60 | L10: 6 | M10: 6 | N10: 1
A11: Jagdbogen | B11: Daikini | C11: Holz | D11: 11 | E11: 1W6+1 | F11: 2 | G11: +6/+2/-8/-22/x | H11: 27m | I11: 6 | J11: 9 | K11: 80 | L11: 6 | M11: 6 | N11: 1
A12: Langbogen | B12: Daikini | C12: Holz | D12: 12 | E12: 1W6+1 | F12: 3 | G12: +5/+2/-8/-20/-30 | H12: 50m | I12: 7 | J12: 9 | K12: 125 | L12: 6 | M12: 6 | N12: 2
A13: Asymmetrischer Bogen | B13: Daikini | C13: Holz | D13: 13 | E13: 1W6+1 | F13: 3 | G13: +7/+2/-8/-20/-30 | H13: 75m | I13: 6 | J13: 9 | K13: 1000 | L13: 6 | M13: 6 | N13: 6
... A42: Drachenbogen | B42: Spezial/Legendaer | C42: Holz, Kaiserdrachen-Bein, Leim | D42: 21 | E42: 1W12+1 | F42: 3 | G42: +6/+1/-13/-29/x/x | H42: 25m | I42: 8 | J42: 9 | K42: 1000000 | L42: 7 | M42: 7 | N42: 7

Sheet Pfeile-Basis
A1: Name | B1: Schaden-Mod | C1: RB-Mod | D1: RW-Mod-Spalte1 | E1: RW-Mod-Spalte2 | F1: Preis | G1: Verfuegbarkeit-NW | H1: Verfuegbarkeit-AW | I1: Verfuegbarkeit-Volk | J1: BE | K1: Spezialitaeten
A2: Improvisierter-Pfeil | B2: +1W4 | C2: 0 | D2: -15m | E2: -15m | F2: nichts | J2: 1
A3: Holzspitzen-Pfeil | B3: +1W6 | C3: 0 | D3: -7m | E3: -7m | F3: 50 FZ | G3: 1 | H3: 5 | J3: 1
A4: Knochenspitzen-Pfeil | B4: +1W6 | C4: 0 | D4: 0 | E4: 0 | F4: 100FZ | G4: 4 | H4: 4 | J4: 1
A5: Steinspitzen-Pfeil | B5: +1W8 | C5: 0 | D5: 0 | E5: 0 | F5: 200 FZ | G5: 1 | H5: 4 | J5: 1
A6: Diamantspatspitzen-Pfeil | B6: +1W8 | C6: +6 | D6: 0 | E6: 0 | F6: 1,5D | G6: 7 | H6: 7 | I6: 2 | J6: 1 | K6: Wird durch UV-Strahlung zersetzt
A7: Bronzespitzen-Pfeil | B7: +1W8 | C7: +1 | D7: 0 | E7: 0 | F7: 300 FZ | G7: 4 | H7: 3 | J7: 1
A8: Eisenspitzen-Pfeil | B8: +1W8 | C8: +2 | D8: 0 | E8: 0 | F8: 500 FZ | G8: 3 | H8: 1 | J8: 1
A9: Stahlspitzen-Pfeil | B9: +1W8 | C9: +3 | D9: 0 | E9: 0 | F9: 1D | G9: 4 | H9: 3 | J9: 1
A10: Edelstahlspitzen-Pfeil | B10: +1W8 | C10: +4 | D10: 0 | E10: 0 | F10: 2,5D | G10: 5 | H10: 4 | J10: 1
A11: Faltstahlspitzen-Pfeil | B11: +1W8 | C11: +5 | D11: 0 | E11: 0 | F11: 5D | G11: 5 | H11: 4 | J11: 1
A12: Nasiumspitzen-Pfeil | B12: +1W8 | C12: +2 | D12: 0 | E12: 0 | F12: 100D | G12: 6 | H12: 5 | J12: 1 | K12: Verzauberungskosten werden stark verringert
A13: Adamantitspitzen-Pfeil | B13: +1W8 | C13: +7 | D13: 0 | E13: 0 | F13: 1000D | G13: 7 | H13: 6 | J13: 1
A14: Diamantspitzen-Pfeil | B14: +1W8 | C14: +5 | D14: 0 | E14: 0 | F14: 100D | G14: 5 | H14: 5 | J14: 1
A15: Silberspitzen-Pfeil | B15: +1W6 | C15: -2 | D15: 0 | E15: 0 | F15: 2,5D | G15: 5 | H15: 5 | J15: 1 | K15: Man sagt es gaebe Wesen die nur mit Silber verletzt oder getoetet werden koennen
A16: Glasspitzen-Pfeil | B16: +1W8 | C16: -2 | D16: 0 | E16: 0 | F16: 10D | G16: 5 | H16: 5 | J16: 2 | K16: Die Spitze zersplittert beim Aufprall, die Splitter bohren sich bei jeder Bewegung ins Fleisch
A17: Breitkopfspitzen-Pfeil | B17: +3 | C17: -1 | D17: -1 | E17: +10m | F17: +2D | G17: 4 | H17: 3 | J17: 2
A18: Hohlspitzen-Pfeil | B18: +2 | C18: +3 | D18: +3 | E18: +5m | F18: +10D | G18: 4 | H18: 4 | J18: 1 | K18: Moderner Arme-Pfeil: wird nur an staatlich Befugte weitergegeben
A19: Widerhaken-Pfeil | B19: 0 | C19: +1 | D19: +1 | E19: -5m | F19: +2D | G19: 4 | H19: 3 | J19: 1 | K19: Ges+Medizin erschwert um 15 beim Rausziehen, sonst 1W8+2 TP direkt auf die TZ
A20: Kanuelen-Pfeil | B20: -2 | C20: +1 | D20: +1 | E20: -5m | F20: +3D | G20: 5 | H20: 4 | J20: 1 | K20: Kann eine groessere Menge Gift transportieren (2 statt 1 Anwendung)
A21: Halbmond-Pfeil | B21: +2 | C21: -3 | D21: -3 | E21: 0 | F21: +2D | G21: 3 | H21: 2 | J21: 2 | K21: Man kann damit Seile durchschiessen
A22: Dornspitzen-Pfeil | B22: -2 | C22: +7 | D22: +7 | E22: 0 | F22: +1D | G22: 3 | H22: 3 | J22: 1
A23: Hohlkoerper-Pfeil | B23: 0 | C23: -2 | D23: -2 | E23: -10m | F23: +5D | G23: 6 | H23: 5 | J23: 1 | K23: In einer Tonkugel an der Spitze kann z.B. Zwergisches Feuer untergebracht werden
A24: (Trolle) Trollbogen-Pfeil | B24: +1W15 | C24: 0 | D24: 0 | E24: 0 | F24: 5D | G24: 7 | H24: 7 | I24: 6 | J24: 10 | K24: Kann nur mit dem Trollbogen abgeschossen werden
A25: (Drow) Elbenbein-Pfeil | B25: +1W8+1 | C25: +1 | D25: 0 | E25: 0 | F25: 4D | G25: 7 | H25: 7 | I25: 4 | J25: 1 | K25: Traditioneller Drow-Pfeil
A26: (Indianer) Schwarzfels-Pfeil | B26: +1W8+1 | C26: +4 | D26: -10m | E26: -10m | F26: nicht V. | G26: 6 | H26: 7 | I26: 5 | J26: 1 | K26: Traditioneller Pfeil einiger Indianerstaemme am Rande der Schwarzen Zone
A27: (Gnome) Kurz-Pfeil | B27: +1W6+1 | C27: +2 | D27: 0 | E27: 0 | F27: 500 FZ | G27: 7 | H27: 7 | I27: 1 | J27: 1 | K27: Kann nur mit den Gnomischen Boegen verschossen werden

Sheet Armbrust-Basis
A1: Name | B1: Volk | C1: Spanntechnik-roh | D1: Schaden | E1: RB | F1: Modifikatoren-roh | G1: RW-m | H1: Preis | I1: Verfuegbarkeit-NW | J1: Verfuegbarkeit-AW | K1: Verfuegbarkeit-Volk | L1: Notiz
A2: Improvisierte Armbrust | B2: Alle | C2: Hand: 9,13sec:4 / Geissfuss: xx,xxsec:x / Winde: xx,xxsec:x | D2: 1W6 | E2: 2 | F2: +8/-4/-25/-39/x | G2: 5m | H2: 0.001 | I2: 1 | J2: 1 | K2: 1
A3: Hand Armbrust | B3: Daikini | C3: Hand: 9,14sec:4 / Geissfuss: 5,30sec:2 / Winde: 3,60sec:1 | D3: 1W6 | E3: 3 | F3: +11/-3/-24/-38/x | G3: 5m | H3: 100 | I3: 6 | J3: 7 | K3: 4
A4: Leichte Armbrust | B4: Daikini | C4: Hand: 12,14sec:4 / Geissfuss: 7,30sec:2 / Winde: 4,60sec:1 | D4: 1W8 | E4: 4 | F4: +10/+2/-14/-31/x | G4: 10m | H4: 120 | I4: 6 | J4: 7 | K4: 2
A5: Mittelschwere Armbrust | B5: Daikini | C5: Hand: 25,14sec:4 / Geissfuss: 12,30sec:2 / Winde: 7,60sec:1 | D5: 1W10 | E5: 5 | F5: +9/+6/-9/-25/x | G5: 15m | H5: 200 | I5: 6 | J5: 7 | K5: 3
A6: Schwere Armbrust | B6: Daikini | C6: Hand: 37,14sec:4 / Geissfuss: 20,30sec:2 / Winde: 14,60sec:1 | D6: 1W12 | E6: 6 | F6: +8/+5/-5/-21/x | G6: 20m | H6: 800 | I6: 6 | J6: 7 | K6: 4
A7: Repetier Armbrust | B7: Daikini | C7: Repetiern:11,6sec:10 / 5xBolzen nachladen: 1,16sec:6(Erg:5 fuer 1) | D7: 1W4 | E7: 4 | F7: +7/0/-17/-34/x | G7: 5m | H7: 900 | I7: 6 | J7: 7 | K7: 6 | L7: Nur normale Bolzen mit normaler Spitze im 5-Schuss-Magazin
A8: Hand Armbrust | B8: Goblin | C8: Hand: 7,14sec:4 / Geissfuss: 3,30sec:2 / Winde: 1,60sec:1 | D8: 1W6 | E8: 2 | F8: +10/-4/-25/-39/x | G8: 5m | H8: 75 | I8: 5 | J8: 5 | K8: 3
A9: Leichte Armbrust | B9: Goblin | C9: Hand: 10,14sec:4 / Geissfuss: 5,30sec:2 / Winde: 2,60sec:1 | D9: 1W8 | E9: 2 | F9: +9/+3/-15/-32/x | G9: 10m | H9: 90 | I9: 4 | J9: 4 | K9: 1
A10: Mittelschwere Armbrust | B10: Goblin | C10: Hand: 23,14sec:4 / Geissfuss: 10,30sec:2 / Winde: 5,60sec:1 | D10: 1W10 | E10: 4 | F10: +8/+5/-10/-26/x | G10: 15m | H10: 150 | I10: 4 | J10: 4 | K10: 2
A11: Schwere Armbrust | B11: Goblin | C11: Hand: 35,14sec:4 / Geissfuss: 18,30sec:2 / Winde: 12,60sec:1 | D11: 1W12 | E11: 5 | F11: +7/+4/-6/-22/x | G11: 20m | H11: 600 | I11: 4 | J11: 4 | K11: 3
A12: Repetier Armbrust | B12: Goblin | C12: Repetiern:9,6sec:10 / 5xBolzen nachladen: 1,16sec:6(Erg:5 fuer 1) | D12: 1W4 | E12: 3 | F12: +6/-1/-18/-35/x | G12: 5m | H12: 675 | I12: 4 | J12: 4 | K12: 5 | L12: Nur normale Bolzen mit normaler Spitze im 5-Schuss-Magazin
A13: Hand Armbrust | B13: Ork | C13: Hand: 13,14sec:4 / Geissfuss: 9,30sec:2 / Winde: 7,60sec:1 | D13: 1W6 | E13: 4 | F13: +11/-3/-24/-38/x | G13: 5m | H13: 100 | I13: 6 | J13: 6 | K13: 4
A14: Leichte Armbrust | B14: Ork | C14: Hand: 16,14sec:4 / Geissfuss: 11,30sec:2 / Winde: 8,60sec:1 | D14: 1W8 | E14: 5 | F14: +10/+2/-14/-31/x | G14: 10m | H14: 120 | I14: 5 | J14: 5 | K14: 2
A15: Mittelschwere Armbrust | B15: Ork | C15: Hand: 29,14sec:4 / Geissfuss: 16,30sec:2 / Winde: 11,60sec:1 | D15: 1W10 | E15: 6 | F15: +9/+6/-9/-25/x | G15: 15m | H15: 200 | I15: 5 | J15: 5 | K15: 3
A16: Schwere Armbrust | B16: Ork | C16: Hand: 41,14sec:4 / Geissfuss: 24,30sec:2 / Winde: 18,60sec:1 | D16: 1W12 | E16: 7 | F16: +8/+5/-5/-21/x | G16: 20m | H16: 800 | I16: 5 | J16: 5 | K16: 4
A17: Schwerer Kriegsweiler | B17: Ork | C17: Hand: 46,15sec:4 / Geissfuss: 29,31sec:2 / Winde: 23,61sec:1 | D17: 1W15 | E17: 7 | F17: +8/+5/-5/-21/x | G17: 25m | H17: 1500 | I17: 5 | J17: 5 | K17: 5
A18: Repetier Armbrust | B18: Ork | C18: Repetiern:15,6sec:10 / 5xBolzen nachladen: 1,16sec:6(Erg:5 fuer 1) | D18: 1W4 | E18: 5 | F18: +7/0/-17/-34/x | G18: 5m | H18: 900 | I18: 7 | J18: 7 | K18: 7 | L18: Nur normale Bolzen mit normaler Spitze im 5-Schuss-Magazin
A19: Hand Armbrust | B19: Elf | C19: Hand: 9,14sec:4 / Geissfuss: 5,30sec:2 / Winde: 3,60sec:1 | D19: 1W6 | E19: 2 | F19: +13/-1/-22/-36/x | G19: 5m | H19: 125 | I19: 6 | J19: 6 | K19: 4
A20: Leichte Armbrust | B20: Elf | C20: Hand: 12,14sec:4 / Geissfuss: 7,30sec:2 / Winde: 4,60sec:1 | D20: 1W8 | E20: 3 | F20: +12/+4/-12/-29/x | G20: 10m | H20: 150 | I20: 6 | J20: 6 | K20: 2
A21: Mittelschwere Armbrust | B21: Elf | C21: Hand: 25,14sec:4 / Geissfuss: 12,30sec:2 / Winde: 7,60sec:1 | D21: 1W10 | E21: 4 | F21: +11/+7/-7/-23/x | G21: 15m | H21: 250 | I21: 6 | J21: 6 | K21: 3
A22: Schwere Armbrust | B22: Elf | C22: Hand: 37,14sec:4 / Geissfuss: 20,30sec:2 / Winde: 14,60sec:1 | D22: 1W12 | E22: 5 | F22: +10/+6/-3/-19/x | G22: 20m | H22: 1000 | I22: 6 | J22: 6 | K22: 4
A23: Repetier Armbrust | B23: Elf | C23: Repetiern:11,6sec:10 / 5xBolzen nachladen: 1,16sec:6(Erg:5 fuer 1) | D23: 1W4 | E23: 3 | F23: +9/+2/-15/-32/x | G23: 5m | H23: 1125 | I23: 6 | J23: 6 | K23: 6 | L23: Nur normale Bolzen mit normaler Spitze im 5-Schuss-Magazin
A24: Hand Armbrust | B24: Drow | C24: Hand: 9,14sec:4 / Geissfuss: 5,30sec:2 / Winde: 3,60sec:1 | D24: 1W6+1 | E24: 3 | F24: +10/-4/-25/-39/x | G24: 5m | H24: 120 | I24: 7 | J24: 7 | K24: 4
A25: Leichte Armbrust | B25: Drow | C25: Hand: 12,14sec:4 / Geissfuss: 7,30sec:2 / Winde: 4,60sec:1 | D25: 1W8+1 | E25: 4 | F25: +9/+1/-15/-32/x | G25: 10m | H25: 145 | I25: 7 | J25: 7 | K25: 2
A26: Mittelschwere Armbrust | B26: Drow | C26: Hand: 25,14sec:4 / Geissfuss: 12,30sec:2 / Winde: 7,60sec:1 | D26: 1W10+1 | E26: 5 | F26: +8/+5/-10/-26/x | G26: 15m | H26: 245 | I26: 7 | J26: 7 | K26: 3
A27: Schwere Armbrust | B27: Drow | C27: Hand: 37,14sec:4 / Geissfuss: 20,30sec:2 / Winde: 14,60sec:1 | D27: 1W12+1 | E27: 6 | F27: +7/+4/-6/-22/x | G27: 20m | H27: 995 | I27: 7 | J27: 7 | K27: 4
A28: Repetier Armbrust | B28: Drow | C28: Repetiern:11,6sec:10 / 5xBolzen nachladen: 1,16sec:6(Erg:5 fuer 1) | D28: 1W4+1 | E28: 4 | F28: +6/-1/-18/-35/x | G28: 5m | H28: 1120 | I28: 7 | J28: 7 | K28: 6 | L28: Nur normale Bolzen mit normaler Spitze im 5-Schuss-Magazin
A29: Hand Armbrust | B29: Gnom | C29: Hand: 5,14sec:4 / Geissfuss: 1,30sec:2 / Winde: 1,60sec:1 | D29: 1W2 | E29: 2 | F29: +11/-3/-24/-38/x | G29: 5m | H29: 125 | I29: 7 | J29: 7 | K29: 4
A30: Leichte Armbrust | B30: Gnom | C30: Hand: 8,14sec:4 / Geissfuss: 3,30sec:2 / Winde: 1,60sec:1 | D30: 1W4 | E30: 2 | F30: +10/+2/-14/-31/x | G30: 10m | H30: 150 | I30: 7 | J30: 7 | K30: 2
A31: Mittelschwere Armbrust | B31: Gnom | C31: Hand: 21,14sec:4 / Geissfuss: 8,30sec:2 / Winde: 3,60sec:1 | D31: 1W6 | E31: 3 | F31: +9/+6/-9/-25/x | G31: 15m | H31: 250 | I31: 7 | J31: 7 | K31: 3
A32: Schwere Armbrust | B32: Gnom | C32: Hand: 33,14sec:4 / Geissfuss: 16,30sec:2 / Winde: 10,60sec:1 | D32: 1W8 | E32: 4 | F32: +8/+5/-5/-21/x | G32: 20m | H32: 1000 | I32: 7 | J32: 7 | K32: 4
A33: Repetier Armbrust | B33: Gnom | C33: Repetiern:8,6sec:10 / 5xBolzen nachladen: 1,16sec:6(Erg:5 fuer 1) | D33: 1W2 | E33: 2 | F33: +7/0/-17/-34/x | G33: 5m | H33: 1125 | I33: 7 | J33: 7 | K33: 6 | L33: Nur normale Bolzen mit normaler Spitze im 5-Schuss-Magazin
A34: Hand Armbrust | B34: Zwerg | C34: Hand: 10,14sec:4 / Geissfuss: 6,30sec:2 / Winde: 4,60sec:1 | D34: 1W6 | E34: 3 | F34: +12/-2/-23/-37/x | G34: 10m | H34: 160 | I34: 6 | J34: 5 | K34: 4
A35: Leichte Armbrust | B35: Zwerg | C35: Hand: 13,14sec:4 / Geissfuss: 8,30sec:2 / Winde: 5,60sec:1 | D35: 1W8 | E35: 4 | F35: +11/+3/-13/-30/x | G35: 15m | H35: 180 | I35: 6 | J35: 5 | K35: 2
A36: Mittelschwere Armbrust | B36: Zwerg | C36: Hand: 26,14sec:4 / Geissfuss: 13,30sec:2 / Winde: 8,60sec:1 | D36: 1W10 | E36: 5 | F36: +10/+7/-8/-24/x | G36: 20m | H36: 300 | I36: 6 | J36: 5 | K36: 3
A37: Schwere Armbrust | B37: Zwerg | C37: Hand: 38,14sec:4 / Geissfuss: 21,30sec:2 / Winde: 15,60sec:1 | D37: 1W12 | E37: 6 | F37: +9/+6/-4/-20/x | G37: 25m | H37: 1200 | I37: 6 | J37: 5 | K37: 4
A38: Repetier Armbrust | B38: Zwerg | C38: Repetiern:12,6sec:10 / 5xBolzen nachladen: 1,16sec:6(Erg:5 fuer 1) | D38: 1W4 | E38: 4 | F38: +8/+1/-16/-33/x | G38: 10m | H38: 1350 | I38: 6 | J38: 6 | K38: 6 | L38: Nur normale Bolzen mit normaler Spitze im 5-Schuss-Magazin
A39: Balläster | B39: Spezial/Legendaer | C39: Hand: 13,14sec:4 / Geissfuss: x,xxsec:x / Winde: x,xxsec:x | D39: 1W4 | E39: 2 | F39: +11/+3/-13/-30/x | G39: 10m | H39: 300 | I39: 7 | J39: 4 | K39: 5 | L39: Zur Steinschleuder umgebaute Armbrust fuer die Vogeljagd; Munition kullert leicht aus der Abschusshalterung

Sheet Bolzen-Basis
A1: Name | B1: Schaden-Mod | C1: RB-Mod | D1: RW-Mod-Spalte1 | E1: RW-Mod-Spalte2 | F1: Preis | G1: Verfuegbarkeit-NW | H1: Verfuegbarkeit-AW | I1: Verfuegbarkeit-Volk | J1: BE | K1: Spezialitaeten
A2: Improvisierter-Bolzen | B2: +1W4 | C2: 0 | D2: -15 | E2: -15 | F2: nicht V | J2: 1
A3: Holzspitzen-Bolzen | B3: +1W4 | C3: 0 | D3: -7 | E3: -7 | F3: 200 FZ | G3: 6 | H3: 6 | J3: 1
A4: Knochenspitzen-Bolzen | B4: +1W6 | C4: 0 | D4: 0 | E4: 0 | F4: 400FZ | G4: 6 | H4: 6 | J4: 1
A5: Steinspitzen-Bolzen | B5: +1W8 | C5: 0 | D5: 0 | E5: 0 | F5: 800 FZ | G5: 6 | H5: 6 | J5: 1
A6: Diamantspatspitzen-Bolzen | B6: +1W10 | C6: +6 | D6: 0 | E6: 0 | F6: 3,5D | G6: 7 | H6: 7 | I6: 3 | J6: 1 | K6: Wird durch UV-Strahlung zersetzt
A7: Bronzespitzen-Bolzen | B7: +1W8 | C7: +1 | D7: 0 | E7: 0 | F7: 1,2D | G7: 6 | H7: 6 | J7: 1
A8: Eisenspitzen-Bolzen | B8: +1W10 | C8: +2 | D8: 0 | E8: 0 | F8: 2D | G8: 3 | H8: 2 | J8: 1
A9: Stahlspitzen-Bolzen | B9: +1W10 | C9: +3 | D9: 0 | E9: 0 | F9: 4D | G9: 4 | H9: 2 | J9: 1
A10: Edelstahlspitzen-Bolzen | B10: +1W10 | C10: +4 | D10: 0 | E10: 0 | F10: 10D | G10: 5 | H10: 4 | J10: 1
A11: Faltstahlspitzen-Bolzen | B11: +1W10 | C11: +5 | D11: 0 | E11: 0 | F11: 20D | G11: 6 | H11: 5 | J11: 1
A12: Nasiumspitzen-Bolzen | B12: +1W10 | C12: +2 | D12: 0 | E12: 0 | F12: 400D | G12: 6 | H12: 5 | J12: 1 | K12: Verzauberungskosten werden stark verringert
A13: Adamantidspitzen-Bolzen | B13: +1W10 | C13: +7 | D13: 0 | E13: 0 | F13: 10000D | G13: 7 | H13: 6 | J13: 1
A14: Diamantspitzen-Bolzen | B14: +1W10 | C14: +6 | D14: 0 | E14: 0 | F14: 400D | G14: 6 | H14: 6 | J14: 1
A15: Silberspitzen-Bolzen | B15: +1W8 | C15: -2 | D15: 0 | E15: 0 | F15: 10D | G15: 4 | H15: 4 | J15: 1 | K15: Man sagt es gaebe Wesen die nur mit Silber verletzt oder getoetet werden koennen
A16: Glasspitzen-Bolzen | B16: +1W8 | C16: -2 | D16: 0 | E16: 0 | F16: 40D | G16: 5 | H16: 5 | J16: 2 | K16: Die Spitze zersplittert beim Aufprall, die Splitter bohren sich bei jeder Bewegung ins Fleisch
A17: Breitkopfspitzen-Bolzen | B17: +3 | C17: -4 | D17: -4 | E17: +5m | F17: +8D | G17: 5 | H17: 4 | J17: 3
A18: Hohlspitzen-Bolzen | B18: +2 | C18: +4 | D18: +4 | E18: +5m | F18: +40D | G18: 5 | H18: 5 | J18: 1 | K18: Moderner Arme-Bolzen: wird nur an staatlich Befugte weitergegeben
A19: Widerhaken-Bolzen | B19: 0 | C19: +2 | D19: +2 | E19: -5m | F19: +8D | G19: 5 | H19: 4 | J19: 1 | K19: Ges+Medizin erschwert um 15 beim Rausziehen, sonst 1W8+4 TP direkt auf die TZ
A20: Kanuelen-Bolzen | B20: -2 | C20: +1 | D20: +1 | E20: -5m | F20: +12D | G20: 6 | H20: 5 | J20: 1 | K20: Kann eine groessere Menge Gift transportieren (2 statt 1 Anwendung)
A21: Halbmond-Bolzen | B21: +2 | C21: -4 | D21: -4 | E21: 0 | F21: +8D | G21: 4 | H21: 3 | J21: 3 | K21: Man kann damit Seile durchschiessen
A22: Dornspitzen-Bolzen | B22: -2 | C22: +10 | D22: +10 | E22: 0 | F22: +4D | G22: 4 | H22: 4 | J22: 1
A23: Hohlkoerper-Bolzen | B23: 0 | C23: -2 | D23: -2 | E23: -10m | F23: +20D | G23: 6 | H23: 6 | J23: 1 | K23: In einer Tonkugel an der Spitze kann z.B. Zwergisches Feuer untergebracht werden
A24: Improvisierte Balläster-Munition | B24: +1W4 | C24: 0 | D24: -5m | E24: -5m | F24: nicht V | J24: 0 | K24: Meistens ein Stein
A25: Balläster-Munition | B25: +1W6 | C25: 0 | D25: 0 | E25: 0 | F25: 600 FZ | G25: 5 | H25: 4 | J25: 0 | K25: Meistens eine murmelgrosse Stahlkugel

Sheet Runengewehr-Basis
A1: Name | B1: Munitionsrune-Slots | C1: RW-max-m | D1: Mod-10m | E1: Mod-30m | F1: Mod-60m | G1: Mod-100m | H1: Mod-150m | I1: Mod-210m | J1: Preis
A2: Zwergisch Standard | B2: 1 | C2: 100m | D2: 12 | E2: 6 | F2: 0 | G2: -6 | H2: -12 | J2: 85D
A3: Zwergisch Militaer Neu | B3: 2 | C3: 115m | D3: 12 | E3: 6 | F3: 1 | G3: -5 | H3: -10 | I3: -15 | J3: 190D+
A4: Goblinisch kurz | B4: 1 | C4: 80m | D4: 12 | E4: 5 | F4: -2 | G4: -8 | H4: -14 | J4: 65D
A5: Drow modifiziert Zwergisch | B5: 1 | C5: 105m | D5: 12 | E5: 6 | F5: 0 | G5: -5 | H5: -10 | J5: 130D+

Sheet Runengewehr-Munition
A1: Munitionsrune | B1: Schaden-Formel | C1: RB | D1: Zusatzeffekt | E1: Preis
A2: Saeure | B2: W8+St. | C2: RSx2 | D2: Wenn SP>0: nach 2 und 5 sec je (W6+St.) SP (gleiche TZ) | E2: 2,5D
A3: Feuer | B3: 2W8+(2xSt.) | C3: 0 | E3: 2D
A4: Luft | B4: W6+St. | C4: 0 | D4: Immer Selbstbeherrschungs-Probe zusaetzlich erschwert um (3xSt.) gegen Kampfunfaehigkeit fuer Differenz in Sekunden | E4: 3,5D
A5: Erde | B5: 2W10+St. | C5: St. | E5: 3D
A6: Eis | B6: W12+(2xSt.) | C6: St.+2 | E6: 5D
A7: Blitz | B7: W10+St. | C7: 4 | D7: Immer Selbstbeherrschungs-Probe zusaetzlich erschwert um (3xSt.) gegen Bewusstlosigkeit fuer Differenz in Sekunden | E7: 8D
A8: Licht | B8: W15+(2xSt.) | C8: 2xSt. | D8: Opfer haben keine Gluecks-Probe. FK-Patzer-Maximum=5 | E8: 10D

Sheet Runengewehr-Gewehrrunen
A1: Stufe | B1: Preis
A2: 1 | B2: 35D
A3: 2 | B3: 70D
A4: 3 | B4: 200D
A5: 4 | B5: 450D
A6: 5 | B6: 1000D+
A7: 6 | B7: 2000D+
A8: 7 | B8: 5000D+

Sheet Sprachstufe-Kosten
A1: Wert | B1: Gesamt-EP | C1: EP-Kosten (Schritt)
A2: 0 | B2: 0 | C2: 0
A3: 1 | B3: 15 | C3: 15
A4: 2 | B4: 30 | C4: 15
A5: 3 | B5: 50 | C5: 20
A6: 4 | B6: 75 | C6: 25

Sheet Kulturstufe-Kosten
A1: Wert | B1: Gesamt-EP | C1: EP-Kosten (Schritt)
A2: 0 | B2: 0 | C2: 0
A3: 1 | B3: 10 | C3: 10
A4: 2 | B4: 25 | C4: 15
A5: 3 | B5: 40 | C5: 15
A6: 4 | B6: 55 | C6: 15

Sheet Boegen
A1: Name | B1: Volk | C1: Typ | D1: Material | E1: Gewicht | F1: Min. Stä | G1: 1.W | H1: 2.W | I1: Fixschaden | J1: RB | K1: 10m | L1: 30m | M1: 60m | N1: 100m | O1: 150m | P1: 210m | Q1: RW | R1: Nachladezeit | S1: Nachladen TaW-Teiler | T1: Patzermodifikator | U1: Verfügbarkeit | V1: Preis | W1: Herstellungszeit | X1: Materialpreis
A2: Improvisierter Bogen | B2: Alle | D2: Holz | F2: 7 | G2: 1W4 | J2: 0 | K2: +4 | L2: 0 | M2: -15 | N2: x | O2: x | P2: x | Q2: 15m | R2: 6 | S2: 9 | V2: nicht V.
A3: Goblin Kurzbogen | B3: Goblin | D3: Holz | F3: 5 | G3: 1W4 | I3: +1 | J3: 1 | K3: +8 | L3: +2 | M3: -13 | N3: -25 | O3: x | P3: x | Q3: 15m | R3: 6 | S3: 9 | U3: 1 | V3: 50D
A4: Goblin Jagdbogen | B4: Goblin | D4: Holz | F4: 7 | G4: 1W6 | I4: +1 | J4: 2 | K4: +6 | L4: +2 | M4: -8 | N4: -22 | O4: x | P4: x | Q4: 20m | R4: 6 | S4: 9 | U4: 1 | V4: 60D
A5: Goblin Langbogen | B5: Goblin | D5: Holz | F5: 10 | G5: 1W6 | I5: +1 | J5: 3 | K5: +5 | L5: +2 | M5: -8 | N5: -20 | O5: -30 | P5: x | Q5: 60m | R5: 7 | S5: 9 | U5: 1 | V5: 100D
A6: Bogen von der Firma Froggler | B6: Goblin | D6: Holz | F6: 7 | G6: 1W6 | J6: 1 | K6: +6 | L6: +2 | M6: -8 | N6: -22 | O6: x | P6: x | Q6: 25m | R6: 7 | S6: 9 | U6: 1 | V6: 55D
A7: Indianer Bogen | B7: Indianer | D7: Holz | F7: 9 | G7: 1W6 | I7: +1 | J7: 2 | K7: +7 | L7: +2 | M7: -8 | N7: -23 | O7: x | P7: x | Q7: 25m | R7: 6 | S7: 9 | U7: 1 | V7: 1D
A8: Indianer Langbogen | B8: Indianer | D8: Holz | F8: 12 | G8: 1W6 | I8: +1 | J8: 3 | K8: +6 | L8: +2 | M8: -8 | N8: -21 | O8: x | P8: x | Q8: 75m | R8: 7 | S8: 9 | U8: 4 | V8: 2D
A9: Schwarzfels Bogen | B9: Indianer | D9: Holz, Schwarzfels, Seil, Leim | F9: 15 | G9: 1W8 | I9: +1 | J9: 3 | K9: +6 | L9: +2 | M9: -7 | N9: -22 | O9: x | P9: x | Q9: 40m | R9: 9 | S9: 9 | U9: 6 | V9: nicht V.
A10: Daikini Kurzbogen | B10: Daikini | D10: Holz | F10: 9 | G10: 1W4 | I10: +1 | J10: 2 | K10: +7 | L10: +2 | M10: -11 | N10: -25 | O10: x | P10: x | Q10: 20m | R10: 6 | S10: 9 | U10: 1 | V10: 60D
A11: Daikini Jagdbogen | B11: Daikini | D11: Holz | F11: 11 | G11: 1W6 | I11: +1 | J11: 2 | K11: +6 | L11: +2 | M11: -8 | N11: -22 | O11: x | P11: x | Q11: 27m | R11: 6 | S11: 9 | U11: 1 | V11: 80D
A12: Daikini Langbogen | B12: Daikini | D12: Holz | F12: 12 | G12: 1W6 | I12: +1 | J12: 3 | K12: +5 | L12: +2 | M12: -8 | N12: -20 | O12: -30 | P12: x | Q12: 50m | R12: 7 | S12: 9 | U12: 2 | V12: 125D
A13: Asymmetrischer Bogen | B13: Daikini | D13: Holz | F13: 13 | G13: 1W6 | I13: +1 | J13: 3 | K13: +7 | L13: +2 | M13: -8 | N13: -20 | O13: -30 | P13: x | Q13: 75m | R13: 6 | S13: 9 | U13: 6 | V13: 1000D
A14: Elfen Kurzbogen | B14: Elf | D14: Holz | F14: 9 | G14: 1W4 | I14: +1 | J14: 2 | K14: +8 | L14: +3 | M14: -9 | N14: -22 | O14: x | P14: x | Q14: 25m | R14: 6 | S14: 9 | U14: 1 | V14: 85D
A15: Elfen Jagdbogen | B15: Elf | D15: Holz | F15: 11 | G15: 1W6 | I15: +1 | J15: 2 | K15: +7 | L15: +3 | M15: -8 | N15: -20 | O15: x | P15: x | Q15: 33m | R15: 6 | S15: 9 | U15: 1 | V15: 130D
A16: Elfen Langbogen | B16: Elf | D16: Holz | F16: 12 | G16: 1W6 | I16: +1 | J16: 2 | K16: +5 | L16: +2 | M16: -6 | N16: -17 | O16: x | P16: x | Q16: 110m | R16: 6 | S16: 9 | U16: 1 | V16: 180D
A17: Kompositbogen kurz (Elf) | B17: Elf | D17: Holz, Horn, Leim | F17: 12 | G17: 1W6 | I17: +1 | J17: 2 | K17: +9 | L17: +3 | M17: -9 | N17: -22 | O17: x | P17: x | Q17: 22m | R17: 6 | S17: 9 | U17: 3 | V17: 200D
A18: Kompositbogen lang (Elf) | B18: Elf | D18: Holz, Horn, Leim | F18: 13 | G18: 1W8 | I18: +1 | J18: 2 | K18: +6 | L18: +2 | M18: -6 | N18: -17 | O18: x | P18: x | Q18: 23m | R18: 6 | S18: 9 | U18: 3 | V18: 250D
... A31: Kompositbogen kurz (Zentaur) | B31: Zentaur | D31: Holz, Horn, Leim | F31: 12 | G31: 1W6 | I31: +1 | J31: 3 | K31: +9 | L31: +3 | M31: -9 | N31: -22 | O31: x | P31: x | Q31: 22m | R31: 6 | S31: 9 | U31: 3 | V31: 200D+
A32: Improvisierter Trollbogen | B32: Troll | D32: 1 Junger Baum | F32: 33 | G32: 1W20 | I32: +1 | J32: 0 | K32: 0 | L32: -5 | M32: -25 | N32: x | O32: x | P32: x | Q32: 10m | R32: 15 | S32: 10 | V32: nicht V.
A33: Trollbogen | B33: Troll | D33: 1 Junger Baum | F33: 28 | G33: 1W30 | I33: +1 | J33: 0 | K33: +4 | L33: 0 | M33: -15 | N33: x | O33: x | P33: x | Q33: 25m | R33: 13 | S33: 10 | U33: 5 | V33: 100D+
A34: Drow Kurzbogen | B34: Drow | D34: Noristawurz | F34: 10 | G34: 1W4 | I34: +2 | J34: 2 | K34: +8 | L34: +3 | M34: -11 | N34: -25 | O34: x | P34: x | Q34: 15m | R34: 6 | S34: 9 | U34: 1 | V34: 60D
A35: Drow Jagdbogen | B35: Drow | D35: Noristawurz | F35: 12 | G35: 1W6 | I35: +2 | J35: 2 | K35: +7 | L35: +3 | M35: -8 | N35: -22 | O35: x | P35: x | Q35: 22m | R35: 6 | S35: 9 | U35: 4 | V35: 80D
A36: Drow Langbogen | B36: Drow | D36: Noristawurz | F36: 13 | G36: 1W6 | I36: +2 | J36: 3 | K36: +5 | L36: +2 | M36: -8 | N36: -20 | O36: -30 | P36: x | Q36: 60m | R36: 7 | S36: 9 | U36: 5 | V36: 125D
A37: Elbenbeinbogen | B37: Drow | D37: Noristawurz, Elbenbein, Leim | F37: 13 | G37: 1W8 | I37: +1 | J37: 4 | K37: +6 | L37: +2 | M37: -6 | N37: -17 | O37: x | P37: x | Q37: 23m | R37: 6 | S37: 9 | U37: 5 | V37: 250D
A38: Gnom Kurzbogen | B38: Gnom | D38: Holz | F38: 4 | G38: 1W2 | I38: +1 | J38: 2 | K38: +7 | L38: +2 | M38: -11 | N38: -25 | O38: x | P38: x | Q38: 10m | R38: 5 | S38: 9 | U38: 1 | V38: 60D+
A39: Gnom Jagdbogen | B39: Gnom | D39: Holz | F39: 6 | G39: 1W4 | I39: +1 | J39: 2 | K39: +6 | L39: +2 | M39: -8 | N39: -22 | O39: x | P39: x | Q39: 14m | R39: 5 | S39: 9 | U39: 1 | V39: 80D+
A40: Gnom Langbogen | B40: Gnom | D40: Holz | F40: 7 | G40: 1W4 | I40: +1 | J40: 3 | K40: +5 | L40: +2 | M40: -8 | N40: -20 | O40: -30 | P40: x | Q40: 30m | R40: 6 | S40: 9 | U40: 1 | V40: 125D+
A41: Umspannbogen (Gnom) | B41: Gnom | D41: Holz, G Federstahl, G Stahl | F41: 10 | G41: 1W6 | I41: +1 | J41: 5 | K41: +6 | L41: +2 | M41: -6 | N41: -17 | O41: -25 | P41: x | Q41: 25m | R41: 4 | S41: 10 | U41: 5 | V41: 10000D+
A42: Drachenbogen | B42: Spezial/Legendaer | D42: Holz, Kaiserdrachen-Bein, Leim | F42: 21 | G42: 1W12 | I42: +1 | J42: 3 | K42: +6 | L42: +1 | M42: -13 | N42: -29 | O42: x | P42: x | Q42: 25m | R42: 8 | S42: 9 | U42: M | V42: 1 Mio. D

Sheet Armbrust
A1: Name | B1: Volk | C1: Typ | D1: Armrüste: Ladetechnik Hand | E1: Armrüste: Ladetechnik Geißfuß | F1: Armrüste: Ladetechnik Winde | G1: Gewicht | H1: Min. Stä | I1: 1.W | J1: 2.W | K1: Fixschaden | L1: RB | M1: 10m | N1: 30m | O1: 60m | P1: 100m | Q1: 150m | R1: 210m | S1: RW | T1: Nachladezeit | U1: Nachladen TaW-Teiler | V1: Patzermodifikator | W1: Verfügbarkeit | X1: Preis | Y1: Herstellungszeit | Z1: Material | AA1: Materialpreis | AB1: Notiz
A2: Improvisierte Armbrust | B2: Alle | D2: 9,13sec:4 | E2: x | F2: x | H2: 9 | I2: 1W6 | L2: 2 | M2: +8 | N2: -4 | O2: -25 | P2: -39 | Q2: x | R2: x | S2: 5m | T2: 13sec | U2: 4 | X2: nicht V.
A3: Hand Armbrust (Daikini) | B3: Daikini | D3: 9,14sec:4 | E3: 5,30sec:2 | F3: 3,60sec:1 | H3: 9 | I3: 1W6 | L3: 3 | M3: +11 | N3: -3 | O3: -24 | P3: -38 | Q3: x | R3: x | S3: 5m | T3: 14sec | U3: 4 | W3: 4 | X3: 100D
A4: Leichte Armbrust (Daikini) | B4: Daikini | D4: 12,14sec:4 | E4: 7,30sec:2 | F4: 4,60sec:1 | H4: 12 | I4: 1W8 | L4: 4 | M4: +10 | N4: +2 | O4: -14 | P4: -31 | Q4: x | R4: x | S4: 10m | T4: 14sec | U4: 4 | W4: 2 | X4: 120D
A5: Mittelschwere Armbrust (Daikini) | B5: Daikini | D5: 25,14sec:4 | E5: 12,30sec:2 | F5: 7,60sec:1 | H5: 25 | I5: 1W10 | L5: 5 | M5: +9 | N5: +6 | O5: -9 | P5: -25 | Q5: x | R5: x | S5: 15m | T5: 14sec | U5: 4 | W5: 3 | X5: 200D
A6: Schwere Armbrust (Daikini) | B6: Daikini | D6: 37,14sec:4 | E6: 20,30sec:2 | F6: 14,60sec:1 | H6: 37 | I6: 1W12 | L6: 6 | M6: +8 | N6: +5 | O6: -5 | P6: -21 | Q6: x | R6: x | S6: 20m | T6: 14sec | U6: 4 | W6: 4 | X6: 800D
A7: Repetier Armbrust (Daikini)* | B7: Daikini | D7: Repetiern:11,6sec:10 / 5xBolzen nachladen: 1,16sec:6(Erg:5 fuer 1) | I7: 1W4 | L7: 4 | M7: +7 | N7: 0 | O7: -17 | P7: -34 | Q7: x | R7: x | S7: 5m | W7: 6 | X7: 900D | AB7: Nur normale Bolzen mit normaler Spitze im 5-Schuss-Magazin
A8: Hand Armbrust (Goblin) | B8: Goblin | D8: 7,14sec:4 | E8: 3,30sec:2 | F8: 1,60sec:1 | H8: 7 | I8: 1W6 | L8: 2 | M8: +10 | N8: -4 | O8: -25 | P8: -39 | Q8: x | R8: x | S8: 5m | T8: 14sec | U8: 4 | W8: 3 | X8: 75D
A9: Leichte Armbrust (Goblin) | B9: Goblin | D9: 10,14sec:4 | E9: 5,30sec:2 | F9: 2,60sec:1 | H9: 10 | I9: 1W8 | L9: 2 | M9: +9 | N9: +3 | O9: -15 | P9: -32 | Q9: x | R9: x | S9: 10m | T9: 14sec | U9: 4 | W9: 1 | X9: 90D
A10: Mittelschwere Armbrust (Goblin) | B10: Goblin | D10: 23,14sec:4 | E10: 10,30sec:2 | F10: 5,60sec:1 | H10: 23 | I10: 1W10 | L10: 4 | M10: +8 | N10: +5 | O10: -10 | P10: -26 | Q10: x | R10: x | S10: 15m | T10: 14sec | U10: 4 | W10: 2 | X10: 150D
A11: Schwere Armbrust (Goblin) | B11: Goblin | D11: 35,14sec:4 | E11: 18,30sec:2 | F11: 12,60sec:1 | H11: 35 | I11: 1W12 | L11: 5 | M11: +7 | N11: +4 | O11: -6 | P11: -22 | Q11: x | R11: x | S11: 20m | T11: 14sec | U11: 4 | W11: 3 | X11: 600D
A12: Repetier Armbrust (Goblin)* | B12: Goblin | D12: Repetiern:9,6sec:10 / 5xBolzen nachladen: 1,16sec:6(Erg:5 fuer 1) | I12: 1W4 | L12: 3 | M12: +6 | N12: -1 | O12: -18 | P12: -35 | Q12: x | R12: x | S12: 5m | W12: 5 | X12: 675D | AB12: Nur normale Bolzen mit normaler Spitze im 5-Schuss-Magazin
A13: Hand Armbrust (Ork) | B13: Ork | D13: 13,14sec:4 | E13: 9,30sec:2 | F13: 7,60sec:1 | H13: 13 | I13: 1W6 | L13: 4 | M13: +11 | N13: -3 | O13: -24 | P13: -38 | Q13: x | R13: x | S13: 5m | T13: 14sec | U13: 4 | W13: 4 | X13: 100D
A14: Leichte Armbrust (Ork) | B14: Ork | D14: 16,14sec:4 | E14: 11,30sec:2 | F14: 8,60sec:1 | H14: 16 | I14: 1W8 | L14: 5 | M14: +10 | N14: +2 | O14: -14 | P14: -31 | Q14: x | R14: x | S14: 10m | T14: 14sec | U14: 4 | W14: 2 | X14: 120D
A15: Mittelschwere Armbrust (Ork) | B15: Ork | D15: 29,14sec:4 | E15: 16,30sec:2 | F15: 11,60sec:1 | H15: 29 | I15: 1W10 | L15: 6 | M15: +9 | N15: +6 | O15: -9 | P15: -25 | Q15: x | R15: x | S15: 15m | T15: 14sec | U15: 4 | W15: 3 | X15: 200D
A16: Schwere Armbrust (Ork) | B16: Ork | D16: 41,14sec:4 | E16: 24,30sec:2 | F16: 18,60sec:1 | H16: 41 | I16: 1W12 | L16: 7 | M16: +8 | N16: +5 | O16: -5 | P16: -21 | Q16: x | R16: x | S16: 20m | T16: 14sec | U16: 4 | W16: 4 | X16: 800D
A17: Schwerer Kriegsweiler | B17: Ork | D17: 46,15sec:4 | E17: 29,31sec:2 | F17: 23,61sec:1 | H17: 46 | I17: 1W15 | L17: 7 | M17: +8 | N17: +5 | O17: -5 | P17: -21 | Q17: x | R17: x | S17: 25m | T17: 15sec | U17: 4 | W17: 5 | X17: 1500D
A18: Repetier Armbrust (Ork)* | B18: Ork | D18: Repetiern:15,6sec:10 / 5xBolzen nachladen: 1,16sec:6(Erg:5 fuer 1) | I18: 1W4 | L18: 5 | M18: +7 | N18: 0 | O18: -17 | P18: -34 | Q18: x | R18: x | S18: 5m | W18: 7 | X18: 900D | AB18: Nur normale Bolzen mit normaler Spitze im 5-Schuss-Magazin
A19: Hand Armbrust (Elf) | B19: Elf | D19: 9,14sec:4 | E19: 5,30sec:2 | F19: 3,60sec:1 | H19: 9 | I19: 1W6 | L19: 2 | M19: +13 | N19: -1 | O19: -22 | P19: -36 | Q19: x | R19: x | S19: 5m | T19: 14sec | U19: 4 | W19: 4 | X19: 125D
A20: Leichte Armbrust (Elf) | B20: Elf | D20: 12,14sec:4 | E20: 7,30sec:2 | F20: 4,60sec:1 | H20: 12 | I20: 1W8 | L20: 3 | M20: +12 | N20: +4 | O20: -12 | P20: -29 | Q20: x | R20: x | S20: 10m | T20: 14sec | U20: 4 | W20: 2 | X20: 150D
A21: Mittelschwere Armbrust (Elf) | B21: Elf | D21: 25,14sec:4 | E21: 12,30sec:2 | F21: 7,60sec:1 | H21: 25 | I21: 1W10 | L21: 4 | M21: +11 | N21: +7 | O21: -7 | P21: -23 | Q21: x | R21: x | S21: 15m | T21: 14sec | U21: 4 | W21: 3 | X21: 250D
A22: Schwere Armbrust (Elf) | B22: Elf | D22: 37,14sec:4 | E22: 20,30sec:2 | F22: 14,60sec:1 | H22: 37 | I22: 1W12 | L22: 5 | M22: +10 | N22: +6 | O22: -3 | P22: -19 | Q22: x | R22: x | S22: 20m | T22: 14sec | U22: 4 | W22: 4 | X22: 1000D
A23: Repetier Armbrust (Elf)* | B23: Elf | D23: Repetiern:11,6sec:10 / 5xBolzen nachladen: 1,16sec:6(Erg:5 fuer 1) | I23: 1W4 | L23: 3 | M23: +9 | N23: +2 | O23: -15 | P23: -32 | Q23: x | R23: x | S23: 5m | W23: 6 | X23: 1125D | AB23: Nur normale Bolzen mit normaler Spitze im 5-Schuss-Magazin
A24: Hand Armbrust (Drow) | B24: Drow | D24: 9,14sec:4 | E24: 5,30sec:2 | F24: 3,60sec:1 | H24: 9 | I24: 1W6 | K24: +1 | L24: 3 | M24: +10 | N24: -4 | O24: -25 | P24: -39 | Q24: x | R24: x | S24: 5m | T24: 14sec | U24: 4 | W24: 4 | X24: 120D
A25: Leichte Armbrust (Drow) | B25: Drow | D25: 12,14sec:4 | E25: 7,30sec:2 | F25: 4,60sec:1 | H25: 12 | I25: 1W8 | K25: +1 | L25: 4 | M25: +9 | N25: +1 | O25: -15 | P25: -32 | Q25: x | R25: x | S25: 10m | T25: 14sec | U25: 4 | W25: 2 | X25: 145D
A26: Mittelschwere Armbrust (Drow) | B26: Drow | D26: 25,14sec:4 | E26: 12,30sec:2 | F26: 7,60sec:1 | H26: 25 | I26: 1W10 | K26: +1 | L26: 5 | M26: +8 | N26: +5 | O26: -10 | P26: -26 | Q26: x | R26: x | S26: 15m | T26: 14sec | U26: 4 | W26: 3 | X26: 245D
A27: Schwere Armbrust (Drow) | B27: Drow | D27: 37,14sec:4 | E27: 20,30sec:2 | F27: 14,60sec:1 | H27: 37 | I27: 1W12 | K27: +1 | L27: 6 | M27: +7 | N27: +4 | O27: -6 | P27: -22 | Q27: x | R27: x | S27: 20m | T27: 14sec | U27: 4 | W27: 4 | X27: 995D
A28: Repetier Armbrust (Drow)* | B28: Drow | D28: Repetiern:11,6sec:10 / 5xBolzen nachladen: 1,16sec:6(Erg:5 fuer 1) | I28: 1W4 | K28: +1 | L28: 4 | M28: +6 | N28: -1 | O28: -18 | P28: -35 | Q28: x | R28: x | S28: 5m | W28: 6 | X28: 1120D | AB28: Nur normale Bolzen mit normaler Spitze im 5-Schuss-Magazin
A29: Hand Armbrust (Gnom) | B29: Gnom | D29: 5,14sec:4 | E29: 1,30sec:2 | F29: 1,60sec:1 | H29: 5 | I29: 1W2 | L29: 2 | M29: +11 | N29: -3 | O29: -24 | P29: -38 | Q29: x | R29: x | S29: 5m | T29: 14sec | U29: 4 | W29: 4 | X29: 125D
A30: Leichte Armbrust (Gnom) | B30: Gnom | D30: 8,14sec:4 | E30: 3,30sec:2 | F30: 1,60sec:1 | H30: 8 | I30: 1W4 | L30: 2 | M30: +10 | N30: +2 | O30: -14 | P30: -31 | Q30: x | R30: x | S30: 10m | T30: 14sec | U30: 4 | W30: 2 | X30: 150D
A31: Mittelschwere Armbrust (Gnom) | B31: Gnom | D31: 21,14sec:4 | E31: 8,30sec:2 | F31: 3,60sec:1 | H31: 21 | I31: 1W6 | L31: 3 | M31: +9 | N31: +6 | O31: -9 | P31: -25 | Q31: x | R31: x | S31: 15m | T31: 14sec | U31: 4 | W31: 3 | X31: 250D
A32: Schwere Armbrust (Gnom) | B32: Gnom | D32: 33,14sec:4 | E32: 16,30sec:2 | F32: 10,60sec:1 | H32: 33 | I32: 1W8 | L32: 4 | M32: +8 | N32: +5 | O32: -5 | P32: -21 | Q32: x | R32: x | S32: 20m | T32: 14sec | U32: 4 | W32: 4 | X32: 1000D
A33: Repetier Armbrust (Gnom)* | B33: Gnom | D33: Repetiern:8,6sec:10 / 5xBolzen nachladen: 1,16sec:6(Erg:5 fuer 1) | I33: 1W2 | L33: 2 | M33: +7 | N33: 0 | O33: -17 | P33: -34 | Q33: x | R33: x | S33: 5m | W33: 6 | X33: 1125D | AB33: Nur normale Bolzen mit normaler Spitze im 5-Schuss-Magazin
A34: Hand Armbrust (Zwerg) | B34: Zwerg | D34: 10,14sec:4 | E34: 6,30sec:2 | F34: 4,60sec:1 | H34: 10 | I34: 1W6 | L34: 3 | M34: +12 | N34: -2 | O34: -23 | P34: -37 | Q34: x | R34: x | S34: 10m | T34: 14sec | U34: 4 | W34: 4 | X34: 160D
A35: Leichte Armbrust (Zwerg) | B35: Zwerg | D35: 13,14sec:4 | E35: 8,30sec:2 | F35: 5,60sec:1 | H35: 13 | I35: 1W8 | L35: 4 | M35: +11 | N35: +3 | O35: -13 | P35: -30 | Q35: x | R35: x | S35: 15m | T35: 14sec | U35: 4 | W35: 2 | X35: 180D
A36: Mittelschwere Armbrust (Zwerg) | B36: Zwerg | D36: 26,14sec:4 | E36: 13,30sec:2 | F36: 8,60sec:1 | H36: 26 | I36: 1W10 | L36: 5 | M36: +10 | N36: +7 | O36: -8 | P36: -24 | Q36: x | R36: x | S36: 20m | T36: 14sec | U36: 4 | W36: 3 | X36: 300D
A37: Schwere Armbrust (Zwerg) | B37: Zwerg | D37: 38,14sec:4 | E37: 21,30sec:2 | F37: 15,60sec:1 | H37: 38 | I37: 1W12 | L37: 6 | M37: +9 | N37: +6 | O37: -4 | P37: -20 | Q37: x | R37: x | S37: 25m | T37: 14sec | U37: 4 | W37: 4 | X37: 1200D
A38: Repetier Armbrust (Zwerg)* | B38: Zwerg | D38: Repetiern:12,6sec:10 / 5xBolzen nachladen: 1,16sec:6(Erg:5 fuer 1) | I38: 1W4 | L38: 4 | M38: +8 | N38: +1 | O38: -16 | P38: -33 | Q38: x | R38: x | S38: 10m | W38: 6 | X38: 1350D | AB38: Nur normale Bolzen mit normaler Spitze im 5-Schuss-Magazin
A39: Balläster* | B39: Spezial/Legendaer | D39: 13,14sec:4 | E39: x | F39: x | H39: 13 | I39: 1W4 | L39: 2 | M39: +11 | N39: +3 | O39: -13 | P39: -30 | Q39: x | R39: x | S39: 10m | T39: 14sec | U39: 4 | X39: 300D+ | AB39: Zur Steinschleuder umgebaute Armbrust fuer die Vogeljagd; Munition kullert leicht aus der Abschusshalterung

Sheet Feuerwaffen-Munition
A1: Name | B1: Volk | C1: Lademechanik | D1: Munition (Waffen-Bezeichnung) | E1: Kaliber | F1: Munition-Art (primaer) | G1: Preis-1-Schuss (primaer) | H1: Munition-Art (alternativ) | I1: Preis-1-Schuss (alternativ) | J1: Alternativ-Effekt | K1: Notiz
A2: Hakenbüchse | B2: Dalkinisch | C2: Vorderlader | D2: Blei | E2: 19 | F2: S.P.&Blei | G2: =IF(F2="","",IF(COUNTIFS('Munition-Feuerwaffen'!$B$2:$B$35,F2,'Munition-Feuerwaffen'!$C$2:$C$35,E2)=0,"",SUMPRODUCT(('Munition-Feuerwaffen'!$B$2:$B$35=F2)*('Munition-Feuerwaffen'!$C$2:$C$35=E2)*'Munition-Feuerwaffen'!$D$2:$D$35))) -> 0.42042 | H2: VL. Papierpatrone | I2: =IF(H2="","",IF(COUNTIFS('Munition-Feuerwaffen'!$B$2:$B$35,H2,'Munition-Feuerwaffen'!$C$2:$C$35,E2)=0,"",SUMPRODUCT(('Munition-Feuerwaffen'!$B$2:$B$35=H2)*('Munition-Feuerwaffen'!$C$2:$C$35=E2)*'Munition-Feuerwaffen'!$D$2:$D$35))) -> 0.4531125 | J2: Reduziert die Nachladezeit um 5 Sekunden
A3: Muskete | B3: Dalkinisch | C3: Vorderlader | D3: Blei | E3: 17 | F3: S.P.&Blei | G3: =IF(F3="","",IF(COUNTIFS('Munition-Feuerwaffen'!$B$2:$B$35,F3,'Munition-Feuerwaffen'!$C$2:$C$35,E3)=0,"",SUMPRODUCT(('Munition-Feuerwaffen'!$B$2:$B$35=F3)*('Munition-Feuerwaffen'!$C$2:$C$35=E3)*'Munition-Feuerwaffen'!$D$2:$D$35))) -> 0.405132 | H3: VL. Papierpatrone | I3: =IF(H3="","",IF(COUNTIFS('Munition-Feuerwaffen'!$B$2:$B$35,H3,'Munition-Feuerwaffen'!$C$2:$C$35,E3)=0,"",SUMPRODUCT(('Munition-Feuerwaffen'!$B$2:$B$35=H3)*('Munition-Feuerwaffen'!$C$2:$C$35=E3)*'Munition-Feuerwaffen'!$D$2:$D$35))) -> 0.4404675 | J3: Reduziert die Nachladezeit um 5 Sekunden
A4: Schweres Gewehr | B4: Dalkinisch | C4: Vorderlader | D4: Blei | E4: 18 | F4: S.P.&Blei | G4: =IF(F4="","",IF(COUNTIFS('Munition-Feuerwaffen'!$B$2:$B$35,F4,'Munition-Feuerwaffen'!$C$2:$C$35,E4)=0,"",SUMPRODUCT(('Munition-Feuerwaffen'!$B$2:$B$35=F4)*('Munition-Feuerwaffen'!$C$2:$C$35=E4)*'Munition-Feuerwaffen'!$D$2:$D$35))) -> 0.412776 | H4: VL. Papierpatrone | I4: =IF(H4="","",IF(COUNTIFS('Munition-Feuerwaffen'!$B$2:$B$35,H4,'Munition-Feuerwaffen'!$C$2:$C$35,E4)=0,"",SUMPRODUCT(('Munition-Feuerwaffen'!$B$2:$B$35=H4)*('Munition-Feuerwaffen'!$C$2:$C$35=E4)*'Munition-Feuerwaffen'!$D$2:$D$35))) -> 0.44679 | J4: Reduziert die Nachladezeit um 5 Sekunden
A5: Langpistole | B5: Dalkinisch | C5: Vorderlader | D5: Blei | E5: 14 | F5: S.P.&Blei | G5: =IF(F5="","",IF(COUNTIFS('Munition-Feuerwaffen'!$B$2:$B$35,F5,'Munition-Feuerwaffen'!$C$2:$C$35,E5)=0,"",SUMPRODUCT(('Munition-Feuerwaffen'!$B$2:$B$35=F5)*('Munition-Feuerwaffen'!$C$2:$C$35=E5)*'Munition-Feuerwaffen'!$D$2:$D$35))) -> 0.3822 | H5: VL. Papierpatrone | I5: =IF(H5="","",IF(COUNTIFS('Munition-Feuerwaffen'!$B$2:$B$35,H5,'Munition-Feuerwaffen'!$C$2:$C$35,E5)=0,"",SUMPRODUCT(('Munition-Feuerwaffen'!$B$2:$B$35=H5)*('Munition-Feuerwaffen'!$C$2:$C$35=E5)*'Munition-Feuerwaffen'!$D$2:$D$35))) -> 0.4215 | J5: Reduziert die Nachladezeit um 5 Sekunden
A6: Pistole | B6: Dalkinisch | C6: Vorderlader | D6: Blei | E6: 14 | F6: S.P.&Blei | G6: =IF(F6="","",IF(COUNTIFS('Munition-Feuerwaffen'!$B$2:$B$35,F6,'Munition-Feuerwaffen'!$C$2:$C$35,E6)=0,"",SUMPRODUCT(('Munition-Feuerwaffen'!$B$2:$B$35=F6)*('Munition-Feuerwaffen'!$C$2:$C$35=E6)*'Munition-Feuerwaffen'!$D$2:$D$35))) -> 0.3822 | H6: VL. Papierpatrone | I6: =IF(H6="","",IF(COUNTIFS('Munition-Feuerwaffen'!$B$2:$B$35,H6,'Munition-Feuerwaffen'!$C$2:$C$35,E6)=0,"",SUMPRODUCT(('Munition-Feuerwaffen'!$B$2:$B$35=H6)*('Munition-Feuerwaffen'!$C$2:$C$35=E6)*'Munition-Feuerwaffen'!$D$2:$D$35))) -> 0.4215 | J6: Reduziert die Nachladezeit um 5 Sekunden
A7: verb. Langpistole | B7: Dalkinisch | C7: Vorderlader | D7: Blei | E7: 14 | F7: S.P.&Blei | G7: =IF(F7="","",IF(COUNTIFS('Munition-Feuerwaffen'!$B$2:$B$35,F7,'Munition-Feuerwaffen'!$C$2:$C$35,E7)=0,"",SUMPRODUCT(('Munition-Feuerwaffen'!$B$2:$B$35=F7)*('Munition-Feuerwaffen'!$C$2:$C$35=E7)*'Munition-Feuerwaffen'!$D$2:$D$35))) -> 0.3822 | H7: VL. Papierpatrone | I7: =IF(H7="","",IF(COUNTIFS('Munition-Feuerwaffen'!$B$2:$B$35,H7,'Munition-Feuerwaffen'!$C$2:$C$35,E7)=0,"",SUMPRODUCT(('Munition-Feuerwaffen'!$B$2:$B$35=H7)*('Munition-Feuerwaffen'!$C$2:$C$35=E7)*'Munition-Feuerwaffen'!$D$2:$D$35))) -> 0.4215 | J7: Reduziert die Nachladezeit um 5 Sekunden
A8: Schalarr | B8: Drow | C8: Hinterlader | D8: Papier Patrone | E8: 18 | F8: Papierpatrone | G8: =IF(F8="","",IF(COUNTIFS('Munition-Feuerwaffen'!$B$2:$B$35,F8,'Munition-Feuerwaffen'!$C$2:$C$35,E8)=0,"",SUMPRODUCT(('Munition-Feuerwaffen'!$B$2:$B$35=F8)*('Munition-Feuerwaffen'!$C$2:$C$35=E8)*'Munition-Feuerwaffen'!$D$2:$D$35))) -> 0.72150667
A9: Schapschu | B9: Drow | C9: Klapplauf | D9: Messing Patrone | E9: 12 | F9: Messingpatrone | G9: =IF(F9="","",IF(COUNTIFS('Munition-Feuerwaffen'!$B$2:$B$35,F9,'Munition-Feuerwaffen'!$C$2:$C$35,E9)=0,"",SUMPRODUCT(('Munition-Feuerwaffen'!$B$2:$B$35=F9)*('Munition-Feuerwaffen'!$C$2:$C$35=E9)*'Munition-Feuerwaffen'!$D$2:$D$35)))
A10: Ssussun | B10: Drow | C10: Vorderlader | D10: Blei | E10: 18 | F10: S.P.&Blei | G10: =IF(F10="","",IF(COUNTIFS('Munition-Feuerwaffen'!$B$2:$B$35,F10,'Munition-Feuerwaffen'!$C$2:$C$35,E10)=0,"",SUMPRODUCT(('Munition-Feuerwaffen'!$B$2:$B$35=F10)*('Munition-Feuerwaffen'!$C$2:$C$35=E10)*'Munition-Feuerwaffen'!$D$2:$D$35))) -> 0.412776 | H10: VL. Papierpatrone | I10: =IF(H10="","",IF(COUNTIFS('Munition-Feuerwaffen'!$B$2:$B$35,H10,'Munition-Feuerwaffen'!$C$2:$C$35,E10)=0,"",SUMPRODUCT(('Munition-Feuerwaffen'!$B$2:$B$35=H10)*('Munition-Feuerwaffen'!$C$2:$C$35=E10)*'Munition-Feuerwaffen'!$D$2:$D$35))) -> 0.44679 | J10: Reduziert die Nachladezeit um 5 Sekunden
A11: Wissperr | B11: Drow | C11: Hinterlader | D11: Papier Patrone | E11: 18 | F11: Papierpatrone | G11: =IF(F11="","",IF(COUNTIFS('Munition-Feuerwaffen'!$B$2:$B$35,F11,'Munition-Feuerwaffen'!$C$2:$C$35,E11)=0,"",SUMPRODUCT(('Munition-Feuerwaffen'!$B$2:$B$35=F11)*('Munition-Feuerwaffen'!$C$2:$C$35=E11)*'Munition-Feuerwaffen'!$D$2:$D$35))) -> 0.72150667
A12: Dunar | B12: Drow | C12: Klapplauf | D12: Messing Patrone | E12: 9 | F12: Messingpatrone | G12: =IF(F12="","",IF(COUNTIFS('Munition-Feuerwaffen'!$B$2:$B$35,F12,'Munition-Feuerwaffen'!$C$2:$C$35,E12)=0,"",SUMPRODUCT(('Munition-Feuerwaffen'!$B$2:$B$35=F12)*('Munition-Feuerwaffen'!$C$2:$C$35=E12)*'Munition-Feuerwaffen'!$D$2:$D$35))) -> 0.8689168
A13: Schatten | B13: Drow | C13: Klapplauf | D13: Messing Patrone | E13: 10 | F13: Messingpatrone | G13: =IF(F13="","",IF(COUNTIFS('Munition-Feuerwaffen'!$B$2:$B$35,F13,'Munition-Feuerwaffen'!$C$2:$C$35,E13)=0,"",SUMPRODUCT(('Munition-Feuerwaffen'!$B$2:$B$35=F13)*('Munition-Feuerwaffen'!$C$2:$C$35=E13)*'Munition-Feuerwaffen'!$D$2:$D$35))) -> 0.9126752
A14: Suliss | B14: Drow | C14: Vorderlader | D14: Blei | E14: 15 | F14: S.P.&Blei | G14: =IF(F14="","",IF(COUNTIFS('Munition-Feuerwaffen'!$B$2:$B$35,F14,'Munition-Feuerwaffen'!$C$2:$C$35,E14)=0,"",SUMPRODUCT(('Munition-Feuerwaffen'!$B$2:$B$35=F14)*('Munition-Feuerwaffen'!$C$2:$C$35=E14)*'Munition-Feuerwaffen'!$D$2:$D$35))) -> 0.389844 | H14: VL. Papierpatrone | I14: =IF(H14="","",IF(COUNTIFS('Munition-Feuerwaffen'!$B$2:$B$35,H14,'Munition-Feuerwaffen'!$C$2:$C$35,E14)=0,"",SUMPRODUCT(('Munition-Feuerwaffen'!$B$2:$B$35=H14)*('Munition-Feuerwaffen'!$C$2:$C$35=E14)*'Munition-Feuerwaffen'!$D$2:$D$35))) -> 0.4278225 | J14: Reduziert die Nachladezeit um 5 Sekunden
A15: Taschenalb | B15: Drow | C15: Klapplauf | D15: Messing Patrone | E15: 7 | F15: Messingpatrone | G15: =IF(F15="","",IF(COUNTIFS('Munition-Feuerwaffen'!$B$2:$B$35,F15,'Munition-Feuerwaffen'!$C$2:$C$35,E15)=0,"",SUMPRODUCT(('Munition-Feuerwaffen'!$B$2:$B$35=F15)*('Munition-Feuerwaffen'!$C$2:$C$35=E15)*'Munition-Feuerwaffen'!$D$2:$D$35))) -> 0.718784
A16: Adler | B16: Elfisch | C16: Vorderlader | D16: Blei | E16: 17 | F16: S.P.&Blei | G16: =IF(F16="","",IF(COUNTIFS('Munition-Feuerwaffen'!$B$2:$B$35,F16,'Munition-Feuerwaffen'!$C$2:$C$35,E16)=0,"",SUMPRODUCT(('Munition-Feuerwaffen'!$B$2:$B$35=F16)*('Munition-Feuerwaffen'!$C$2:$C$35=E16)*'Munition-Feuerwaffen'!$D$2:$D$35))) -> 0.405132 | H16: VL. Papierpatrone | I16: =IF(H16="","",IF(COUNTIFS('Munition-Feuerwaffen'!$B$2:$B$35,H16,'Munition-Feuerwaffen'!$C$2:$C$35,E16)=0,"",SUMPRODUCT(('Munition-Feuerwaffen'!$B$2:$B$35=H16)*('Munition-Feuerwaffen'!$C$2:$C$35=E16)*'Munition-Feuerwaffen'!$D$2:$D$35))) -> 0.4404675 | J16: Reduziert die Nachladezeit um 5 Sekunden
A17: Bussard | B17: Elfisch | C17: Klapplauf | D17: Messing Patrone | E17: 11 | F17: Messingpatrone | G17: =IF(F17="","",IF(COUNTIFS('Munition-Feuerwaffen'!$B$2:$B$35,F17,'Munition-Feuerwaffen'!$C$2:$C$35,E17)=0,"",SUMPRODUCT(('Munition-Feuerwaffen'!$B$2:$B$35=F17)*('Munition-Feuerwaffen'!$C$2:$C$35=E17)*'Munition-Feuerwaffen'!$D$2:$D$35)))
A18: Kondor | B18: Elfisch | C18: Vorderlader | D18: Blei | E18: 17 | F18: S.P.&Blei | G18: =IF(F18="","",IF(COUNTIFS('Munition-Feuerwaffen'!$B$2:$B$35,F18,'Munition-Feuerwaffen'!$C$2:$C$35,E18)=0,"",SUMPRODUCT(('Munition-Feuerwaffen'!$B$2:$B$35=F18)*('Munition-Feuerwaffen'!$C$2:$C$35=E18)*'Munition-Feuerwaffen'!$D$2:$D$35))) -> 0.405132 | H18: VL. Papierpatrone | I18: =IF(H18="","",IF(COUNTIFS('Munition-Feuerwaffen'!$B$2:$B$35,H18,'Munition-Feuerwaffen'!$C$2:$C$35,E18)=0,"",SUMPRODUCT(('Munition-Feuerwaffen'!$B$2:$B$35=H18)*('Munition-Feuerwaffen'!$C$2:$C$35=E18)*'Munition-Feuerwaffen'!$D$2:$D$35))) -> 0.4404675 | J18: Reduziert die Nachladezeit um 5 Sekunden
